[
  {
    "name": "M痘",
    "url": "https://www.cdc.gov.tw/File/Get/c2QLiq13D73BYYQAKV83ew",
    "source_category": "第二類",
    "content": "M 痘\n(Mpox)\n一、臨床條件\n需具下列條件:\n(一) 皮膚病灶如皮疹、斑疹、斑丘疹、水泡、膿疱等,且無法以其\n他已知病因解釋。\n(二) 具有任一下列症狀:\n發燒(≧38°C)、畏寒/寒顫、出汗、頭痛、肌肉痛、背痛、關\n節痛、淋巴腺腫大(如耳周、腋窩、頸部或腹股溝等處)。\n二、檢驗條件\n具有下列任一個條件:\n(一) 臨床檢體(如病患發病期內皮膚水泡、咽喉擦拭檢體或膿疱檢\n體)分離並鑑定出 M痘病毒。\n(二) 臨床檢體 M痘病毒分子生物學核酸檢測為陽性。\n三、流行病學條件\n發病前21日內,具有下列任一個條件:\n(一) 曾經與確定病例或出現症狀的極可能病例有密切接觸。\n(二) 具有 M痘確定病例報告之國家旅遊史。\n(三) 具有野生動物或非洲特有外來種動物(含屍體)暴露史。\n四、通報定義\n具有下列任一個條件:\n(一) 符合臨床條件。\n(二) 符合檢驗條件。\n五、疾病分類\n(一) 極可能病例:符合臨床條件及流病條件。\n(二) 確定病例:符合檢驗條件。\n1\n六、檢體採檢送驗事項\n傳染病 應保存種類\n採檢項目 採檢目的 採檢時間 採檢量及規定 送驗方式\n名稱 (應保存時間)\n以無菌病毒拭子擦\n拭皮膚病灶之水疱\n水疱液、膿 病 毒 株 ( 30\n液或膿疱內容物,\n疱內容物 2-8°C(A 日);水疱液、\n病原體 插入病毒保存輸送\nM痘 立即採檢 類感染性物 膿疱內容物及\n檢測 管。\n質包裝) 咽 喉 擦 拭 液\n以無菌病毒拭子擦\n(30日)\n咽喉擦拭液 拭咽喉,插入病毒\n保存輸送管。\n2",
    "pdf_path": "pdfs/M痘.pdf",
    "臨床條件": "需具下列條件:\n(一) 皮膚病灶如皮疹、斑疹、斑丘疹、水泡、膿疱等,且無法以其\n他已知病因解釋。\n(二) 具有任一下列症狀:\n發燒(≧38°C)、畏寒/寒顫、出汗、頭痛、肌肉痛、背痛、關\n節痛、淋巴腺腫大(如耳周、腋窩、頸部或腹股溝等處)。",
    "檢驗條件": "具有下列任一個條件:\n(一) 臨床檢體(如病患發病期內皮膚水泡、咽喉擦拭檢體或膿疱檢\n體)分離並鑑定出 M痘病毒。\n(二) 臨床檢體 M痘病毒分子生物學核酸檢測為陽性。",
    "流行病學條件": "發病前21日內,具有下列任一個條件:\n(一) 曾經與確定病例或出現症狀的極可能病例有密切接觸。\n(二) 具有 M痘確定病例報告之國家旅遊史。\n(三) 具有野生動物或非洲特有外來種動物(含屍體)暴露史。",
    "通報定義": "具有下列任一個條件:\n(一) 符合臨床條件。\n(二) 符合檢驗條件。",
    "疾病分類": "(一) 極可能病例:符合臨床條件及流病條件。\n(二) 確定病例:符合檢驗條件。\n1",
    "檢體採檢送驗事項": "傳染病 應保存種類\n採檢項目 採檢目的 採檢時間 採檢量及規定 送驗方式\n名稱 (應保存時間)\n以無菌病毒拭子擦\n拭皮膚病灶之水疱\n水疱液、膿 病 毒 株 ( 30\n液或膿疱內容物,\n疱內容物 2-8°C(A 日);水疱液、\n病原體 插入病毒保存輸送\nM痘 立即採檢 類感染性物 膿疱內容物及\n檢測 管。\n質包裝) 咽 喉 擦 拭 液\n以無菌病毒拭子擦\n(30日)\n咽喉擦拭液 拭咽喉,插入病毒\n保存輸送管。\n2",
    "english_name": "Mpox",
    "suspected_case": "",
    "probable_case": "符合臨床條件及流病條件。",
    "confirmed_case": "符合檢驗條件。\n1"
  },
  {
    "name": "Q熱",
    "url": "https://www.cdc.gov.tw/File/Get/46rMxDdAD4FJRsJOmgVwBA",
    "source_category": "第四類",
    "content": "Q 熱\n(Q fever)\n一、臨床條件\n發燒、畏寒、噁心嘔吐、腹瀉、盜汗、頭痛、身體不適、肌肉酸痛,\n急性肝炎或急性黃疸、肺炎以及腦膜腦炎等。\n二、檢驗條件\n符合下列檢驗結果之任一項者,定義為檢驗結果陽性:\n(一) 臨床檢體分子生物學核酸檢測陽性。\n(二) 以間接免疫螢光抗體法(Indirect Immunofluorescene Assay,\nIFA)檢測急性期(或初次採檢)血清,Phase II IgM 力價達\n1:80 以上,或配對血清(急性期及恢復期)Phase II IgG 力\n價達 4 倍以上上升。\n三、流行病學條件\nNA\n四、通報定義\n符合臨床條件。\n五、病例分類\n(一) 可能病例:NA\n(二) 極可能病例:NA\n(三) 確定病例:符合間接免疫螢光抗體法(IFA)檢驗結果陽性定\n義。\n2019年3月\n六、檢體採檢送驗事項\n傳染病 採檢量及 應保存種類\n採檢項目 採檢目的 採檢時間 送驗方式 注意事項\n名稱 規定 應保存時間\n1. 請於未投藥\n前採血。\n2. 血清檢體採\n檢注意事項\n請參閱傳染\n以無菌試管\n病檢體採檢\n陽性血清\n血清 抗體檢測 立即採檢 收集3 mL\n手冊 2.8.3\n(30日)\n血清\n及 2.8.4 備\n註說明,血\n清檢體採檢\n步驟請參閱\n傳染病檢體\n採檢手冊第\n2–8 °C 3.3節。\nQ熱 B類感染性 3. 抗凝固全血\n物質包裝 檢體採檢步\n驟請參閱傳\n染病檢體採\n以含抗凝劑\n檢 手 冊 第\n(heparin\n3.2節。\n抗凝固 病原體 急性期 或EDTA)\n4. Q 熱之檢驗\n-\n全血 檢測 發病14日內 採血管採集\n以不做二採\n5–10 mL\n為原則,如\n血液檢體\n有臨床上個\n別需要,請\n聯繫衛生福\n利部疾病管\n制署檢體單\n一窗口。\n衛生福利部疾病管制署「傳染病檢體採檢手冊」可至衛福部疾管署全球資訊網(cdd.gov.tw)首頁之檢驗\n(傳染病檢驗資訊與規定)項下查詢。\nQ 熱之檢驗方法、步驟及結果判定等相關資訊,可參閱衛生福利部疾病管制署「傳染病標準檢驗方法手\n冊」(衛福部疾管署全球資訊網/首頁/檢驗(傳染病檢驗資訊與規定))。\n2019年3月",
    "pdf_path": "pdfs/Q熱.pdf",
    "臨床條件": "發燒、畏寒、噁心嘔吐、腹瀉、盜汗、頭痛、身體不適、肌肉酸痛,\n急性肝炎或急性黃疸、肺炎以及腦膜腦炎等。",
    "檢驗條件": "符合下列檢驗結果之任一項者,定義為檢驗結果陽性:\n(一) 臨床檢體分子生物學核酸檢測陽性。\n(二) 以間接免疫螢光抗體法(Indirect Immunofluorescene Assay,\nIFA)檢測急性期(或初次採檢)血清,Phase II IgM 力價達\n1:80 以上,或配對血清(急性期及恢復期)Phase II IgG 力\n價達 4 倍以上上升。",
    "流行病學條件": "NA",
    "通報定義": "符合臨床條件。",
    "疾病分類": "(一) 可能病例:NA\n(二) 極可能病例:NA\n(三) 確定病例:符合間接免疫螢光抗體法(IFA)檢驗結果陽性定\n義。\n2019年3月",
    "檢體採檢送驗事項": "傳染病 採檢量及 應保存種類\n採檢項目 採檢目的 採檢時間 送驗方式 注意事項\n名稱 規定 應保存時間\n1. 請於未投藥\n前採血。\n2. 血清檢體採\n檢注意事項\n請參閱傳染\n以無菌試管\n病檢體採檢\n陽性血清\n血清 抗體檢測 立即採檢 收集3 mL\n手冊 2.8.3\n(30日)\n血清\n及 2.8.4 備\n註說明,血\n清檢體採檢\n步驟請參閱\n傳染病檢體\n採檢手冊第\n2–8 °C 3.3節。\nQ熱 B類感染性 3. 抗凝固全血\n物質包裝 檢體採檢步\n驟請參閱傳\n染病檢體採\n以含抗凝劑\n檢 手 冊 第\n(heparin\n3.2節。\n抗凝固 病原體 急性期 或EDTA)\n4. Q 熱之檢驗\n-\n全血 檢測 發病14日內 採血管採集\n以不做二採\n5–10 mL\n為原則,如\n血液檢體\n有臨床上個\n別需要,請\n聯繫衛生福\n利部疾病管\n制署檢體單\n一窗口。\n衛生福利部疾病管制署「傳染病檢體採檢手冊」可至衛福部疾管署全球資訊網(cdd.gov.tw)首頁之檢驗\n(傳染病檢驗資訊與規定)項下查詢。\nQ 熱之檢驗方法、步驟及結果判定等相關資訊,可參閱衛生福利部疾病管制署「傳染病標準檢驗方法手\n冊」(衛福部疾管署全球資訊網/首頁/檢驗(傳染病檢驗資訊與規定))。\n2019年3月",
    "english_name": "Q fever",
    "suspected_case": "NA",
    "probable_case": "NA",
    "confirmed_case": "符合間接免疫螢光抗體法(IFA)檢驗結果陽性定\n義。\n2019年3月"
  },
  {
    "name": "中東呼吸症候群冠狀病毒感染症",
    "url": "https://www.cdc.gov.tw/File/Get/slN7SPgc2BZ7Mz12GRH9zA",
    "source_category": "第五類",
    "content": "附件一\n中東呼吸症候群冠狀病毒感染症\n(Middle East Respiratory Syndrome\nCoronavirus Infections)\n一、 臨床條件\n同時符合以下兩項條件:\n(一) 急性呼吸道感染,臨床症狀可能包括發燒(≧38°C)及\n咳嗽。\n(二) 臨床、放射線診斷或病理學上顯示肺部實質疾病。\n二、 檢驗條件\n具有下列任一個條件:\n(一) 臨床檢體(如咽喉擦拭液、痰液或下呼吸道抽取液、血\n液等)分離並鑑定出中東呼吸症候群冠狀病毒。\n(二) 臨床檢體中東呼吸症候群冠狀病毒分子生物學核酸檢測\n陽性。\n三、 流行病學條件\n發病前 14 日內,具有下列任一個條件:\n(一) 曾經與出現症狀的極可能病例或確定病例有密切接觸,\n包括在無適當防護下提供照護、相處、或有呼吸道分泌\n物、體液之直接接觸,或\n(二) 具有中東呼吸症候群冠狀病毒疫情流行地區之旅遊或居\n住史。\n四、 通報定義\n具有下列任一個條件:\n(一) 符合臨床條件及流行病學條件,或\n(二) 僅符合臨床條件第(一)項及流行病學條件第(一)項,或\n(三) 符合檢驗條件。\n五、 疾病分類\n(一) 極可能病例:\n雖未經實驗室檢驗證實,但符合臨床條件,且於發病前\n14 日內,曾經與出現症狀之確定病例有密切接觸者。\n(二) 確定病例: 符合檢驗條件。\n六、 檢體採檢送驗事項\n請參閱「傳染病檢體採檢手冊」(https://gov.tw/pK8)",
    "pdf_path": "pdfs/中東呼吸症候群冠狀病毒感染症.pdf",
    "臨床條件": "同時符合以下兩項條件:\n(一) 急性呼吸道感染,臨床症狀可能包括發燒(≧38°C)及\n咳嗽。\n(二) 臨床、放射線診斷或病理學上顯示肺部實質疾病。",
    "檢驗條件": "具有下列任一個條件:\n(一) 臨床檢體(如咽喉擦拭液、痰液或下呼吸道抽取液、血\n液等)分離並鑑定出中東呼吸症候群冠狀病毒。\n(二) 臨床檢體中東呼吸症候群冠狀病毒分子生物學核酸檢測\n陽性。",
    "流行病學條件": "發病前 14 日內,具有下列任一個條件:\n(一) 曾經與出現症狀的極可能病例或確定病例有密切接觸,\n包括在無適當防護下提供照護、相處、或有呼吸道分泌\n物、體液之直接接觸,或\n(二) 具有中東呼吸症候群冠狀病毒疫情流行地區之旅遊或居\n住史。",
    "通報定義": "具有下列任一個條件:\n(一) 符合臨床條件及流行病學條件,或\n(二) 僅符合臨床條件第(一)項及流行病學條件第(一)項,或\n(三) 符合檢驗條件。",
    "疾病分類": "(一) 極可能病例:\n雖未經實驗室檢驗證實,但符合臨床條件,且於發病前\n14 日內,曾經與出現症狀之確定病例有密切接觸者。\n(二) 確定病例: 符合檢驗條件。",
    "檢體採檢送驗事項": "請參閱「傳染病檢體採檢手冊」(https://gov.tw/pK8)",
    "english_name": "Middle East Respiratory Syndrome Coronavirus Infections",
    "suspected_case": "",
    "probable_case": "雖未經實驗室檢驗證實,但符合臨床條件,且於發病前\n14 日內,曾經與出現症狀之確定病例有密切接觸者。",
    "confirmed_case": "符合檢驗條件。"
  },
  {
    "name": "人類免疫缺乏病毒(愛滋病毒)感染",
    "url": "https://www.cdc.gov.tw/File/Get/iPNO8zSCF08pPOP7Uwl5Yg",
    "source_category": "第三類",
    "content": "人類免疫缺乏病毒感染\n(HIV Infection)\n一、臨床條件\nNA\n二、檢驗條件\n(一)符合下列任一情形。\n1. HIV 抗原/抗體複合型篩檢( HIV antibody and antigen\ncombination assay)或抗體篩檢*(EIA 或 PA)陽性,再\n經 HIV-1/2 抗體確認檢驗方法(抗體免疫層析檢驗法或西\n方墨點法),確認為陽性反應者(年齡須大於 18 個月)。\n2. HIV 分子生物學核酸檢測(NAT)呈陽性反應者。\n3. HIV 抗原 p24 篩檢陽性,且進行中和試驗(Neutralization\ntest,NT),確認為陽性反應者。(年齡須大於 1 個月)\n*若使用快速抗體篩檢檢測陽性者,仍需進行 HIV 抗原/抗體\n複合型篩檢或抗體篩檢。\n(二)新生兒以 HIV 抗原/抗體複合型篩檢或抗體篩檢呈陽性者。\n(三)孕產婦以 HIV 抗原/抗體複合型篩檢或抗體篩檢呈陽性者。\n三、流行病學條件\n(一)符合下列任一情形之新生兒。\n1. 其生母為人類免疫缺乏病毒感染者。\n2. 其生母臨產時為 HIV 抗原/抗體複合型篩檢或抗體篩檢呈\n陽性者。\n(二)符合下列任一情形者,為急性初期感染。\n1. 依據過去檢驗紀錄:符合檢驗條件第(一)項 1 或 2,且確\n診通報前 180 天內,有任一 HIV 檢驗結果是陰性或未確定\n者,包含:HIV 抗原/抗體複合型篩檢、抗體篩檢(EIA 或\nPA)、HIV-1/2 抗體確認檢驗或 HIV 分子生物學核酸檢測\n(NAT)。\n2. 本次確診檢驗流程中,於 HIV 分子生物學核酸檢測 NAT 檢\n驗陽性前後 180 日內有任一抗體確認檢驗結果為陰性或未\n確定者。\n3. 本次檢驗流程中,HIV 抗原/抗體複合型篩檢結果為「抗原陽\n性」者。\n四、通報定義\n符合檢驗條件任一項或流行病學條件第(一)項者。\n五、疾病分類\n(一)可能病例:\nNA\n(二)極可能病例:\n符合檢驗條件第(二)項或第(三)項或流行病學條件第\n(一)項。\n(三)確定病例:\n符合檢驗條件第(一)項。如同時符合流行病學條件第\n(二)項,則為急性初期感染。",
    "pdf_path": "pdfs/人類免疫缺乏病毒(愛滋病毒)感染.pdf",
    "臨床條件": "NA",
    "檢驗條件": "(一)符合下列任一情形。\n1. HIV 抗原/抗體複合型篩檢( HIV antibody and antigen\ncombination assay)或抗體篩檢*(EIA 或 PA)陽性,再\n經 HIV-1/2 抗體確認檢驗方法(抗體免疫層析檢驗法或西\n方墨點法),確認為陽性反應者(年齡須大於 18 個月)。\n2. HIV 分子生物學核酸檢測(NAT)呈陽性反應者。\n3. HIV 抗原 p24 篩檢陽性,且進行中和試驗(Neutralization\ntest,NT),確認為陽性反應者。(年齡須大於 1 個月)\n*若使用快速抗體篩檢檢測陽性者,仍需進行 HIV 抗原/抗體\n複合型篩檢或抗體篩檢。\n(二)新生兒以 HIV 抗原/抗體複合型篩檢或抗體篩檢呈陽性者。\n(三)孕產婦以 HIV 抗原/抗體複合型篩檢或抗體篩檢呈陽性者。",
    "流行病學條件": "(一)符合下列任一情形之新生兒。\n1. 其生母為人類免疫缺乏病毒感染者。\n2. 其生母臨產時為 HIV 抗原/抗體複合型篩檢或抗體篩檢呈\n陽性者。\n(二)符合下列任一情形者,為急性初期感染。\n1. 依據過去檢驗紀錄:符合檢驗條件第(一)項 1 或 2,且確\n診通報前 180 天內,有任一 HIV 檢驗結果是陰性或未確定\n者,包含:HIV 抗原/抗體複合型篩檢、抗體篩檢(EIA 或\nPA)、HIV-1/2 抗體確認檢驗或 HIV 分子生物學核酸檢測\n(NAT)。\n2. 本次確診檢驗流程中,於 HIV 分子生物學核酸檢測 NAT 檢\n驗陽性前後 180 日內有任一抗體確認檢驗結果為陰性或未\n確定者。\n3. 本次檢驗流程中,HIV 抗原/抗體複合型篩檢結果為「抗原陽\n性」者。",
    "通報定義": "符合檢驗條件任一項或流行病學條件第(一)項者。",
    "疾病分類": "(一)可能病例:\nNA\n(二)極可能病例:\n符合檢驗條件第(二)項或第(三)項或流行病學條件第\n(一)項。\n(三)確定病例:\n符合檢驗條件第(一)項。如同時符合流行病學條件第\n(二)項,則為急性初期感染。",
    "檢體採檢送驗事項": "",
    "english_name": "HIV Infection",
    "suspected_case": "NA",
    "probable_case": "符合檢驗條件第(二)項或第(三)項或流行病學條件第\n(一)項。",
    "confirmed_case": "符合檢驗條件第(一)項。如同時符合流行病學條件第\n(二)項,則為急性初期感染。"
  },
  {
    "name": "伊波拉病毒感染",
    "url": "https://www.cdc.gov.tw/File/Get/QoRIfzLnjNEeyUJkidSugA",
    "source_category": "第五類",
    "content": "附件一\n伊波拉病毒感染\n(Ebola Virus Disease)\n一、臨床條件\n具有下列任一個條件:\n(一) 急性發燒(≧38°C)\n(二) 頭痛、肌肉痛、噁心、嘔吐、腹瀉、腹痛等任一臨床描\n述。\n(三) 不明原因出血。\n(四) 突發性不明原因死亡。\n二、檢驗條件\n具有下列任一個條件:\n(一) 臨床檢體分離並鑑定出伊波拉病毒。\n(二) 臨床檢體分子生物學核酸檢測陽性。\n(三) 血清學抗體檢測陽性。\n(四) 組織切片免疫化學染色(IHC)陽性。\n三、流行病學條件\n發病前 3 週內,具有下列任一個條件:\n(一) 具有伊波拉病毒感染流行地區之旅遊史或居住史。\n(二) 接觸極可能病例或確定病例之血液或體液或其汙染物。\n(三) 具有伊波拉病毒感染流行地區動物(例如蝙蝠、豬隻、羚\n羊、囓齒動物或靈長類等)之接觸史。\n(四) 進行伊波拉病毒或檢體之實驗室操作。\n四、通報定義\n具有下列任一個條件:\n(一) 符合臨床條件以及流行病學條件。\n(二) 符合檢驗條件。\n五、 疾病分類\n(一) 極可能病例:\n雖未經實驗室證實,但符合臨床條件,且於發病前 3 週\n內接觸確定病例之血液或體液者。\n(二) 確定病例:\n符合檢驗條件。\n六、檢體採檢送驗事項\n請參閱「傳染病檢體採檢手冊」(https://gov.tw/pK8)",
    "pdf_path": "pdfs/伊波拉病毒感染.pdf",
    "臨床條件": "具有下列任一個條件:\n(一) 急性發燒(≧38°C)\n(二) 頭痛、肌肉痛、噁心、嘔吐、腹瀉、腹痛等任一臨床描\n述。\n(三) 不明原因出血。\n(四) 突發性不明原因死亡。",
    "檢驗條件": "具有下列任一個條件:\n(一) 臨床檢體分離並鑑定出伊波拉病毒。\n(二) 臨床檢體分子生物學核酸檢測陽性。\n(三) 血清學抗體檢測陽性。\n(四) 組織切片免疫化學染色(IHC)陽性。",
    "流行病學條件": "發病前 3 週內,具有下列任一個條件:\n(一) 具有伊波拉病毒感染流行地區之旅遊史或居住史。\n(二) 接觸極可能病例或確定病例之血液或體液或其汙染物。\n(三) 具有伊波拉病毒感染流行地區動物(例如蝙蝠、豬隻、羚\n羊、囓齒動物或靈長類等)之接觸史。\n(四) 進行伊波拉病毒或檢體之實驗室操作。",
    "通報定義": "具有下列任一個條件:\n(一) 符合臨床條件以及流行病學條件。\n(二) 符合檢驗條件。",
    "疾病分類": "(一) 極可能病例:\n雖未經實驗室證實,但符合臨床條件,且於發病前 3 週\n內接觸確定病例之血液或體液者。\n(二) 確定病例:\n符合檢驗條件。",
    "檢體採檢送驗事項": "請參閱「傳染病檢體採檢手冊」(https://gov.tw/pK8)",
    "english_name": "Ebola Virus Disease",
    "suspected_case": "",
    "probable_case": "雖未經實驗室證實,但符合臨床條件,且於發病前 3 週\n內接觸確定病例之血液或體液者。",
    "confirmed_case": "符合檢驗條件。"
  },
  {
    "name": "侵襲性b型嗜血桿菌感染症",
    "url": "https://www.cdc.gov.tw/File/Get/DLoiALY997VITcAY_jOwDQ",
    "source_category": "第三類",
    "content": "侵襲性 b 型嗜血桿菌感染症\n(Invasive Haemophilus influenzae Type b Infection)\n一、 臨床條件\n由 b 型流行性感冒嗜血桿菌所引起的侵襲性疾病,可能產生的臨床症\n狀包括:腦膜炎、菌血症、肺炎、蜂窩組織炎、敗血性關節炎、骨髓\n炎、會厭炎等。\n二、 檢驗條件\n正常無菌檢體(血液、腦脊髓液、關節液、肋膜液、心包膜液等體液)\n分離並鑑定出 b 型嗜血桿菌(Haemophilus influenzae type b)。\n三、 流行病學條件\n曾經與確定病例或極可能病例具有密切接觸,即照護、同住、或與確\n定病例有呼吸道分泌物、體液之直接接觸。\n四、 通報定義\n符合臨床條件,且經醫院自行檢驗,符合檢驗條件。\n五、 疾病分類\n(一) 可能病例:\n符合臨床條件。\n(二) 極可能病例:\nNA\n(三) 確定病例:\n符合臨床條件及檢驗條件。\n六、 檢體採檢送驗事項\n採檢項目 檢體種類 採檢目的 採檢時機 採檢規定 運送條件 注意事項\n以 採 血 管 採 全 1. 全血採檢請\n血,立即注入嗜氧 參考第 3.1 節。\n未投藥前立\n全血 性血瓶(血液與培 2. 腦脊髓液採\n即採檢\n養液比例為 1:5 至 檢步驟請參考第\n1:10)。 3.6 節,由醫師採\n病原體檢測 常溫\n以無菌容器收集 檢。\n腦 脊 髓\n侵襲性 b 至少 1 mL 腦脊髓 3. 肋膜液、關節\n液、肋膜 未投藥前立\n液等體液採檢請\n型嗜血桿 液或體液。或直接\n液、關節液 即採檢 參考第 3.10 節。\n菌感染症 接種於巧克力培\n等\n養基。\n常溫\n接種於巧克力培\n未投藥前立養基,以封口膜\n菌株 菌株鑑定 (B 類感染\n即採檢 (paraffin)密封,\n性物質包\n並加夾鏈袋運送。\n裝)",
    "pdf_path": "pdfs/侵襲性b型嗜血桿菌感染症.pdf",
    "臨床條件": "由 b 型流行性感冒嗜血桿菌所引起的侵襲性疾病,可能產生的臨床症\n狀包括:腦膜炎、菌血症、肺炎、蜂窩組織炎、敗血性關節炎、骨髓\n炎、會厭炎等。",
    "檢驗條件": "正常無菌檢體(血液、腦脊髓液、關節液、肋膜液、心包膜液等體液)\n分離並鑑定出 b 型嗜血桿菌(Haemophilus influenzae type b)。",
    "流行病學條件": "曾經與確定病例或極可能病例具有密切接觸,即照護、同住、或與確\n定病例有呼吸道分泌物、體液之直接接觸。",
    "通報定義": "符合臨床條件,且經醫院自行檢驗,符合檢驗條件。",
    "疾病分類": "(一) 可能病例:\n符合臨床條件。\n(二) 極可能病例:\nNA\n(三) 確定病例:\n符合臨床條件及檢驗條件。",
    "檢體採檢送驗事項": "採檢項目 檢體種類 採檢目的 採檢時機 採檢規定 運送條件 注意事項\n以 採 血 管 採 全 1. 全血採檢請\n血,立即注入嗜氧 參考第 3.1 節。\n未投藥前立\n全血 性血瓶(血液與培 2. 腦脊髓液採\n即採檢\n養液比例為 1:5 至 檢步驟請參考第\n1:10)。 3.6 節,由醫師採\n病原體檢測 常溫\n以無菌容器收集 檢。\n腦 脊 髓\n侵襲性 b 至少 1 mL 腦脊髓 3. 肋膜液、關節\n液、肋膜 未投藥前立\n液等體液採檢請\n型嗜血桿 液或體液。或直接\n液、關節液 即採檢 參考第 3.10 節。\n菌感染症 接種於巧克力培\n等\n養基。\n常溫\n接種於巧克力培\n未投藥前立養基,以封口膜\n菌株 菌株鑑定 (B 類感染\n即採檢 (paraffin)密封,\n性物質包\n並加夾鏈袋運送。\n裝)",
    "english_name": "Invasive Haemophilus influenzae Type b Infection",
    "suspected_case": "符合臨床條件。",
    "probable_case": "NA",
    "confirmed_case": "符合臨床條件及檢驗條件。"
  },
  {
    "name": "侵襲性肺炎鏈球菌感染症",
    "url": "https://www.cdc.gov.tw/File/Get/dTTMlNEZfoUwF-9X_yllzA",
    "source_category": "第四類",
    "content": "侵襲性肺炎鏈球菌感染症\n(Invasive Pneumococcal Disease)\n一、 臨床條件\n由肺炎鏈球菌(Streptococcus pneumoniae)引起之侵襲性疾病,如:敗血症、\n肺炎、腦膜炎、關節炎、骨髓炎、心包膜炎、腹膜炎...等。\n二、 檢驗條件\n正常無菌檢體(血液、腦脊髓液、關節液等體液)分離並鑑定出肺炎鏈球\n菌(Streptococcus pneumoniae)。\n三、 流行病學條件\nNA\n四、 通報定義\n符合臨床條件,且經醫院自行檢驗,符合檢驗條件。\n五、 疾病分類\n(一) 可能病例:NA。\n(二) 極可能病例:NA。\n(三) 確定病例:符合臨床條件及檢驗條件者。\n六、 檢體採檢送驗事項\n採檢項目 檢體種類 採檢目的 採檢時間 採檢量及規定 送驗方式 注意事項\n以侵襲性肺炎 1. 肺炎鏈球菌\n鏈球菌專用拭 常溫 易死亡,採檢\n侵襲性肺\n病原體血清 已分離菌 子之棉棒採集 (B 類感 後儘速送驗。\n炎鏈球菌 菌株\n型別檢測 株時 菌株,插Amies 染性物質 2. 見2.8.6 備註\n感染症\nw/charcoal 保 包裝) 說 明 及 圖\n存輸送培管。 2.4。",
    "pdf_path": "pdfs/侵襲性肺炎鏈球菌感染症.pdf",
    "臨床條件": "由肺炎鏈球菌(Streptococcus pneumoniae)引起之侵襲性疾病,如:敗血症、\n肺炎、腦膜炎、關節炎、骨髓炎、心包膜炎、腹膜炎...等。",
    "檢驗條件": "正常無菌檢體(血液、腦脊髓液、關節液等體液)分離並鑑定出肺炎鏈球\n菌(Streptococcus pneumoniae)。",
    "流行病學條件": "NA",
    "通報定義": "符合臨床條件,且經醫院自行檢驗,符合檢驗條件。",
    "疾病分類": "(一) 可能病例:NA。\n(二) 極可能病例:NA。\n(三) 確定病例:符合臨床條件及檢驗條件者。",
    "檢體採檢送驗事項": "採檢項目 檢體種類 採檢目的 採檢時間 採檢量及規定 送驗方式 注意事項\n以侵襲性肺炎 1. 肺炎鏈球菌\n鏈球菌專用拭 常溫 易死亡,採檢\n侵襲性肺\n病原體血清 已分離菌 子之棉棒採集 (B 類感 後儘速送驗。\n炎鏈球菌 菌株\n型別檢測 株時 菌株,插Amies 染性物質 2. 見2.8.6 備註\n感染症\nw/charcoal 保 包裝) 說 明 及 圖\n存輸送培管。 2.4。",
    "english_name": "Invasive Pneumococcal Disease",
    "suspected_case": "NA。",
    "probable_case": "NA。",
    "confirmed_case": "符合臨床條件及檢驗條件者。"
  },
  {
    "name": "傷寒",
    "url": "https://www.cdc.gov.tw/File/Get/Pn3HWw3c_8qhl_pM-mpfXg",
    "source_category": "第二類",
    "content": "傷寒\n(Typhoid Fever)\n一、 臨床條件\n具有下列任一個條件:\n(一) 持續性發燒。\n(二) 頭痛、不適、厭食。\n(三) 相對性心跳過慢。\n(四) 脾臟腫大。\n(五) 身軀出現紅疹。\n(六) 成年人較常出現便秘或腹瀉、淋巴組織病變。\n感染者也可能只有輕微或非典型之症狀。\n二、 檢驗條件\n臨床檢體(糞便或血液)分離並鑑定出傷寒桿菌(Salmonella typhi)。\n三、 流行病學條件\n具有下列任一個條件\n(一) 食用被患者、帶菌者糞便或尿所污染之食物、飲水。\n(二) 與確定病例具有密切接觸(如照護、同住),或食用確定病例\n所烹調處理之食物。\n四、 通報定義\n具有下列任一個條件:\n(一) 符合臨床條件。\n(二) 經醫院自行檢驗,符合檢驗條件。\n五、 疾病分類\n(一) 可能病例:\nNA\n(二) 極可能病例:\nNA\n(三) 確定病例:\n符合檢驗條件。\n六、 檢體採檢送驗事項\n採檢項目 檢體種類 採檢目的 採檢時機 採檢規定 運送條件 注意事項\n以採血管採 5-10 mL\n未投藥前血液,立即注入含 50\n全血採檢步驟請參\n全血 之發燒期mL TSB或BHI培養基 常溫\n考第 3.1 節。\n間 之嗜氧血瓶內,充分混\n合。\n以無菌細菌拭子之棉\n棒,沾取混合均勻之糞 見 2.8.6 備註說明及\n糞便 便 檢 體 , 置 入 圖 2.5,糞便採檢步\nCary-Blair 保存輸送培 驟請參考第 3.5 節。\n養基。\n未投藥前 尿液檢體請參考第\n立即採檢 3.4 節。尿液檢體採\n病原體檢\n自下列患者:\n測\n以無菌容器收集 10mL 1. 確定合併感染埃\n尿液\n傷寒 中段尿液。 及血吸蟲患者\n低溫\n2. 無症狀帶菌者或\n慢性帶菌者中尿\n液帶菌者\n以無菌容器或採水袋\n收集1 L以上可疑污染\n自來水環\n源水檢體,每 1 L 加\n境檢體\n0.05 g 硫代硫酸鈉\n(sodium thiosulfate)\n井水、水 以無菌容器或採水袋 傷寒、副傷寒流行病\n溝水等環 收集1 L以上可疑污染 學調查時的檢體。\n境檢體 源水檢體。\n菌株鑑定 儘速送驗 純化之菌株以拭子沾 低溫(B\n滿 一 圈 後 置 入類感染性\n菌株\nCary-Blair 輸送培養 物質包\n基。 裝)",
    "pdf_path": "pdfs/傷寒.pdf",
    "臨床條件": "具有下列任一個條件:\n(一) 持續性發燒。\n(二) 頭痛、不適、厭食。\n(三) 相對性心跳過慢。\n(四) 脾臟腫大。\n(五) 身軀出現紅疹。\n(六) 成年人較常出現便秘或腹瀉、淋巴組織病變。\n感染者也可能只有輕微或非典型之症狀。",
    "檢驗條件": "臨床檢體(糞便或血液)分離並鑑定出傷寒桿菌(Salmonella typhi)。",
    "流行病學條件": "具有下列任一個條件\n(一) 食用被患者、帶菌者糞便或尿所污染之食物、飲水。\n(二) 與確定病例具有密切接觸(如照護、同住),或食用確定病例\n所烹調處理之食物。",
    "通報定義": "具有下列任一個條件:\n(一) 符合臨床條件。\n(二) 經醫院自行檢驗,符合檢驗條件。",
    "疾病分類": "(一) 可能病例:\nNA\n(二) 極可能病例:\nNA\n(三) 確定病例:\n符合檢驗條件。",
    "檢體採檢送驗事項": "採檢項目 檢體種類 採檢目的 採檢時機 採檢規定 運送條件 注意事項\n以採血管採 5-10 mL\n未投藥前血液,立即注入含 50\n全血採檢步驟請參\n全血 之發燒期mL TSB或BHI培養基 常溫\n考第 3.1 節。\n間 之嗜氧血瓶內,充分混\n合。\n以無菌細菌拭子之棉\n棒,沾取混合均勻之糞 見 2.8.6 備註說明及\n糞便 便 檢 體 , 置 入 圖 2.5,糞便採檢步\nCary-Blair 保存輸送培 驟請參考第 3.5 節。\n養基。\n未投藥前 尿液檢體請參考第\n立即採檢 3.4 節。尿液檢體採\n病原體檢\n自下列患者:\n測\n以無菌容器收集 10mL 1. 確定合併感染埃\n尿液\n傷寒 中段尿液。 及血吸蟲患者\n低溫\n2. 無症狀帶菌者或\n慢性帶菌者中尿\n液帶菌者\n以無菌容器或採水袋\n收集1 L以上可疑污染\n自來水環\n源水檢體,每 1 L 加\n境檢體\n0.05 g 硫代硫酸鈉\n(sodium thiosulfate)\n井水、水 以無菌容器或採水袋 傷寒、副傷寒流行病\n溝水等環 收集1 L以上可疑污染 學調查時的檢體。\n境檢體 源水檢體。\n菌株鑑定 儘速送驗 純化之菌株以拭子沾 低溫(B\n滿 一 圈 後 置 入類感染性\n菌株\nCary-Blair 輸送培養 物質包\n基。 裝)",
    "english_name": "Typhoid Fever",
    "suspected_case": "NA",
    "probable_case": "NA",
    "confirmed_case": "符合檢驗條件。"
  },
  {
    "name": "先天性德國麻疹症候群",
    "url": "https://www.cdc.gov.tw/File/Get/Ko9aOjafsd6CnhUnprfoNA",
    "source_category": "第三類",
    "content": "先天性德國麻疹症候群\n(Congenital Rubella Syndrome)\n一、 臨床條件\n小於一歲孩童或死產嬰兒,出現第一項之任何一種缺陷及第二項之任\n何一種缺陷,或第一項中之任兩種缺陷者。\n(一) 先天性白內障、先天性青光眼、色素性視網膜病變、失聰、先\n天性心臟病(常見:開放性動脈導管、周邊肺動脈狹窄)。\n(二) 紫斑症、閉塞性黃疸(24 小時內發生)、脾腫大、小腦症、心\n智發育遲緩、腦膜腦炎或長骨放射線透度異常。\n二、 檢驗條件\n具有下列任一個條件:\n(一) 臨床檢體(尿液、咽喉擦拭液、血液或臍帶血)分離並鑑定出\n德國麻疹病毒(Rubella virus)。\n(二) 臨床檢體分子生物學核酸檢測陽性。\n(三) 血清學抗體檢測陽性:排除疫苗接種影響下,抗德國麻疹 IgM\n抗體陽性或 IgG 抗體未如預期隨著時間逐漸衰減。\n三、 流行病學條件\n母親於孕期中被確診德國麻疹。\n四、 通報定義\n符合臨床條件。\n五、 疾病分類\n為配合三麻一風疾病根除保全與消除作業,個案需由防疫醫師進行判\n定。\n(一) 可能病例:\n符合臨床條件。\n(二) 極可能病例:\nNA\n(三) 確定病例:\n具有下列任一個條件:\n1. 符合臨床條件(第一項中任二種缺陷;或第一、二項中任\n一種)與檢驗條件。\n2. 符合臨床條件及流行病學條件。\n3. 任何死產嬰兒,排除其他可能致死原因並符合檢驗條件。\n六、 檢體採檢送驗事項\n採檢項目 檢體種類 採檢目的 採檢時機 採檢規定 運送條件 注意事項\n以無菌容器收集 尿液檢體採檢請\n尿液 10-50 mL 尿液, 參考第 3.4 節。\n緊密封口。\n出生後3個\n病原體檢測 以無菌病毒拭子 低溫 見 2.8.5 備註說明\n月內\n咽喉擦拭 之 棉 棒 擦 拭 咽 及咽喉採檢步驟\n液 喉,插入病毒保存 請參考第3.7節及\n輸送管。 圖 3.7。\n1. 疑似個案必\n先天性德\n要時得於其後\n國麻疹症\n3-6 個月內再採\n候群\n第 2 次血清送\n驗,血清量至少\n血清或臍 出生後6個以無菌試管收集\n抗體檢測 低溫 1 mL。\n帶血 月內 至少 2 mL 血清。\n2. 血清檢體見\n2.8.3及2.8.4備\n註說明,血清採\n檢步驟請參考第\n3.3 節。",
    "pdf_path": "pdfs/先天性德國麻疹症候群.pdf",
    "臨床條件": "小於一歲孩童或死產嬰兒,出現第一項之任何一種缺陷及第二項之任\n何一種缺陷,或第一項中之任兩種缺陷者。\n(一) 先天性白內障、先天性青光眼、色素性視網膜病變、失聰、先\n天性心臟病(常見:開放性動脈導管、周邊肺動脈狹窄)。\n(二) 紫斑症、閉塞性黃疸(24 小時內發生)、脾腫大、小腦症、心\n智發育遲緩、腦膜腦炎或長骨放射線透度異常。",
    "檢驗條件": "具有下列任一個條件:\n(一) 臨床檢體(尿液、咽喉擦拭液、血液或臍帶血)分離並鑑定出\n德國麻疹病毒(Rubella virus)。\n(二) 臨床檢體分子生物學核酸檢測陽性。\n(三) 血清學抗體檢測陽性:排除疫苗接種影響下,抗德國麻疹 IgM\n抗體陽性或 IgG 抗體未如預期隨著時間逐漸衰減。",
    "流行病學條件": "母親於孕期中被確診德國麻疹。",
    "通報定義": "符合臨床條件。",
    "疾病分類": "為配合三麻一風疾病根除保全與消除作業,個案需由防疫醫師進行判\n定。\n(一) 可能病例:\n符合臨床條件。\n(二) 極可能病例:\nNA\n(三) 確定病例:\n具有下列任一個條件:\n1. 符合臨床條件(第一項中任二種缺陷;或第一、二項中任\n一種)與檢驗條件。\n2. 符合臨床條件及流行病學條件。\n3. 任何死產嬰兒,排除其他可能致死原因並符合檢驗條件。",
    "檢體採檢送驗事項": "採檢項目 檢體種類 採檢目的 採檢時機 採檢規定 運送條件 注意事項\n以無菌容器收集 尿液檢體採檢請\n尿液 10-50 mL 尿液, 參考第 3.4 節。\n緊密封口。\n出生後3個\n病原體檢測 以無菌病毒拭子 低溫 見 2.8.5 備註說明\n月內\n咽喉擦拭 之 棉 棒 擦 拭 咽 及咽喉採檢步驟\n液 喉,插入病毒保存 請參考第3.7節及\n輸送管。 圖 3.7。\n1. 疑似個案必\n先天性德\n要時得於其後\n國麻疹症\n3-6 個月內再採\n候群\n第 2 次血清送\n驗,血清量至少\n血清或臍 出生後6個以無菌試管收集\n抗體檢測 低溫 1 mL。\n帶血 月內 至少 2 mL 血清。\n2. 血清檢體見\n2.8.3及2.8.4備\n註說明,血清採\n檢步驟請參考第\n3.3 節。",
    "english_name": "Congenital Rubella Syndrome",
    "suspected_case": "符合臨床條件。",
    "probable_case": "NA",
    "confirmed_case": "具有下列任一個條件:\n1. 符合臨床條件(第一項中任二種缺陷;或第一、二項中任\n一種)與檢驗條件。\n2. 符合臨床條件及流行病學條件。\n3. 任何死產嬰兒,排除其他可能致死原因並符合檢驗條件。"
  },
  {
    "name": "先天性梅毒",
    "url": "https://www.cdc.gov.tw/File/Get/_YwDhdbXL-TlhtfPK9-mMw",
    "source_category": "第三類",
    "content": "先天性梅毒\n(Congenital Syphilis)\n一、 臨床條件\n出現下列任一項症狀或症候:\n鼻塞伴黏性或血性分泌物、肝脾腫大、皮膚黏膜病變、扁平濕疣、非病\n毒性肝炎引起之黃疸、腎病症候群或營養不良引起之水腫、假性麻痺、\n影像學上可見長骨異常(如:骨膜炎、幹骺端(Metaphysis)病變包含\nWegner sign、 Metaphyseal serration、 Wimberger sign)等。\n二、 檢驗條件\n(一) 血清學特異性梅毒螺旋體試驗(treponemal test)1陽性。\n(二) 血清學非特異性梅毒螺旋體試驗(non-treponemal test)2陽性。\n(三) 臨床檢體(病灶滲出液、組織、胎盤、臍帶、屍體、鼻腔分泌物\n等)以暗視野顯微鏡、螢光抗體檢驗或核酸檢驗檢測出梅毒螺\n旋體。\n(四) 血清學特異性梅毒螺旋體 IgM 試驗(treponemal-specific IgM)\n3陽性。\n(五) 腦脊髓液性病研究實驗室試驗(CSF-VDRL)陽性。\n註1: 特異性梅毒螺旋體試驗(treponemal test):梅毒螺旋體血液凝集試驗\n(TPHA)、梅毒螺旋體粒子凝集試驗(TPPA)、梅毒抗體間接螢光染色法\n(FTA-abs)、梅毒螺旋體乳膠凝集試驗(TPLA)、梅毒螺旋體酵素免疫分\n析法(EIA)或梅毒螺旋體化學冷光免疫分析法(CIA)。\n註2: 非特異性梅毒螺旋體試驗(non-treponemal test):快速血漿反應素試驗\n(RPR)或性病研究實驗室試驗(VDRL)。\n註3: 特異性梅毒螺旋體IgM試驗(treponemal-specific IgM):梅毒螺旋體IgM\n酵素免疫分析法(IgM EIA)或梅毒IgM抗體間接螢光染色法(IgM FTA-\nabs)。\n三、 流行病學條件\n(一) 其生母為梅毒個案,但生產時未治療、尚未完成治療、治療狀況\n不明或已接受治療但 RPR/VDRL 效價尚未呈現 4 倍以上下降。\n(二) 其生母之梅毒病史不清楚。\n四、 通報定義\n年齡未滿 24 個月,且具有下列任一個條件:\n(一) 符合流行病學條件第(一)項。\n(二) 符合流行病學條件第(二)項及任一檢驗條件。\n(三) 符合臨床條件及任一檢驗條件。\n五、 疾病分類\n(一) 可能病例:\nNA\n(二) 極可能病例:\n具有下列任一個條件:\n1. 符合流行病學條件第(一)項。\n2. 符合流行病學條件第(二)項,且符合檢驗條件第(一)、(二)、\n(四)、(五)之任一項。\n3. 符合臨床條件,且符合檢驗條件第(一)、(二)、(四)、(五)之任\n一項。\n(三) 確定病例:\n具有下列任一個條件:\n1. 符合檢驗條件第(二)項及第(四)項。\n2. 符合檢驗條件第(二)項,且嬰兒效價大於母親生產時效價之四\n倍以上。\n3. 符合檢驗條件第(三)項。\n4. 符合檢驗條件第(五)項,且腦脊髓液符合下列任一項細胞計數\n和生化檢查異常情形:\n(1) 年齡未滿 1 個月:>15 WBC/microL, protein >120 mg/dL\n(2) 年齡 1 個月以上:>5 WBC/microL, protein >40 mg/dL\n5. 年齡 15 個月以上,符合檢驗條件第(一)項,且排除後天梅毒\n暴露史。",
    "pdf_path": "pdfs/先天性梅毒.pdf",
    "臨床條件": "出現下列任一項症狀或症候:\n鼻塞伴黏性或血性分泌物、肝脾腫大、皮膚黏膜病變、扁平濕疣、非病\n毒性肝炎引起之黃疸、腎病症候群或營養不良引起之水腫、假性麻痺、\n影像學上可見長骨異常(如:骨膜炎、幹骺端(Metaphysis)病變包含\nWegner sign、 Metaphyseal serration、 Wimberger sign)等。",
    "檢驗條件": "(一) 血清學特異性梅毒螺旋體試驗(treponemal test)1陽性。\n(二) 血清學非特異性梅毒螺旋體試驗(non-treponemal test)2陽性。\n(三) 臨床檢體(病灶滲出液、組織、胎盤、臍帶、屍體、鼻腔分泌物\n等)以暗視野顯微鏡、螢光抗體檢驗或核酸檢驗檢測出梅毒螺\n旋體。\n(四) 血清學特異性梅毒螺旋體 IgM 試驗(treponemal-specific IgM)\n3陽性。\n(五) 腦脊髓液性病研究實驗室試驗(CSF-VDRL)陽性。\n註1: 特異性梅毒螺旋體試驗(treponemal test):梅毒螺旋體血液凝集試驗\n(TPHA)、梅毒螺旋體粒子凝集試驗(TPPA)、梅毒抗體間接螢光染色法\n(FTA-abs)、梅毒螺旋體乳膠凝集試驗(TPLA)、梅毒螺旋體酵素免疫分\n析法(EIA)或梅毒螺旋體化學冷光免疫分析法(CIA)。\n註2: 非特異性梅毒螺旋體試驗(non-treponemal test):快速血漿反應素試驗\n(RPR)或性病研究實驗室試驗(VDRL)。\n註3: 特異性梅毒螺旋體IgM試驗(treponemal-specific IgM):梅毒螺旋體IgM\n酵素免疫分析法(IgM EIA)或梅毒IgM抗體間接螢光染色法(IgM FTA-\nabs)。",
    "流行病學條件": "(一) 其生母為梅毒個案,但生產時未治療、尚未完成治療、治療狀況\n不明或已接受治療但 RPR/VDRL 效價尚未呈現 4 倍以上下降。\n(二) 其生母之梅毒病史不清楚。",
    "通報定義": "年齡未滿 24 個月,且具有下列任一個條件:\n(一) 符合流行病學條件第(一)項。\n(二) 符合流行病學條件第(二)項及任一檢驗條件。\n(三) 符合臨床條件及任一檢驗條件。",
    "疾病分類": "(一) 可能病例:\nNA\n(二) 極可能病例:\n具有下列任一個條件:\n1. 符合流行病學條件第(一)項。\n2. 符合流行病學條件第(二)項,且符合檢驗條件第(一)、(二)、\n(四)、(五)之任一項。\n3. 符合臨床條件,且符合檢驗條件第(一)、(二)、(四)、(五)之任\n一項。\n(三) 確定病例:\n具有下列任一個條件:\n1. 符合檢驗條件第(二)項及第(四)項。\n2. 符合檢驗條件第(二)項,且嬰兒效價大於母親生產時效價之四\n倍以上。\n3. 符合檢驗條件第(三)項。\n4. 符合檢驗條件第(五)項,且腦脊髓液符合下列任一項細胞計數\n和生化檢查異常情形:\n(1) 年齡未滿 1 個月:>15 WBC/microL, protein >120 mg/dL\n(2) 年齡 1 個月以上:>5 WBC/microL, protein >40 mg/dL\n5. 年齡 15 個月以上,符合檢驗條件第(一)項,且排除後天梅毒\n暴露史。",
    "檢體採檢送驗事項": "",
    "english_name": "Congenital Syphilis",
    "suspected_case": "NA",
    "probable_case": "具有下列任一個條件:\n1. 符合流行病學條件第(一)項。\n2. 符合流行病學條件第(二)項,且符合檢驗條件第(一)、(二)、\n(四)、(五)之任一項。\n3. 符合臨床條件,且符合檢驗條件第(一)、(二)、(四)、(五)之任\n一項。",
    "confirmed_case": "具有下列任一個條件:\n1. 符合檢驗條件第(二)項及第(四)項。\n2. 符合檢驗條件第(二)項,且嬰兒效價大於母親生產時效價之四\n倍以上。\n3. 符合檢驗條件第(三)項。\n4. 符合檢驗條件第(五)項,且腦脊髓液符合下列任一項細胞計數\n和生化檢查異常情形:\n(1) 年齡未滿 1 個月:>15 WBC/microL, protein >120 mg/dL\n(2) 年齡 1 個月以上:>5 WBC/microL, protein >40 mg/dL\n5. 年齡 15 個月以上,符合檢驗條件第(一)項,且排除後天梅毒\n暴露史。"
  },
  {
    "name": "兔熱病",
    "url": "https://www.cdc.gov.tw/File/Get/lBi3fC8Mtdmw4Ac7n8mMtw",
    "source_category": "第四類",
    "content": "兔熱病\nTularemia\n( )\n一、 臨床條件\n突然出現高燒、寒顫、頭痛、疲倦、肌肉痛、感染部位疼痛,並伴有\n盜汗。若不及時治療,疾病可遞延數月。病程期間常伴有淋巴結和肝\n脾腫大、食慾減退等現象。根據感染方式和部位,可分為:\n(一) 潰瘍腺體型(ulceroglandular type):\n伴隨局部性淋巴結腫大的皮膚潰瘍,此型最為常見,一般係由\n叮咬感染,佔發病總數的 75%至 85%。在病原入侵處會產生\n一小潰瘍,輕度疼痛,皮膚可見發炎、膿瘍性丘疹,之後潰瘍\n附近的腋下或腹股溝淋巴結腫大或壞死,50%經 1 至 2 個月\n後消退。偶而會有淋巴結破潰流膿、傷口經久不癒的病患。\n(二) 腺體型(glandular type):\n有一個或以上腫大疼痛的淋巴結,但無原發性皮膚潰瘍。\n(三) 眼部及口咽型(oculoglandular type and oropharyngeal\ntype):\n發膿結膜炎,眼瞼有黃色的肉芽腫,並伴隨耳前淋巴腺炎;咽\n頭炎或扁桃腺炎並伴隨頸部淋巴腺炎;眼結膜及咽部潰瘍,頸\n或頜下淋巴結腫大或化膿,形成潰瘍,其膿液可培養出土倫病\n菌。\n(四) 胃腸型(intestinal type):\n係由攝食被污染的食物或水而感染,細菌經小腸黏膜侵入。除\n會發冷、發熱外,還會有腹痛、噁心、嘔吐、腹瀉、腸道膜淋\n巴結腫大等現象,偶有腹膜炎。\n(五) 肋膜肺部型(pleuropulmonary type):\n經血液感染,細菌侵入肺部及肋膜腔。病徵為咳嗽、少痰、胸\n骨壓痛。可能併發支氣管發炎、肺炎、肺囊腫、初級肺肋膜病\n變或胸膜炎等,肺門淋巴結異常腫大。\n(六) 類傷寒型(typhoidal type):\n臨床表現似傷寒,肝脾腫大,血液培養陽性,病情較重,致死\n率高;符合上述臨床症狀,且有節肢動物叮咬、與感染病原哺\n乳類宿主之接觸史、或接觸可能受污染的水等暴露史。\n二、 檢驗條件\n具有下列任一個條件:\n(一) 臨床檢體(皮膚病灶、胃抽出液、淋巴結抽出液或切片、鼻咽\n沖洗液或痰)分離並鑑定出土拉倫法氏菌(Francisella\ntularensis)。\n(二) 血清學抗體檢測陽性:恢復期血清較急性期血清抗體效價≧4\n倍上升。\n三、 流行病學條件\n具有下列任一個條件:\n(一) 遭帶病原之壁蝨、鹿蠅等吸血性節肢動物叮咬。\n(二) 曾接觸嚙齒類動物,或處理受污染之動物、屍體、毛皮、排泄\n物。\n(三) 食用或飲用受污染的食物、水,或吸入空中的致病原。\n四、 通報定義\n符合臨床條件及流行病學條件。\n五、 疾病分類\n(一) 可能病例:\nNA\n(二) 極可能病例:\nNA\n(三) 確定病例:\n符合臨床條件及檢驗條件。\n六、 檢體採檢送驗事項\n採檢項目 檢體種類 採檢目的 採檢時間 採檢量及規定 送驗方式 注意事項\n1. 若無法取得急性期之血\n清,請改採至少間隔 7\n急性期(發病 天之恢復期血清 2 次。\n7 天內) 以無菌試管收集 2. 檢體勿加入任何添加\n血清 抗體檢測 ;恢復期(發\n病14-20天之\n3 mL血清。\n物。\n間) 3. 血清檢體見 2.8.3 及\n兔熱病 低溫 2.8.4 備註說明,血清採\n檢步驟請參考第 3.3 節\n純化之菌株以拭\n病原體鑑已分離菌株子沾滿一圈後置 本菌傳染性高,應謹慎操\n菌株\n定 時 入Cary-Blair保 作。\n存輸送培養基。",
    "pdf_path": "pdfs/兔熱病.pdf",
    "臨床條件": "突然出現高燒、寒顫、頭痛、疲倦、肌肉痛、感染部位疼痛,並伴有\n盜汗。若不及時治療,疾病可遞延數月。病程期間常伴有淋巴結和肝\n脾腫大、食慾減退等現象。根據感染方式和部位,可分為:\n(一) 潰瘍腺體型(ulceroglandular type):\n伴隨局部性淋巴結腫大的皮膚潰瘍,此型最為常見,一般係由\n叮咬感染,佔發病總數的 75%至 85%。在病原入侵處會產生\n一小潰瘍,輕度疼痛,皮膚可見發炎、膿瘍性丘疹,之後潰瘍\n附近的腋下或腹股溝淋巴結腫大或壞死,50%經 1 至 2 個月\n後消退。偶而會有淋巴結破潰流膿、傷口經久不癒的病患。\n(二) 腺體型(glandular type):\n有一個或以上腫大疼痛的淋巴結,但無原發性皮膚潰瘍。\n(三) 眼部及口咽型(oculoglandular type and oropharyngeal\ntype):\n發膿結膜炎,眼瞼有黃色的肉芽腫,並伴隨耳前淋巴腺炎;咽\n頭炎或扁桃腺炎並伴隨頸部淋巴腺炎;眼結膜及咽部潰瘍,頸\n或頜下淋巴結腫大或化膿,形成潰瘍,其膿液可培養出土倫病\n菌。\n(四) 胃腸型(intestinal type):\n係由攝食被污染的食物或水而感染,細菌經小腸黏膜侵入。除\n會發冷、發熱外,還會有腹痛、噁心、嘔吐、腹瀉、腸道膜淋\n巴結腫大等現象,偶有腹膜炎。\n(五) 肋膜肺部型(pleuropulmonary type):\n經血液感染,細菌侵入肺部及肋膜腔。病徵為咳嗽、少痰、胸\n骨壓痛。可能併發支氣管發炎、肺炎、肺囊腫、初級肺肋膜病\n變或胸膜炎等,肺門淋巴結異常腫大。\n(六) 類傷寒型(typhoidal type):\n臨床表現似傷寒,肝脾腫大,血液培養陽性,病情較重,致死\n率高;符合上述臨床症狀,且有節肢動物叮咬、與感染病原哺\n乳類宿主之接觸史、或接觸可能受污染的水等暴露史。",
    "檢驗條件": "具有下列任一個條件:\n(一) 臨床檢體(皮膚病灶、胃抽出液、淋巴結抽出液或切片、鼻咽\n沖洗液或痰)分離並鑑定出土拉倫法氏菌(Francisella\ntularensis)。\n(二) 血清學抗體檢測陽性:恢復期血清較急性期血清抗體效價≧4\n倍上升。",
    "流行病學條件": "具有下列任一個條件:\n(一) 遭帶病原之壁蝨、鹿蠅等吸血性節肢動物叮咬。\n(二) 曾接觸嚙齒類動物,或處理受污染之動物、屍體、毛皮、排泄\n物。\n(三) 食用或飲用受污染的食物、水,或吸入空中的致病原。",
    "通報定義": "符合臨床條件及流行病學條件。",
    "疾病分類": "(一) 可能病例:\nNA\n(二) 極可能病例:\nNA\n(三) 確定病例:\n符合臨床條件及檢驗條件。",
    "檢體採檢送驗事項": "採檢項目 檢體種類 採檢目的 採檢時間 採檢量及規定 送驗方式 注意事項\n1. 若無法取得急性期之血\n清,請改採至少間隔 7\n急性期(發病 天之恢復期血清 2 次。\n7 天內) 以無菌試管收集 2. 檢體勿加入任何添加\n血清 抗體檢測 ;恢復期(發\n病14-20天之\n3 mL血清。\n物。\n間) 3. 血清檢體見 2.8.3 及\n兔熱病 低溫 2.8.4 備註說明,血清採\n檢步驟請參考第 3.3 節\n純化之菌株以拭\n病原體鑑已分離菌株子沾滿一圈後置 本菌傳染性高,應謹慎操\n菌株\n定 時 入Cary-Blair保 作。\n存輸送培養基。",
    "english_name": "Tularemia",
    "suspected_case": "NA",
    "probable_case": "NA",
    "confirmed_case": "符合臨床條件及檢驗條件。"
  },
  {
    "name": "副傷寒",
    "url": "https://www.cdc.gov.tw/File/Get/2nVvks5ZQwbyITYFo4t0qA",
    "source_category": "第二類",
    "content": "副傷寒\n(Paratyphoid Fever)\n一、 臨床條件\n具有下列任一個條件:\n(一) 持續性發燒。\n(二) 頭痛、不適、厭食。\n(三) 相對性心跳過慢。\n(四) 脾臟腫大。\n(五) 身軀出現紅疹。\n(六) 成年人較常出現便秘或腹瀉、淋巴組織病變。\n感染者也可能只有輕微或非典型之症狀。\n二、 檢驗條件\n臨床檢體(糞便或血液)分離並鑑定出副傷寒桿菌(Salmonella\nparatyphi A)。\n三、 流行病學條件\n具有下列任一個條件\n(一) 食用被患者、帶菌者糞便或尿所污染之食物、飲水。\n(二) 與確定病例具有密切接觸(如照護、同住),或食用確定病例\n所烹調處理之食物。\n四、 通報定義\n具有下列任一個條件:\n(一) 符合臨床條件。\n(二) 經醫院自行檢驗,符合檢驗條件。\n五、 疾病分類\n(一) 可能病例:\nNA\n(二) 極可能病例:\nNA\n(三) 確定病例:\n符合檢驗條件。\n六、 檢體採檢送驗事項\n採檢項目 檢體種類 採檢目的 採檢時機 採檢規定 運送條件 注意事項\n以採血管採 5-10 mL\n未投藥前血液,立即注入含 50\n全血採檢步驟請參\n全血 之發燒期mL TSB或BHI培養基 常溫\n考第 3.1 節。\n間 之嗜氧血瓶內,充分混\n合。\n以無菌細菌拭子之棉\n棒,沾取混合均勻之糞 見 2.8.6 備註說明及\n糞便 便 檢 體 , 置 入 圖 2.5,糞便採檢步\nCary-Blair 保存輸送培 驟請參考第 3.5 節。\n養基。\n未投藥前 尿液檢體請參考第\n立即採檢 3.4 節。尿液檢體採\n病原體檢\n自下列患者:\n測\n以無菌容器收集 10mL 1. 確定合併感染埃\n尿液\n副傷寒 中段尿液。 及血吸蟲患者\n低溫\n2. 無症狀帶菌者或\n慢性帶菌者中尿\n液帶菌者\n以無菌容器或採水袋\n收集1 L以上可疑污染\n自來水環\n源水檢體,每 1 L 加\n境檢體\n0.05 g 硫代硫酸鈉\n(sodium thiosulfate)\n井水、水 以無菌容器或採水袋 傷寒、副傷寒流行病\n溝水等環 收集1 L以上可疑污染 學調查時的檢體。\n境檢體 源水檢體。\n菌株鑑定 儘速送驗 純化之菌株以拭子沾 低溫(B\n滿 一 圈 後 置 入類感染性\n菌株\nCary-Blair 輸送培養 物質包\n基。 裝)",
    "pdf_path": "pdfs/副傷寒.pdf",
    "臨床條件": "具有下列任一個條件:\n(一) 持續性發燒。\n(二) 頭痛、不適、厭食。\n(三) 相對性心跳過慢。\n(四) 脾臟腫大。\n(五) 身軀出現紅疹。\n(六) 成年人較常出現便秘或腹瀉、淋巴組織病變。\n感染者也可能只有輕微或非典型之症狀。",
    "檢驗條件": "臨床檢體(糞便或血液)分離並鑑定出副傷寒桿菌(Salmonella\nparatyphi A)。",
    "流行病學條件": "具有下列任一個條件\n(一) 食用被患者、帶菌者糞便或尿所污染之食物、飲水。\n(二) 與確定病例具有密切接觸(如照護、同住),或食用確定病例\n所烹調處理之食物。",
    "通報定義": "具有下列任一個條件:\n(一) 符合臨床條件。\n(二) 經醫院自行檢驗,符合檢驗條件。",
    "疾病分類": "(一) 可能病例:\nNA\n(二) 極可能病例:\nNA\n(三) 確定病例:\n符合檢驗條件。",
    "檢體採檢送驗事項": "採檢項目 檢體種類 採檢目的 採檢時機 採檢規定 運送條件 注意事項\n以採血管採 5-10 mL\n未投藥前血液,立即注入含 50\n全血採檢步驟請參\n全血 之發燒期mL TSB或BHI培養基 常溫\n考第 3.1 節。\n間 之嗜氧血瓶內,充分混\n合。\n以無菌細菌拭子之棉\n棒,沾取混合均勻之糞 見 2.8.6 備註說明及\n糞便 便 檢 體 , 置 入 圖 2.5,糞便採檢步\nCary-Blair 保存輸送培 驟請參考第 3.5 節。\n養基。\n未投藥前 尿液檢體請參考第\n立即採檢 3.4 節。尿液檢體採\n病原體檢\n自下列患者:\n測\n以無菌容器收集 10mL 1. 確定合併感染埃\n尿液\n副傷寒 中段尿液。 及血吸蟲患者\n低溫\n2. 無症狀帶菌者或\n慢性帶菌者中尿\n液帶菌者\n以無菌容器或採水袋\n收集1 L以上可疑污染\n自來水環\n源水檢體,每 1 L 加\n境檢體\n0.05 g 硫代硫酸鈉\n(sodium thiosulfate)\n井水、水 以無菌容器或採水袋 傷寒、副傷寒流行病\n溝水等環 收集1 L以上可疑污染 學調查時的檢體。\n境檢體 源水檢體。\n菌株鑑定 儘速送驗 純化之菌株以拭子沾 低溫(B\n滿 一 圈 後 置 入類感染性\n菌株\nCary-Blair 輸送培養 物質包\n基。 裝)",
    "english_name": "Paratyphoid Fever",
    "suspected_case": "NA",
    "probable_case": "NA",
    "confirmed_case": "符合檢驗條件。"
  },
  {
    "name": "嚴重急性呼吸道症候群",
    "url": "https://www.cdc.gov.tw/File/Get/kgKsgv6JsJ00Cwofil7W3g",
    "source_category": "第一類",
    "content": "嚴重急性呼吸道症候群\n(Severe Acute Respiratory Syndrome, SARS)\n一、 臨床條件\n同時具有下列四項條件:\n(一) 發燒(≧38°C)。\n(二) 一種或以上的下呼吸道症狀(咳嗽、呼吸困難、呼吸短促)。\n(三) 放射線診斷學上有與肺炎或呼吸窘迫症候群一致的肺浸潤的\n證據或者屍體解剖的發現與肺炎或呼吸窘迫症候群的病理學\n一致。\n(四) 無其他可替代的診斷能完全解釋疾病。\n二、 檢驗條件\n具有下列任一個條件:\n(一) 臨床檢體(咽喉擦拭液、痰液、糞便及血液)分離並鑑定出\nSARS-CoV 病毒。\n(二) 臨床檢體 SARS-CoV 分子生物學核酸檢測陽性。\n1. 至少二種不同之臨床檢體呈現陽性,比如:咽喉和糞便。\n2. 相同部位但在疾病過程中,二個或二個以上不同時間取得\n的檢體均呈現陽性,比如:一系列鼻咽部抽取液。\n3. 從臨床檢體萃取出的 RNA 做二次不同的檢驗或重新萃取\n的 RNA 進行重複 PCR 均呈陽性。\n(三) 血清學抗體檢測陽性:ELISA 或 IFA 檢測抗體陽轉\n(seroconversion)\n1. 急性期血清抗體陰性,但恢復期血清抗體呈陽性。\n2. 恢復期血清較急性期血清抗體效價≧4 倍上升。\n三、 流行病學條件\n發病前 10 日,具有下列任一個條件:\n(一) 有 SARS 流行地區(經 WHO 宣布)之旅遊史。\n(二) 有 SARS 確定病例之接觸史。\n(三) 有與活性 SARS 冠狀病毒及感染 SARS 冠狀病毒個案臨床檢\n體相關之暴露史。\n四、 通報定義\n具有下列任一個條件:\n(一) 符合臨床條件及流行病學條件。\n(二) 醫師或法醫師高度懷疑。\n五、 疾病分類\n(一) 可能病例:\n具有下列任一個條件:\n1. 符合臨床條件及流行病學條件。\n2. 未符合流行病學條件,但符合臨床條件,且為醫師高度懷\n疑。\n(二) 極可能病例:\n符合臨床條件,且與確定病例具有流行病學之關聯。\n(三) 確定病例:\n1. 兩次流行期之間:同時符合臨床條件、流行病學條件及檢\n驗條件。\n2. 爆發流行時:符合檢驗條件與流行病學條件第一項至第三\n項之任一條件。\n六、 檢體採檢送驗事項\n採檢項目 檢體種類 採檢目的 採檢時間 採檢量及規定 送驗方式 注意事項\n以無菌病毒拭子之 見2.8.5備註說明及咽\n咽喉擦拭\n棉棒擦拭咽喉,插入 喉採檢步驟請參考第\n液 發病\n病毒保存輸送管。 3.7 節及圖 3.7。\n病 原 體 檢5 天內\n以無菌容器收集排 痰液採檢步驟請參考\n痰液 測\n出之痰液。 第 3.9 節。\n嚴重急性\n發病 以糞便專用採檢瓶 見2.8.2備註說明及採\n呼吸道症 糞便\n7 天後 挖取約 1 g糞便。 低溫 檢步驟請見第 3.5 節。\n候群\n急性期 1. 血清檢體共需採檢\n(SARS)\n(發病 2 次。\n病原體檢\n1-5 天) 以無菌試管收集至 2. 血清檢體見2.8.3及\n血清 測;抗體檢\n;恢復期 少 3 mL血清。 2.8.4 備註說明及血\n測\n(發病 清採檢步驟請參考\n14-20 天) 第 3.3 節。",
    "pdf_path": "pdfs/嚴重急性呼吸道症候群.pdf",
    "臨床條件": "同時具有下列四項條件:\n(一) 發燒(≧38°C)。\n(二) 一種或以上的下呼吸道症狀(咳嗽、呼吸困難、呼吸短促)。\n(三) 放射線診斷學上有與肺炎或呼吸窘迫症候群一致的肺浸潤的\n證據或者屍體解剖的發現與肺炎或呼吸窘迫症候群的病理學\n一致。\n(四) 無其他可替代的診斷能完全解釋疾病。",
    "檢驗條件": "具有下列任一個條件:\n(一) 臨床檢體(咽喉擦拭液、痰液、糞便及血液)分離並鑑定出\nSARS-CoV 病毒。\n(二) 臨床檢體 SARS-CoV 分子生物學核酸檢測陽性。\n1. 至少二種不同之臨床檢體呈現陽性,比如:咽喉和糞便。\n2. 相同部位但在疾病過程中,二個或二個以上不同時間取得\n的檢體均呈現陽性,比如:一系列鼻咽部抽取液。\n3. 從臨床檢體萃取出的 RNA 做二次不同的檢驗或重新萃取\n的 RNA 進行重複 PCR 均呈陽性。\n(三) 血清學抗體檢測陽性:ELISA 或 IFA 檢測抗體陽轉\n(seroconversion)\n1. 急性期血清抗體陰性,但恢復期血清抗體呈陽性。\n2. 恢復期血清較急性期血清抗體效價≧4 倍上升。",
    "流行病學條件": "發病前 10 日,具有下列任一個條件:\n(一) 有 SARS 流行地區(經 WHO 宣布)之旅遊史。\n(二) 有 SARS 確定病例之接觸史。\n(三) 有與活性 SARS 冠狀病毒及感染 SARS 冠狀病毒個案臨床檢\n體相關之暴露史。",
    "通報定義": "具有下列任一個條件:\n(一) 符合臨床條件及流行病學條件。\n(二) 醫師或法醫師高度懷疑。",
    "疾病分類": "(一) 可能病例:\n具有下列任一個條件:\n1. 符合臨床條件及流行病學條件。\n2. 未符合流行病學條件,但符合臨床條件,且為醫師高度懷\n疑。\n(二) 極可能病例:\n符合臨床條件,且與確定病例具有流行病學之關聯。\n(三) 確定病例:\n1. 兩次流行期之間:同時符合臨床條件、流行病學條件及檢\n驗條件。\n2. 爆發流行時:符合檢驗條件與流行病學條件第一項至第三\n項之任一條件。",
    "檢體採檢送驗事項": "採檢項目 檢體種類 採檢目的 採檢時間 採檢量及規定 送驗方式 注意事項\n以無菌病毒拭子之 見2.8.5備註說明及咽\n咽喉擦拭\n棉棒擦拭咽喉,插入 喉採檢步驟請參考第\n液 發病\n病毒保存輸送管。 3.7 節及圖 3.7。\n病 原 體 檢5 天內\n以無菌容器收集排 痰液採檢步驟請參考\n痰液 測\n出之痰液。 第 3.9 節。\n嚴重急性\n發病 以糞便專用採檢瓶 見2.8.2備註說明及採\n呼吸道症 糞便\n7 天後 挖取約 1 g糞便。 低溫 檢步驟請見第 3.5 節。\n候群\n急性期 1. 血清檢體共需採檢\n(SARS)\n(發病 2 次。\n病原體檢\n1-5 天) 以無菌試管收集至 2. 血清檢體見2.8.3及\n血清 測;抗體檢\n;恢復期 少 3 mL血清。 2.8.4 備註說明及血\n測\n(發病 清採檢步驟請參考\n14-20 天) 第 3.3 節。",
    "english_name": "Severe Acute Respiratory Syndrome, SARS",
    "suspected_case": "具有下列任一個條件:\n1. 符合臨床條件及流行病學條件。\n2. 未符合流行病學條件,但符合臨床條件,且為醫師高度懷\n疑。",
    "probable_case": "符合臨床條件,且與確定病例具有流行病學之關聯。",
    "confirmed_case": "1. 兩次流行期之間:同時符合臨床條件、流行病學條件及檢\n驗條件。\n2. 爆發流行時:符合檢驗條件與流行病學條件第一項至第三\n項之任一條件。"
  },
  {
    "name": "地方性斑疹傷寒",
    "url": "https://www.cdc.gov.tw/File/Get/lmPoQ5hjEnjYd2HWX18VsQ",
    "source_category": "第四類",
    "content": "地方性斑疹性傷寒\n(Endemic Typhus Fever)\n一、 臨床條件\n有頭痛、惡寒、疲勞、發燒、全身疼痛及出疹等現象。\n二、 檢驗條件\n符合下列檢驗結果之任一項者,定義為檢驗結果陽性:\n(一) 臨床檢體(血液)分離並鑑定出莫氏立克次體(Rickettsia\ntyphi)。\n(二) 臨床檢體分子生物學核酸檢測陽性。\n(三) 以間接免疫螢光染色法( Indirect Immunofluorescene\nAssay,IFA)檢測急性期(或初次採檢)血清,IgM 抗體≧\n1:80 且 IgG 抗體≧1:320。\n(四) 以間接免疫螢光染色法,檢測配對(恢復期及急性期)血清,\n莫氏立克次體特異性IgG 抗體有陽轉或4 倍以上上升。\n三、 流行病學條件\nNA\n四、 通報定義\n符合臨床條件。\n五、 疾病分類\n(一) 可能病例:\nNA\n(二) 極可能病例:\nNA\n(三) 確定病例:\n符合檢驗結果陽性定義之任一項。\n六、 檢體採檢送驗事項\n採檢項目 檢體種類 採檢目的 採檢時間 採檢規定 運送條件 注意事項\n1.抗凝固全血採\n檢請參考傳染病\n以含抗凝劑\n檢體採檢手冊第\n抗凝固全 病原體檢 急性期且未\n(heparin或\nEDTA)採血管採 3.2節。\n血 測\n投藥前\n集5-10 mL靜脈\n2.血清勿加入任\n血,並混合均勻 2-8°C(B\n類感染性 何添加物。\n物質包裝)\n3.血清檢體見傳\n地方性斑\n染病檢體採檢手\n疹傷寒\n冊2.8.3及2.8.4\n備註說明及採檢\n步驟見第3.3節。\n立即採檢 以無菌試管收集\n血清 抗體檢測\n3 mL血清 4.以不做二採為\n原則,如有臨床上\n個別需要,請連繫\n檢體單一窗口。",
    "pdf_path": "pdfs/地方性斑疹傷寒.pdf",
    "臨床條件": "有頭痛、惡寒、疲勞、發燒、全身疼痛及出疹等現象。",
    "檢驗條件": "符合下列檢驗結果之任一項者,定義為檢驗結果陽性:\n(一) 臨床檢體(血液)分離並鑑定出莫氏立克次體(Rickettsia\ntyphi)。\n(二) 臨床檢體分子生物學核酸檢測陽性。\n(三) 以間接免疫螢光染色法( Indirect Immunofluorescene\nAssay,IFA)檢測急性期(或初次採檢)血清,IgM 抗體≧\n1:80 且 IgG 抗體≧1:320。\n(四) 以間接免疫螢光染色法,檢測配對(恢復期及急性期)血清,\n莫氏立克次體特異性IgG 抗體有陽轉或4 倍以上上升。",
    "流行病學條件": "NA",
    "通報定義": "符合臨床條件。",
    "疾病分類": "(一) 可能病例:\nNA\n(二) 極可能病例:\nNA\n(三) 確定病例:\n符合檢驗結果陽性定義之任一項。",
    "檢體採檢送驗事項": "採檢項目 檢體種類 採檢目的 採檢時間 採檢規定 運送條件 注意事項\n1.抗凝固全血採\n檢請參考傳染病\n以含抗凝劑\n檢體採檢手冊第\n抗凝固全 病原體檢 急性期且未\n(heparin或\nEDTA)採血管採 3.2節。\n血 測\n投藥前\n集5-10 mL靜脈\n2.血清勿加入任\n血,並混合均勻 2-8°C(B\n類感染性 何添加物。\n物質包裝)\n3.血清檢體見傳\n地方性斑\n染病檢體採檢手\n疹傷寒\n冊2.8.3及2.8.4\n備註說明及採檢\n步驟見第3.3節。\n立即採檢 以無菌試管收集\n血清 抗體檢測\n3 mL血清 4.以不做二採為\n原則,如有臨床上\n個別需要,請連繫\n檢體單一窗口。",
    "english_name": "Endemic Typhus Fever",
    "suspected_case": "NA",
    "probable_case": "NA",
    "confirmed_case": "符合檢驗結果陽性定義之任一項。"
  },
  {
    "name": "多重抗藥性結核病",
    "url": "https://www.cdc.gov.tw/File/Get/cnGwiX4fGbsDwBX0dL5mgQ",
    "source_category": "第二類",
    "content": "多重抗藥性結核病\n(Multidrug-Resistant Tuberculosis)\n一、 臨床條件\n(一)具有結核病之徵候或症狀如長期咳嗽、體重減輕、發燒等,\n或胸部 X 光顯示疑似結核病灶。\n(二)經抗結核藥物治療後臨床症狀或徵候之表現,無明顯改善,\n懷疑為多重抗藥性結核病。\n二、 檢驗條件\n具下列任一條件:\n(一)臨床檢體(如痰、肋膜液、胃洗液、支氣管沖洗液、組織\n切片等)培養後,菌株經鑑定為結核菌群(Mycobacterium\ntuberculosis complex),且藥物感受性試驗顯示至少同時對\nisoniazid 及 rifampicin 具抗藥性。\n(二)臨床檢體或鑑定為結核菌群(Mycobacterium tuberculosis\ncomplex)之菌株,經分子檢測顯示至少同時對 isoniazid 及\nrifampicin 具抗藥性。\n三、 流行病學條件\n(一)具有與多重抗藥性結核病確定病例之接觸史。\n(二)醫師依據病史認為復發個案;或經抗結核藥物治療後失敗\n或失落個案。\n(三)居住於國內抗藥性高風險地區或具有 WHO 公布之結核\n病或多重抗藥性結核病高負擔國家旅遊。\n四、 通報定義\n符合檢驗條件且已通報結核病。\n五、 疾病分類\n(一)可能病例:\nNA\n(二)極可能病例:\n符合檢驗條件。\n(三)確定病例:\n同時具備下列兩項條件:\n1. 符合極可能病例。\n2. 藥物感受性試驗檢驗單位,傳統檢測須為疾病管制署\n或多重抗藥性結核病認可實驗室,分子檢測須為疾病\n管制署或指定實驗室。\n六、 檢體採檢送驗事項\n傳染病 檢體種類 採檢目的 採檢時間 採檢量及規定 送驗方式 應保存種類 注 意\n名稱 (應保存時間) 事項\n病原體檢\n測、藥物 2-8°C\n臨床檢體 菌株(2年)\n感受性試 詳傳染病檢體 (B 類感\n驗 採檢手冊 3.9 染性物質\n初次驗痰 痰液檢體 P650 包\n多重抗藥 (未服藥 裝)\n臨床檢體\n性結核病 前)或\n分子病原\n配合案例\n菌株 體檢測、 詳傳染病檢體 2-8°C 菌株(2年)\n藥物感受 採檢手冊 (A類感\n性試驗 3.15.2菌株檢 染性物質\n體 P620包\n裝)",
    "pdf_path": "pdfs/多重抗藥性結核病.pdf",
    "臨床條件": "(一)具有結核病之徵候或症狀如長期咳嗽、體重減輕、發燒等,\n或胸部 X 光顯示疑似結核病灶。\n(二)經抗結核藥物治療後臨床症狀或徵候之表現,無明顯改善,\n懷疑為多重抗藥性結核病。",
    "檢驗條件": "具下列任一條件:\n(一)臨床檢體(如痰、肋膜液、胃洗液、支氣管沖洗液、組織\n切片等)培養後,菌株經鑑定為結核菌群(Mycobacterium\ntuberculosis complex),且藥物感受性試驗顯示至少同時對\nisoniazid 及 rifampicin 具抗藥性。\n(二)臨床檢體或鑑定為結核菌群(Mycobacterium tuberculosis\ncomplex)之菌株,經分子檢測顯示至少同時對 isoniazid 及\nrifampicin 具抗藥性。",
    "流行病學條件": "(一)具有與多重抗藥性結核病確定病例之接觸史。\n(二)醫師依據病史認為復發個案;或經抗結核藥物治療後失敗\n或失落個案。\n(三)居住於國內抗藥性高風險地區或具有 WHO 公布之結核\n病或多重抗藥性結核病高負擔國家旅遊。",
    "通報定義": "符合檢驗條件且已通報結核病。",
    "疾病分類": "(一)可能病例:\nNA\n(二)極可能病例:\n符合檢驗條件。\n(三)確定病例:\n同時具備下列兩項條件:\n1. 符合極可能病例。\n2. 藥物感受性試驗檢驗單位,傳統檢測須為疾病管制署\n或多重抗藥性結核病認可實驗室,分子檢測須為疾病\n管制署或指定實驗室。",
    "檢體採檢送驗事項": "傳染病 檢體種類 採檢目的 採檢時間 採檢量及規定 送驗方式 應保存種類 注 意\n名稱 (應保存時間) 事項\n病原體檢\n測、藥物 2-8°C\n臨床檢體 菌株(2年)\n感受性試 詳傳染病檢體 (B 類感\n驗 採檢手冊 3.9 染性物質\n初次驗痰 痰液檢體 P650 包\n多重抗藥 (未服藥 裝)\n臨床檢體\n性結核病 前)或\n分子病原\n配合案例\n菌株 體檢測、 詳傳染病檢體 2-8°C 菌株(2年)\n藥物感受 採檢手冊 (A類感\n性試驗 3.15.2菌株檢 染性物質\n體 P620包\n裝)",
    "english_name": "Multidrug-Resistant Tuberculosis",
    "suspected_case": "NA",
    "probable_case": "符合檢驗條件。",
    "confirmed_case": "同時具備下列兩項條件:\n1. 符合極可能病例。\n2. 藥物感受性試驗檢驗單位,傳統檢測須為疾病管制署\n或多重抗藥性結核病認可實驗室,分子檢測須為疾病\n管制署或指定實驗室。"
  },
  {
    "name": "天花",
    "url": "https://www.cdc.gov.tw/File/Get/PliZELrp1f-tjibHx7v3FQ",
    "source_category": "第一類",
    "content": "天花\n(Smallpox)\n一、 臨床條件\n(一) 爆發流行前:\n突然發燒 38.3°C(101°F)以上,接著會依序出現不同型態\n及進展一致的皮膚病灶如紅疹、丘疹、水泡或膿疱,且無\n其他明顯病因,並須特別與水痘(VZV)做鑑別診斷。\n(二) 爆發流行時:\n於發現第一例天花病例後,具有下列任一個條件:\n1. 發燒 1 至 4 天後出現皮疹,且演進的發展性皮疹。\n2. 突然發燒 38.3°C(101°F)以上;或並未出現符合臨床通\n報定義之症狀。\n二、 檢驗條件\n具有下列任一個條件:\n(一)臨床檢體(水泡液、膿疱液、瘡痂或組織等)分離並鑑\n定出天花病毒(Variola virus)。\n(二)臨床檢體分子生物學核酸檢測陽性。\n三、 流行病學條件\n曾接觸天花確定病例,如與確定病例有唾液、血液、組織液、\n水泡液、脫落的皮屑、結痂、排泄物之接觸,或接觸天花病人\n使用過沾有天花病毒之物品等。\n四、 通報定義\n具有下列任一個條件:\n(一)符合臨床條件。\n(二)爆發流行時,雖未出現臨床症狀,但醫師或法醫師高度\n懷疑, 且患者與確定病例具有流行病學上相關者。\n五、 疾病分類\n(一) 可能病例:\n符合臨床條件\n(二)極可能病例:\n病患並未出現符合臨床通報定義之症狀,但臨床醫師高\n度懷疑 是天花,且與確定病例具有流行病學之關聯。\n(三)確定病例:具有下列任一個條件:\n1. 符合臨床條件及檢驗條件。\n2. 符合臨床條件,且與確定病例具有流行病學之關聯。\n六、 檢體採檢送驗事項\n請參閱「傳染病檢體採檢手冊」(https://gov.tw/pK8)",
    "pdf_path": "pdfs/天花.pdf",
    "臨床條件": "(一) 爆發流行前:\n突然發燒 38.3°C(101°F)以上,接著會依序出現不同型態\n及進展一致的皮膚病灶如紅疹、丘疹、水泡或膿疱,且無\n其他明顯病因,並須特別與水痘(VZV)做鑑別診斷。\n(二) 爆發流行時:\n於發現第一例天花病例後,具有下列任一個條件:\n1. 發燒 1 至 4 天後出現皮疹,且演進的發展性皮疹。\n2. 突然發燒 38.3°C(101°F)以上;或並未出現符合臨床通\n報定義之症狀。",
    "檢驗條件": "具有下列任一個條件:\n(一)臨床檢體(水泡液、膿疱液、瘡痂或組織等)分離並鑑\n定出天花病毒(Variola virus)。\n(二)臨床檢體分子生物學核酸檢測陽性。",
    "流行病學條件": "曾接觸天花確定病例,如與確定病例有唾液、血液、組織液、\n水泡液、脫落的皮屑、結痂、排泄物之接觸,或接觸天花病人\n使用過沾有天花病毒之物品等。",
    "通報定義": "具有下列任一個條件:\n(一)符合臨床條件。\n(二)爆發流行時,雖未出現臨床症狀,但醫師或法醫師高度\n懷疑, 且患者與確定病例具有流行病學上相關者。",
    "疾病分類": "(一) 可能病例:\n符合臨床條件\n(二)極可能病例:\n病患並未出現符合臨床通報定義之症狀,但臨床醫師高\n度懷疑 是天花,且與確定病例具有流行病學之關聯。\n(三)確定病例:具有下列任一個條件:\n1. 符合臨床條件及檢驗條件。\n2. 符合臨床條件,且與確定病例具有流行病學之關聯。",
    "檢體採檢送驗事項": "請參閱「傳染病檢體採檢手冊」(https://gov.tw/pK8)",
    "english_name": "Smallpox",
    "suspected_case": "符合臨床條件",
    "probable_case": "病患並未出現符合臨床通報定義之症狀,但臨床醫師高\n度懷疑 是天花,且與確定病例具有流行病學之關聯。",
    "confirmed_case": "具有下列任一個條件:\n1. 符合臨床條件及檢驗條件。\n2. 符合臨床條件,且與確定病例具有流行病學之關聯。"
  },
  {
    "name": "小兒麻痺症/急性無力肢體麻痺",
    "url": "https://www.cdc.gov.tw/File/Get/YAgIUm8HqMTb_CZ5Gpvyow",
    "source_category": "第二類",
    "content": "急性無力肢體麻痺(小兒麻痺症監視指標)\n(Acute Flaccid Paralysis and Poliomyelitis)\n一、 AFP 臨床條件\n15 歲以下孩童出現任何急性無力肢體麻痺現象,但沒有感覺或認知\n功能障礙。\n二、 檢驗條件\n臨床檢體(糞便或腦脊髓液)分離並鑑定出野生株小兒麻痺病毒(Wild\nPoliovirus)。\n三、 流行病學條件\n具有下列任一個條件:\n(一) 發病前 35 天,有小兒麻痺症疫區之旅遊史。\n(二) 曾接觸確定感染個案之上呼吸道、口咽等分泌物或排泄物,與\n確定感染個案有流行病學上關聯。\n四、 通報定義\n15 歲以下符合急性無力肢體麻痺臨床條件。\n五、 疾病分類\n(一) AFP 確定病例:\n通報病例經 AFP 監視調查專家進行臨床調查後,判定符合\nAFP 病例定義。\n(二) 小兒麻痺症確定病例:\n符合 AFP 確定病例條件及小兒麻痺症檢驗條件,經衛生福利\n部傳染病防治審議委員會-小兒麻痺症根除成果保全證明組\n專家審查確定。\n六、 檢體採檢送驗事項\n應保存種類\n採檢項目 檢體種類 採檢目的 採檢時間 採檢量及規定 送驗方式 注意事項\n(應保存時間)\n1. 糞便過大時,可用\n發 病 14\n扁平木棒將其弄\n日內採取以本署提供之\n小,放入瓶內,勿\n2 次糞便密閉廣口塑膠 沾瓶口並旋緊瓶\n蓋。\n糞便 檢體,2瓶採集約 10 g\n2. 檢體採集後立即冷\n小兒麻痺 份檢體隔(約荔枝大) 2-8°C 藏,於72小時內送\n症/急性無 病原體檢 日或連日新鮮糞便。 (B類生物 病毒株\n達檢驗單位。\n3. 糞便採檢步驟請參\n力肢體麻 測 採取 物 質 包 (30日)\n考第3.5.5節。\n痺(AFP) 以無菌病毒拭裝)\n發 病 14\n子之棉棒擦拭\n見2.8.5備註說明及\n咽喉擦 天內採集\n咽喉,插入病 咽喉採檢步驟請參\n拭液 咽喉擦拭\n考第3.7節及圖3.7。\n毒 保 存 輸 送\n液1次。\n管。",
    "pdf_path": "pdfs/小兒麻痺症_急性無力肢體麻痺.pdf",
    "臨床條件": "15 歲以下孩童出現任何急性無力肢體麻痺現象,但沒有感覺或認知\n功能障礙。",
    "檢驗條件": "臨床檢體(糞便或腦脊髓液)分離並鑑定出野生株小兒麻痺病毒(Wild\nPoliovirus)。",
    "流行病學條件": "具有下列任一個條件:\n(一) 發病前 35 天,有小兒麻痺症疫區之旅遊史。\n(二) 曾接觸確定感染個案之上呼吸道、口咽等分泌物或排泄物,與\n確定感染個案有流行病學上關聯。",
    "通報定義": "15 歲以下符合急性無力肢體麻痺臨床條件。",
    "疾病分類": "(一) AFP 確定病例:\n通報病例經 AFP 監視調查專家進行臨床調查後,判定符合\nAFP 病例定義。\n(二) 小兒麻痺症確定病例:\n符合 AFP 確定病例條件及小兒麻痺症檢驗條件,經衛生福利\n部傳染病防治審議委員會-小兒麻痺症根除成果保全證明組\n專家審查確定。",
    "檢體採檢送驗事項": "應保存種類\n採檢項目 檢體種類 採檢目的 採檢時間 採檢量及規定 送驗方式 注意事項\n(應保存時間)\n1. 糞便過大時,可用\n發 病 14\n扁平木棒將其弄\n日內採取以本署提供之\n小,放入瓶內,勿\n2 次糞便密閉廣口塑膠 沾瓶口並旋緊瓶\n蓋。\n糞便 檢體,2瓶採集約 10 g\n2. 檢體採集後立即冷\n小兒麻痺 份檢體隔(約荔枝大) 2-8°C 藏,於72小時內送\n症/急性無 病原體檢 日或連日新鮮糞便。 (B類生物 病毒株\n達檢驗單位。\n3. 糞便採檢步驟請參\n力肢體麻 測 採取 物 質 包 (30日)\n考第3.5.5節。\n痺(AFP) 以無菌病毒拭裝)\n發 病 14\n子之棉棒擦拭\n見2.8.5備註說明及\n咽喉擦 天內採集\n咽喉,插入病 咽喉採檢步驟請參\n拭液 咽喉擦拭\n考第3.7節及圖3.7。\n毒 保 存 輸 送\n液1次。\n管。",
    "english_name": "Acute Flaccid Paralysis and Poliomyelitis",
    "suspected_case": "",
    "probable_case": "",
    "confirmed_case": ""
  },
  {
    "name": "屈公病",
    "url": "https://www.cdc.gov.tw/File/Get/_rm8dfC15WLrQ55dC245Tg",
    "source_category": "第二類",
    "content": "屈公病\n(Chikungunya Fever)\n一、 臨床條件\n急性發燒≧38°C且有嚴重關節炎或關節痛,無法以其他醫學診斷解\n釋者。\n二、 檢驗條件\n符合下列檢驗結果之任一項者,定義為檢驗結果陽性:\n(一)臨床檢體分離並鑑定出屈公病毒。\n(二)臨床檢體分子生物學核酸檢測陽性。\n(三)急性期(或初次採檢)血清中,屈公病毒特異性IgM或IgG抗\n體為陽性者。\n(四)成對血清(恢復期及急性期)中,屈公病毒特異性IgM或IgG\n抗體(二者任一)有陽轉或≧4倍上升。\n三、 流行病學條件\n具有下列任一個條件:\n(一)住家或活動範圍附近有屈公病確定病例或有與屈公病確定病\n例接觸史。\n(二)有屈公病流行地區相關旅遊史。\n四、 通報定義\n符合臨床條件及流行病學條件。\n五、 疾病分類\n(一) 可能病例:\nNA\n(二) 極可能病例:\n符合臨床條件及檢驗結果陽性定義之第三項。\n(三) 確定病例:\n符合檢驗結果陽性定義之第一、二、四項之任一項。\n六、 檢體採檢送驗事項\n傳染病 採檢量及 應保存種類\n採檢項目 採檢目的 採檢時間 送驗方式 注意事項\n名稱 規定 應保存時間\n1.檢體勿加入任\n病毒株 何添加物。\n急性期 (30 日) 2.若無法取得急\n(發病7\n日內) ;陽性血清 性期之血\n(30 日) 液,請採間隔\n7日之恢復期\n血清,分 2次\n2-8°C 送驗。\n病原體檢 以無菌試 B類感染 3.血清檢體採檢\n測;抗體 管收集 3 性物質 注意事項請\n屈公病 血清\n檢測 mL 血清 P650包裝 參閱傳染病\n恢復期 檢體採檢手\n(發病 陽性血清\n冊2.8.3 及\n14-40日 (30 日)\n之間) 2.8.4備註說\n明,血清檢體\n採檢步驟請\n參閱傳染病\n檢體採檢手\n冊第3.3 節。",
    "pdf_path": "pdfs/屈公病.pdf",
    "臨床條件": "急性發燒≧38°C且有嚴重關節炎或關節痛,無法以其他醫學診斷解\n釋者。",
    "檢驗條件": "符合下列檢驗結果之任一項者,定義為檢驗結果陽性:\n(一)臨床檢體分離並鑑定出屈公病毒。\n(二)臨床檢體分子生物學核酸檢測陽性。\n(三)急性期(或初次採檢)血清中,屈公病毒特異性IgM或IgG抗\n體為陽性者。\n(四)成對血清(恢復期及急性期)中,屈公病毒特異性IgM或IgG\n抗體(二者任一)有陽轉或≧4倍上升。",
    "流行病學條件": "具有下列任一個條件:\n(一)住家或活動範圍附近有屈公病確定病例或有與屈公病確定病\n例接觸史。\n(二)有屈公病流行地區相關旅遊史。",
    "通報定義": "符合臨床條件及流行病學條件。",
    "疾病分類": "(一) 可能病例:\nNA\n(二) 極可能病例:\n符合臨床條件及檢驗結果陽性定義之第三項。\n(三) 確定病例:\n符合檢驗結果陽性定義之第一、二、四項之任一項。",
    "檢體採檢送驗事項": "傳染病 採檢量及 應保存種類\n採檢項目 採檢目的 採檢時間 送驗方式 注意事項\n名稱 規定 應保存時間\n1.檢體勿加入任\n病毒株 何添加物。\n急性期 (30 日) 2.若無法取得急\n(發病7\n日內) ;陽性血清 性期之血\n(30 日) 液,請採間隔\n7日之恢復期\n血清,分 2次\n2-8°C 送驗。\n病原體檢 以無菌試 B類感染 3.血清檢體採檢\n測;抗體 管收集 3 性物質 注意事項請\n屈公病 血清\n檢測 mL 血清 P650包裝 參閱傳染病\n恢復期 檢體採檢手\n(發病 陽性血清\n冊2.8.3 及\n14-40日 (30 日)\n之間) 2.8.4備註說\n明,血清檢體\n採檢步驟請\n參閱傳染病\n檢體採檢手\n冊第3.3 節。",
    "english_name": "Chikungunya Fever",
    "suspected_case": "NA",
    "probable_case": "符合臨床條件及檢驗結果陽性定義之第三項。",
    "confirmed_case": "符合檢驗結果陽性定義之第一、二、四項之任一項。"
  },
  {
    "name": "布氏桿菌病",
    "url": "https://www.cdc.gov.tw/File/Get/obMtZcnqzKru8XNv9li6Jw",
    "source_category": "第四類",
    "content": "布氏桿菌病\n(Brucellosis)\n一、 臨床條件\n發燒且出現以下任ㄧ臨床表現,包括:盜汗、頭痛、關節痛、肌肉酸\n痛、體重減輕、食慾不振、倦怠無力、憂鬱、腦膜炎、心內膜炎、肝\n臟或脾臟腫大、睪丸炎或卵巢炎。\n二、 檢驗條件\n符合下列檢驗結果之任ㄧ項者,定義為檢驗結果陽性:\n(一) 臨床檢體分離並鑑定出布氏桿菌屬(Brucella spp.)。\n(二) 急性期或恢復期血清學抗體檢測陽性。\n三、 流行病學條件\n具有下列任ㄧ個條件:\n(一)有布氏桿菌相關流行地區旅遊史,且曾食用未經消毒或消毒不\n完全之動物製品(尤其乳製品)。\n(二)曾接觸疑似受布氏桿菌感染之動物。\n(三)進行布氏桿菌或檢體實驗室操作。\n四、 通報定義\n具有下列任一個條件:\n(一)符合臨床條件及流行病學條件。\n(二)經醫院自行檢驗,符合檢驗條件。\n五、 疾病分類\n(一)可能病例:\nNA\n(二)極可能病例:\n雖未經實驗室證實,但符合臨床條件及流行病學條件。\n(三)確定病例:\n符合臨床條件及檢驗條件。\n六、 檢體採檢送驗事項\n採檢項目 檢體種類 採檢目的 採檢時間 採檢量及規定 送驗方式 注意事項\n血清檢體見 2.8.3\n急性期;以無菌試管收集至 及 2.8.4 備註說\n血清 抗體檢測 低溫\n恢復期 少3 mL血清。 明,血清採檢步驟\n請參考第3.3節。\n1. 以含抗凝劑\n(heparin或\nEDTA)採血管採\n集5-10 mL 血液\n全血採檢步驟請\n檢體。\n布氏桿菌 抗凝固全病原體檢急性發燒 參考第3.1節,抗\n2. 以採血管採 5-10 常溫\n病 血或全血 測 期 凝固全血採檢請\nmL全血,立即注\n參考第3.2節。\n入嗜氧性血液培\n養瓶(血液與培養\n液比例為 1:5 至\n1:10)。\n純化之菌株以拭子低溫 1. 本 菌 傳 染 性\n已分離菌 沾滿一圈後,置入(A 類感染 高,應謹慎操\n菌株 菌株鑑定\n株時 Cary-Blair 保存輸送性物質包 作。\n培養基。 裝) 2. 儘速送驗。",
    "pdf_path": "pdfs/布氏桿菌病.pdf",
    "臨床條件": "發燒且出現以下任ㄧ臨床表現,包括:盜汗、頭痛、關節痛、肌肉酸\n痛、體重減輕、食慾不振、倦怠無力、憂鬱、腦膜炎、心內膜炎、肝\n臟或脾臟腫大、睪丸炎或卵巢炎。",
    "檢驗條件": "符合下列檢驗結果之任ㄧ項者,定義為檢驗結果陽性:\n(一) 臨床檢體分離並鑑定出布氏桿菌屬(Brucella spp.)。\n(二) 急性期或恢復期血清學抗體檢測陽性。",
    "流行病學條件": "具有下列任ㄧ個條件:\n(一)有布氏桿菌相關流行地區旅遊史,且曾食用未經消毒或消毒不\n完全之動物製品(尤其乳製品)。\n(二)曾接觸疑似受布氏桿菌感染之動物。\n(三)進行布氏桿菌或檢體實驗室操作。",
    "通報定義": "具有下列任一個條件:\n(一)符合臨床條件及流行病學條件。\n(二)經醫院自行檢驗,符合檢驗條件。",
    "疾病分類": "(一)可能病例:\nNA\n(二)極可能病例:\n雖未經實驗室證實,但符合臨床條件及流行病學條件。\n(三)確定病例:\n符合臨床條件及檢驗條件。",
    "檢體採檢送驗事項": "採檢項目 檢體種類 採檢目的 採檢時間 採檢量及規定 送驗方式 注意事項\n血清檢體見 2.8.3\n急性期;以無菌試管收集至 及 2.8.4 備註說\n血清 抗體檢測 低溫\n恢復期 少3 mL血清。 明,血清採檢步驟\n請參考第3.3節。\n1. 以含抗凝劑\n(heparin或\nEDTA)採血管採\n集5-10 mL 血液\n全血採檢步驟請\n檢體。\n布氏桿菌 抗凝固全病原體檢急性發燒 參考第3.1節,抗\n2. 以採血管採 5-10 常溫\n病 血或全血 測 期 凝固全血採檢請\nmL全血,立即注\n參考第3.2節。\n入嗜氧性血液培\n養瓶(血液與培養\n液比例為 1:5 至\n1:10)。\n純化之菌株以拭子低溫 1. 本 菌 傳 染 性\n已分離菌 沾滿一圈後,置入(A 類感染 高,應謹慎操\n菌株 菌株鑑定\n株時 Cary-Blair 保存輸送性物質包 作。\n培養基。 裝) 2. 儘速送驗。",
    "english_name": "Brucellosis",
    "suspected_case": "NA",
    "probable_case": "雖未經實驗室證實,但符合臨床條件及流行病學條件。",
    "confirmed_case": "符合臨床條件及檢驗條件。"
  },
  {
    "name": "庫賈氏病",
    "url": "https://www.cdc.gov.tw/File/Get/SEB9twXT4NxGEseA3mkXpQ",
    "source_category": "第四類",
    "content": "庫賈氏病\n(Creutzfeldt-Jakob Disease)\n人類普利昂病(human prion diseases)又稱人類傳播性海綿樣腦症(human\ntransmissible spongiform encephalopathies,TSEs),係指庫賈氏病\n(Creutzfeldt-Jakob Disease,CJD)、新型庫賈氏病(variant Creutzfeldt-Jakob\nDisease,vCJD)、吉斯曼-史特斯勤-先克症候群(Gerstmann-Sträussler-Scheinker\nsyndrome,GSS)、致死性家族性失眠症(fatal familial insomnia,FFI)及庫\n魯病(Kuru)。其中庫賈氏病(CJD)又分為散發型(sporadic CJD,sCJD)、\n醫源型(iatrogenic CJD,iCJD)及遺傳型(familial or inherited CJD)3 種型\n式。而吉斯曼-史特斯勤-先克症候群(GSS)及致死性家族性失眠症(FFI)\n均為遺傳型普利昂病。\n壹、 臨床條件\n一、 庫賈氏病(Creutzfeldt-Jakob Disease,CJD)\n具有下列任一個條件:\n(一) 進展快速之失智症或智能衰退(mental decline),且常規檢查\n已排除可導致此情況的其他疾病。\n(二) 具有下列任一個神經學症狀:\n1. 肌躍症(myoclonus)。\n2. 視覺異常(visual disturbance)或小腦功能失調(cerebellar\ndysfunction)。\n3. 錐體路(pyramidal)或錐體外路(extrapyramidal)功能異常。\n4. 不動不語症(akinetic mutism)。\n(三) 進行性神經精神異常(progressive neuropsychiatric disorder)。\n二、 新型庫賈氏病(variant Creutzfeldt-Jakob Disease,vCJD)\n具有下列任一個條件:\n(一) 具有以下症狀:\n1.進 行 性 神 經 性 精 神 異 常 ( progressive neuropsychiatric\ndisorder)且已排除其他疾病。\n2. 無醫療暴露史。\n3. 排除遺傳型人類傳播性海綿樣腦症。\n(二) 具有下列任一症狀:\n1. 有焦慮、憂鬱、退縮、淡漠及妄想等精神症狀。\n104年7月16日核定\n2. 明顯疼痛(frank pain) 和/或感覺異樣(dysaesthesia)。\n3. 運動失調(ataxia)。\n4. 肌躍症(myoclonus)或舞蹈症(chorea)或張力不全\n(dystonia)。\n5. 失智症(dementia)。\n貳、 檢驗條件\n一、 庫賈氏病(Creutzfeldt-Jakob Disease,CJD)\n具有下列任一個條件:\n(一) 腦電圖(EEG):有週期性尖銳組合波(periodic sharp wave\ncomplex, PSWC)。\n(二) 腦部核磁共振(MRI):在尾核(caudate)或殼核(putamen)\n有高密度變化(high density in diffusion and or flair/T2);或皮\n質緞帶徵象(cortical ribbon)。\n(三) 臨床檢體(腦脊髓液):14-3-3 蛋白檢測陽性。\n(四) 經免疫細胞化學反應(immunocytochemistry)或西方點墨法\n(western blot)檢驗發現有能抵抗蛋白脢分解的普利昂蛋白\n(protease-resistant prion protein,PrP-res)。\n(五) 具有下列任一個條件:\n1. 大腦或小腦的皮質或皮質下灰質有海綿樣腦病變。\n2. 腦病變伴隨普利昂蛋白免疫反應(PrP immunoreactivity)(此\n免疫反應的型態有: plaque、diffuse synaptic and patchy/\nperivacuolar types)。\n(六) 特異性普利昂蛋白質基因(PRNP)突變。\n二、 新型庫賈氏病(variant Creutzfeldt-Jakob Disease,vCJD)\n具有下列任一個條件:\n(一) 病程初期腦電圖無散發型庫賈氏病之典型週期性尖銳組合波\n(periodic sharp wave complex, PSWC)。\n(二) 核磁共振顯示在丘腦枕(pulvinar)有雙側對稱性墊狀隆起病\n徵(pulvinar high signal)。\n(三) 扁桃腺組織檢查陽性。\n(四) 大腦及小腦有海綿樣腦病變、大量普利昂蛋白沈積物及多樣\n性斑塊(florid plaques)。\n參、 流行病學條件\n104年7月16日核定\n具有下列任一個條件:\n(一) 曾使用人類腦下垂體賀爾蒙製劑治療。\n(二) 曾接受人類硬腦膜移植。\n(三) 曾接受確定/極可能/可能庫賈氏病個案之眼角膜移植。\n(四) 曾有暴露於確定/極可能/可能庫賈氏病個案所接觸過之神經外\n科器械者。\n肆、 通報定義\n進展快速之失智症或智能衰退(mental decline) 或 進行性神經性精\n神異常(progressive neuropsychiatric disorder),且已排除其他疾病,\n並 具有下列任一個條件:\n(一) 具有下列任一個神經學症狀:\n1. 肌躍症(myoclonus)或舞蹈症(chorea)或張力不全\n(dystonia)。\n2. 視覺異常(visual disturbance)或小腦功能失調(cerebellar\ndysfunction)。\n3. 錐體路(pyramidal)或錐體外路(extrapyramidal)功能異\n常。\n4. 不動不語症(akinetic mutism)。\n5. 明顯疼痛(frank pain) 和/或感覺異樣(dysaesthesia)。\n(二) 腦電圖(EEG)有週期性尖銳組合波(periodic sharp wave\ncomplex, PSWC)。\n(三) 腦部核磁共振(MRI)具有下列任一條件:\n1. 在尾核(caudate)或殼核(putamen)有高密度變化(high\ndensity in diffusion and or flair/T2)或皮質緞帶徵象(cortical\nribbon)。\n2. 丘腦枕(pulvinar)有雙側對稱性墊狀隆起病徵(pulvinar high\nsignal)。\n伍、 疾病分類\n一、 散發型庫賈氏病(sporadic CJD, sCJD):\n(一) 可能病例:\n符合臨床條件一、(一) 與\n臨床條件一、(二)4 項中至少 2 項症狀,且病程小於 2 年。\n104年7月16日核定\n(二) 極可能病例:\n具有下列任一個條件:\n1. 符合臨床條件一、(一) 與\n臨床條件一、(二)4 項中至少 2 項症狀 及\n檢驗條件一、(一)。\n2. 符合臨床條件一、(一) 與\n臨床條件一、(二)4 項中至少 2 項症狀 及\n檢驗條件一、(二)。\n3. 為散發型庫賈氏病可能病例 且\n符合檢驗條件一、(三)。\n(三) 確定病例:\n具有下列任一條件:\n1. 符合檢驗條件一、(四)。\n2. 符合檢驗條件一、(五)。\n二、 醫源型庫賈氏病(iatrogenic CJD, iCJD):\n(一) 可能病例:\n為散發型庫賈氏病可能病例 且\n具有 4 項流行病學條件中任一項。\n(二) 極可能病例:\n為散發型庫賈氏病極可能病例 且\n具有 4 項流行病學條件中任一項。\n(三) 確定病例:\n為散發型庫賈氏病確定病例 且\n具有 4 項流行病學條件中任一項。\n三、 遺傳型庫賈氏病(familial or inherited CJD):\n(一) 可能病例:\n無 (not applicable)\n(二) 極可能病例:\n具有下列任一個條件:\n104年7月16日核定\n1. 符合臨床條件一、(三) 且\n其父母、兄弟姊妹或子女中有人類普利昂病之確定或極可能\n病例。\n2. 符合臨床條件一、(三) 且\n符合檢驗條件一、(六)。\n(三) 確定病例:\n具有下列任一個條件:\n1. 經病理學確診為人類普利昂病 且\n其父母、兄弟姊妹或子女中有人類普利昂病之確定或極可能\n病例。\n2. 經病理學確診為人類普利昂病 且\n符合檢驗條件一、(六)。\n四、 新型庫賈氏病(variant Creutzfeldt-Jakob Disease, vCJD):\n(一) 可能病例\n符合臨床條件二、(一) 與\n臨床條件二、(二)5 項中至少 4 項症狀 及\n檢驗條件二、(一),且經衛生福利部疾病管制署庫賈氏病之病\n例審查會議專家審查確定。\n(二) 極可能病例\n具有下列任一個條件,且經衛生福利部疾病管制署庫賈氏病之\n病例審查會議專家審查確定:\n1. 符合臨床條件二、(一) 與\n臨床條件二、(二)5 項中至少 4 項症狀 及\n檢驗條件二、(一)與(二)。\n2. 符合臨床條件二、(一) 及\n檢驗條件二、(三)。\n(三) 確定病例\n符合臨床條件二、(一)第 1 項症狀 與 檢驗條件二、(四),\n且經衛生福利部疾病管制署庫賈氏病之病例審查會議專家審\n查確定。\n104年7月16日核定\n陸、 檢體採檢送驗事項\n應保存種類\n傳染病\n採檢項目 採檢目的 採檢時間 採檢量及規定 送驗方式 (應保存時 注意事項\n名稱\n間)\n1. 請參閱「庫賈\n氏病及其他人\n1. 防漏無菌試管(塑\n類傳播性海綿\n臨床測定 膠材質)收集腦脊\n樣腦症感染管\n庫賈氏病 (EEG、 髓液至少2 mL。\n制與病例通報\n腦脊髓液 標示蛋白 MRI、 2. 每 管 外 覆 吸 水 -\n指引手冊」。\n檢測 CTScan) 紙,並以夾鏈袋密2-8oC\n2. 脊髓液採檢步\n疑似時 封,再置於檢體罐(B類感染\n驟請參考第 3.6\n(第二層容器)中。性物質包\n節,由醫師採\n裝)\n檢。\n臨床測定\n以含抗凝劑\n(EEG、\n基因型別 (heparin或EDTA)\nMRI、 -\n檢測* 採血管採集5-10 mL\nCTScan)\n抗凝固全血採檢\n抗凝固全 血液檢體。\n疑似時 步驟請參考第 3.2\n血\n以含抗凝劑 22-35oC 節。\n庫賈氏病\n普利昂蛋 病例審查 (heparin或EDTA)(B類感染\n白檢測 會建議時 採血管採集5-10 mL 性物質包\n血液檢體2管。 裝)\n1.無菌容\n器之組織\n以冷凍方\n請參閱「庫賈氏病\n扁桃腺組織分別以 式運送。 及其他人類傳播\n1.無菌容器收集至\n2.泡置於 性海綿樣腦症\n扁桃腺組 普利昂蛋 病例審查 福馬林之 感染管制與病例\n少50 mg。\n織檢體 白檢測 會建議時 組織以常 通報指引手冊」及\n2.含有福馬林之容\n溫22-35 「醫療機構感染\n器收集至少50 mg。 oC運送。 管制手冊彙編」。\n(B類感染\n性物質包\n裝)\n*基於倫理考量,有關基因型別檢測請醫師對病患本人或其法定代理人或家屬說明檢測\n之原因、效益,請其填妥後附之同意書(1 式 2 份)後始得為之,並請於檢體送驗時\n併附同意書正本1份。\n104年7月16日核定\n庫賈氏病通報個案 基因檢測說明書\n一、疾病簡介:\n人類普利昂病又稱人類傳播性海綿樣腦症,係指庫賈氏病(CJD)、新\n型庫賈氏病(vCJD)等,其中的庫賈氏病(CJD)分為散發型、醫源型及\n遺傳型3種型式。依據國外文獻資料顯示,散發型庫賈氏病佔總病例數約85\n%,發生原因不明;醫源型庫賈氏病佔總病例數少於1%,為各種醫療行為\n所造成之感染;遺傳型庫賈氏病佔總病例數10~15%,吉斯曼-史特斯勤-先\n克症候群(Gerstmann-Sträussler-Scheinker syndrome,GSS)與致死性家族\n性失眠症(Fatal Familial Insomnia,FFI)均為家族顯性遺傳型普利昂病,\n可應用基因檢測「普利昂蛋白質基因(PRNP)」協助診斷此類遺傳型庫賈\n氏病。\n依文獻資料顯示,吉斯曼-史特斯勤-先克症候群(GSS)每年發生率約\n為千萬分之一,病患皆有家族史,發病年齡平均為43-48歲,發病後平均壽\n命為5年;而致命性家族性失眠症(FFI),平均發病年齡為56歲,發病後平\n均壽命為13個月。\n二、檢測效益:\n本項基因檢測可瞭解庫賈氏病通報個案是否有普利昂蛋白質基因\n(PRNP)變異,其結果可提供本人疾病診斷之依據。\n三、檢體種類:\n104年7月16日核定\n5-10 c.c.血液。\n四、檢測風險:\n與一般抽血檢驗相同,少數人抽血部位會因皮下滲血而瘀青。\n五、檢體處理與保存:\n抽取之血液將置於含抗凝劑(heparin或EDTA)之試管,以低溫(2-8°C)\n運送至衛生福利部疾病管制署研究檢驗中心。受檢者之檢體會被妥善使\n用、處理與保存,檢測完畢後,檢測單位將以無法辨認個人資料的方式保\n存或確實銷毀。\n六、檢驗費用及報告時程:\n庫賈氏病為第4類法定傳染病,檢驗費用由公務預算支應。實驗室於接\n獲檢體後3個月內將檢驗結果提供給通報醫師。\n七、其他事項\n基因檢測有其侷限性,檢驗結果無法明確預測近親罹患遺傳型庫賈氏\n病的機率,僅供臨床參考。\n104年7月16日核定\n庫賈氏病通報個案 基因檢測同意書\n病人: ,出生於民國 年 月 日,因疑似罹患庫\n賈氏病,同意接受特異性普利昂蛋白質基因(PRNP)基因檢測。立同意書\n人已經與醫師討論過接受這個檢測的效益與風險,對醫師的說明都已充分\n了解且同意由 醫院代為抽血送交衛生福利部疾病管制署進\n行該項基因檢測,並同意將檢驗結果提供疾病管制署及通報醫院作為疾病\n研判的參考。\n檢驗結果是否提供立同意書人(請勾選):\n□提供,檢驗結果寄送地址:\n□不提供\n立同意書人: (簽章) 身分證字號:\n與病人之關係(請圈選):本人、配偶、父、母、兒、女、其他:___\n住址: 電話:\n日期:民國 年 月 日\n104年7月16日核定",
    "pdf_path": "pdfs/庫賈氏病.pdf",
    "臨床條件": "一、 庫賈氏病(Creutzfeldt-Jakob Disease,CJD)\n具有下列任一個條件:\n(一) 進展快速之失智症或智能衰退(mental decline),且常規檢查\n已排除可導致此情況的其他疾病。\n(二) 具有下列任一個神經學症狀:\n1. 肌躍症(myoclonus)。\n2. 視覺異常(visual disturbance)或小腦功能失調(cerebellar\ndysfunction)。\n3. 錐體路(pyramidal)或錐體外路(extrapyramidal)功能異常。\n4. 不動不語症(akinetic mutism)。\n(三) 進行性神經精神異常(progressive neuropsychiatric disorder)。\n二、 新型庫賈氏病(variant Creutzfeldt-Jakob Disease,vCJD)\n具有下列任一個條件:\n(一) 具有以下症狀:\n1.進 行 性 神 經 性 精 神 異 常 ( progressive neuropsychiatric\ndisorder)且已排除其他疾病。\n2. 無醫療暴露史。\n3. 排除遺傳型人類傳播性海綿樣腦症。\n(二) 具有下列任一症狀:\n1. 有焦慮、憂鬱、退縮、淡漠及妄想等精神症狀。\n104年7月16日核定\n2. 明顯疼痛(frank pain) 和/或感覺異樣(dysaesthesia)。\n3. 運動失調(ataxia)。\n4. 肌躍症(myoclonus)或舞蹈症(chorea)或張力不全\n(dystonia)。\n5. 失智症(dementia)。",
    "檢驗條件": "一、 庫賈氏病(Creutzfeldt-Jakob Disease,CJD)\n具有下列任一個條件:\n(一) 腦電圖(EEG):有週期性尖銳組合波(periodic sharp wave\ncomplex, PSWC)。\n(二) 腦部核磁共振(MRI):在尾核(caudate)或殼核(putamen)\n有高密度變化(high density in diffusion and or flair/T2);或皮\n質緞帶徵象(cortical ribbon)。\n(三) 臨床檢體(腦脊髓液):14-3-3 蛋白檢測陽性。\n(四) 經免疫細胞化學反應(immunocytochemistry)或西方點墨法\n(western blot)檢驗發現有能抵抗蛋白脢分解的普利昂蛋白\n(protease-resistant prion protein,PrP-res)。\n(五) 具有下列任一個條件:\n1. 大腦或小腦的皮質或皮質下灰質有海綿樣腦病變。\n2. 腦病變伴隨普利昂蛋白免疫反應(PrP immunoreactivity)(此\n免疫反應的型態有: plaque、diffuse synaptic and patchy/\nperivacuolar types)。\n(六) 特異性普利昂蛋白質基因(PRNP)突變。\n二、 新型庫賈氏病(variant Creutzfeldt-Jakob Disease,vCJD)\n具有下列任一個條件:\n(一) 病程初期腦電圖無散發型庫賈氏病之典型週期性尖銳組合波\n(periodic sharp wave complex, PSWC)。\n(二) 核磁共振顯示在丘腦枕(pulvinar)有雙側對稱性墊狀隆起病\n徵(pulvinar high signal)。\n(三) 扁桃腺組織檢查陽性。\n(四) 大腦及小腦有海綿樣腦病變、大量普利昂蛋白沈積物及多樣\n性斑塊(florid plaques)。",
    "流行病學條件": "104年7月16日核定\n具有下列任一個條件:\n(一) 曾使用人類腦下垂體賀爾蒙製劑治療。\n(二) 曾接受人類硬腦膜移植。\n(三) 曾接受確定/極可能/可能庫賈氏病個案之眼角膜移植。\n(四) 曾有暴露於確定/極可能/可能庫賈氏病個案所接觸過之神經外\n科器械者。",
    "通報定義": "進展快速之失智症或智能衰退(mental decline) 或 進行性神經性精\n神異常(progressive neuropsychiatric disorder),且已排除其他疾病,\n並 具有下列任一個條件:\n(一) 具有下列任一個神經學症狀:\n1. 肌躍症(myoclonus)或舞蹈症(chorea)或張力不全\n(dystonia)。\n2. 視覺異常(visual disturbance)或小腦功能失調(cerebellar\ndysfunction)。\n3. 錐體路(pyramidal)或錐體外路(extrapyramidal)功能異\n常。\n4. 不動不語症(akinetic mutism)。\n5. 明顯疼痛(frank pain) 和/或感覺異樣(dysaesthesia)。\n(二) 腦電圖(EEG)有週期性尖銳組合波(periodic sharp wave\ncomplex, PSWC)。\n(三) 腦部核磁共振(MRI)具有下列任一條件:\n1. 在尾核(caudate)或殼核(putamen)有高密度變化(high\ndensity in diffusion and or flair/T2)或皮質緞帶徵象(cortical\nribbon)。\n2. 丘腦枕(pulvinar)有雙側對稱性墊狀隆起病徵(pulvinar high\nsignal)。",
    "疾病分類": "一、 散發型庫賈氏病(sporadic CJD, sCJD):\n(一) 可能病例:\n符合臨床條件一、(一) 與\n臨床條件一、(二)4 項中至少 2 項症狀,且病程小於 2 年。\n104年7月16日核定\n(二) 極可能病例:\n具有下列任一個條件:\n1. 符合臨床條件一、(一) 與\n臨床條件一、(二)4 項中至少 2 項症狀 及\n檢驗條件一、(一)。\n2. 符合臨床條件一、(一) 與\n臨床條件一、(二)4 項中至少 2 項症狀 及\n檢驗條件一、(二)。\n3. 為散發型庫賈氏病可能病例 且\n符合檢驗條件一、(三)。\n(三) 確定病例:\n具有下列任一條件:\n1. 符合檢驗條件一、(四)。\n2. 符合檢驗條件一、(五)。\n二、 醫源型庫賈氏病(iatrogenic CJD, iCJD):\n(一) 可能病例:\n為散發型庫賈氏病可能病例 且\n具有 4 項流行病學條件中任一項。\n(二) 極可能病例:\n為散發型庫賈氏病極可能病例 且\n具有 4 項流行病學條件中任一項。\n(三) 確定病例:\n為散發型庫賈氏病確定病例 且\n具有 4 項流行病學條件中任一項。\n三、 遺傳型庫賈氏病(familial or inherited CJD):\n(一) 可能病例:\n無 (not applicable)\n(二) 極可能病例:\n具有下列任一個條件:\n104年7月16日核定\n1. 符合臨床條件一、(三) 且\n其父母、兄弟姊妹或子女中有人類普利昂病之確定或極可能\n病例。\n2. 符合臨床條件一、(三) 且\n符合檢驗條件一、(六)。\n(三) 確定病例:\n具有下列任一個條件:\n1. 經病理學確診為人類普利昂病 且\n其父母、兄弟姊妹或子女中有人類普利昂病之確定或極可能\n病例。\n2. 經病理學確診為人類普利昂病 且\n符合檢驗條件一、(六)。\n四、 新型庫賈氏病(variant Creutzfeldt-Jakob Disease, vCJD):\n(一) 可能病例\n符合臨床條件二、(一) 與\n臨床條件二、(二)5 項中至少 4 項症狀 及\n檢驗條件二、(一),且經衛生福利部疾病管制署庫賈氏病之病\n例審查會議專家審查確定。\n(二) 極可能病例\n具有下列任一個條件,且經衛生福利部疾病管制署庫賈氏病之\n病例審查會議專家審查確定:\n1. 符合臨床條件二、(一) 與\n臨床條件二、(二)5 項中至少 4 項症狀 及\n檢驗條件二、(一)與(二)。\n2. 符合臨床條件二、(一) 及\n檢驗條件二、(三)。\n(三) 確定病例\n符合臨床條件二、(一)第 1 項症狀 與 檢驗條件二、(四),\n且經衛生福利部疾病管制署庫賈氏病之病例審查會議專家審\n查確定。\n104年7月16日核定",
    "檢體採檢送驗事項": "應保存種類\n傳染病\n採檢項目 採檢目的 採檢時間 採檢量及規定 送驗方式 (應保存時 注意事項\n名稱\n間)\n1. 請參閱「庫賈\n氏病及其他人\n1. 防漏無菌試管(塑\n類傳播性海綿\n臨床測定 膠材質)收集腦脊\n樣腦症感染管\n庫賈氏病 (EEG、 髓液至少2 mL。\n制與病例通報\n腦脊髓液 標示蛋白 MRI、 2. 每 管 外 覆 吸 水 -\n指引手冊」。\n檢測 CTScan) 紙,並以夾鏈袋密2-8oC\n2. 脊髓液採檢步\n疑似時 封,再置於檢體罐(B類感染\n驟請參考第 3.6\n(第二層容器)中。性物質包\n節,由醫師採\n裝)\n檢。\n臨床測定\n以含抗凝劑\n(EEG、\n基因型別 (heparin或EDTA)\nMRI、 -\n檢測* 採血管採集5-10 mL\nCTScan)\n抗凝固全血採檢\n抗凝固全 血液檢體。\n疑似時 步驟請參考第 3.2\n血\n以含抗凝劑 22-35oC 節。\n庫賈氏病\n普利昂蛋 病例審查 (heparin或EDTA)(B類感染\n白檢測 會建議時 採血管採集5-10 mL 性物質包\n血液檢體2管。 裝)\n1.無菌容\n器之組織\n以冷凍方\n請參閱「庫賈氏病\n扁桃腺組織分別以 式運送。 及其他人類傳播\n1.無菌容器收集至\n2.泡置於 性海綿樣腦症\n扁桃腺組 普利昂蛋 病例審查 福馬林之 感染管制與病例\n少50 mg。\n織檢體 白檢測 會建議時 組織以常 通報指引手冊」及\n2.含有福馬林之容\n溫22-35 「醫療機構感染\n器收集至少50 mg。 oC運送。 管制手冊彙編」。\n(B類感染\n性物質包\n裝)\n*基於倫理考量,有關基因型別檢測請醫師對病患本人或其法定代理人或家屬說明檢測\n之原因、效益,請其填妥後附之同意書(1 式 2 份)後始得為之,並請於檢體送驗時\n併附同意書正本1份。\n104年7月16日核定\n庫賈氏病通報個案 基因檢測說明書\n一、疾病簡介:\n人類普利昂病又稱人類傳播性海綿樣腦症,係指庫賈氏病(CJD)、新\n型庫賈氏病(vCJD)等,其中的庫賈氏病(CJD)分為散發型、醫源型及\n遺傳型3種型式。依據國外文獻資料顯示,散發型庫賈氏病佔總病例數約85\n%,發生原因不明;醫源型庫賈氏病佔總病例數少於1%,為各種醫療行為\n所造成之感染;遺傳型庫賈氏病佔總病例數10~15%,吉斯曼-史特斯勤-先\n克症候群(Gerstmann-Sträussler-Scheinker syndrome,GSS)與致死性家族\n性失眠症(Fatal Familial Insomnia,FFI)均為家族顯性遺傳型普利昂病,\n可應用基因檢測「普利昂蛋白質基因(PRNP)」協助診斷此類遺傳型庫賈\n氏病。\n依文獻資料顯示,吉斯曼-史特斯勤-先克症候群(GSS)每年發生率約\n為千萬分之一,病患皆有家族史,發病年齡平均為43-48歲,發病後平均壽\n命為5年;而致命性家族性失眠症(FFI),平均發病年齡為56歲,發病後平\n均壽命為13個月。\n二、檢測效益:\n本項基因檢測可瞭解庫賈氏病通報個案是否有普利昂蛋白質基因\n(PRNP)變異,其結果可提供本人疾病診斷之依據。\n三、檢體種類:\n104年7月16日核定\n5-10 c.c.血液。\n四、檢測風險:\n與一般抽血檢驗相同,少數人抽血部位會因皮下滲血而瘀青。\n五、檢體處理與保存:\n抽取之血液將置於含抗凝劑(heparin或EDTA)之試管,以低溫(2-8°C)\n運送至衛生福利部疾病管制署研究檢驗中心。受檢者之檢體會被妥善使\n用、處理與保存,檢測完畢後,檢測單位將以無法辨認個人資料的方式保\n存或確實銷毀。\n六、檢驗費用及報告時程:\n庫賈氏病為第4類法定傳染病,檢驗費用由公務預算支應。實驗室於接\n獲檢體後3個月內將檢驗結果提供給通報醫師。\n七、其他事項\n基因檢測有其侷限性,檢驗結果無法明確預測近親罹患遺傳型庫賈氏\n病的機率,僅供臨床參考。\n104年7月16日核定\n庫賈氏病通報個案 基因檢測同意書\n病人: ,出生於民國 年 月 日,因疑似罹患庫\n賈氏病,同意接受特異性普利昂蛋白質基因(PRNP)基因檢測。立同意書\n人已經與醫師討論過接受這個檢測的效益與風險,對醫師的說明都已充分\n了解且同意由 醫院代為抽血送交衛生福利部疾病管制署進\n行該項基因檢測,並同意將檢驗結果提供疾病管制署及通報醫院作為疾病\n研判的參考。\n檢驗結果是否提供立同意書人(請勾選):\n□提供,檢驗結果寄送地址:\n□不提供\n立同意書人: (簽章) 身分證字號:\n與病人之關係(請圈選):本人、配偶、父、母、兒、女、其他:___\n住址: 電話:\n日期:民國 年 月 日\n104年7月16日核定",
    "english_name": "Creutzfeldt-Jakob Disease",
    "suspected_case": "符合臨床條件二、(一) 與\n臨床條件二、(二)5 項中至少 4 項症狀 及\n檢驗條件二、(一),且經衛生福利部疾病管制署庫賈氏病之病\n例審查會議專家審查確定。",
    "probable_case": "具有下列任一個條件,且經衛生福利部疾病管制署庫賈氏病之\n病例審查會議專家審查確定:\n1. 符合臨床條件二、(一) 與\n臨床條件二、(二)5 項中至少 4 項症狀 及\n檢驗條件二、(一)與(二)。\n2. 符合臨床條件二、(一) 及\n檢驗條件二、(三)。",
    "confirmed_case": "符合臨床條件二、(一)第 1 項症狀 與 檢驗條件二、(四),\n且經衛生福利部疾病管制署庫賈氏病之病例審查會議專家審\n查確定。\n104年7月16日核定"
  },
  {
    "name": "弓形蟲感染症",
    "url": "https://www.cdc.gov.tw/File/Get/CtQBEKJZfLJQIYl_5ab5dg",
    "source_category": "第四類",
    "content": "弓形蟲感染症\n(Toxoplasmosis)\n一、臨床條件\n具備下列任一條件者:\n(一)先天性感染者:新生兒出生後出現疑似弓形蟲感染症,如:腦鈣\n化、水腦、小腦、視網膜脈絡膜炎、青光眼、肺炎、心肌炎、肝脾腫\n大、皮疹、新生兒黃疸等症狀。\n(二)後天感染者:大部分無症狀,僅10%~20%的病人會於急性期出\n現淋巴結腫大或類似感冒症狀。免疫系統缺陷的人則可能有視網膜\n脈絡膜炎、肺炎、心包膜炎、心肌炎、腦炎等症狀。\n二、檢驗條件\n具有下列任一個條件:\n(一)組織切片發現弓形蟲。\n(二)臨床檢體(血液或體液)分離並鑑定出弓形蟲(Toxoplasma\ngondii)。\n(三)臨床檢體分子生物學核酸檢測陽性。\n(四) 血清學檢測抗體陽性:成對血清中,抗弓形蟲之 IgM 及 IgG 抗\n體陽性,且第一次血清 IgG 親和力試驗為低親和力,第二次血\n清抗弓形蟲之 IgG 抗體顯著上升。\n三、流行病學條件\n具有下列任一個條件:\n(一) 曾有貓的接觸史。\n(二) 食入未經煮熟的動物肉、組織或體液,或食入含有貓排出的卵\n囊污染的食物或水。。\n2020年8月\n(三) 母子垂直感染。\n(四) 輸血、器官移植感染。\n四、通報定義\n具有下列任一個條件:\n(一)符合臨床條件。\n(二)經醫院自行檢驗,符合檢驗條件。\n五、病例分類\n(一) 可能病例:NA\n(二) 極可能病例:雖未經實驗室證實,但符合臨床條件及流行病學\n條件。\n(三) 確定病例:符合臨床條件及任一項檢驗條件。\n六、檢體採檢送驗事項\n傳染病名稱 採檢項目 採檢目的 採檢時機 採檢量及規定 送驗 注意事項\n抗凝固全 病原體檢 未投藥前立 以含抗凝劑(EDTA 抗凝固全血採檢步\n血 測 即採檢 採血管採集 5 mL 驟請參考第 3.2 節。\n血液,並混合均勻。\n腦脊髓液採檢步驟\n請參考第3.6節,由醫\n腦脊髓液 病原體檢 未投藥前立 以無菌檢體小瓶收 師採檢。\n測 即採檢 集0.5mL腦脊髓液\n弓形蟲\n2-8oC\n共需採檢2次。但一\n(B 類感染\n採血清 IgG 及 IgM\n感染症\n性 物 質\n皆為陰性者,則不需\nP650包裝)\n再做二採。\n急性期(發\n血清檢體見 2.8.3 及\n病7日內);\n血清 抗體檢測 恢復期(發 以無菌試管收集 2.8.4 備註說明,血\n3 mL 血清 清採檢步驟請參考\n病14天後)\n第3.3 節。\n若無法取得急性期\n之血液,請採間隔\n14天-20天之恢復期\n血清,分2次送驗。\n2020年8月",
    "pdf_path": "pdfs/弓形蟲感染症.pdf",
    "臨床條件": "具備下列任一條件者:\n(一)先天性感染者:新生兒出生後出現疑似弓形蟲感染症,如:腦鈣\n化、水腦、小腦、視網膜脈絡膜炎、青光眼、肺炎、心肌炎、肝脾腫\n大、皮疹、新生兒黃疸等症狀。\n(二)後天感染者:大部分無症狀,僅10%~20%的病人會於急性期出\n現淋巴結腫大或類似感冒症狀。免疫系統缺陷的人則可能有視網膜\n脈絡膜炎、肺炎、心包膜炎、心肌炎、腦炎等症狀。",
    "檢驗條件": "具有下列任一個條件:\n(一)組織切片發現弓形蟲。\n(二)臨床檢體(血液或體液)分離並鑑定出弓形蟲(Toxoplasma\ngondii)。\n(三)臨床檢體分子生物學核酸檢測陽性。\n(四) 血清學檢測抗體陽性:成對血清中,抗弓形蟲之 IgM 及 IgG 抗\n體陽性,且第一次血清 IgG 親和力試驗為低親和力,第二次血\n清抗弓形蟲之 IgG 抗體顯著上升。",
    "流行病學條件": "具有下列任一個條件:\n(一) 曾有貓的接觸史。\n(二) 食入未經煮熟的動物肉、組織或體液,或食入含有貓排出的卵\n囊污染的食物或水。。\n2020年8月\n(三) 母子垂直感染。\n(四) 輸血、器官移植感染。",
    "通報定義": "具有下列任一個條件:\n(一)符合臨床條件。\n(二)經醫院自行檢驗,符合檢驗條件。",
    "疾病分類": "(一) 可能病例:NA\n(二) 極可能病例:雖未經實驗室證實,但符合臨床條件及流行病學\n條件。\n(三) 確定病例:符合臨床條件及任一項檢驗條件。",
    "檢體採檢送驗事項": "傳染病名稱 採檢項目 採檢目的 採檢時機 採檢量及規定 送驗 注意事項\n抗凝固全 病原體檢 未投藥前立 以含抗凝劑(EDTA 抗凝固全血採檢步\n血 測 即採檢 採血管採集 5 mL 驟請參考第 3.2 節。\n血液,並混合均勻。\n腦脊髓液採檢步驟\n請參考第3.6節,由醫\n腦脊髓液 病原體檢 未投藥前立 以無菌檢體小瓶收 師採檢。\n測 即採檢 集0.5mL腦脊髓液\n弓形蟲\n2-8oC\n共需採檢2次。但一\n(B 類感染\n採血清 IgG 及 IgM\n感染症\n性 物 質\n皆為陰性者,則不需\nP650包裝)\n再做二採。\n急性期(發\n血清檢體見 2.8.3 及\n病7日內);\n血清 抗體檢測 恢復期(發 以無菌試管收集 2.8.4 備註說明,血\n3 mL 血清 清採檢步驟請參考\n病14天後)\n第3.3 節。\n若無法取得急性期\n之血液,請採間隔\n14天-20天之恢復期\n血清,分2次送驗。\n2020年8月",
    "english_name": "Toxoplasmosis",
    "suspected_case": "NA",
    "probable_case": "雖未經實驗室證實,但符合臨床條件及流行病學\n條件。",
    "confirmed_case": "符合臨床條件及任一項檢驗條件。"
  },
  {
    "name": "後天免疫缺乏症候群",
    "url": "https://www.cdc.gov.tw/File/Get/eJQb1JmRMxdxMgL8L5F3RA",
    "source_category": "第三類",
    "content": "後天免疫缺乏症候群\n(AIDS)\n一、臨床條件\n經醫師診斷為伺機性感染或AIDS 有關的腫瘤,如:肺囊蟲肺炎、\n弓形蟲感染、隱球菌症、食道念珠菌症等(詳如次頁後天免疫缺\n乏症候群個案報告單背面表列,AIDS 之診斷依據)。\n二、檢驗條件\n確認為HIV感染,且依不同年齡,其CD4值或比例為:\n(一)年齡滿 6 歲(含)以上:<200 Cells/mm3 或<14%。\n(二)年齡介於 1 至 6 歲:<500 Cells/mm3 或<22%。\n(三)年齡小於 1 歲:<750 Cells/mm3 或<26%。\n三、流行病學條件\nNA\n四、通報定義\n具有下列任一個條件,且排除 HIV 急性初期感染*\n(一)確認為 HIV 感染者,符合臨床條件。\n(二)確認為 HIV 感染者,CD4 值或比例符合檢驗條件(CD4\n值為診斷之優先考量,若無 CD4 值才採用 CD4 比例。)\n* HIV 急性初期感染(符合以下任一條件):\n1. 依據過去檢驗紀錄:本次 HIV-1/2 抗體確認檢驗方法\n(抗體免疫層析檢驗法或西方墨點法)或 HIV 分子生物\n學核酸檢測(NAT)陽性,且確診通報前 180 天內,有\n任一 HIV 檢驗結果是陰性或未確定者,包含:HIV 抗原/\n抗體複合型篩檢、抗體篩檢(EIA 或 PA)、HIV-1/2抗\n體確認檢驗或 HIV 分子生物學核酸檢測(NAT)。\n2. 本次確診檢驗流程中,於 HIV 分子生物學核酸檢測NAT\n檢驗陽性前後 180 日內有任一抗體檢驗結果為陰性或未\n確定者。\n3. 本次檢驗流程中,HIV 抗原/抗體複合型篩檢結果為「抗\n原陽性」者。\n五、疾病分類\n(一)可能病例:\nNA\n(二)極可能病例:\nNA\n(三)確定病例:\n排除 HIV 急性初期感染,且符合臨床條件或檢驗條件。\n【密件】 後天免疫缺乏症候群(AIDS)個案報告單\n※【確認為 HIV 感染者,欲通報 AIDS 前,請先排除個案為「急性初期感染」再行通報,若不清楚最近\n180 天內的檢驗結果,符合 AIDS 通報定義仍請通報】\nHIV 急性初期感染(符合以下任一條件):\n(1) 依據過去檢驗紀錄:本次 HIV-1/2 抗體確認檢驗方法(抗體免疫層析檢驗法或西方墨點法)或 HIV\n分子生物學核酸檢測(NAT)陽性,且確診通報前 180 天內,有任一 HIV 檢驗結果是陰性或未確定\n者,包含:HIV 抗原/抗體複合型篩檢、抗體篩檢(EIA 或 PA)、HIV-1/2 抗體確認檢驗或 HIV 分子\n生物學核酸檢測(NAT)。\n(2) 個案本次確診檢驗流程中,於 HIV 分子生物學核酸檢測 NAT 檢驗陽性前後 180 日內有任一抗體檢\n驗結果為陰性或未確定者。\n(3) 本次檢驗流程中,HIV 抗原/抗體複合型篩檢結果為「抗原陽性」者。\nHIV(+)NO.\n□□□-□□-□□\n電腦編號:\n醫師診斷日: 年 月 日 AIDS NO.\n醫師報告日: 年 月 日 □第一次報告 □資料更新\n(衛福部編號,請勿填寫)\n個案目前狀況:□1.住院治療 □2.門診治療 □3.死亡( 年 月 日)\n□4.離境( 年 月 日) □5.其他 □6.不詳\n一、 基本資料\n出生日期 性別 電話\n個案姓名 身分證字號(護照號碼)\n年 月 日 男 女 (區域碼)話號碼\n公\n宅\n□中華民國 □台灣地區 □大陸地區 已婚 未婚 離婚 分居 鰥寡\n國籍 婚姻狀況\n□外籍 (填寫國家名稱)\n是 是\n職業 目前是否懷孕? 是否曾經受過 HIV 抗體檢查?\n否 否\n縣 鄉市 村\n市 鎮區 里 鄰\n戶籍所在地\n路\n街 段 巷 弄 號之 ( 樓)\n縣 鄉市 村\n市 鎮區 里 鄰\n現住址\n路\n街 段 巷 弄 號之 ( 樓)\n二、 AIDS 確診之診斷依據\n確認為 HIV 感染者,且\n□1.CD4 值或比例符合檢驗條件 (CD4= cells/mm3 或 %)或 □2.出現以下任一種伺機性感染\n三、 臨床症狀診斷依據:\n日 日\n診斷依據(疾病) 勾 期 診斷依據(疾病) 勾 期\n選 選\n年 月 年 月\nCandidiasis of bronchi, trachea, or lungs Lymphoma, immunoblastic (or equivalent term)\n念珠菌症(支氣管、氣管、或肺) 淋巴瘤(免疫芽細胞)\nCandidiasis, esophageal Lymphoma, primary, of brain\n念珠菌症(食道) 淋巴瘤(腦部之初發性)\nCoccidioidomycosis, disseminated or extrapulmonary Mycobacterium avium complex or M. kansasii,\n珠狀孢子蟲病(散佈性或肺外部位) disseminated or extrapulmonary\n散佈性或肺外部位禽型分枝桿菌群或堪薩斯分枝桿\n菌感染\n日 日\n診斷依據(疾病) 勾 期 診斷依據(疾病) 勾 期\n選 選\n年 月 年 月\nCryptococcosis, extrapulmonary M. tuberculosis infection, pulmonary\n隱球菌症(肺外) 肺結核***\nCryptosporidiosis, chronic intestinal (greater than 1\nM. tuberculosis infection, extrapulmonary\nmonth's duration)\n肺外結核\n隱孢子蟲症(慢性腸炎)(一個月以上)\nMycobacterium, other species or unidentified\nCytomegalovirus disease (other than liver, spleen, or\nspecies, disseminated or extrapulmonary\nnodes)\n其他種類或未確定種類的分枝桿菌引起的散佈性或\n巨細胞病毒症(肝臟、脾臟或淋巴結以外)\n肺外部位感染\nPneumonia, recurrent (more than one episode in\nCytomegalovirus retinitis (with loss of vision)\na 1-year period)\n巨細胞病毒性視網膜炎**\n一年之內復發的肺炎***\nEncephalopathy, HIV-related Pneumocystis carinii (jiroveci) pneumonia\n愛滋病毒性腦病變 肺囊蟲肺炎\nHerpes simplex: chronic ulcer(s) greater than 1\nmonth's duration); or bronchitis, pneumonitis, or Progressive multifocal leukoencephalopathy\nesophagitis 單純性疱疹病毒感染:慢性潰瘍(一個月\n進行性多發性白質腦病變\n以上)或支氣管炎、肺炎及食道炎**\nHistoplasmosis, disseminated or extrapulmonary Salmonella septicemia, recurrent\n組織胞漿菌症(散佈性或肺外部位) 沙門氏菌血症(再發性)\nIsosporiasis, chronic intestinal (greater than 1\nmonth's duration)等孢子蟲症(慢性腸炎)(一個月以 Toxoplasmosis of brain 腦部弓蟲症**\n上)\nKaposi’s sarcoma Wasting syndrome due to HIV\n卡波西氏肉瘤 HIV 引起的消耗性症候群\nLymphoma, Burkitt's (or equivalent term) Cervical cancer, invasive\n勃克氏淋巴瘤 侵犯性的子宮頸癌***\nPenicilliosis marneffei, disseminated or Bacterial infections, multiple or recurrent\nextrapulmonary 青黴菌感染(散佈性或肺外部位) 多重或復發的細菌感染*\n*Only among children aged <6 years. 僅適用於年齡 6 歲以下個案。**Onset at age >1 month. 僅適用於年齡滿 1 個月後診斷之個案。\n***Only among adults, adolescents, and children aged ≥6 years. 僅適用於年齡滿 6 歲(含)以上個案。\n備註(補充資料):\n報告所 院 所\n名 稱 住 址\n診斷師 聯 絡 ( )\n簽 章 電 話\n此欄由衛生局填寫( 縣市衛生局)\n收到日期 承辦人簽章 科(課)長簽章\n年 月 日\n衛生福利部疾病管制署 (02)2395-9825 FAX:(02)2391-3482",
    "pdf_path": "pdfs/後天免疫缺乏症候群.pdf",
    "臨床條件": "經醫師診斷為伺機性感染或AIDS 有關的腫瘤,如:肺囊蟲肺炎、\n弓形蟲感染、隱球菌症、食道念珠菌症等(詳如次頁後天免疫缺\n乏症候群個案報告單背面表列,AIDS 之診斷依據)。",
    "檢驗條件": "確認為HIV感染,且依不同年齡,其CD4值或比例為:\n(一)年齡滿 6 歲(含)以上:<200 Cells/mm3 或<14%。\n(二)年齡介於 1 至 6 歲:<500 Cells/mm3 或<22%。\n(三)年齡小於 1 歲:<750 Cells/mm3 或<26%。",
    "流行病學條件": "NA",
    "通報定義": "具有下列任一個條件,且排除 HIV 急性初期感染*\n(一)確認為 HIV 感染者,符合臨床條件。\n(二)確認為 HIV 感染者,CD4 值或比例符合檢驗條件(CD4\n值為診斷之優先考量,若無 CD4 值才採用 CD4 比例。)\n* HIV 急性初期感染(符合以下任一條件):\n1. 依據過去檢驗紀錄:本次 HIV-1/2 抗體確認檢驗方法\n(抗體免疫層析檢驗法或西方墨點法)或 HIV 分子生物\n學核酸檢測(NAT)陽性,且確診通報前 180 天內,有\n任一 HIV 檢驗結果是陰性或未確定者,包含:HIV 抗原/\n抗體複合型篩檢、抗體篩檢(EIA 或 PA)、HIV-1/2抗\n體確認檢驗或 HIV 分子生物學核酸檢測(NAT)。\n2. 本次確診檢驗流程中,於 HIV 分子生物學核酸檢測NAT\n檢驗陽性前後 180 日內有任一抗體檢驗結果為陰性或未\n確定者。\n3. 本次檢驗流程中,HIV 抗原/抗體複合型篩檢結果為「抗\n原陽性」者。",
    "疾病分類": "(一)可能病例:\nNA\n(二)極可能病例:\nNA\n(三)確定病例:\n排除 HIV 急性初期感染,且符合臨床條件或檢驗條件。\n【密件】 後天免疫缺乏症候群(AIDS)個案報告單\n※【確認為 HIV 感染者,欲通報 AIDS 前,請先排除個案為「急性初期感染」再行通報,若不清楚最近\n180 天內的檢驗結果,符合 AIDS 通報定義仍請通報】\nHIV 急性初期感染(符合以下任一條件):\n(1) 依據過去檢驗紀錄:本次 HIV-1/2 抗體確認檢驗方法(抗體免疫層析檢驗法或西方墨點法)或 HIV\n分子生物學核酸檢測(NAT)陽性,且確診通報前 180 天內,有任一 HIV 檢驗結果是陰性或未確定\n者,包含:HIV 抗原/抗體複合型篩檢、抗體篩檢(EIA 或 PA)、HIV-1/2 抗體確認檢驗或 HIV 分子\n生物學核酸檢測(NAT)。\n(2) 個案本次確診檢驗流程中,於 HIV 分子生物學核酸檢測 NAT 檢驗陽性前後 180 日內有任一抗體檢\n驗結果為陰性或未確定者。\n(3) 本次檢驗流程中,HIV 抗原/抗體複合型篩檢結果為「抗原陽性」者。\nHIV(+)NO.\n□□□-□□-□□\n電腦編號:\n醫師診斷日: 年 月 日 AIDS NO.\n醫師報告日: 年 月 日 □第一次報告 □資料更新\n(衛福部編號,請勿填寫)\n個案目前狀況:□1.住院治療 □2.門診治療 □3.死亡( 年 月 日)\n□4.離境( 年 月 日) □5.其他 □6.不詳\n一、 基本資料\n出生日期 性別 電話\n個案姓名 身分證字號(護照號碼)\n年 月 日 男 女 (區域碼)話號碼\n公\n宅\n□中華民國 □台灣地區 □大陸地區 已婚 未婚 離婚 分居 鰥寡\n國籍 婚姻狀況\n□外籍 (填寫國家名稱)\n是 是\n職業 目前是否懷孕? 是否曾經受過 HIV 抗體檢查?\n否 否\n縣 鄉市 村\n市 鎮區 里 鄰\n戶籍所在地\n路\n街 段 巷 弄 號之 ( 樓)\n縣 鄉市 村\n市 鎮區 里 鄰\n現住址\n路\n街 段 巷 弄 號之 ( 樓)\n二、 AIDS 確診之診斷依據\n確認為 HIV 感染者,且\n□1.CD4 值或比例符合檢驗條件 (CD4= cells/mm3 或 %)或 □2.出現以下任一種伺機性感染\n三、 臨床症狀診斷依據:\n日 日\n診斷依據(疾病) 勾 期 診斷依據(疾病) 勾 期\n選 選\n年 月 年 月\nCandidiasis of bronchi, trachea, or lungs Lymphoma, immunoblastic (or equivalent term)\n念珠菌症(支氣管、氣管、或肺) 淋巴瘤(免疫芽細胞)\nCandidiasis, esophageal Lymphoma, primary, of brain\n念珠菌症(食道) 淋巴瘤(腦部之初發性)\nCoccidioidomycosis, disseminated or extrapulmonary Mycobacterium avium complex or M. kansasii,\n珠狀孢子蟲病(散佈性或肺外部位) disseminated or extrapulmonary\n散佈性或肺外部位禽型分枝桿菌群或堪薩斯分枝桿\n菌感染\n日 日\n診斷依據(疾病) 勾 期 診斷依據(疾病) 勾 期\n選 選\n年 月 年 月\nCryptococcosis, extrapulmonary M. tuberculosis infection, pulmonary\n隱球菌症(肺外) 肺結核***\nCryptosporidiosis, chronic intestinal (greater than 1\nM. tuberculosis infection, extrapulmonary\nmonth's duration)\n肺外結核\n隱孢子蟲症(慢性腸炎)(一個月以上)\nMycobacterium, other species or unidentified\nCytomegalovirus disease (other than liver, spleen, or\nspecies, disseminated or extrapulmonary\nnodes)\n其他種類或未確定種類的分枝桿菌引起的散佈性或\n巨細胞病毒症(肝臟、脾臟或淋巴結以外)\n肺外部位感染\nPneumonia, recurrent (more than one episode in\nCytomegalovirus retinitis (with loss of vision)\na 1-year period)\n巨細胞病毒性視網膜炎**\n一年之內復發的肺炎***\nEncephalopathy, HIV-related Pneumocystis carinii (jiroveci) pneumonia\n愛滋病毒性腦病變 肺囊蟲肺炎\nHerpes simplex: chronic ulcer(s) greater than 1\nmonth's duration); or bronchitis, pneumonitis, or Progressive multifocal leukoencephalopathy\nesophagitis 單純性疱疹病毒感染:慢性潰瘍(一個月\n進行性多發性白質腦病變\n以上)或支氣管炎、肺炎及食道炎**\nHistoplasmosis, disseminated or extrapulmonary Salmonella septicemia, recurrent\n組織胞漿菌症(散佈性或肺外部位) 沙門氏菌血症(再發性)\nIsosporiasis, chronic intestinal (greater than 1\nmonth's duration)等孢子蟲症(慢性腸炎)(一個月以 Toxoplasmosis of brain 腦部弓蟲症**\n上)\nKaposi’s sarcoma Wasting syndrome due to HIV\n卡波西氏肉瘤 HIV 引起的消耗性症候群\nLymphoma, Burkitt's (or equivalent term) Cervical cancer, invasive\n勃克氏淋巴瘤 侵犯性的子宮頸癌***\nPenicilliosis marneffei, disseminated or Bacterial infections, multiple or recurrent\nextrapulmonary 青黴菌感染(散佈性或肺外部位) 多重或復發的細菌感染*\n*Only among children aged <6 years. 僅適用於年齡 6 歲以下個案。**Onset at age >1 month. 僅適用於年齡滿 1 個月後診斷之個案。\n***Only among adults, adolescents, and children aged ≥6 years. 僅適用於年齡滿 6 歲(含)以上個案。\n備註(補充資料):\n報告所 院 所\n名 稱 住 址\n診斷師 聯 絡 ( )\n簽 章 電 話\n此欄由衛生局填寫( 縣市衛生局)\n收到日期 承辦人簽章 科(課)長簽章\n年 月 日\n衛生福利部疾病管制署 (02)2395-9825 FAX:(02)2391-3482",
    "檢體採檢送驗事項": "",
    "english_name": "AIDS",
    "suspected_case": "NA",
    "probable_case": "NA",
    "confirmed_case": "排除 HIV 急性初期感染,且符合臨床條件或檢驗條件。\n【密件】 後天免疫缺乏症候群(AIDS)個案報告單\n※【確認為 HIV 感染者,欲通報 AIDS 前,請先排除個案為「急性初期感染」再行通報,若不清楚最近\n180 天內的檢驗結果,符合 AIDS 通報定義仍請通報】\nHIV 急性初期感染(符合以下任一條件):\n(1) 依據過去檢驗紀錄:本次 HIV-1/2 抗體確認檢驗方法(抗體免疫層析檢驗法或西方墨點法)或 HIV\n分子生物學核酸檢測(NAT)陽性,且確診通報前 180 天內,有任一 HIV 檢驗結果是陰性或未確定\n者,包含:HIV 抗原/抗體複合型篩檢、抗體篩檢(EIA 或 PA)、HIV-1/2 抗體確認檢驗或 HIV 分子\n生物學核酸檢測(NAT)。\n(2) 個案本次確診檢驗流程中,於 HIV 分子生物學核酸檢測 NAT 檢驗陽性前後 180 日內有任一抗體檢\n驗結果為陰性或未確定者。\n(3) 本次檢驗流程中,HIV 抗原/抗體複合型篩檢結果為「抗原陽性」者。\nHIV(+)NO.\n□□□-□□-□□\n電腦編號:\n醫師診斷日: 年 月 日 AIDS NO.\n醫師報告日: 年 月 日 □第一次報告 □資料更新\n(衛福部編號,請勿填寫)\n個案目前狀況:□1.住院治療 □2.門診治療 □3.死亡( 年 月 日)\n□4.離境( 年 月 日) □5.其他 □6.不詳\n一、 基本資料\n出生日期 性別 電話\n個案姓名 身分證字號(護照號碼)\n年 月 日 男 女 (區域碼)話號碼\n公\n宅\n□中華民國 □台灣地區 □大陸地區 已婚 未婚 離婚 分居 鰥寡\n國籍 婚姻狀況\n□外籍 (填寫國家名稱)\n是 是\n職業 目前是否懷孕? 是否曾經受過 HIV 抗體檢查?\n否 否\n縣 鄉市 村\n市 鎮區 里 鄰\n戶籍所在地\n路\n街 段 巷 弄 號之 ( 樓)\n縣 鄉市 村\n市 鎮區 里 鄰\n現住址\n路\n街 段 巷 弄 號之 ( 樓)\n二、 AIDS 確診之診斷依據\n確認為 HIV 感染者,且\n□1.CD4 值或比例符合檢驗條件 (CD4= cells/mm3 或 %)或 □2.出現以下任一種伺機性感染\n三、 臨床症狀診斷依據:\n日 日\n診斷依據(疾病) 勾 期 診斷依據(疾病) 勾 期\n選 選\n年 月 年 月\nCandidiasis of bronchi, trachea, or lungs Lymphoma, immunoblastic (or equivalent term)\n念珠菌症(支氣管、氣管、或肺) 淋巴瘤(免疫芽細胞)\nCandidiasis, esophageal Lymphoma, primary, of brain\n念珠菌症(食道) 淋巴瘤(腦部之初發性)\nCoccidioidomycosis, disseminated or extrapulmonary Mycobacterium avium complex or M. kansasii,\n珠狀孢子蟲病(散佈性或肺外部位) disseminated or extrapulmonary\n散佈性或肺外部位禽型分枝桿菌群或堪薩斯分枝桿\n菌感染\n日 日\n診斷依據(疾病) 勾 期 診斷依據(疾病) 勾 期\n選 選\n年 月 年 月\nCryptococcosis, extrapulmonary M. tuberculosis infection, pulmonary\n隱球菌症(肺外) 肺結核***\nCryptosporidiosis, chronic intestinal (greater than 1\nM. tuberculosis infection, extrapulmonary\nmonth's duration)\n肺外結核\n隱孢子蟲症(慢性腸炎)(一個月以上)\nMycobacterium, other species or unidentified\nCytomegalovirus disease (other than liver, spleen, or\nspecies, disseminated or extrapulmonary\nnodes)\n其他種類或未確定種類的分枝桿菌引起的散佈性或\n巨細胞病毒症(肝臟、脾臟或淋巴結以外)\n肺外部位感染\nPneumonia, recurrent (more than one episode in\nCytomegalovirus retinitis (with loss of vision)\na 1-year period)\n巨細胞病毒性視網膜炎**\n一年之內復發的肺炎***\nEncephalopathy, HIV-related Pneumocystis carinii (jiroveci) pneumonia\n愛滋病毒性腦病變 肺囊蟲肺炎\nHerpes simplex: chronic ulcer(s) greater than 1\nmonth's duration); or bronchitis, pneumonitis, or Progressive multifocal leukoencephalopathy\nesophagitis 單純性疱疹病毒感染:慢性潰瘍(一個月\n進行性多發性白質腦病變\n以上)或支氣管炎、肺炎及食道炎**\nHistoplasmosis, disseminated or extrapulmonary Salmonella septicemia, recurrent\n組織胞漿菌症(散佈性或肺外部位) 沙門氏菌血症(再發性)\nIsosporiasis, chronic intestinal (greater than 1\nmonth's duration)等孢子蟲症(慢性腸炎)(一個月以 Toxoplasmosis of brain 腦部弓蟲症**\n上)\nKaposi’s sarcoma Wasting syndrome due to HIV\n卡波西氏肉瘤 HIV 引起的消耗性症候群\nLymphoma, Burkitt's (or equivalent term) Cervical cancer, invasive\n勃克氏淋巴瘤 侵犯性的子宮頸癌***\nPenicilliosis marneffei, disseminated or Bacterial infections, multiple or recurrent\nextrapulmonary 青黴菌感染(散佈性或肺外部位) 多重或復發的細菌感染*\n*Only among children aged <6 years. 僅適用於年齡 6 歲以下個案。**Onset at age >1 month. 僅適用於年齡滿 1 個月後診斷之個案。\n***Only among adults, adolescents, and children aged ≥6 years. 僅適用於年齡滿 6 歲(含)以上個案。\n備註(補充資料):\n報告所 院 所\n名 稱 住 址\n診斷師 聯 絡 ( )\n簽 章 電 話\n此欄由衛生局填寫( 縣市衛生局)\n收到日期 承辦人簽章 科(課)長簽章\n年 月 日\n衛生福利部疾病管制署 (02)2395-9825 FAX:(02)2391-3482"
  },
  {
    "name": "德國麻疹",
    "url": "https://www.cdc.gov.tw/File/Get/rOf66uuG5CobgGeRxR-Jtw",
    "source_category": "第二類",
    "content": "德國麻疹\nRubella\n( )\n一、 臨床條件\n同時具備下列症狀者:\n(一) 急性全身出現斑丘疹。\n(二) 耳溫或肛溫≧37.2°C。\n(三) 有關節炎、關節痛、急性頸部或頭部淋巴腺腫大、或結膜炎等\n症狀之一者。\n二、 檢驗條件\n具有下列任一個條件:\n(一) 臨床檢體(血液或咽喉擦拭液)分離並鑑定出德國麻疹病毒\n(Rubella virus)。\n(二) 臨床檢體分子生物學核酸檢測陽性。\n(三) 血清學抗體檢測陽性:單一血清檢體 IgM 抗體陽性或急性期\n與恢復期之成對血清檢體 IgG 抗體顯著上升。\n三、 流行病學條件\n具有下列任一個條件:\n(一) 發病前三週內,曾有德國麻疹流行地區旅遊史。\n(二) 確定病例之接觸者,或曾直接接觸確定病例之鼻咽分泌物。\n四、 通報定義\n具有下列任一個條件:\n(一) 符合臨床條件。\n(二) 經醫院自行檢驗,符合檢驗條件。\n五、 疾病分類\n為配合三麻一風疾病根除保全與消除作業,部分個案需由防疫醫師進\n行病例判定。\n(一) 可能病例:\n符合臨床條件。\n(二) 極可能病例:\n雖未經實驗室檢驗證實,但符合臨床條件及流行病學條件任一\n項。\n(三) 確定病例:\n具有下列任一個條件:\n1. 符合臨床條件及檢驗條件。\n2. 符合臨床條件,未接種德國麻疹相關疫苗或接種史不明,\n且符合流行病學條件\n六、 檢體採檢送驗事項\n採檢項目 檢體種類 採檢目的 採檢時機 採檢規定 運送條件 注意事項\n1. 檢體對象若\n為懷孕婦女,請\n特別於附送之檢\n體送驗單內註\n急性期(發\n明”孕婦”。\n病 7 天\n2. 血清檢體必\n內);恢復期以無菌試管收集至\n血清 抗體檢測 要時需採檢 2\n( 發 病少 2 mL 血清。\n次。\n14-40 天之\n德國麻疹 低溫 3. 血清檢體見\n間)\n2.8.3及2.8.4備\n註說明及血清採\n檢步驟請參考第\n3.3 節。\n以無菌病毒拭子之 咽喉採檢見 2.8.5\n咽喉擦拭 發病 棉棒擦拭咽喉,插 備註說明及咽喉\n病原體檢測\n液 7 天內 入病毒保存輸送 採檢步驟請參考\n管。 第3.7節及圖3.7。",
    "pdf_path": "pdfs/德國麻疹.pdf",
    "臨床條件": "同時具備下列症狀者:\n(一) 急性全身出現斑丘疹。\n(二) 耳溫或肛溫≧37.2°C。\n(三) 有關節炎、關節痛、急性頸部或頭部淋巴腺腫大、或結膜炎等\n症狀之一者。",
    "檢驗條件": "具有下列任一個條件:\n(一) 臨床檢體(血液或咽喉擦拭液)分離並鑑定出德國麻疹病毒\n(Rubella virus)。\n(二) 臨床檢體分子生物學核酸檢測陽性。\n(三) 血清學抗體檢測陽性:單一血清檢體 IgM 抗體陽性或急性期\n與恢復期之成對血清檢體 IgG 抗體顯著上升。",
    "流行病學條件": "具有下列任一個條件:\n(一) 發病前三週內,曾有德國麻疹流行地區旅遊史。\n(二) 確定病例之接觸者,或曾直接接觸確定病例之鼻咽分泌物。",
    "通報定義": "具有下列任一個條件:\n(一) 符合臨床條件。\n(二) 經醫院自行檢驗,符合檢驗條件。",
    "疾病分類": "為配合三麻一風疾病根除保全與消除作業,部分個案需由防疫醫師進\n行病例判定。\n(一) 可能病例:\n符合臨床條件。\n(二) 極可能病例:\n雖未經實驗室檢驗證實,但符合臨床條件及流行病學條件任一\n項。\n(三) 確定病例:\n具有下列任一個條件:\n1. 符合臨床條件及檢驗條件。\n2. 符合臨床條件,未接種德國麻疹相關疫苗或接種史不明,\n且符合流行病學條件",
    "檢體採檢送驗事項": "採檢項目 檢體種類 採檢目的 採檢時機 採檢規定 運送條件 注意事項\n1. 檢體對象若\n為懷孕婦女,請\n特別於附送之檢\n體送驗單內註\n急性期(發\n明”孕婦”。\n病 7 天\n2. 血清檢體必\n內);恢復期以無菌試管收集至\n血清 抗體檢測 要時需採檢 2\n( 發 病少 2 mL 血清。\n次。\n14-40 天之\n德國麻疹 低溫 3. 血清檢體見\n間)\n2.8.3及2.8.4備\n註說明及血清採\n檢步驟請參考第\n3.3 節。\n以無菌病毒拭子之 咽喉採檢見 2.8.5\n咽喉擦拭 發病 棉棒擦拭咽喉,插 備註說明及咽喉\n病原體檢測\n液 7 天內 入病毒保存輸送 採檢步驟請參考\n管。 第3.7節及圖3.7。",
    "english_name": "Rubella",
    "suspected_case": "符合臨床條件。",
    "probable_case": "雖未經實驗室檢驗證實,但符合臨床條件及流行病學條件任一\n項。",
    "confirmed_case": "具有下列任一個條件:\n1. 符合臨床條件及檢驗條件。\n2. 符合臨床條件,未接種德國麻疹相關疫苗或接種史不明,\n且符合流行病學條件"
  },
  {
    "name": "急性病毒性A型肝炎",
    "url": "https://www.cdc.gov.tw/File/Get/O10f9cko_ouJDUc9zGVyNQ",
    "source_category": "第二類",
    "content": "急性病毒性A型肝炎\n(Acute Hepatitis A)\n一、 臨床條件\n同時具有下列二個條件:\n(一) 出現急性發作症狀:包括發燒、全身倦怠、噁心、嘔吐、腹部不舒\n服等。\n(二) 黃疸或ALT上升。\n二、 檢驗條件\n具有下列任一個條件:\n(一) 血清學 A 型肝炎 IgM 抗體檢測陽性且12週內未接種A型肝炎疫\n苗。\n(二) A型肝炎病毒核酸(RNA)檢測陽性。\n三、 流行病學條件\n具有下列任一個條件:\n(一) 於發病前15-50天內曾與確定病例有密切接觸(例如:同住、性接觸\n等)。\n(二) 食用受污染的水、食物等,或曾與確定病例暴露共同感染源。\n四、 通報定義\n(一) 符合臨床條件及檢驗條件者。\n(二) 符合臨床條件及流行病學條件者。\n(三) 符合檢驗條件(二)。\n五、 疾病分類\n(一)可能病例:\nNA\n(二)極可能病例:\n符合臨床條件及流行病學條件者。\n(三)確定病例:\n具有下列任一個條件:\n1. 符合臨床條件及檢驗條件(一)。\n2. 符合檢驗條件(二)。\n2024年11月12日修訂,2025年1月1日實施\n六、檢體採檢送驗事項:\n請參閱「傳染病檢體採檢手冊」(路徑:衛生福利部疾病管制署全球資訊\n網(https://www.cdc.gov.tw/)/應用專區/檢驗/傳染病檢體採檢手冊)。\n2024年11月12日修訂,2025年1月1日實施",
    "pdf_path": "pdfs/急性病毒性A型肝炎.pdf",
    "臨床條件": "同時具有下列二個條件:\n(一) 出現急性發作症狀:包括發燒、全身倦怠、噁心、嘔吐、腹部不舒\n服等。\n(二) 黃疸或ALT上升。",
    "檢驗條件": "具有下列任一個條件:\n(一) 血清學 A 型肝炎 IgM 抗體檢測陽性且12週內未接種A型肝炎疫\n苗。\n(二) A型肝炎病毒核酸(RNA)檢測陽性。",
    "流行病學條件": "具有下列任一個條件:\n(一) 於發病前15-50天內曾與確定病例有密切接觸(例如:同住、性接觸\n等)。\n(二) 食用受污染的水、食物等,或曾與確定病例暴露共同感染源。",
    "通報定義": "(一) 符合臨床條件及檢驗條件者。\n(二) 符合臨床條件及流行病學條件者。\n(三) 符合檢驗條件(二)。",
    "疾病分類": "(一)可能病例:\nNA\n(二)極可能病例:\n符合臨床條件及流行病學條件者。\n(三)確定病例:\n具有下列任一個條件:\n1. 符合臨床條件及檢驗條件(一)。\n2. 符合檢驗條件(二)。\n2024年11月12日修訂,2025年1月1日實施",
    "檢體採檢送驗事項": "請參閱「傳染病檢體採檢手冊」(路徑:衛生福利部疾病管制署全球資訊\n網(https://www.cdc.gov.tw/)/應用專區/檢驗/傳染病檢體採檢手冊)。\n2024年11月12日修訂,2025年1月1日實施",
    "english_name": "Acute Hepatitis A",
    "suspected_case": "NA",
    "probable_case": "符合臨床條件及流行病學條件者。",
    "confirmed_case": "具有下列任一個條件:\n1. 符合臨床條件及檢驗條件(一)。\n2. 符合檢驗條件(二)。\n2024年11月12日修訂,2025年1月1日實施"
  },
  {
    "name": "急性病毒性B型肝炎",
    "url": "https://www.cdc.gov.tw/File/Get/Ss2safe_60JK6biJb7j-jw",
    "source_category": "第三類",
    "content": "急性病毒性 B 型肝炎\n(Acute Hepatitis B)\n一、 臨床條件\n同時具有以下三項條件:\n(一) 急性肝炎症狀或肝功能異常(ALT≧100 IU/l)\n(二) 血清學 HBsAg 抗原檢測陽性。\n(三) 排除慢性肝炎急性發作或其他原因引起之肝功能異常發炎。\n二、 檢驗條件\n血清學 B 型肝炎 IgM 核心抗體(IgM anti-HBc) 檢測陽性。\n三、 流行病學條件\nNA\n四、 通報定義\n符合臨床條件或檢驗條件。\n五、 疾病分類\n(一)可能病例:\nNA\n(二)極可能病例:\nNA\n(三)確定病例:\n符合臨床條件及檢驗條件。\n六、 檢體採檢送驗事項\n採檢項目 檢體種類 採檢目的 採檢時機 採檢量及規定 送驗條件 注意事項\n1.檢體勿加入\n任何添加物。\n急性病毒 2.血清檢體見\n抗體檢 以無菌試管收\n性B 型肝 血清 立即採檢 低溫 2.8.3 及2.8.4\n測 集3 mL 血清。\n炎 備註說明,血\n清採檢步驟請\n參考第3.3 節",
    "pdf_path": "pdfs/急性病毒性B型肝炎.pdf",
    "臨床條件": "同時具有以下三項條件:\n(一) 急性肝炎症狀或肝功能異常(ALT≧100 IU/l)\n(二) 血清學 HBsAg 抗原檢測陽性。\n(三) 排除慢性肝炎急性發作或其他原因引起之肝功能異常發炎。",
    "檢驗條件": "血清學 B 型肝炎 IgM 核心抗體(IgM anti-HBc) 檢測陽性。",
    "流行病學條件": "NA",
    "通報定義": "符合臨床條件或檢驗條件。",
    "疾病分類": "(一)可能病例:\nNA\n(二)極可能病例:\nNA\n(三)確定病例:\n符合臨床條件及檢驗條件。",
    "檢體採檢送驗事項": "採檢項目 檢體種類 採檢目的 採檢時機 採檢量及規定 送驗條件 注意事項\n1.檢體勿加入\n任何添加物。\n急性病毒 2.血清檢體見\n抗體檢 以無菌試管收\n性B 型肝 血清 立即採檢 低溫 2.8.3 及2.8.4\n測 集3 mL 血清。\n炎 備註說明,血\n清採檢步驟請\n參考第3.3 節",
    "english_name": "Acute Hepatitis B",
    "suspected_case": "NA",
    "probable_case": "NA",
    "confirmed_case": "符合臨床條件及檢驗條件。"
  },
  {
    "name": "急性病毒性C型肝炎",
    "url": "https://www.cdc.gov.tw/File/Get/SDUQZqDz7qhQbweJurRWjQ",
    "source_category": "第三類",
    "content": "急性病毒性 C 型肝炎\n(Acute Hepatitis C)\n一、臨床條件\n同時具有以下二項條件:\n(一) 急性肝炎症狀或肝功能異常(ALT ≥ 100 IU/L)。\n(二) 排除慢性肝炎急性發作或其他原因引起之肝功能異常發炎。\n二、檢驗條件\n(一) 血清 C 型肝炎病毒抗體(anti-HCV)、C 型肝炎病毒核酸(HCV RNA)、\nC 型肝炎病毒抗原(HCV antigen)任一檢測陽性。\n(二) 曾檢驗血清 anti-HCV 陰性,後於一年內轉變成 anti-HCV 陽性\n※1。\n(三) 血清 HCV RNA 或 HCV antigen 檢測陽性,且 anti-HCV 陰性。\n(四) 曾檢驗血清HCV RNA或HCV antigen陰性,後於一年內轉變成HCV\nRNA 或 HCV antigen 陽性\n※2。\n(五) C 型肝炎治療療程結束且達持續性病毒反應(sustained viral response,\nSVR)者,後經檢驗轉變成 HCV RNA 或 HCV antigen 陽性,且經臨\n床及檢驗評估排除延遲復發屬新感染個案。\n三、流行病學條件\nNA\n四、通報定義\n符合臨床條件及檢驗條件第(一)項,或符合檢驗條件第(二)項至第(五)\n項之任一項。\n※1 若臨床醫師懷疑第一次 anti-HCV 陽性可能為偽陽性尚未通報,請複驗 anti-HCV,\n或檢測HCV RNA、HCV antigen,依檢驗結果,即時通報。\n※2 於 C 型肝炎治療中或曾接受治療但尚未達 SVR 之患者,若經檢測為感染不同基因\n型別C 型肝炎病毒之新感染,須通報。\n2021年2月\n五、病例分類\n(一) 可能病例:NA。\n(二) 極可能病例:NA。\n(三) 確定病例:符合臨床條件及檢驗條件第(一)項,或符合檢驗條件\n第(二)項至第(五)項之任一項。\n六、檢體採檢送驗事項\n傳染病 採檢量及 應保存種類\n採檢項目 採檢目的 採檢時間 送驗方式 注意事項\n名稱 規定 應保存時間\n抗體檢測\n1. 檢體請勿加\n入任何添加\n物。\n2. 血清檢體採\n檢注意事項\n急性 2–8 °C\n抗原檢測 以無菌試管 請參閱「傳染\n病毒性 B類感染性 陽性血清\n血清 立即採檢 收集3 mL血 病檢體採檢\nC型 物質P650 (30日)\n清 手冊」2.8.3\n肝炎 包裝\n及 2.8.4備註\n說明,血清檢\n體採檢步驟\n請參閱該手\n病原體 冊第3.3節。\n檢測\n備註:\n1. C型肝炎病毒之檢驗方法、步驟及結果判定等資訊,可參閱「傳染病標準檢驗方法手冊」。\n2. 「傳染病檢體採檢手冊」及「傳染病標準檢驗方法手冊」可至疾病管制署全球資訊網\n(https://www.cdc.gov.tw)首頁之檢驗(傳染病檢驗資訊與規定)項下查詢。\n2021年2月",
    "pdf_path": "pdfs/急性病毒性C型肝炎.pdf",
    "臨床條件": "同時具有以下二項條件:\n(一) 急性肝炎症狀或肝功能異常(ALT ≥ 100 IU/L)。\n(二) 排除慢性肝炎急性發作或其他原因引起之肝功能異常發炎。",
    "檢驗條件": "(一) 血清 C 型肝炎病毒抗體(anti-HCV)、C 型肝炎病毒核酸(HCV RNA)、\nC 型肝炎病毒抗原(HCV antigen)任一檢測陽性。\n(二) 曾檢驗血清 anti-HCV 陰性,後於一年內轉變成 anti-HCV 陽性\n※1。\n(三) 血清 HCV RNA 或 HCV antigen 檢測陽性,且 anti-HCV 陰性。\n(四) 曾檢驗血清HCV RNA或HCV antigen陰性,後於一年內轉變成HCV\nRNA 或 HCV antigen 陽性\n※2。\n(五) C 型肝炎治療療程結束且達持續性病毒反應(sustained viral response,\nSVR)者,後經檢驗轉變成 HCV RNA 或 HCV antigen 陽性,且經臨\n床及檢驗評估排除延遲復發屬新感染個案。",
    "流行病學條件": "NA",
    "通報定義": "符合臨床條件及檢驗條件第(一)項,或符合檢驗條件第(二)項至第(五)\n項之任一項。\n※1 若臨床醫師懷疑第一次 anti-HCV 陽性可能為偽陽性尚未通報,請複驗 anti-HCV,\n或檢測HCV RNA、HCV antigen,依檢驗結果,即時通報。\n※2 於 C 型肝炎治療中或曾接受治療但尚未達 SVR 之患者,若經檢測為感染不同基因\n型別C 型肝炎病毒之新感染,須通報。\n2021年2月",
    "疾病分類": "(一) 可能病例:NA。\n(二) 極可能病例:NA。\n(三) 確定病例:符合臨床條件及檢驗條件第(一)項,或符合檢驗條件\n第(二)項至第(五)項之任一項。",
    "檢體採檢送驗事項": "傳染病 採檢量及 應保存種類\n採檢項目 採檢目的 採檢時間 送驗方式 注意事項\n名稱 規定 應保存時間\n抗體檢測\n1. 檢體請勿加\n入任何添加\n物。\n2. 血清檢體採\n檢注意事項\n急性 2–8 °C\n抗原檢測 以無菌試管 請參閱「傳染\n病毒性 B類感染性 陽性血清\n血清 立即採檢 收集3 mL血 病檢體採檢\nC型 物質P650 (30日)\n清 手冊」2.8.3\n肝炎 包裝\n及 2.8.4備註\n說明,血清檢\n體採檢步驟\n請參閱該手\n病原體 冊第3.3節。\n檢測\n備註:\n1. C型肝炎病毒之檢驗方法、步驟及結果判定等資訊,可參閱「傳染病標準檢驗方法手冊」。\n2. 「傳染病檢體採檢手冊」及「傳染病標準檢驗方法手冊」可至疾病管制署全球資訊網\n(https://www.cdc.gov.tw)首頁之檢驗(傳染病檢驗資訊與規定)項下查詢。\n2021年2月",
    "english_name": "Acute Hepatitis C",
    "suspected_case": "NA。",
    "probable_case": "NA。",
    "confirmed_case": "符合臨床條件及檢驗條件第(一)項,或符合檢驗條件\n第(二)項至第(五)項之任一項。"
  },
  {
    "name": "急性病毒性D型肝炎",
    "url": "https://www.cdc.gov.tw/File/Get/eQXAisx81-mOhm5oB5IPHA",
    "source_category": "第三類",
    "content": "急性病毒性 D 型肝炎\n(Acute Hepatitis D)\n一、 臨床條件\n個案為 B 型肝炎帶原者,且經醫師臨床診斷為急性 D 型肝炎。\n並同時具有下列二項條件:\n(一) 出現急性發作症狀:包括發燒、全身倦怠、噁心、嘔吐、腹部\n不舒服等。\n(二) 黃疸或 ALT 上升。\n二、 檢驗條件\n血清學 B 型肝炎表面抗原(HBsAg)及 D 型肝炎 IgM 抗體(IgM\nanti-HDV)檢測陽性。(急性 D 型肝炎檢驗部分送疾病管制署確認)\n三、 流行病學條件\n個案為 B 型肝炎帶原者,並具有下列任一個條件:\n(一) 與 D 型肝炎個案性行為或血體液接觸。\n(二) 使用受 D 型肝炎病毒所污染之注射器、針頭、針灸紋眉、穿\n耳洞、刺青等器具。\n(三) 與 D 型肝炎感染者共用刮鬍刀、牙刷等行為。\n(四) 與經實驗室證實之確定病例具有流行病學之關聯。\n四、 通報定義\n符合臨床條件、檢驗條件及流行病學條件任一者。\n五、 疾病分類\n(一) 可能病例:\nNA\n(二) 極可能病例:\nNA\n(三) 確定病例:\n符合臨床條件及檢驗條件。\n六、 檢體採檢送驗事項\n採檢項目 檢體種類 採檢目的 採檢時機 採檢規定 運送條件 注意事項\n1. 檢體勿加入\n任何添加物。\n急性病毒\n2. 血清檢體見\n性肝炎 以無菌試管收集\n血清 抗體檢測 立即採檢 低溫 2.8.3及2.8.4備\n(除 A 型 3 mL 血清。\n註說明,血清採\n外)\n檢步驟請參考第\n3.3 節。",
    "pdf_path": "pdfs/急性病毒性D型肝炎.pdf",
    "臨床條件": "個案為 B 型肝炎帶原者,且經醫師臨床診斷為急性 D 型肝炎。\n並同時具有下列二項條件:\n(一) 出現急性發作症狀:包括發燒、全身倦怠、噁心、嘔吐、腹部\n不舒服等。\n(二) 黃疸或 ALT 上升。",
    "檢驗條件": "血清學 B 型肝炎表面抗原(HBsAg)及 D 型肝炎 IgM 抗體(IgM\nanti-HDV)檢測陽性。(急性 D 型肝炎檢驗部分送疾病管制署確認)",
    "流行病學條件": "個案為 B 型肝炎帶原者,並具有下列任一個條件:\n(一) 與 D 型肝炎個案性行為或血體液接觸。\n(二) 使用受 D 型肝炎病毒所污染之注射器、針頭、針灸紋眉、穿\n耳洞、刺青等器具。\n(三) 與 D 型肝炎感染者共用刮鬍刀、牙刷等行為。\n(四) 與經實驗室證實之確定病例具有流行病學之關聯。",
    "通報定義": "符合臨床條件、檢驗條件及流行病學條件任一者。",
    "疾病分類": "(一) 可能病例:\nNA\n(二) 極可能病例:\nNA\n(三) 確定病例:\n符合臨床條件及檢驗條件。",
    "檢體採檢送驗事項": "採檢項目 檢體種類 採檢目的 採檢時機 採檢規定 運送條件 注意事項\n1. 檢體勿加入\n任何添加物。\n急性病毒\n2. 血清檢體見\n性肝炎 以無菌試管收集\n血清 抗體檢測 立即採檢 低溫 2.8.3及2.8.4備\n(除 A 型 3 mL 血清。\n註說明,血清採\n外)\n檢步驟請參考第\n3.3 節。",
    "english_name": "Acute Hepatitis D",
    "suspected_case": "NA",
    "probable_case": "NA",
    "confirmed_case": "符合臨床條件及檢驗條件。"
  },
  {
    "name": "急性病毒性E型肝炎",
    "url": "https://www.cdc.gov.tw/File/Get/8FAsD6HI0EVMPU6PDwAQSw",
    "source_category": "第三類",
    "content": "急性病毒性 E 型肝炎\n(Acute Hepatitis E)\n一、臨床條件\n經醫師臨床診斷為急性病毒性肝炎,且排除急性 A、B、C 型肝炎感染,\n並同時具有下列二項條件:\n(一) 出現急性發作症狀:包括發燒、全身倦怠、噁心、嘔吐、腹部\n不舒服等。\n(二) 黃疸或 ALT 上升。\n二、檢驗條件\n(一) 血清學 E 型肝炎 IgM 抗體(IgM anti-HEV)檢測陽性。\n(二) E 型肝炎病毒核酸(RNA)檢測陽性。\n三、流行病學條件\n具有下列任一個條件:\n(一) 曾與確定病例有密切接觸、同住。\n(二) 食用受污染的水、食物等,或曾與確定病例暴露共同感染源。\n四、通報定義\n符合臨床條件、檢驗條件及流行病學條件任一者。\n五、病例分類\n(一) 可能病例:NA\n(二) 極可能病例:符合臨床條件及流行病學條件。\n(三) 確定病例:符合臨床條件及任一項檢驗條件。\n2019年7月\n六、檢體採檢送驗事項\n採檢量 應保存種類\n傳染病名稱 採檢項目 採檢目的 採檢時間 送驗方式 注意事項\n及規定 應保存時間\n1. 檢體勿加\n入 任 何添\n加物。\n2. 血清檢體\n抗體檢測\n採 檢 注意\n事 項 請參\n閱 傳 染病\n急性病毒性 以無菌試管 檢 體 採檢\n2–8 °C 陽性血清\nE型肝炎 血清 立即採檢 收集3 mL 手冊 2.8.3\nB 類感染性物質 (30日)\n血清 及 2.8.4 備\nP650包裝\n註說明,血\n清 檢 體 採\n病原體 檢 步 驟請\n檢測 參 閱 傳染\n病 檢 體 採\n檢 手 冊 第\n3.3節。\n2019年7月",
    "pdf_path": "pdfs/急性病毒性E型肝炎.pdf",
    "臨床條件": "經醫師臨床診斷為急性病毒性肝炎,且排除急性 A、B、C 型肝炎感染,\n並同時具有下列二項條件:\n(一) 出現急性發作症狀:包括發燒、全身倦怠、噁心、嘔吐、腹部\n不舒服等。\n(二) 黃疸或 ALT 上升。",
    "檢驗條件": "(一) 血清學 E 型肝炎 IgM 抗體(IgM anti-HEV)檢測陽性。\n(二) E 型肝炎病毒核酸(RNA)檢測陽性。",
    "流行病學條件": "具有下列任一個條件:\n(一) 曾與確定病例有密切接觸、同住。\n(二) 食用受污染的水、食物等,或曾與確定病例暴露共同感染源。",
    "通報定義": "符合臨床條件、檢驗條件及流行病學條件任一者。",
    "疾病分類": "(一) 可能病例:NA\n(二) 極可能病例:符合臨床條件及流行病學條件。\n(三) 確定病例:符合臨床條件及任一項檢驗條件。\n2019年7月",
    "檢體採檢送驗事項": "採檢量 應保存種類\n傳染病名稱 採檢項目 採檢目的 採檢時間 送驗方式 注意事項\n及規定 應保存時間\n1. 檢體勿加\n入 任 何添\n加物。\n2. 血清檢體\n抗體檢測\n採 檢 注意\n事 項 請參\n閱 傳 染病\n急性病毒性 以無菌試管 檢 體 採檢\n2–8 °C 陽性血清\nE型肝炎 血清 立即採檢 收集3 mL 手冊 2.8.3\nB 類感染性物質 (30日)\n血清 及 2.8.4 備\nP650包裝\n註說明,血\n清 檢 體 採\n病原體 檢 步 驟請\n檢測 參 閱 傳染\n病 檢 體 採\n檢 手 冊 第\n3.3節。\n2019年7月",
    "english_name": "Acute Hepatitis E",
    "suspected_case": "NA",
    "probable_case": "符合臨床條件及流行病學條件。",
    "confirmed_case": "符合臨床條件及任一項檢驗條件。\n2019年7月"
  },
  {
    "name": "急性病毒性肝炎未定型",
    "url": "https://www.cdc.gov.tw/File/Get/VI0ZW7okpJgReFZza2yPgg",
    "source_category": "第三類",
    "content": "急性病毒性肝炎未定型\n(Acute Viral Hepatitis Unspecified)\n一、臨床條件\n具有急性肝炎之症狀(如黃疸、茶色尿、疲倦、腹痛、胃口差、噁心、\n嘔吐)及 ALT 上升 2.5 倍以上,排除藥物、中毒性肝炎、自體免疫性\n肝炎、酒精性肝炎、膽道疾病、心血管疾病(如鬱血性心衰竭、休克\n等)\n二、檢驗條件\n血清學標記(IgM anti -HAV、IgM anti -HBc、HBsAg、anti-HCV、IgM anti-\nHEV)檢驗項目均為陰性。\n三、流行病學條件\nNA\n四、通報定義\n符合臨床條件及檢驗條件。\n(急性 E 型肝炎檢驗,送疾病管制署確認)\n五、病例分類\n(一) 可能病例:\nNA\n(二) 極可能病例:\nNA\n(三) 確定病例:\n符合臨床條件及檢驗條件。\n六、檢體採檢送驗事項\n傳染病 應保存種類\n採檢項目 採檢目的 採檢時間 採檢規定 送驗方式 注意事項\n名稱 應保存時間\n1. 檢體勿加\n入任何添\n加物。\n2. 血清檢體\n見2.8.3 及\n急性病 2.8.4備註\n毒性肝 2–8 °C 說明,血\n以無菌試管\n炎 B 類感染性 陽性血清 清採檢步\n血清 抗體檢測 立即採檢 收集3 mL\n(除 物質 P650 (30 日)\n血清 驟請參考\nA 型 包裝\n第 3.3\n外)\n節。\n3. D 肝送驗\n需HBsAg\n檢測為陽\n性。",
    "pdf_path": "pdfs/急性病毒性肝炎未定型.pdf",
    "臨床條件": "具有急性肝炎之症狀(如黃疸、茶色尿、疲倦、腹痛、胃口差、噁心、\n嘔吐)及 ALT 上升 2.5 倍以上,排除藥物、中毒性肝炎、自體免疫性\n肝炎、酒精性肝炎、膽道疾病、心血管疾病(如鬱血性心衰竭、休克\n等)",
    "檢驗條件": "血清學標記(IgM anti -HAV、IgM anti -HBc、HBsAg、anti-HCV、IgM anti-\nHEV)檢驗項目均為陰性。",
    "流行病學條件": "NA",
    "通報定義": "符合臨床條件及檢驗條件。\n(急性 E 型肝炎檢驗,送疾病管制署確認)",
    "疾病分類": "(一) 可能病例:\nNA\n(二) 極可能病例:\nNA\n(三) 確定病例:\n符合臨床條件及檢驗條件。",
    "檢體採檢送驗事項": "傳染病 應保存種類\n採檢項目 採檢目的 採檢時間 採檢規定 送驗方式 注意事項\n名稱 應保存時間\n1. 檢體勿加\n入任何添\n加物。\n2. 血清檢體\n見2.8.3 及\n急性病 2.8.4備註\n毒性肝 2–8 °C 說明,血\n以無菌試管\n炎 B 類感染性 陽性血清 清採檢步\n血清 抗體檢測 立即採檢 收集3 mL\n(除 物質 P650 (30 日)\n血清 驟請參考\nA 型 包裝\n第 3.3\n外)\n節。\n3. D 肝送驗\n需HBsAg\n檢測為陽\n性。",
    "english_name": "Acute Viral Hepatitis Unspecified",
    "suspected_case": "NA",
    "probable_case": "NA",
    "confirmed_case": "符合臨床條件及檢驗條件。"
  },
  {
    "name": "恙蟲病",
    "url": "https://www.cdc.gov.tw/File/Get/HokZ-GoxP8OiWXEM8pi8tg",
    "source_category": "第四類",
    "content": "恙蟲病(Scrub Typhus)\n一、 臨床條件\n猝發且持續性高燒、頭痛、背痛、惡寒、盜汗、淋巴結腫大、恙蟎\n叮咬處出現無痛性的焦痂、1 週後皮膚出現紅色斑狀丘疹,有時會\n併發肺炎或肝功能異常。\n二、 檢驗條件\n符合下列檢驗結果之任一項者,定義為檢驗結果陽性:\n(一) 臨床檢體(血液或皮膚傷口(焦痂))分離並鑑定出恙蟲病立\n克次體(Orientia tsutsugamushi)。\n(二) 臨床檢體分子生物學核酸檢測陽性。\n(三) 以間接免疫螢光抗體法(Indirect Immunofluorescene Assay,\nIFA)檢測急性期(或初次採檢)血清,IgM 抗體力價達1:80\n以上 且 IgG 抗體力價達1:320以上。\n(四) 以間接免疫螢光染色法,檢測配對(急性期及恢復期)血清,\n恙蟲病立克次體特異性IgG 抗體力價達4倍以上上升。\n三、 流行病學條件\n有恙蟲病相關流行地區旅遊史,並遭恙蟎叮咬或曾接觸嚙齒類等動\n物。\n四、 通報定義\n符合臨床條件。\n五、 病例分類\n(一) 可能病例:\nNA\n(二) 極可能病例:\nNA\n(三) 確定病例:\n符合檢驗結果陽性定義之任一項。\n六、 檢體採檢送驗事項\n傳染病 應保存種類\n採檢項目 採檢目的 採檢時間 採檢量及規定 送驗方式 注意事項\n名稱 (應保存時間)\n1.抗凝固全血\n採檢請參考\n以含抗凝劑 閱傳染病檢\n(heparin 或 體採檢手冊\n抗凝固全 病原體檢 急性期,且 EDTA)採血管 菌株 第 3.2 節。\n血 測 未投藥前 採 集5-10 mL (30日) 2.血清勿加入\n靜脈血,並混 任何添加物。\n合均勻。 3.血清檢體請\n2-8°C 參閱傳染病檢\n(B類感 體採檢手冊\n恙蟲病 染性物質 2.8.3 及\n包裝) 2.8.4備註說\n明及採檢步驟\n請參閱傳染病\n檢體採檢手冊\n立即採檢 以無菌試管收 陽性血清\n抗體檢測 第 3.3 節。\n血清\n集3mL血清。 (30日)\n4.以不做二採\n為原則,如有\n臨床上個別需\n要,請連繫檢\n體單一窗口。",
    "pdf_path": "pdfs/恙蟲病.pdf",
    "臨床條件": "猝發且持續性高燒、頭痛、背痛、惡寒、盜汗、淋巴結腫大、恙蟎\n叮咬處出現無痛性的焦痂、1 週後皮膚出現紅色斑狀丘疹,有時會\n併發肺炎或肝功能異常。",
    "檢驗條件": "符合下列檢驗結果之任一項者,定義為檢驗結果陽性:\n(一) 臨床檢體(血液或皮膚傷口(焦痂))分離並鑑定出恙蟲病立\n克次體(Orientia tsutsugamushi)。\n(二) 臨床檢體分子生物學核酸檢測陽性。\n(三) 以間接免疫螢光抗體法(Indirect Immunofluorescene Assay,\nIFA)檢測急性期(或初次採檢)血清,IgM 抗體力價達1:80\n以上 且 IgG 抗體力價達1:320以上。\n(四) 以間接免疫螢光染色法,檢測配對(急性期及恢復期)血清,\n恙蟲病立克次體特異性IgG 抗體力價達4倍以上上升。",
    "流行病學條件": "有恙蟲病相關流行地區旅遊史,並遭恙蟎叮咬或曾接觸嚙齒類等動\n物。",
    "通報定義": "符合臨床條件。",
    "疾病分類": "(一) 可能病例:\nNA\n(二) 極可能病例:\nNA\n(三) 確定病例:\n符合檢驗結果陽性定義之任一項。",
    "檢體採檢送驗事項": "傳染病 應保存種類\n採檢項目 採檢目的 採檢時間 採檢量及規定 送驗方式 注意事項\n名稱 (應保存時間)\n1.抗凝固全血\n採檢請參考\n以含抗凝劑 閱傳染病檢\n(heparin 或 體採檢手冊\n抗凝固全 病原體檢 急性期,且 EDTA)採血管 菌株 第 3.2 節。\n血 測 未投藥前 採 集5-10 mL (30日) 2.血清勿加入\n靜脈血,並混 任何添加物。\n合均勻。 3.血清檢體請\n2-8°C 參閱傳染病檢\n(B類感 體採檢手冊\n恙蟲病 染性物質 2.8.3 及\n包裝) 2.8.4備註說\n明及採檢步驟\n請參閱傳染病\n檢體採檢手冊\n立即採檢 以無菌試管收 陽性血清\n抗體檢測 第 3.3 節。\n血清\n集3mL血清。 (30日)\n4.以不做二採\n為原則,如有\n臨床上個別需\n要,請連繫檢\n體單一窗口。",
    "english_name": "Scrub Typhus",
    "suspected_case": "NA",
    "probable_case": "NA",
    "confirmed_case": "符合檢驗結果陽性定義之任一項。"
  },
  {
    "name": "拉薩熱",
    "url": "https://www.cdc.gov.tw/File/Get/_JK-ICjzglm9OiyacrdhPQ",
    "source_category": "第五類",
    "content": "附件一\n拉薩熱\n(Lassa Fever)\n一、 臨床條件\n同時具有下列二項條件:\n(一)急性發燒(≧38°C)\n(二)符合下列部分或全部臨床描述:倦怠、頭痛、喉嚨痛、\n咳嗽、噁心、嘔吐、腹瀉、肌肉酸痛、胸痛、腹痛、斑\n丘疹、出血等症狀。\n二、 檢驗條件\n具有下列任一個條件:\n(一)臨床檢體(血液、尿液或咽喉擦拭液)分離並鑑定出拉\n薩病毒(Lassa virus)。\n(二)臨床檢體分子生物學核酸檢測陽性或檢測出拉薩病毒抗\n原。\n(三)血清學抗體檢測陽性: IgM 抗體陽性或成對血清檢體\n之 IgG 抗體陽轉。\n(四)組織切片的免疫化學染色(IHC)陽性。\n三、 流行病學條件\n發病前 3 周內,具有下列任一個條件:\n(一)具有拉薩熱流行地區之旅遊史或居住史。\n(二)接觸極可能病例或確定病例之血液或體液或其污染物。\n(三)進行拉薩熱病毒或檢體之實驗室操作。\n四、 通報定義\n具有下列任一個條件:\n(一)符合臨床條件及流行病學條件。\n(二)符合檢驗條件。\n五、 疾病分類\n(一)極可能病例:\n雖未經實驗室證實,但符合臨床條件及流行病學條件。\n(二)確定病例:\n符合檢驗條件。\n六、 檢體採檢送驗事項\n請參閱「傳染病檢體採檢手冊」(https://gov.tw/pK8)",
    "pdf_path": "pdfs/拉薩熱.pdf",
    "臨床條件": "同時具有下列二項條件:\n(一)急性發燒(≧38°C)\n(二)符合下列部分或全部臨床描述:倦怠、頭痛、喉嚨痛、\n咳嗽、噁心、嘔吐、腹瀉、肌肉酸痛、胸痛、腹痛、斑\n丘疹、出血等症狀。",
    "檢驗條件": "具有下列任一個條件:\n(一)臨床檢體(血液、尿液或咽喉擦拭液)分離並鑑定出拉\n薩病毒(Lassa virus)。\n(二)臨床檢體分子生物學核酸檢測陽性或檢測出拉薩病毒抗\n原。\n(三)血清學抗體檢測陽性: IgM 抗體陽性或成對血清檢體\n之 IgG 抗體陽轉。\n(四)組織切片的免疫化學染色(IHC)陽性。",
    "流行病學條件": "發病前 3 周內,具有下列任一個條件:\n(一)具有拉薩熱流行地區之旅遊史或居住史。\n(二)接觸極可能病例或確定病例之血液或體液或其污染物。\n(三)進行拉薩熱病毒或檢體之實驗室操作。",
    "通報定義": "具有下列任一個條件:\n(一)符合臨床條件及流行病學條件。\n(二)符合檢驗條件。",
    "疾病分類": "(一)極可能病例:\n雖未經實驗室證實,但符合臨床條件及流行病學條件。\n(二)確定病例:\n符合檢驗條件。",
    "檢體採檢送驗事項": "請參閱「傳染病檢體採檢手冊」(https://gov.tw/pK8)",
    "english_name": "Lassa Fever",
    "suspected_case": "",
    "probable_case": "雖未經實驗室證實,但符合臨床條件及流行病學條件。",
    "confirmed_case": "符合檢驗條件。"
  },
  {
    "name": "新冠併發重症",
    "url": "https://www.cdc.gov.tw/File/Get/2USmDt2EJKaXeRs1L9Uz7Q",
    "source_category": "第四類",
    "content": "新冠併發重症\n(Severe Complicated COVID-19)\n一、臨床條件\n發燒(≧ 38°C)或有呼吸道症狀後14 日(含)內出現肺炎或其他併\n發症,因而需加護病房治療或死亡者。\n二、檢驗條件\n具有下列任一個條件:\n(一) 臨床檢體(如鼻咽或咽喉擦拭液、痰液或下呼吸道抽取液等)分離並鑑定\n出新型冠狀病毒。\n(二) 臨床檢體新型冠狀病毒分子生物學核酸檢測陽性。\n(三) 臨床檢體新型冠狀病毒抗原檢測陽性(醫事人員執行抗原快篩)。\n三、通報定義\n符合臨床條件及檢驗條件。\n四、疾病分類\n確定病例:符合臨床條件及檢驗條件。\n五、檢體採檢送驗事項\n送驗方 保存種類應 注意事項\n傳染病名稱 採檢項目 採檢目的 採檢時間\n式 保存時間\n病毒株(30 1.醫師可視病情\n日) ;咽喉 變化再度送檢。\n擦拭液(30 2.見 2.8.5 備註說\n日) 明及咽喉採檢 步\n驟請參考第 3.7\n鼻咽或咽喉 節 。\n擦拭液 3.建議使用有 o-\nring 或其他防滲\n漏設計之檢體 容\n器送驗,若檢 驗單\n病原體檢測 發病3 日內 2-8°C\n位發現檢 體滲漏,\n(B 類感 則不予 檢驗。\n新冠併發重症\n染性物 病毒株(30 1.適用於輕症咳\n質P650 日) ;痰液 嗽有痰、肺炎或 重\n包裝) (30 日 症者。\n痰液或下呼 2.醫師可視病情\n吸道抽取物 變化再度送檢。\n3.勿採患者口水。\n4.痰液採檢步驟\n請參考第 3.9節。\n急性期(發病 血清(30 日) 血清檢體見 2.8.3\n抗體檢測 1-5日); 及 2.8.4 備註說明\n血清\n(檢體保留) 恢復期(發病 及血清採檢步驟\n14-40 日) 請參考第3.3節。",
    "pdf_path": "pdfs/新冠併發重症.pdf",
    "臨床條件": "發燒(≧ 38°C)或有呼吸道症狀後14 日(含)內出現肺炎或其他併\n發症,因而需加護病房治療或死亡者。",
    "檢驗條件": "具有下列任一個條件:\n(一) 臨床檢體(如鼻咽或咽喉擦拭液、痰液或下呼吸道抽取液等)分離並鑑定\n出新型冠狀病毒。\n(二) 臨床檢體新型冠狀病毒分子生物學核酸檢測陽性。\n(三) 臨床檢體新型冠狀病毒抗原檢測陽性(醫事人員執行抗原快篩)。",
    "流行病學條件": "",
    "通報定義": "符合臨床條件及檢驗條件。",
    "疾病分類": "確定病例:符合臨床條件及檢驗條件。",
    "檢體採檢送驗事項": "送驗方 保存種類應 注意事項\n傳染病名稱 採檢項目 採檢目的 採檢時間\n式 保存時間\n病毒株(30 1.醫師可視病情\n日) ;咽喉 變化再度送檢。\n擦拭液(30 2.見 2.8.5 備註說\n日) 明及咽喉採檢 步\n驟請參考第 3.7\n鼻咽或咽喉 節 。\n擦拭液 3.建議使用有 o-\nring 或其他防滲\n漏設計之檢體 容\n器送驗,若檢 驗單\n病原體檢測 發病3 日內 2-8°C\n位發現檢 體滲漏,\n(B 類感 則不予 檢驗。\n新冠併發重症\n染性物 病毒株(30 1.適用於輕症咳\n質P650 日) ;痰液 嗽有痰、肺炎或 重\n包裝) (30 日 症者。\n痰液或下呼 2.醫師可視病情\n吸道抽取物 變化再度送檢。\n3.勿採患者口水。\n4.痰液採檢步驟\n請參考第 3.9節。\n急性期(發病 血清(30 日) 血清檢體見 2.8.3\n抗體檢測 1-5日); 及 2.8.4 備註說明\n血清\n(檢體保留) 恢復期(發病 及血清採檢步驟\n14-40 日) 請參考第3.3節。",
    "english_name": "Severe Complicated COVID-19",
    "suspected_case": "",
    "probable_case": "",
    "confirmed_case": "符合臨床條件及檢驗條件。"
  },
  {
    "name": "新型A型流感",
    "url": "https://www.cdc.gov.tw/File/Get/YLZbi_tOu5vjCEfnhVsZUw",
    "source_category": "第五類",
    "content": "新型 A 型流感傳染病病例定義暨防疫檢體採檢送驗事項\n一、 臨床條件\n同時具有以下二項條件:\n(一) 急性呼吸道感染[臨床症狀可能包括發燒(≧38°C)、咳嗽等]或\n急性結膜炎;\n(二) 臨床、放射線診斷或病理學上顯示肺部實質疾病。\n二、 檢驗條件\n具有下列任一個條件:\n(一) 臨床檢體培養分離及鑑定出新型 A 型流感病毒(非現行於人類\n流行傳播之 A(H1N1)、A(H3N2)季節性流感病毒);\n(二) 臨床檢體新型 A 型流感病毒核酸檢測陽性;\n(三) 血清學抗體檢測呈現為最近感染新型 A 型流感。\n三、 流行病學條件\n發病前 10 日內,具有下列任一個條件:\n(一) 曾與出現症狀的極可能或確定病例有密切接觸,包括在無適當\n防護下提供照護、相處、或有呼吸道分泌物、體液之直接接觸;\n(二) 曾至有出現新型 A 型流感流行疫情地區之旅遊史或居住史;\n(三) 曾有禽鳥、豬暴露史或至禽鳥、豬相關場所;\n(四) 禽流感 A(H5N1)動物疫情接觸史;\n(五) 在實驗室或其他環境,無適當防護下處理動物或人類之檢體,\n而該檢體可能含有新型 A 型流感病毒。\n四、 通報定義\n具有下列任一個條件:\n(一) 符合臨床條件及流行病學條件;\n(二) 僅符合臨床條件第(一)項及流行病學條件第(一)項或第(四)項;\n(三) 符合檢驗條件。\n1\n五、 疾病分類\n(一) 極可能病例:\n雖未經實驗室檢驗證實,但符合臨床條件,且於發病前 10 日\n內,曾經與出現症狀的確定病例有密切接觸者。\n(二) 確定病例:\n符合檢驗條件。\n六、 檢體採檢送驗事項\n應保存\n傳染病 採檢 採檢 採檢 採檢量 送驗 種類\n注意事項\n名稱 項目 目的 時間 及規定 方式 (應保存\n時間)\n以無菌\n病毒拭\n病毒株\n子之棉\n(30日) 1. 醫師可視病情變\n咽喉 棒擦拭\n;咽喉\n化再度送檢。\n擦拭液 咽喉,插\n2. 結膜擦拭液採檢\n擦拭液\n入病毒\n項目,適用於有急\n(30日)\n保存輸\n性結膜炎症狀者。\n送管\n3. 咽喉擦拭液採檢\n步驟請參考衛生\n2-8°C 福利部疾病管制\n(B類感 署傳染病檢體採\n新型A 病原體 發病3\n以無菌 染性物 檢手冊第 3.7 節、\n型流感 檢測 日內\n病毒拭 質P650 結膜擦拭液採檢\n子之棉 包裝) 步驟請參考第3.17\n棒在結 病毒株 節。\n膜慢慢 (30日) 4. 建議使用有 oring\n結膜\n旋轉,採 ;結膜 或其他防滲漏設\n擦拭液\n集化膿 擦拭液 計之檢體容器送\n的檢體 (30日) 驗,若檢驗單位發\n插入病 現檢體滲漏,則不\n毒保存 予檢驗。\n輸送管。\n2\n應保存\n傳染病 採檢 採檢 採檢 採檢量 送驗 種類\n注意事項\n名稱 項目 目的 時間 及規定 方式 (應保存\n時間)\n1. 適用於輕症咳嗽有\n痰、肺炎或重症\n者。\n以無菌 2. 醫師可視病情變化\n痰液或 病毒株\n容器收 再度送檢。\n下呼吸 (30日)\n集排出 3. 勿採患者口水。\n道抽取 ;痰液\n之痰液 4. 痰液檢體採檢步驟\n物 (30日)\n請參考衛生福利\n部疾病管制署傳\n染病檢體採檢手\n冊第3.9節。\n以無菌 血清檢體採檢步驟\n抗體 急性期\n試管收 請參考衛生福利部\n檢測 (發病 血清\n血清 集至少 疾病管制署傳染病\n(檢體 1-5日) (30日)\n3mL 血 檢體採檢手冊第 3.3\n保留)\n清 節。\n3",
    "pdf_path": "pdfs/新型A型流感.pdf",
    "臨床條件": "同時具有以下二項條件:\n(一) 急性呼吸道感染[臨床症狀可能包括發燒(≧38°C)、咳嗽等]或\n急性結膜炎;\n(二) 臨床、放射線診斷或病理學上顯示肺部實質疾病。",
    "檢驗條件": "具有下列任一個條件:\n(一) 臨床檢體培養分離及鑑定出新型 A 型流感病毒(非現行於人類\n流行傳播之 A(H1N1)、A(H3N2)季節性流感病毒);\n(二) 臨床檢體新型 A 型流感病毒核酸檢測陽性;\n(三) 血清學抗體檢測呈現為最近感染新型 A 型流感。",
    "流行病學條件": "發病前 10 日內,具有下列任一個條件:\n(一) 曾與出現症狀的極可能或確定病例有密切接觸,包括在無適當\n防護下提供照護、相處、或有呼吸道分泌物、體液之直接接觸;\n(二) 曾至有出現新型 A 型流感流行疫情地區之旅遊史或居住史;\n(三) 曾有禽鳥、豬暴露史或至禽鳥、豬相關場所;\n(四) 禽流感 A(H5N1)動物疫情接觸史;\n(五) 在實驗室或其他環境,無適當防護下處理動物或人類之檢體,\n而該檢體可能含有新型 A 型流感病毒。",
    "通報定義": "具有下列任一個條件:\n(一) 符合臨床條件及流行病學條件;\n(二) 僅符合臨床條件第(一)項及流行病學條件第(一)項或第(四)項;\n(三) 符合檢驗條件。\n1",
    "疾病分類": "(一) 極可能病例:\n雖未經實驗室檢驗證實,但符合臨床條件,且於發病前 10 日\n內,曾經與出現症狀的確定病例有密切接觸者。\n(二) 確定病例:\n符合檢驗條件。",
    "檢體採檢送驗事項": "應保存\n傳染病 採檢 採檢 採檢 採檢量 送驗 種類\n注意事項\n名稱 項目 目的 時間 及規定 方式 (應保存\n時間)\n以無菌\n病毒拭\n病毒株\n子之棉\n(30日) 1. 醫師可視病情變\n咽喉 棒擦拭\n;咽喉\n化再度送檢。\n擦拭液 咽喉,插\n2. 結膜擦拭液採檢\n擦拭液\n入病毒\n項目,適用於有急\n(30日)\n保存輸\n性結膜炎症狀者。\n送管\n3. 咽喉擦拭液採檢\n步驟請參考衛生\n2-8°C 福利部疾病管制\n(B類感 署傳染病檢體採\n新型A 病原體 發病3\n以無菌 染性物 檢手冊第 3.7 節、\n型流感 檢測 日內\n病毒拭 質P650 結膜擦拭液採檢\n子之棉 包裝) 步驟請參考第3.17\n棒在結 病毒株 節。\n膜慢慢 (30日) 4. 建議使用有 oring\n結膜\n旋轉,採 ;結膜 或其他防滲漏設\n擦拭液\n集化膿 擦拭液 計之檢體容器送\n的檢體 (30日) 驗,若檢驗單位發\n插入病 現檢體滲漏,則不\n毒保存 予檢驗。\n輸送管。\n2\n應保存\n傳染病 採檢 採檢 採檢 採檢量 送驗 種類\n注意事項\n名稱 項目 目的 時間 及規定 方式 (應保存\n時間)\n1. 適用於輕症咳嗽有\n痰、肺炎或重症\n者。\n以無菌 2. 醫師可視病情變化\n痰液或 病毒株\n容器收 再度送檢。\n下呼吸 (30日)\n集排出 3. 勿採患者口水。\n道抽取 ;痰液\n之痰液 4. 痰液檢體採檢步驟\n物 (30日)\n請參考衛生福利\n部疾病管制署傳\n染病檢體採檢手\n冊第3.9節。\n以無菌 血清檢體採檢步驟\n抗體 急性期\n試管收 請參考衛生福利部\n檢測 (發病 血清\n血清 集至少 疾病管制署傳染病\n(檢體 1-5日) (30日)\n3mL 血 檢體採檢手冊第 3.3\n保留)\n清 節。\n3",
    "english_name": "≧38°C",
    "suspected_case": "",
    "probable_case": "雖未經實驗室檢驗證實,但符合臨床條件,且於發病前 10 日\n內,曾經與出現症狀的確定病例有密切接觸者。",
    "confirmed_case": "符合檢驗條件。"
  },
  {
    "name": "新生兒破傷風",
    "url": "https://www.cdc.gov.tw/File/Get/SSMiO4sDy_y3znynl7c0ow",
    "source_category": "第三類",
    "content": "新生兒破傷風\nNeonatal Tetanus\n( )\n一、 臨床條件\n具有下列任一個條件:\n(一) 新生兒於出生兩天內具正常之哭泣及吸奶動作,出生三到二十\n八天間出現哭聲微弱及吸奶困難現象,伴隨出現牙關緊閉,肌\n肉僵直,全身痙攣症狀。\n(二) 任何新生兒於出生三到二十八天間發生不明原因死亡,且不當\n斷臍者。\n二、 檢驗條件\nNA\n三、 流行病學條件\nNA\n四、 通報定義\n符合臨床條件。\n五、 疾病分類\n(一) 可能病例:\n符合臨床條件。\n(二) 極可能病例:\nNA\n(三) 確定病例:\n符合臨床條件,且相關就醫病歷資料經專家審查判定。\n六、 檢體採檢送驗事項\n採檢項目 檢體種類 採檢目的 採檢時機 採檢規定 運送條件 注意事項\n破傷風桿菌自感染部\n位檢出機率極低,通\n破傷風、 常無法從患者血液中\n無(見注\n新生兒破 無 無 無 無 檢出抗體反應。故不\n意事項)\n傷風 採集疑似患者檢體檢\n驗,以臨床症狀作為\n病例確認判定依據。",
    "pdf_path": "pdfs/新生兒破傷風.pdf",
    "臨床條件": "具有下列任一個條件:\n(一) 新生兒於出生兩天內具正常之哭泣及吸奶動作,出生三到二十\n八天間出現哭聲微弱及吸奶困難現象,伴隨出現牙關緊閉,肌\n肉僵直,全身痙攣症狀。\n(二) 任何新生兒於出生三到二十八天間發生不明原因死亡,且不當\n斷臍者。",
    "檢驗條件": "NA",
    "流行病學條件": "NA",
    "通報定義": "符合臨床條件。",
    "疾病分類": "(一) 可能病例:\n符合臨床條件。\n(二) 極可能病例:\nNA\n(三) 確定病例:\n符合臨床條件,且相關就醫病歷資料經專家審查判定。",
    "檢體採檢送驗事項": "採檢項目 檢體種類 採檢目的 採檢時機 採檢規定 運送條件 注意事項\n破傷風桿菌自感染部\n位檢出機率極低,通\n破傷風、 常無法從患者血液中\n無(見注\n新生兒破 無 無 無 無 檢出抗體反應。故不\n意事項)\n傷風 採集疑似患者檢體檢\n驗,以臨床症狀作為\n病例確認判定依據。",
    "english_name": "Neonatal Tetanus",
    "suspected_case": "符合臨床條件。",
    "probable_case": "NA",
    "confirmed_case": "符合臨床條件,且相關就醫病歷資料經專家審查判定。"
  },
  {
    "name": "日本腦炎",
    "url": "https://www.cdc.gov.tw/File/Get/eLHlAUeum24JmOuelMou9w",
    "source_category": "第三類",
    "content": "日本腦炎\n(Japanese Encephalitis)\n一、臨床條件\n出現下列急性神經症狀:發燒、意識障礙、嘔吐、頸部僵硬、抽筋、\n肌張力異常、頭痛、腦膜刺激症狀及精神症狀(譫妄、意識不清等)。\n二、檢驗條件\n符合下列檢驗結果之任一項者,定義為檢驗結果陽性:\n(一) 臨床檢體(血液、腦脊髓液或組織)分離並鑑定出日本腦炎病\n毒。\n(二) 臨床檢體分子生物學核酸檢測陽性,或腦脊髓液中日本腦炎病\n毒特異性 IgM 抗體陽性。\n(三) 急性期(或初次採檢)血清中,日本腦炎病毒特異性 IgM 抗體\n或 IgG 抗體陽性。\n(四) 在最近未接受預防注射及排除其他黃病毒交叉反應的情形下,\n成對血清(急性期及恢復期)中,日本腦炎病毒特異性 IgM 抗\n體或 IgG 抗體(二者任一)有陽轉或達 4 倍以上上升。\n三、流行病學條件\n具有下列任一個條件:\n(一) 住家或活動範圍附近有日本腦炎確定病例。\n(二) 有日本腦炎相關流行地區旅遊史。\n四、通報定義\n具有下列任一個條件:\n(一) 符合臨床條件。\n(二) 醫師高度懷疑與確定病例具有流行病學上相關。\n五、病例分類\n(一) 可能病例:NA\n(二) 極可能病例:符合臨床條件及檢驗結果陽性定義之第三項。\n(三) 確定病例:符合檢驗結果陽性定義之第一、二、四項之任一項。\n2017年05月\n六、檢體採檢送驗事項\n傳染病 採檢量及 應保存種類\n採檢項目 採檢目的 採檢時間 送驗方式 注意事項\n名稱 規定 應保存時間\n1. 若無法取得\n急性期之血\n病毒株\n清檢體,請\n急性期 (30日)\n採集間隔 7\n立即採檢 陽性血清\n日之恢復期\n(30日)\n血清檢體,\n以無菌試管\n並分 2 次送\n血清 收集3 mL 驗。\n血清\n2. 檢體請勿加\n入任何添加\n恢復期 陽性血清 物。\n發病14–40日 (30日) 3. 血清檢體採\n檢注意事項\n病原體\n請參閱傳染\n檢測 2–8 °C\n日本 病檢體採檢\nB類感染性\n腦炎 手冊 2.8.3\n抗體檢測 物質包裝\n及 2.8.4 備\n註說明,血\n清檢體採檢\n步驟請參閱\n傳染病檢體\n以無菌容器 採檢手冊第\n病毒株\n腦脊髓液 住院期間 收集2–3 mL 3.3節。\n(30日)\n4. 腦脊髓液檢\n腦脊髓液\n體採檢步驟\n請參閱傳染\n病檢體採檢\n手冊第 3.6\n節,由醫師\n採檢。\n檢體採檢送驗事項相關資訊請參閱衛生福利部疾病管制署「傳染病檢體採檢手冊」,與「衛福部疾管署全\n球資訊網首頁之檢驗(傳染病檢驗資訊與規定)」項下資料。\n2017年05月",
    "pdf_path": "pdfs/日本腦炎.pdf",
    "臨床條件": "出現下列急性神經症狀:發燒、意識障礙、嘔吐、頸部僵硬、抽筋、\n肌張力異常、頭痛、腦膜刺激症狀及精神症狀(譫妄、意識不清等)。",
    "檢驗條件": "符合下列檢驗結果之任一項者,定義為檢驗結果陽性:\n(一) 臨床檢體(血液、腦脊髓液或組織)分離並鑑定出日本腦炎病\n毒。\n(二) 臨床檢體分子生物學核酸檢測陽性,或腦脊髓液中日本腦炎病\n毒特異性 IgM 抗體陽性。\n(三) 急性期(或初次採檢)血清中,日本腦炎病毒特異性 IgM 抗體\n或 IgG 抗體陽性。\n(四) 在最近未接受預防注射及排除其他黃病毒交叉反應的情形下,\n成對血清(急性期及恢復期)中,日本腦炎病毒特異性 IgM 抗\n體或 IgG 抗體(二者任一)有陽轉或達 4 倍以上上升。",
    "流行病學條件": "具有下列任一個條件:\n(一) 住家或活動範圍附近有日本腦炎確定病例。\n(二) 有日本腦炎相關流行地區旅遊史。",
    "通報定義": "具有下列任一個條件:\n(一) 符合臨床條件。\n(二) 醫師高度懷疑與確定病例具有流行病學上相關。",
    "疾病分類": "(一) 可能病例:NA\n(二) 極可能病例:符合臨床條件及檢驗結果陽性定義之第三項。\n(三) 確定病例:符合檢驗結果陽性定義之第一、二、四項之任一項。\n2017年05月",
    "檢體採檢送驗事項": "傳染病 採檢量及 應保存種類\n採檢項目 採檢目的 採檢時間 送驗方式 注意事項\n名稱 規定 應保存時間\n1. 若無法取得\n急性期之血\n病毒株\n清檢體,請\n急性期 (30日)\n採集間隔 7\n立即採檢 陽性血清\n日之恢復期\n(30日)\n血清檢體,\n以無菌試管\n並分 2 次送\n血清 收集3 mL 驗。\n血清\n2. 檢體請勿加\n入任何添加\n恢復期 陽性血清 物。\n發病14–40日 (30日) 3. 血清檢體採\n檢注意事項\n病原體\n請參閱傳染\n檢測 2–8 °C\n日本 病檢體採檢\nB類感染性\n腦炎 手冊 2.8.3\n抗體檢測 物質包裝\n及 2.8.4 備\n註說明,血\n清檢體採檢\n步驟請參閱\n傳染病檢體\n以無菌容器 採檢手冊第\n病毒株\n腦脊髓液 住院期間 收集2–3 mL 3.3節。\n(30日)\n4. 腦脊髓液檢\n腦脊髓液\n體採檢步驟\n請參閱傳染\n病檢體採檢\n手冊第 3.6\n節,由醫師\n採檢。\n檢體採檢送驗事項相關資訊請參閱衛生福利部疾病管制署「傳染病檢體採檢手冊」,與「衛福部疾管署全\n球資訊網首頁之檢驗(傳染病檢驗資訊與規定)」項下資料。\n2017年05月",
    "english_name": "Japanese Encephalitis",
    "suspected_case": "NA",
    "probable_case": "符合臨床條件及檢驗結果陽性定義之第三項。",
    "confirmed_case": "符合檢驗結果陽性定義之第一、二、四項之任一項。\n2017年05月"
  },
  {
    "name": "李斯特菌症",
    "url": "https://www.cdc.gov.tw/File/Get/kN4-xYBaE3SAV63odpXkvg",
    "source_category": "第四類",
    "content": "李斯特菌症\n(Listeriosis)\n一、 臨床條件\n具有下列任一個條件:\n(一)由李斯特菌(Listeria monocytogenes)引起之侵襲性疾病,\n如:敗血症、腦膜炎、骨髓炎、心包膜炎、腹膜炎...等。\n(二)孕婦流產、死胎或胎兒早產。\n二、 檢驗條件\n具有下列任一個條件:\n(一)自正常無菌部位臨床檢體(如血液、腦脊髓液等體液)\n分離並鑑定出李斯特菌(Listeria monocytogenes)。\n(二)自流產或死胎之胎盤或胎兒組織(含羊水、胎便、腸胃\n道 內 容 物 等 ) 分 離 並 鑑 定 出 李 斯 特 菌 ( Listeria\nmonocytogenes)。\n三、 流行病學條件\nNA\n四、 通報定義\n符合臨床條件,且經醫院自行檢驗,符合檢驗條件。\n五、 疾病分類\n(一)可能病例:\nNA\n(二)極可能病例:\nNA\n(三)確定病例:\n符合臨床條件及檢驗條件。\n李斯特菌症(Listeriosis)病例定義-1\n六、 檢體採檢送驗事項\n請參閱「傳染病檢體採檢手冊」(https://gov.tw/HBK)\n李斯特菌症(Listeriosis)病例定義-2",
    "pdf_path": "pdfs/李斯特菌症.pdf",
    "臨床條件": "具有下列任一個條件:\n(一)由李斯特菌(Listeria monocytogenes)引起之侵襲性疾病,\n如:敗血症、腦膜炎、骨髓炎、心包膜炎、腹膜炎...等。\n(二)孕婦流產、死胎或胎兒早產。",
    "檢驗條件": "具有下列任一個條件:\n(一)自正常無菌部位臨床檢體(如血液、腦脊髓液等體液)\n分離並鑑定出李斯特菌(Listeria monocytogenes)。\n(二)自流產或死胎之胎盤或胎兒組織(含羊水、胎便、腸胃\n道 內 容 物 等 ) 分 離 並 鑑 定 出 李 斯 特 菌 ( Listeria\nmonocytogenes)。",
    "流行病學條件": "NA",
    "通報定義": "符合臨床條件,且經醫院自行檢驗,符合檢驗條件。",
    "疾病分類": "(一)可能病例:\nNA\n(二)極可能病例:\nNA\n(三)確定病例:\n符合臨床條件及檢驗條件。\n李斯特菌症(Listeriosis)病例定義-1",
    "檢體採檢送驗事項": "請參閱「傳染病檢體採檢手冊」(https://gov.tw/HBK)\n李斯特菌症(Listeriosis)病例定義-2",
    "english_name": "Listeriosis",
    "suspected_case": "NA",
    "probable_case": "NA",
    "confirmed_case": "符合臨床條件及檢驗條件。\n李斯特菌症(Listeriosis)病例定義-1"
  },
  {
    "name": "桿菌性痢疾",
    "url": "https://www.cdc.gov.tw/File/Get/2qZGgnxjOjPst8tj7w-TuA",
    "source_category": "第二類",
    "content": "桿菌性痢疾\n(Shigellosis)\n修訂日期:109 年11月11日\n一、 臨床條件\n出現嚴重程度不等的腹瀉、發燒、噁心、嘔吐、腹部絞痛、裏急後重\n(tenesmus)、血便或黏液便等症狀。\n二、 檢驗條件\n臨床檢體(如糞便、肛門拭子或血液等)分離與鑑定出志賀氏桿菌\n(Shigella dysenteriae、S. flexneri、S. boydii 或 S. sonnei)。\n三、 流行病學條件\n具有下列任一個條件:\n(一)曾經與確定病例具有密切接觸。\n(二)攝食曾被病人或帶菌者糞便直接或間接汙染之食物、飲用水。\n(三)與確定病例暴露於共同感染源。\n四、 通報定義\n具有下列任一個條件:\n(一) 符合檢驗條件。\n(二) 符合臨床條件及流行病學條件。\n五、 疾病分類\n(一) 可能病例:\nNA\n(二) 極可能病例:\nNA\n(三) 確定病例:\n符合檢驗條件。\n六、 檢體採檢送驗事項\n傳染病 採檢\n採檢目的 採檢時間 採檢量及規定 送驗方式 注意事項\n名稱 項目\n以無菌之細菌\n拭子棉棒,採\n直腸或混合均 請參閱傳染病檢體採\n肛門拭子 勻之糞便檢體 檢手冊 2.8.6.備註說\n或糞便 檢體,置入 明及圖 2.5,糞便採檢\nCary-Blair 保 步驟請參閱第3.5節。\n存輸送培養\n基。\n以含抗凝劑 1. 桿菌性痢疾採檢項\n2-8oC\n(heparin 或 目以肛門拭子或糞\n病 原 體 檢未 投 藥 前 (B類感染性\n抗凝固全 EDTA)採血管 便為原則。\n測 立即採檢 物 質 P650\n血 採集 5mL 血 2. 全血及尿液的採檢\n包裝)\n液,並混合均 時機為醫師認為臨\n勻。 床上有需要時方採\n桿菌性 檢送驗。\n痢疾 3. 抗凝固全血採檢步\n驟請參閱傳染病檢\n以無菌尿管\n體採檢手冊第 3.2\n收集約10 mL\n尿液 節。\n尿液,緊密封\n4. 尿液採檢請參閱傳\n口。\n染病檢體採檢手冊\n第3.4節。\n2-8oC\n純化之菌株以 (志賀氏痢疾\n拭子沾滿一圈 桿菌第一型A\n菌株鑑\n已 分 離 菌 後,置入 類感染性物\n菌株 定;血清 立即送驗\n株時 Cary-Blair 質包裝;其他\n型別鑑定\n保存輸送培養 型別 B 類感\n基。 染 性 物 質\nP650包裝)",
    "pdf_path": "pdfs/桿菌性痢疾.pdf",
    "臨床條件": "出現嚴重程度不等的腹瀉、發燒、噁心、嘔吐、腹部絞痛、裏急後重\n(tenesmus)、血便或黏液便等症狀。",
    "檢驗條件": "臨床檢體(如糞便、肛門拭子或血液等)分離與鑑定出志賀氏桿菌\n(Shigella dysenteriae、S. flexneri、S. boydii 或 S. sonnei)。",
    "流行病學條件": "具有下列任一個條件:\n(一)曾經與確定病例具有密切接觸。\n(二)攝食曾被病人或帶菌者糞便直接或間接汙染之食物、飲用水。\n(三)與確定病例暴露於共同感染源。",
    "通報定義": "具有下列任一個條件:\n(一) 符合檢驗條件。\n(二) 符合臨床條件及流行病學條件。",
    "疾病分類": "(一) 可能病例:\nNA\n(二) 極可能病例:\nNA\n(三) 確定病例:\n符合檢驗條件。",
    "檢體採檢送驗事項": "傳染病 採檢\n採檢目的 採檢時間 採檢量及規定 送驗方式 注意事項\n名稱 項目\n以無菌之細菌\n拭子棉棒,採\n直腸或混合均 請參閱傳染病檢體採\n肛門拭子 勻之糞便檢體 檢手冊 2.8.6.備註說\n或糞便 檢體,置入 明及圖 2.5,糞便採檢\nCary-Blair 保 步驟請參閱第3.5節。\n存輸送培養\n基。\n以含抗凝劑 1. 桿菌性痢疾採檢項\n2-8oC\n(heparin 或 目以肛門拭子或糞\n病 原 體 檢未 投 藥 前 (B類感染性\n抗凝固全 EDTA)採血管 便為原則。\n測 立即採檢 物 質 P650\n血 採集 5mL 血 2. 全血及尿液的採檢\n包裝)\n液,並混合均 時機為醫師認為臨\n勻。 床上有需要時方採\n桿菌性 檢送驗。\n痢疾 3. 抗凝固全血採檢步\n驟請參閱傳染病檢\n以無菌尿管\n體採檢手冊第 3.2\n收集約10 mL\n尿液 節。\n尿液,緊密封\n4. 尿液採檢請參閱傳\n口。\n染病檢體採檢手冊\n第3.4節。\n2-8oC\n純化之菌株以 (志賀氏痢疾\n拭子沾滿一圈 桿菌第一型A\n菌株鑑\n已 分 離 菌 後,置入 類感染性物\n菌株 定;血清 立即送驗\n株時 Cary-Blair 質包裝;其他\n型別鑑定\n保存輸送培養 型別 B 類感\n基。 染 性 物 質\nP650包裝)",
    "english_name": "Shigellosis",
    "suspected_case": "NA",
    "probable_case": "NA",
    "confirmed_case": "符合檢驗條件。"
  },
  {
    "name": "梅毒",
    "url": "https://www.cdc.gov.tw/File/Get/jJKbN19nKtW2AYEGKaiaSQ",
    "source_category": "第三類",
    "content": "梅毒\n(Syphilis)\n一、 臨床條件\n(一) 出現一期梅毒臨床症狀,如無痛性潰瘍、硬性下疳等。\n(二) 出現二期梅毒臨床症狀,如全身性梅毒紅疹、全身性淋巴腺\n腫、發燒、頭痛、倦怠、咽喉炎、肌肉關節疼痛、禿髮、扁\n平濕疣等。\n(三) 出現三期梅毒臨床症狀,如皮膚梅毒腫、心臟血管性梅毒或\n神經性梅毒等。\n二、 檢驗條件\n具下列任一條件:\n(一) 未曾接受梅毒治療或病史不清楚者,其血清學非特異性梅毒\n螺旋體試驗(non-treponemal test)1及特異性梅毒螺旋體試驗\n(treponemal test)2陽性。\n(二) 臨床檢體(病灶滲出液、組織等)以暗視野顯微鏡、螢光抗\n體檢驗或核酸檢驗檢測出梅毒螺旋體。\n(三) 腦脊髓液性病研究實驗室試驗(CSF-VDRL)陽性。\n(四) 曾經接受梅毒治療者,其血清學非特異性梅毒螺旋體試驗\n(non-treponemal test)1效價≧4倍上升。\n註1:非特異性梅毒螺旋體試驗(non-treponemal test):快速血漿反應素試驗(RPR)\n或性病研究實驗室試驗(VDRL)。\n註2:特異性梅毒螺旋體試驗(treponemal test):梅毒螺旋體血液凝集試驗(TPHA)、\n梅毒螺旋體粒子凝集試驗(TPPA)、、梅毒抗體間接螢光染色法(FTA-abs)、\n梅毒螺旋體乳膠凝集試驗(TPLA)、梅毒螺旋體酵素免疫分析法(EIA)或梅\n毒螺旋體化學冷光免疫分析法(CIA/CLIA/CMIA)、梅毒螺旋體電化學發光免\n疫分析法(ECLIA)。\n三、 流行病學條件\nNA\n四、 通報定義\n符合檢驗條件\n五、 疾病分類\n(一) 可能病例:\nNA\n(二) 極可能病例:\nNA\n(三) 確定病例:\n1. 一期梅毒:符合臨床條件第(一)項及檢驗條件\n2. 二期梅毒:符合臨床條件第(二)項及檢驗條件\n3. 三期梅毒:符合臨床條件第(三)項及檢驗條件\n4. 潛伏性梅毒:無臨床症狀,但符合檢驗條件",
    "pdf_path": "pdfs/梅毒.pdf",
    "臨床條件": "(一) 出現一期梅毒臨床症狀,如無痛性潰瘍、硬性下疳等。\n(二) 出現二期梅毒臨床症狀,如全身性梅毒紅疹、全身性淋巴腺\n腫、發燒、頭痛、倦怠、咽喉炎、肌肉關節疼痛、禿髮、扁\n平濕疣等。\n(三) 出現三期梅毒臨床症狀,如皮膚梅毒腫、心臟血管性梅毒或\n神經性梅毒等。",
    "檢驗條件": "具下列任一條件:\n(一) 未曾接受梅毒治療或病史不清楚者,其血清學非特異性梅毒\n螺旋體試驗(non-treponemal test)1及特異性梅毒螺旋體試驗\n(treponemal test)2陽性。\n(二) 臨床檢體(病灶滲出液、組織等)以暗視野顯微鏡、螢光抗\n體檢驗或核酸檢驗檢測出梅毒螺旋體。\n(三) 腦脊髓液性病研究實驗室試驗(CSF-VDRL)陽性。\n(四) 曾經接受梅毒治療者,其血清學非特異性梅毒螺旋體試驗\n(non-treponemal test)1效價≧4倍上升。\n註1:非特異性梅毒螺旋體試驗(non-treponemal test):快速血漿反應素試驗(RPR)\n或性病研究實驗室試驗(VDRL)。\n註2:特異性梅毒螺旋體試驗(treponemal test):梅毒螺旋體血液凝集試驗(TPHA)、\n梅毒螺旋體粒子凝集試驗(TPPA)、、梅毒抗體間接螢光染色法(FTA-abs)、\n梅毒螺旋體乳膠凝集試驗(TPLA)、梅毒螺旋體酵素免疫分析法(EIA)或梅\n毒螺旋體化學冷光免疫分析法(CIA/CLIA/CMIA)、梅毒螺旋體電化學發光免\n疫分析法(ECLIA)。",
    "流行病學條件": "NA",
    "通報定義": "符合檢驗條件",
    "疾病分類": "(一) 可能病例:\nNA\n(二) 極可能病例:\nNA\n(三) 確定病例:\n1. 一期梅毒:符合臨床條件第(一)項及檢驗條件\n2. 二期梅毒:符合臨床條件第(二)項及檢驗條件\n3. 三期梅毒:符合臨床條件第(三)項及檢驗條件\n4. 潛伏性梅毒:無臨床症狀,但符合檢驗條件",
    "檢體採檢送驗事項": "",
    "english_name": "Syphilis",
    "suspected_case": "NA",
    "probable_case": "NA",
    "confirmed_case": "1. 一期梅毒:符合臨床條件第(一)項及檢驗條件\n2. 二期梅毒:符合臨床條件第(二)項及檢驗條件\n3. 三期梅毒:符合臨床條件第(三)項及檢驗條件\n4. 潛伏性梅毒:無臨床症狀,但符合檢驗條件"
  },
  {
    "name": "水痘併發症",
    "url": "https://www.cdc.gov.tw/File/Get/M05PJDEyFnyx78TwarighA",
    "source_category": "第四類",
    "content": "水痘併發症\nComplicated Varicella\n一、臨床條件\n具有下列任一條件:\n(一) 水痘併發症住院或死亡..急性發作,出現符合水痘表現之\n皮疹,且於發疹後因繼發性細菌感染、或肺部、神經等其\n它器官系統併發症而住院或死亡者。\n(二) 先天性水痘症候群..胎兒異常,或新生兒出生出現低體重\n(small for gestational age)、依皮節分布瘢痕性的皮膚\n病變及色素沉澱、先天性眼睛、腦部、骨骼及肌肉異常或\n缺陷等症狀。\n二、檢驗條件\n(一) 臨床檢體(水疱液、痂皮、腦脊髓液、胎兒異常之孕婦羊\n水)分子生物學核酸檢測(PCR)陽性。\n(二) 血清學抗體檢測陽性:單一血清檢體 IgM 抗體陽性或急性\n期與恢復期之成對血清中 IgG 抗體顯著上升。\n三、流行病學條件\n母親於孕期曾感染水痘或接觸水痘患者。\n四、通報定義\n(一) 符合臨床條件(一)。\n(二) 同時符合臨床條件(二)及流行病學條件。\n五、疾病分類\n(一) 可能病例:\nNA\n(二) 極可能病例:\nNA\n(三) 確定病例:\n1. 符合臨床條件(一)。\n2. 同時符合臨床條件(二)、流病條件及任一檢驗條件。\n水痘併發症檢體採檢與檢驗方法\n採檢項目 採檢單位 檢體種類 採檢規定 運送條件 檢驗方法 檢驗期間 收件單位 備註\n將乾燥痂皮由皮膚\n痂皮 取下置於無菌試管 常溫\n輸送\n以無菌針頭掀開水\n泡表層, 以病毒拭\n水泡病灶拭子 子之採檢棒擦拭水\n3-5工作日\n泡基底皮膚後插入 聚合脢連鎖反應(PCR)\n病毒保存輸送管\n疾病管制署\n全國各醫療院 以無菌檢體小管收\n水痘併發症 腦脊髓液 昆陽辦公室\n所 集1 ml腦脊髓液\n低溫\n以無菌試管收集20\n羊水\nmL羊水\n疑似個案必要\n時得於距第一\n以無菌試管收2 mL 抗體檢測\n血清 7-10工作日 次採檢後6個\n血清 (ELISA-IgM,ELISA-IgG)\n月再採第二次\n血清送驗。",
    "pdf_path": "pdfs/水痘併發症.pdf",
    "臨床條件": "具有下列任一條件:\n(一) 水痘併發症住院或死亡..急性發作,出現符合水痘表現之\n皮疹,且於發疹後因繼發性細菌感染、或肺部、神經等其\n它器官系統併發症而住院或死亡者。\n(二) 先天性水痘症候群..胎兒異常,或新生兒出生出現低體重\n(small for gestational age)、依皮節分布瘢痕性的皮膚\n病變及色素沉澱、先天性眼睛、腦部、骨骼及肌肉異常或\n缺陷等症狀。",
    "檢驗條件": "(一) 臨床檢體(水疱液、痂皮、腦脊髓液、胎兒異常之孕婦羊\n水)分子生物學核酸檢測(PCR)陽性。\n(二) 血清學抗體檢測陽性:單一血清檢體 IgM 抗體陽性或急性\n期與恢復期之成對血清中 IgG 抗體顯著上升。",
    "流行病學條件": "母親於孕期曾感染水痘或接觸水痘患者。",
    "通報定義": "(一) 符合臨床條件(一)。\n(二) 同時符合臨床條件(二)及流行病學條件。",
    "疾病分類": "(一) 可能病例:\nNA\n(二) 極可能病例:\nNA\n(三) 確定病例:\n1. 符合臨床條件(一)。\n2. 同時符合臨床條件(二)、流病條件及任一檢驗條件。\n水痘併發症檢體採檢與檢驗方法\n採檢項目 採檢單位 檢體種類 採檢規定 運送條件 檢驗方法 檢驗期間 收件單位 備註\n將乾燥痂皮由皮膚\n痂皮 取下置於無菌試管 常溫\n輸送\n以無菌針頭掀開水\n泡表層, 以病毒拭\n水泡病灶拭子 子之採檢棒擦拭水\n3-5工作日\n泡基底皮膚後插入 聚合脢連鎖反應(PCR)\n病毒保存輸送管\n疾病管制署\n全國各醫療院 以無菌檢體小管收\n水痘併發症 腦脊髓液 昆陽辦公室\n所 集1 ml腦脊髓液\n低溫\n以無菌試管收集20\n羊水\nmL羊水\n疑似個案必要\n時得於距第一\n以無菌試管收2 mL 抗體檢測\n血清 7-10工作日 次採檢後6個\n血清 (ELISA-IgM,ELISA-IgG)\n月再採第二次\n血清送驗。",
    "檢體採檢送驗事項": "",
    "english_name": "Complicated Varicella",
    "suspected_case": "NA",
    "probable_case": "NA",
    "confirmed_case": "1. 符合臨床條件(一)。\n2. 同時符合臨床條件(二)、流病條件及任一檢驗條件。\n水痘併發症檢體採檢與檢驗方法\n採檢項目 採檢單位 檢體種類 採檢規定 運送條件 檢驗方法 檢驗期間 收件單位 備註\n將乾燥痂皮由皮膚\n痂皮 取下置於無菌試管 常溫\n輸送\n以無菌針頭掀開水\n泡表層, 以病毒拭\n水泡病灶拭子 子之採檢棒擦拭水\n3-5工作日\n泡基底皮膚後插入 聚合脢連鎖反應(PCR)\n病毒保存輸送管\n疾病管制署\n全國各醫療院 以無菌檢體小管收\n水痘併發症 腦脊髓液 昆陽辦公室\n所 集1 ml腦脊髓液\n低溫\n以無菌試管收集20\n羊水\nmL羊水\n疑似個案必要\n時得於距第一\n以無菌試管收2 mL 抗體檢測\n血清 7-10工作日 次採檢後6個\n血清 (ELISA-IgM,ELISA-IgG)\n月再採第二次\n血清送驗。"
  },
  {
    "name": "流感併發重症",
    "url": "https://www.cdc.gov.tw/File/Get/OX_YLUZbUHKMkZCidu32jA",
    "source_category": "第四類",
    "content": "流感併發重症\n(Severe Complicated Influenza)\n一、 臨床條件\n出現類流感症狀後兩週內因併發症(如肺部併發症、神經系統併\n發症、侵襲性細菌感染、心肌炎或心包膜炎等)而需加護病房治\n療或死亡者。\n二、 檢驗條件\n具有下列任一個條件:\n(一) 呼吸道臨床檢體(咽喉擦拭液等)分離並鑑定出流感病\n毒(Influenza virus)。\n(二) 臨床檢體分子生物學核酸檢測陽性。\n(三) 臨床檢體抗原檢測陽性。\n(四) 臨床檢體血清學抗體檢測陽性:急性期與恢復期流感病\n毒血清抗體效價≧4 倍上升。\n三、 流行病學條件\n曾經與經實驗室證實之確定病例具有密切接觸(close\ncontact),即照護、同住、或與其呼吸道分泌物、體液之直接\n接觸。\n四、 通報定義\n符合臨床條件。\n五、 疾病分類\n(一) 可能病例:\n符合臨床條件。\n(二) 極可能病例:\n符合臨床條件及流行病學條件。\n(三) 確定病例:\n符合臨床條件及檢驗條件。\n1\n六、 檢體採檢送驗事項\n傳染病 採檢 採檢 採檢 應保存種類\n採檢量及規定 送驗方式 注意事項\n名稱 項目 目的 時間 (應保存時間)\n見本署傳染病檢\n以病毒拭子之棉 2-8oC\n體採檢手冊 2.8.5\n咽喉 病原\n流感併 發病3棒擦拭咽喉,插 (B類感染\n備註說明;咽喉採\n擦拭 體檢 病毒株(30日)\n發重症 天內 入病毒保存輸送 性物質包\n檢步驟請參考第\n液 測\n管。 裝)\n3.7節及圖3.7。\n2",
    "pdf_path": "pdfs/流感併發重症.pdf",
    "臨床條件": "出現類流感症狀後兩週內因併發症(如肺部併發症、神經系統併\n發症、侵襲性細菌感染、心肌炎或心包膜炎等)而需加護病房治\n療或死亡者。",
    "檢驗條件": "具有下列任一個條件:\n(一) 呼吸道臨床檢體(咽喉擦拭液等)分離並鑑定出流感病\n毒(Influenza virus)。\n(二) 臨床檢體分子生物學核酸檢測陽性。\n(三) 臨床檢體抗原檢測陽性。\n(四) 臨床檢體血清學抗體檢測陽性:急性期與恢復期流感病\n毒血清抗體效價≧4 倍上升。",
    "流行病學條件": "曾經與經實驗室證實之確定病例具有密切接觸(close\ncontact),即照護、同住、或與其呼吸道分泌物、體液之直接\n接觸。",
    "通報定義": "符合臨床條件。",
    "疾病分類": "(一) 可能病例:\n符合臨床條件。\n(二) 極可能病例:\n符合臨床條件及流行病學條件。\n(三) 確定病例:\n符合臨床條件及檢驗條件。\n1",
    "檢體採檢送驗事項": "傳染病 採檢 採檢 採檢 應保存種類\n採檢量及規定 送驗方式 注意事項\n名稱 項目 目的 時間 (應保存時間)\n見本署傳染病檢\n以病毒拭子之棉 2-8oC\n體採檢手冊 2.8.5\n咽喉 病原\n流感併 發病3棒擦拭咽喉,插 (B類感染\n備註說明;咽喉採\n擦拭 體檢 病毒株(30日)\n發重症 天內 入病毒保存輸送 性物質包\n檢步驟請參考第\n液 測\n管。 裝)\n3.7節及圖3.7。\n2",
    "english_name": "Severe Complicated Influenza",
    "suspected_case": "符合臨床條件。",
    "probable_case": "符合臨床條件及流行病學條件。",
    "confirmed_case": "符合臨床條件及檢驗條件。\n1"
  },
  {
    "name": "流行性腦脊髓膜炎",
    "url": "https://www.cdc.gov.tw/File/Get/GvFfZ5AW1mHqMj9JpE50rQ",
    "source_category": "第二類",
    "content": "流行性腦脊髓膜炎\n(Meningococcal Meningitis)\n修訂日期:113 年 8 月 5 日\n一、 臨床條件\n發燒、劇烈頭痛、噁心、嘔吐、意識模糊、頸部僵直、出血性皮疹、\n瘀斑(purpura)、譫妄、抽搐、昏迷及休克。\n二、 檢驗條件\n具有下列任一個條件:\n(一) 正常無菌檢體(血液、腦脊髓液或其他體液)或皮膚病灶\n(purpuric skin lesion)分離並鑑定出腦膜炎雙球菌。\n(二) 正常無菌檢體(血液、腦脊髓液或其他體液)或皮膚病灶\n(purpuric skin lesion)分子生物學核酸檢測陽性。\n三、 流行病學條件\n與確定病例具有密切接觸,即照護、同住,或與確定病例有呼吸道\n分泌物等接觸。\n四、 通報定義\n具有下列任一個條件:\n(一) 符合臨床條件。\n(二) 經醫院自行檢驗,符合檢驗條件。\n五、 疾病分類\n(一) 可能病例:\n符合臨床條件。\n(二) 極可能病例:\n符合臨床條件(噁心、嘔吐除外)及流行病學條件。\n(三) 確定病例:\n符合檢驗條件。\n六、 檢體採檢送驗事項\n採檢\n檢體種類 採檢目的 採檢時機 採檢規定 運送條件 注意事項\n項目\n以採血管採全血, 1. 採檢種類由臨床\n立即注入嗜氧性血 醫 師 依 症 狀 採\n全血 液培養瓶(血液與 檢,檢體採檢應\n培養液比例為 1:5 由醫師執行為原\n至 1:10)。 則。\n2. 全血採檢步驟請\n未投藥前立 以無菌容器收集至\n腦脊髓液\n參考第3.1節。\n病原體檢測 即採檢 1 mL 腦脊髓液。\n3. 腦脊髓液採檢步\n以無菌容器收集至\n無菌部位體 驟請參考第 3.6\n少1 mL 無菌部位\n液 節,由醫師採檢。\n體液。\n4. 無菌部位體液採\n皮 膚 病 灶 無菌採集,以空針\n檢步驟請參考第\n( purpuric 吸取出血滲出液至\n22-35 oC 3.10節。\nskin lesion) 無菌檢體小瓶。\n流行 5. 腦膜炎雙球菌容\n(B 類感\n已自全血、 接種於巧克力培養\n性腦 易死亡,採檢單\n染性物質\n腦脊髓液、 基,以封口膜\n脊髓 位請先分離菌株\nP650 包\n膜炎 無菌部位體 (paraffin)密封, 後再送驗。\n裝)\n液或皮膚病 並加夾鏈袋運送。 6. 無菌部位體液請\n灶分離菌株\n註明來源(如關\n時 節 液 、 肋 膜 液\n等)。\n菌株鑑定;\n7. 所送菌株為分自\n菌株 血清型別鑑\n全血、腦脊髓液、\n定\n無菌部位體液或\n皮 膚 病 灶\n( purpuric skin\nlesion),並註明來\n源,如全血、腦脊\n髓液或皮膚病灶\n( purpuric skin\nlesion),請採檢單\n位自備巧克力培\n養基。\n8. 檢體送驗地點請\n參考第7.2節。",
    "pdf_path": "pdfs/流行性腦脊髓膜炎.pdf",
    "臨床條件": "發燒、劇烈頭痛、噁心、嘔吐、意識模糊、頸部僵直、出血性皮疹、\n瘀斑(purpura)、譫妄、抽搐、昏迷及休克。",
    "檢驗條件": "具有下列任一個條件:\n(一) 正常無菌檢體(血液、腦脊髓液或其他體液)或皮膚病灶\n(purpuric skin lesion)分離並鑑定出腦膜炎雙球菌。\n(二) 正常無菌檢體(血液、腦脊髓液或其他體液)或皮膚病灶\n(purpuric skin lesion)分子生物學核酸檢測陽性。",
    "流行病學條件": "與確定病例具有密切接觸,即照護、同住,或與確定病例有呼吸道\n分泌物等接觸。",
    "通報定義": "具有下列任一個條件:\n(一) 符合臨床條件。\n(二) 經醫院自行檢驗,符合檢驗條件。",
    "疾病分類": "(一) 可能病例:\n符合臨床條件。\n(二) 極可能病例:\n符合臨床條件(噁心、嘔吐除外)及流行病學條件。\n(三) 確定病例:\n符合檢驗條件。",
    "檢體採檢送驗事項": "採檢\n檢體種類 採檢目的 採檢時機 採檢規定 運送條件 注意事項\n項目\n以採血管採全血, 1. 採檢種類由臨床\n立即注入嗜氧性血 醫 師 依 症 狀 採\n全血 液培養瓶(血液與 檢,檢體採檢應\n培養液比例為 1:5 由醫師執行為原\n至 1:10)。 則。\n2. 全血採檢步驟請\n未投藥前立 以無菌容器收集至\n腦脊髓液\n參考第3.1節。\n病原體檢測 即採檢 1 mL 腦脊髓液。\n3. 腦脊髓液採檢步\n以無菌容器收集至\n無菌部位體 驟請參考第 3.6\n少1 mL 無菌部位\n液 節,由醫師採檢。\n體液。\n4. 無菌部位體液採\n皮 膚 病 灶 無菌採集,以空針\n檢步驟請參考第\n( purpuric 吸取出血滲出液至\n22-35 oC 3.10節。\nskin lesion) 無菌檢體小瓶。\n流行 5. 腦膜炎雙球菌容\n(B 類感\n已自全血、 接種於巧克力培養\n性腦 易死亡,採檢單\n染性物質\n腦脊髓液、 基,以封口膜\n脊髓 位請先分離菌株\nP650 包\n膜炎 無菌部位體 (paraffin)密封, 後再送驗。\n裝)\n液或皮膚病 並加夾鏈袋運送。 6. 無菌部位體液請\n灶分離菌株\n註明來源(如關\n時 節 液 、 肋 膜 液\n等)。\n菌株鑑定;\n7. 所送菌株為分自\n菌株 血清型別鑑\n全血、腦脊髓液、\n定\n無菌部位體液或\n皮 膚 病 灶\n( purpuric skin\nlesion),並註明來\n源,如全血、腦脊\n髓液或皮膚病灶\n( purpuric skin\nlesion),請採檢單\n位自備巧克力培\n養基。\n8. 檢體送驗地點請\n參考第7.2節。",
    "english_name": "Meningococcal Meningitis",
    "suspected_case": "符合臨床條件。",
    "probable_case": "符合臨床條件(噁心、嘔吐除外)及流行病學條件。",
    "confirmed_case": "符合檢驗條件。"
  },
  {
    "name": "流行性腮腺炎",
    "url": "https://www.cdc.gov.tw/File/Get/QjOCRzlaEWaPI76Ta97Uyw",
    "source_category": "第三類",
    "content": "流行性腮腺炎\n(Mumps)\n一、 臨床條件\n急性發作,單或雙側腮腺(或其他唾液腺)疼痛,自限性腫脹持續達\n2 天以上,且無其他明顯原因者。\n二、 檢驗條件\n具有下列任一個條件:\n(一) 臨床檢體(咽喉擦拭液、血液或尿液)分離並鑑定出腮腺炎病\n毒(Mumps virus)。\n(二) 臨床檢體分子生物學核酸檢測陽性。\n(三) 血清學抗體檢測陽性:排除接種疫苗之影響下,IgM 抗體陽性\n或急性期與恢復期血清 IgG 抗體顯著上升。\n三、 流行病學條件\n與確定病例有飛沫接觸,或直接接觸感染病人之唾液、呼吸道分泌物。\n四、 通報定義\n具有下列任一個條件:\n(一) 符合臨床條件。\n(二) 經醫院自行檢驗,符合檢驗條件。\n五、 疾病分類\n(一) 可能病例:\n符合臨床或檢驗條件。\n(二) 極可能病例:\nNA\n(三) 確定病例:\n具有下列任一個條件:\n1. 符合臨床及檢驗條件。\n2. 符合臨床條件,且與經實驗室證實之確定病例具有流行病\n學之關聯。\n六、 檢體採檢送驗事項\n採檢項目 檢體種類 採檢目的 採檢時機 採檢規定 運送條件 注意事項\n採樣前請先按摩 1.疑似個案僅通\n腮腺部位 30 秒, 報,無需採檢。\n再以無菌病毒拭 若經疫調認為有\n頰腔擦拭 發病\n病原體檢測 子之棉棒擦拭咽 群聚感染疑慮,\n液 7 天內\n喉兩頰內側腮腺 則進行採檢。\n流行性腮\n部位,插入病毒保 低溫 2.見 2.8.5 備註說\n腺炎(群\n存輸送管。 明及咽喉拭子採\n聚感染)\n急性期(發 檢步驟請參考第\n病 7 天內) 3.7 節及圖3.7。\n以無菌試管收集\n血清 抗體檢測 ;恢復期(發 3.血清檢體必要時\n至少2 mL 血清。\n病15-30天 需採檢2 次。\n之內)",
    "pdf_path": "pdfs/流行性腮腺炎.pdf",
    "臨床條件": "急性發作,單或雙側腮腺(或其他唾液腺)疼痛,自限性腫脹持續達\n2 天以上,且無其他明顯原因者。",
    "檢驗條件": "具有下列任一個條件:\n(一) 臨床檢體(咽喉擦拭液、血液或尿液)分離並鑑定出腮腺炎病\n毒(Mumps virus)。\n(二) 臨床檢體分子生物學核酸檢測陽性。\n(三) 血清學抗體檢測陽性:排除接種疫苗之影響下,IgM 抗體陽性\n或急性期與恢復期血清 IgG 抗體顯著上升。",
    "流行病學條件": "與確定病例有飛沫接觸,或直接接觸感染病人之唾液、呼吸道分泌物。",
    "通報定義": "具有下列任一個條件:\n(一) 符合臨床條件。\n(二) 經醫院自行檢驗,符合檢驗條件。",
    "疾病分類": "(一) 可能病例:\n符合臨床或檢驗條件。\n(二) 極可能病例:\nNA\n(三) 確定病例:\n具有下列任一個條件:\n1. 符合臨床及檢驗條件。\n2. 符合臨床條件,且與經實驗室證實之確定病例具有流行病\n學之關聯。",
    "檢體採檢送驗事項": "採檢項目 檢體種類 採檢目的 採檢時機 採檢規定 運送條件 注意事項\n採樣前請先按摩 1.疑似個案僅通\n腮腺部位 30 秒, 報,無需採檢。\n再以無菌病毒拭 若經疫調認為有\n頰腔擦拭 發病\n病原體檢測 子之棉棒擦拭咽 群聚感染疑慮,\n液 7 天內\n喉兩頰內側腮腺 則進行採檢。\n流行性腮\n部位,插入病毒保 低溫 2.見 2.8.5 備註說\n腺炎(群\n存輸送管。 明及咽喉拭子採\n聚感染)\n急性期(發 檢步驟請參考第\n病 7 天內) 3.7 節及圖3.7。\n以無菌試管收集\n血清 抗體檢測 ;恢復期(發 3.血清檢體必要時\n至少2 mL 血清。\n病15-30天 需採檢2 次。\n之內)",
    "english_name": "Mumps",
    "suspected_case": "符合臨床或檢驗條件。",
    "probable_case": "NA",
    "confirmed_case": "具有下列任一個條件:\n1. 符合臨床及檢驗條件。\n2. 符合臨床條件,且與經實驗室證實之確定病例具有流行病\n學之關聯。"
  },
  {
    "name": "淋病",
    "url": "https://www.cdc.gov.tw/File/Get/-uWkyQHOn_JTc-aeDKHTkw",
    "source_category": "第三類",
    "content": "淋病\n(Gonorrhea)\n一、 臨床條件\n具有下列任一個條件:\n(一) 泌尿生殖道感染:\n1. 臨床表現包括:尿道炎、睪丸炎、子宮頸炎、子宮內膜炎、輸\n卵管炎、骨盤腔腹膜炎、外陰陰道炎等。\n2. 感染後有些病患會自行痊癒,偶爾有少數成為無明顯症狀之帶\n菌狀態,尤其是女性感染症狀常不明顯。\n(二) 泌尿生殖系統外感染:\n1. 臨床表現包括:直腸感染、喉嚨疼痛、結膜炎、新生兒淋菌性\n結膜炎、菌血症導致瀰漫性感染(disseminated gonococcal\ninfection, DGI),如:淋病性關節炎、皮疹、心內膜炎、腦膜炎。\n2. 直腸及咽喉部位的感染通常無明顯症狀。\n二、 檢驗條件\n具有下列任一個條件:\n(一) 臨床檢體染色鏡檢淋病雙球菌陽性。\n(二) 臨 床 檢 體 分 離 並 鑑 定 出 淋 病 雙 球 菌 ( Neisseria gonorrhoeae)。\n(三) 臨床檢體分子生物學檢測陽性。\n三、 流行病學條件\nNA\n四、 通報定義\n具有下列任一個條件\n(一) 符合臨床條件及檢驗條件。\n(二) 僅符合檢驗條件。\n五、 疾病分類\n1\n(一) 可能病例:NA\n(二) 極可能病例:NA\n(三) 確定病例: 符合檢驗條件。\n六、 檢體採檢送驗事項\n請參閱衛生福利部疾病管制署「傳染病檢體採檢手冊」(可至疾管\n署全球資訊網(cdc.gov.tw)首頁/檢驗項下查閱)。\n2\n應保存種\n傳染病\n採檢項目 採檢目的 採檢時間 採檢量及規定 送驗方式 類(應保存 注意事項\n名稱\n時間)\n以無菌細菌拭子 1. 見 2.8.6 備註說\n明,淋病尿道/\n之 棉 棒 採 集 尿\n尿道分泌 子宮頸分泌物\n道、子宮頸、陰\n物、子宮 檢體採檢請參\n頸 分 泌 道 、 咽 喉 、 直 考第 3.12節。\n物、陰道 腸 、 結 膜 分 泌22-35oC 2. 見 2.8.2 備註說\n分泌物、 (B類感染性\n物,插入含Cary- 明,尿液檢體\n咽喉分泌 物質P650包\n請參考第 3.4\n物、結膜 Blair或Amies保存 裝)\n節。\n分泌物、 輸送培養基,或\n3. 咽喉分泌物檢\n直腸分泌\n接 種 於 Thayer\n物 體採檢請參考\nMartine或巧克力 第3.7節\n培養基。 4. 直腸分泌物檢\n體採檢請參考\n以PCR專用拭子\n尿道分泌\n第3.5節\n物、子宮 採集尿道、子宮\n2-8 oC 5. 關節液採檢請\n頸 分 泌 病原體 頸 、 陰 道 、 咽\n物、陰道 檢測 立即採檢 (B類感染性 參 考 第 3.10\n喉 、 直 腸 分 泌 節。\n分泌物、 物質P650包\n咽喉分泌 物,插入樣品緩 裝) 菌株(30日) 6. 結膜分泌物採\n淋病 物、直腸 衝管或保存輸送 檢 請 參 考 第\n分泌物 3.17 節。\n培養基。\n7. 淋病雙球菌於\n2-8 oC,若 低溫時容易死\n執行淋病雙 亡,故採檢後\n以無菌容器收集 球菌培養則 請立即送檢,\n尿液 無法立即送檢\n10 mL尿液。\n為22-35oC\n須將檢體放於\n(B類感染性\n室溫並於 24 小\n物質P650包\n時內送檢。\n裝)\n以無菌容器收集 22-35oC\n(B類感染性\n關節液 至少 1 mL\n物質P650包\n體液。\n裝)\n接種於巧克力培\n22-35oC\n養基,以封口膜\n已分離菌 (B類感染性\n菌株 菌株鑑定 ( paraffin ) 密\n株時 物質P650包\n封,並加夾鏈袋\n裝)\n運送。\n3",
    "pdf_path": "pdfs/淋病.pdf",
    "臨床條件": "具有下列任一個條件:\n(一) 泌尿生殖道感染:\n1. 臨床表現包括:尿道炎、睪丸炎、子宮頸炎、子宮內膜炎、輸\n卵管炎、骨盤腔腹膜炎、外陰陰道炎等。\n2. 感染後有些病患會自行痊癒,偶爾有少數成為無明顯症狀之帶\n菌狀態,尤其是女性感染症狀常不明顯。\n(二) 泌尿生殖系統外感染:\n1. 臨床表現包括:直腸感染、喉嚨疼痛、結膜炎、新生兒淋菌性\n結膜炎、菌血症導致瀰漫性感染(disseminated gonococcal\ninfection, DGI),如:淋病性關節炎、皮疹、心內膜炎、腦膜炎。\n2. 直腸及咽喉部位的感染通常無明顯症狀。",
    "檢驗條件": "具有下列任一個條件:\n(一) 臨床檢體染色鏡檢淋病雙球菌陽性。\n(二) 臨 床 檢 體 分 離 並 鑑 定 出 淋 病 雙 球 菌 ( Neisseria gonorrhoeae)。\n(三) 臨床檢體分子生物學檢測陽性。",
    "流行病學條件": "NA",
    "通報定義": "具有下列任一個條件\n(一) 符合臨床條件及檢驗條件。\n(二) 僅符合檢驗條件。",
    "疾病分類": "1\n(一) 可能病例:NA\n(二) 極可能病例:NA\n(三) 確定病例: 符合檢驗條件。",
    "檢體採檢送驗事項": "請參閱衛生福利部疾病管制署「傳染病檢體採檢手冊」(可至疾管\n署全球資訊網(cdc.gov.tw)首頁/檢驗項下查閱)。\n2\n應保存種\n傳染病\n採檢項目 採檢目的 採檢時間 採檢量及規定 送驗方式 類(應保存 注意事項\n名稱\n時間)\n以無菌細菌拭子 1. 見 2.8.6 備註說\n明,淋病尿道/\n之 棉 棒 採 集 尿\n尿道分泌 子宮頸分泌物\n道、子宮頸、陰\n物、子宮 檢體採檢請參\n頸 分 泌 道 、 咽 喉 、 直 考第 3.12節。\n物、陰道 腸 、 結 膜 分 泌22-35oC 2. 見 2.8.2 備註說\n分泌物、 (B類感染性\n物,插入含Cary- 明,尿液檢體\n咽喉分泌 物質P650包\n請參考第 3.4\n物、結膜 Blair或Amies保存 裝)\n節。\n分泌物、 輸送培養基,或\n3. 咽喉分泌物檢\n直腸分泌\n接 種 於 Thayer\n物 體採檢請參考\nMartine或巧克力 第3.7節\n培養基。 4. 直腸分泌物檢\n體採檢請參考\n以PCR專用拭子\n尿道分泌\n第3.5節\n物、子宮 採集尿道、子宮\n2-8 oC 5. 關節液採檢請\n頸 分 泌 病原體 頸 、 陰 道 、 咽\n物、陰道 檢測 立即採檢 (B類感染性 參 考 第 3.10\n喉 、 直 腸 分 泌 節。\n分泌物、 物質P650包\n咽喉分泌 物,插入樣品緩 裝) 菌株(30日) 6. 結膜分泌物採\n淋病 物、直腸 衝管或保存輸送 檢 請 參 考 第\n分泌物 3.17 節。\n培養基。\n7. 淋病雙球菌於\n2-8 oC,若 低溫時容易死\n執行淋病雙 亡,故採檢後\n以無菌容器收集 球菌培養則 請立即送檢,\n尿液 無法立即送檢\n10 mL尿液。\n為22-35oC\n須將檢體放於\n(B類感染性\n室溫並於 24 小\n物質P650包\n時內送檢。\n裝)\n以無菌容器收集 22-35oC\n(B類感染性\n關節液 至少 1 mL\n物質P650包\n體液。\n裝)\n接種於巧克力培\n22-35oC\n養基,以封口膜\n已分離菌 (B類感染性\n菌株 菌株鑑定 ( paraffin ) 密\n株時 物質P650包\n封,並加夾鏈袋\n裝)\n運送。\n3",
    "english_name": "Gonorrhea",
    "suspected_case": "NA",
    "probable_case": "NA",
    "confirmed_case": "符合檢驗條件。"
  },
  {
    "name": "漢他病毒症候群",
    "url": "https://www.cdc.gov.tw/File/Get/jLwFi1aHtDoh5G5TUJaEkg",
    "source_category": "第二類",
    "content": "漢他病毒症候群\n(Hantavirus syndrome)\n一、 臨床條件\n具有下列任一個條件:\n(一) 最初以急性發燒、畏寒、肌肉酸痛、頭痛、視力模糊、結膜充血或\n腸胃道症狀等表現,後期可能出現不同程度的出血症狀或腎臟功能\n異常(含蛋白尿、血尿等)。\n(二) 症狀最初以急性發燒、畏寒、肌肉酸痛、頭痛或腸胃道症狀等出\n現,並合併急性呼吸窘迫症候群或雙側肺部瀰漫性間質性水腫或非\n心因性肺水腫;或因不明原因呼吸性疾病致死且經屍體解剖發現非\n心因性肺水腫。\n二、 檢驗條件\n具有下列任一個條件:\n(一) 漢他病毒特異性 IgM抗體檢測陽性。\n(二) 成對血清(恢復期及急性期)中,漢他病毒特異性 IgM或IgG\n抗體(二者任一)有陽轉或≧4 倍上升。\n(三) 臨床檢體分子生物學核酸檢測陽性。\n(四) 組織切片免疫化學染色陽性。\n三、流行病學條件\n發病前兩個月內,具有下列任一個條件:\n(一) 有相關流行地區旅遊史,或曾接觸齧齒類動物或其排泄物、分泌\n物。\n(二) 進行漢他病毒或檢體之實驗室操作。\n(三) 為極可能病例或確定病例之密切接觸者,如:同住家人或醫療照顧\n者等。\n四、通報定義\n具有下列任一個條件:\n(一) 符合臨床條件及流行病學條件。\n(二) 符合檢驗條件。\n(三) 醫師或法醫師高度懷疑。\n109年11月11日修訂\n五、 疾病分類\n(一) 漢他病毒出血熱併腎症候群\n1. 可能病例:NA\n2. 極可能病例:\n符合臨床條件(一)及檢驗條件(一)。\n3. 確定病例:\n符合臨床條件(一)及檢驗條件(二)或(三)或(四)之任一項。\n(二) 漢他病毒肺症候群\n1. 可能病例:NA\n2. 極可能病例:NA\n3. 確定病例:\n符合臨床條件(二)及檢驗條件(二)或(三)或(四)之任一項。\n六、檢體採檢送驗事項\n採檢項目 檢體種類 採檢目的 採檢時機 採檢規定 運送 注意事項\n條件\n漢他病毒 血清 病原體檢 急性期 以無菌試管 低溫 1.檢體勿加入任何添\n症候群 測;抗體 (立即採 收集3mL 加物。\n檢測 檢):恢 血清 2.若無法取得急性期\n復期(發 之血液,請採間隔 7\n病14-40 天之恢復期血清,分\n天之間) 2次送驗。\n3.血清檢體請參閱傳\n染病檢體採檢手冊\n2.8.3 及2.8.4 備註\n說明,血清採檢步驟\n請參閱該手冊第 3.3\n節。\n109年11月11日修訂",
    "pdf_path": "pdfs/漢他病毒症候群.pdf",
    "臨床條件": "具有下列任一個條件:\n(一) 最初以急性發燒、畏寒、肌肉酸痛、頭痛、視力模糊、結膜充血或\n腸胃道症狀等表現,後期可能出現不同程度的出血症狀或腎臟功能\n異常(含蛋白尿、血尿等)。\n(二) 症狀最初以急性發燒、畏寒、肌肉酸痛、頭痛或腸胃道症狀等出\n現,並合併急性呼吸窘迫症候群或雙側肺部瀰漫性間質性水腫或非\n心因性肺水腫;或因不明原因呼吸性疾病致死且經屍體解剖發現非\n心因性肺水腫。",
    "檢驗條件": "具有下列任一個條件:\n(一) 漢他病毒特異性 IgM抗體檢測陽性。\n(二) 成對血清(恢復期及急性期)中,漢他病毒特異性 IgM或IgG\n抗體(二者任一)有陽轉或≧4 倍上升。\n(三) 臨床檢體分子生物學核酸檢測陽性。\n(四) 組織切片免疫化學染色陽性。",
    "流行病學條件": "發病前兩個月內,具有下列任一個條件:\n(一) 有相關流行地區旅遊史,或曾接觸齧齒類動物或其排泄物、分泌\n物。\n(二) 進行漢他病毒或檢體之實驗室操作。\n(三) 為極可能病例或確定病例之密切接觸者,如:同住家人或醫療照顧\n者等。",
    "通報定義": "具有下列任一個條件:\n(一) 符合臨床條件及流行病學條件。\n(二) 符合檢驗條件。\n(三) 醫師或法醫師高度懷疑。\n109年11月11日修訂",
    "疾病分類": "(一) 漢他病毒出血熱併腎症候群\n1. 可能病例:NA\n2. 極可能病例:\n符合臨床條件(一)及檢驗條件(一)。\n3. 確定病例:\n符合臨床條件(一)及檢驗條件(二)或(三)或(四)之任一項。\n(二) 漢他病毒肺症候群\n1. 可能病例:NA\n2. 極可能病例:NA\n3. 確定病例:\n符合臨床條件(二)及檢驗條件(二)或(三)或(四)之任一項。",
    "檢體採檢送驗事項": "採檢項目 檢體種類 採檢目的 採檢時機 採檢規定 運送 注意事項\n條件\n漢他病毒 血清 病原體檢 急性期 以無菌試管 低溫 1.檢體勿加入任何添\n症候群 測;抗體 (立即採 收集3mL 加物。\n檢測 檢):恢 血清 2.若無法取得急性期\n復期(發 之血液,請採間隔 7\n病14-40 天之恢復期血清,分\n天之間) 2次送驗。\n3.血清檢體請參閱傳\n染病檢體採檢手冊\n2.8.3 及2.8.4 備註\n說明,血清採檢步驟\n請參閱該手冊第 3.3\n節。\n109年11月11日修訂",
    "english_name": "Hantavirus syndrome",
    "suspected_case": "NA",
    "probable_case": "NA",
    "confirmed_case": "符合臨床條件(二)及檢驗條件(二)或(三)或(四)之任一項。"
  },
  {
    "name": "漢生病",
    "url": "https://www.cdc.gov.tw/File/Get/rjQxcxpiRmPzzxKcFq6pUQ",
    "source_category": "第三類",
    "content": "漢生病\n(Hansen’s Disease)\n一、 臨床條件\n具有下列任一個條件:\n(一) 皮膚斑疹、結節等持續的皮膚病灶上併感覺喪失或改變。\n(二) 神經腫大併感覺喪失或改變。\n二、 檢驗條件\n具有下列任一個條件:\n(一) 皮 膚 抹 片 或 病 理 切 片 發 現 麻 風 桿 菌 ( Mycobacterium\nleprae)。\n(二) 組織病理有符合漢生病的肉芽腫反應。\n三、 流行病學條件\nNA\n四、 通報定義\n符合臨床條件或檢驗條件。\n五、 疾病分類\n(一) 可能病例:\n符合臨床條件或檢驗條件。\n(二) 極可能病例:\nNA\n(三) 確定病例:\n同時符合臨床條件及檢驗條件。\n六、 檢體採檢送驗事項\n採檢項目 檢體種類 採檢目的 採檢時間 採檢量及規定 送驗方式 注意事項\n石蠟包埋 將5-6片石蠟切片組\n病原體檢\n組織切片 配合案例 織檢體,置入1.5 mL 常溫\n測\n檢體 無菌離心管。\n適用對象:\n1. 漢生病完管個\n1. 以 15 號無菌不銹\n漢生病 鋼刀片,刮取皮膚 案。\n二處不同部位最 2. 疑似漢生病或\n(Hansen’s\n明顯病灶處的組 接觸漢生病個\nDisease)\n病原體檢 織檢體,將含有刮 案。\n皮膚檢體 配合案例 取組織的刀片,置 常溫\n3. 漢生病個案照\n測\n入內含1 mL 70%\n護醫護人員。\n酒精的1.8 mL螺\n旋離心管內。\n2. 至少 2 件皮膚檢\n體。",
    "pdf_path": "pdfs/漢生病.pdf",
    "臨床條件": "具有下列任一個條件:\n(一) 皮膚斑疹、結節等持續的皮膚病灶上併感覺喪失或改變。\n(二) 神經腫大併感覺喪失或改變。",
    "檢驗條件": "具有下列任一個條件:\n(一) 皮 膚 抹 片 或 病 理 切 片 發 現 麻 風 桿 菌 ( Mycobacterium\nleprae)。\n(二) 組織病理有符合漢生病的肉芽腫反應。",
    "流行病學條件": "NA",
    "通報定義": "符合臨床條件或檢驗條件。",
    "疾病分類": "(一) 可能病例:\n符合臨床條件或檢驗條件。\n(二) 極可能病例:\nNA\n(三) 確定病例:\n同時符合臨床條件及檢驗條件。",
    "檢體採檢送驗事項": "採檢項目 檢體種類 採檢目的 採檢時間 採檢量及規定 送驗方式 注意事項\n石蠟包埋 將5-6片石蠟切片組\n病原體檢\n組織切片 配合案例 織檢體,置入1.5 mL 常溫\n測\n檢體 無菌離心管。\n適用對象:\n1. 漢生病完管個\n1. 以 15 號無菌不銹\n漢生病 鋼刀片,刮取皮膚 案。\n二處不同部位最 2. 疑似漢生病或\n(Hansen’s\n明顯病灶處的組 接觸漢生病個\nDisease)\n病原體檢 織檢體,將含有刮 案。\n皮膚檢體 配合案例 取組織的刀片,置 常溫\n3. 漢生病個案照\n測\n入內含1 mL 70%\n護醫護人員。\n酒精的1.8 mL螺\n旋離心管內。\n2. 至少 2 件皮膚檢\n體。",
    "english_name": "Hansen’s Disease",
    "suspected_case": "符合臨床條件或檢驗條件。",
    "probable_case": "NA",
    "confirmed_case": "同時符合臨床條件及檢驗條件。"
  },
  {
    "name": "炭疽病",
    "url": "https://www.cdc.gov.tw/File/Get/-KV36FvRMUavg8mXpOcduQ",
    "source_category": "第二類",
    "content": "附件二\n炭疽病\n(Anthrax)\n一、 臨床條件\n一種急性發作的疾病,可分為四種臨床類型:\n(一) 皮膚型(cutaneous anthrax):皮膚病灶可由無痛、會癢的\n丘疹進展到水泡、伴隨水腫或紅腫的黑色焦痂,可能有\n淋巴結腫大,亦常見發燒。\n(二) 吸入型(inhalational anthrax):早期非特異性症狀包含發\n燒、疲憊;呼吸道症狀包含咳嗽、胸痛、呼吸急促、聽\n診呼吸音異常,影像學檢查常見肋膜積水與縱隔腔變寬;\n伴隨噁心、嘔吐、腹痛、頭痛、發汗及精神狀態改變。\n(三) 攝入型(ingestion anthrax):分為口咽型及腸胃型兩型,\n非特異性症狀包含發燒、疲憊、頭痛、精神狀態改變。\n口咽型症狀包括口腔粘膜病變、喉嚨痛、吞嚥困難和頸\n部腫脹,可能有頸部淋巴結腫大;腸胃型症狀包括腹痛、\n噁心、嘔吐或腹瀉(或血便)、腹脹或腹水。\n(四) 注射型(injection anthrax):注射部位出現明顯水腫或瘀\n血等軟組織感染症狀,通常不形成焦痂,無痛。非特異\n性症狀包含發燒、呼吸急促、噁心,常見凝血功能異常。\n上述四種臨床類型接可能進展成全身性炭疽(systemic anthrax),\n造成敗血症或進展成炭疽性腦膜炎,症狀包含發燒、嚴重頭痛、\n噁心、嘔吐、疲憊、腦膜徵象、抽搐、精神狀態改變。\n二、 檢驗條件\n具有下列任一個條件:\n(一) 臨床檢體(血液、水疱液、腦脊髓液、鼻咽腔分泌物或\n皮膚傷口(焦痂)分離並鑑定出炭疽桿菌(Bacillus\nanthracis)。\n(二) 臨床檢體分子生物學核酸檢測陽性。\n(三) 血清學抗體檢測陽性。\n三、 流行病學條件\n具有下列任一個條件:\n(一) 受汙染之環境、食物、動物、物品之接觸史。\n(二) 與確定病例暴露共同感染源。\n(三) 攝取與確定病例相同食品。\n四、 通報定義\n具有下列任一個條件:\n(一) 符合臨床條件及流行病學條件。\n(二) 經醫院自行檢驗,符合檢驗條件。\n(三) 醫師或法醫師高度懷疑\n五、 疾病分類\n(一) 可能病例:\nNA\n(二) 極可能病例:\n符合臨床條件,且與確定病例具有流行病學之關聯。\n(三) 確定病例:\n符合臨床條件及檢驗條件。\n六、 檢體採檢送驗事項\n請參閱「傳染病檢體採檢手冊」(https://gov.tw/pK8)",
    "pdf_path": "pdfs/炭疽病.pdf",
    "臨床條件": "一種急性發作的疾病,可分為四種臨床類型:\n(一) 皮膚型(cutaneous anthrax):皮膚病灶可由無痛、會癢的\n丘疹進展到水泡、伴隨水腫或紅腫的黑色焦痂,可能有\n淋巴結腫大,亦常見發燒。\n(二) 吸入型(inhalational anthrax):早期非特異性症狀包含發\n燒、疲憊;呼吸道症狀包含咳嗽、胸痛、呼吸急促、聽\n診呼吸音異常,影像學檢查常見肋膜積水與縱隔腔變寬;\n伴隨噁心、嘔吐、腹痛、頭痛、發汗及精神狀態改變。\n(三) 攝入型(ingestion anthrax):分為口咽型及腸胃型兩型,\n非特異性症狀包含發燒、疲憊、頭痛、精神狀態改變。\n口咽型症狀包括口腔粘膜病變、喉嚨痛、吞嚥困難和頸\n部腫脹,可能有頸部淋巴結腫大;腸胃型症狀包括腹痛、\n噁心、嘔吐或腹瀉(或血便)、腹脹或腹水。\n(四) 注射型(injection anthrax):注射部位出現明顯水腫或瘀\n血等軟組織感染症狀,通常不形成焦痂,無痛。非特異\n性症狀包含發燒、呼吸急促、噁心,常見凝血功能異常。\n上述四種臨床類型接可能進展成全身性炭疽(systemic anthrax),\n造成敗血症或進展成炭疽性腦膜炎,症狀包含發燒、嚴重頭痛、\n噁心、嘔吐、疲憊、腦膜徵象、抽搐、精神狀態改變。",
    "檢驗條件": "具有下列任一個條件:\n(一) 臨床檢體(血液、水疱液、腦脊髓液、鼻咽腔分泌物或\n皮膚傷口(焦痂)分離並鑑定出炭疽桿菌(Bacillus\nanthracis)。\n(二) 臨床檢體分子生物學核酸檢測陽性。\n(三) 血清學抗體檢測陽性。",
    "流行病學條件": "具有下列任一個條件:\n(一) 受汙染之環境、食物、動物、物品之接觸史。\n(二) 與確定病例暴露共同感染源。\n(三) 攝取與確定病例相同食品。",
    "通報定義": "具有下列任一個條件:\n(一) 符合臨床條件及流行病學條件。\n(二) 經醫院自行檢驗,符合檢驗條件。\n(三) 醫師或法醫師高度懷疑",
    "疾病分類": "(一) 可能病例:\nNA\n(二) 極可能病例:\n符合臨床條件,且與確定病例具有流行病學之關聯。\n(三) 確定病例:\n符合臨床條件及檢驗條件。",
    "檢體採檢送驗事項": "請參閱「傳染病檢體採檢手冊」(https://gov.tw/pK8)",
    "english_name": "Anthrax",
    "suspected_case": "NA",
    "probable_case": "符合臨床條件,且與確定病例具有流行病學之關聯。",
    "confirmed_case": "符合臨床條件及檢驗條件。"
  },
  {
    "name": "狂犬病",
    "url": "https://www.cdc.gov.tw/File/Get/AvHDvtS1Mgg7AyPCBrQNdA",
    "source_category": "第一類",
    "content": "狂犬病\n(Rabies)\n一、 臨床條件\n符合下列部分或全部臨床描述:\n一種急性病毒性腦脊髓炎,症狀包括焦慮、頭痛、發燒、被動物\n咬傷部位之異樣感。焦燥和恐懼氣流是經常出現的症狀。疾病會\n漸進性發展至麻痺、吞嚥困難,咽喉部肌肉痙攣,以致於引起恐\n水現象,隨後併有精神錯亂及抽搐等現象。\n二、 檢驗條件\n具有下列任一個條件:\n(一) 臨床檢體(唾液、腦脊髓液或中樞神經系統組織等)分\n離並鑑定出狂犬病病毒(Rabies virus)。\n(二) 臨床檢體分子生物學核酸檢測陽性。\n(三) 臨床檢體(腦海馬角部份或頸背毛囊周圍的神經)以直\n接螢光抗體染色法檢測抗原陽性。\n(四) 血清學抗體檢測陽性(血液及腦脊髓液):需排除接種\n過疫苗者。\n三、 流行病學條件\n疾病潛伏期內,具有下列任一個條件:\n(一) 有狂犬病相關流行地區旅遊史,且曾遭犬、貓、蝙蝠、\n浣熊等哺乳動物咬傷,或傷口、黏膜曾接觸帶有狂犬病\n病毒之唾液。\n(二) 曾接受器官移植者,而器官捐贈者疑似感染狂犬病。\n(三) 進行狂犬病病毒或檢體實驗室操作。\n四、 通報定義\n具有下列任一個條件:\n(一) 符合臨床條件及流行病學條件。\n(二) 醫師或法醫師高度懷疑。\n五、 疾病分類\n(一) 可能病例:\nNA\n(二) 極可能病例:\n雖未經實驗室檢驗證實,但符合臨床條件及流行病學條\n件。\n(三) 確定病例:\n符合檢驗條件。\n六、 檢體採檢送驗事項\n請參閱「傳染病檢體採驗手冊」\n網址:衛生福利部疾病管制署全球資訊網/檢驗/傳染病檢體採驗手冊",
    "pdf_path": "pdfs/狂犬病.pdf",
    "臨床條件": "符合下列部分或全部臨床描述:\n一種急性病毒性腦脊髓炎,症狀包括焦慮、頭痛、發燒、被動物\n咬傷部位之異樣感。焦燥和恐懼氣流是經常出現的症狀。疾病會\n漸進性發展至麻痺、吞嚥困難,咽喉部肌肉痙攣,以致於引起恐\n水現象,隨後併有精神錯亂及抽搐等現象。",
    "檢驗條件": "具有下列任一個條件:\n(一) 臨床檢體(唾液、腦脊髓液或中樞神經系統組織等)分\n離並鑑定出狂犬病病毒(Rabies virus)。\n(二) 臨床檢體分子生物學核酸檢測陽性。\n(三) 臨床檢體(腦海馬角部份或頸背毛囊周圍的神經)以直\n接螢光抗體染色法檢測抗原陽性。\n(四) 血清學抗體檢測陽性(血液及腦脊髓液):需排除接種\n過疫苗者。",
    "流行病學條件": "疾病潛伏期內,具有下列任一個條件:\n(一) 有狂犬病相關流行地區旅遊史,且曾遭犬、貓、蝙蝠、\n浣熊等哺乳動物咬傷,或傷口、黏膜曾接觸帶有狂犬病\n病毒之唾液。\n(二) 曾接受器官移植者,而器官捐贈者疑似感染狂犬病。\n(三) 進行狂犬病病毒或檢體實驗室操作。",
    "通報定義": "具有下列任一個條件:\n(一) 符合臨床條件及流行病學條件。\n(二) 醫師或法醫師高度懷疑。",
    "疾病分類": "(一) 可能病例:\nNA\n(二) 極可能病例:\n雖未經實驗室檢驗證實,但符合臨床條件及流行病學條\n件。\n(三) 確定病例:\n符合檢驗條件。",
    "檢體採檢送驗事項": "請參閱「傳染病檢體採驗手冊」\n網址:衛生福利部疾病管制署全球資訊網/檢驗/傳染病檢體採驗手冊",
    "english_name": "Rabies",
    "suspected_case": "NA",
    "probable_case": "雖未經實驗室檢驗證實,但符合臨床條件及流行病學條\n件。",
    "confirmed_case": "符合檢驗條件。"
  },
  {
    "name": "球黴菌症",
    "url": "https://www.cdc.gov.tw/File/Get/PtoMagZXJEspZyyfmJ6WkQ",
    "source_category": "其他",
    "content": "衛生福利部疾病管制署\n球黴菌症送驗條件、檢體採檢及運送規定\n球黴菌症之送驗條件\n同時符合下列臨床條件及流行病學條件:\n一、 臨床條件\n具有下列任一個條件:\n(一) 胸部X光異常,包括實質化、空洞性病灶、肺部結節等。\n(二) 肺外病灶(如皮膚潰瘍、骨關節炎、腦膜腦炎等)。\n(三) 免疫低下者或孕婦有發燒、畏寒、咳嗽、呼吸喘、胸痛、\n皮疹(結節性紅斑或多形性紅斑)等任一症狀。\n二、 流行病學條件\n具有下列任一個條件:\n(一) 發病前1-4週內或發現無症狀之胸部X光異常前1年內,具\n有球黴菌症流行地區之活動史。如美國西南部、墨西哥、\n中南美洲等沙漠或類沙漠地區。\n(二) 發病前1-4週內或發現無症狀之胸部X光異常前1年內,曾\n於無適當防護情形下,操作球黴菌培養物或針對培養陽性\n檢體執行會產生氣膠之程序,致有吸入孢子風險者。\n1\n「球黴菌症」檢體採檢及運送規定\n傳染病名\n採檢項目 採檢目的 採檢時間 採檢量及規定 送驗方式 注意事項\n稱\n支氣管肺病原體檢出現臨床 1. 以無菌容器收 1. 適用對象:同\n泡灌洗液 測\n症狀 集 5 mL支氣管 時符合臨床條\n(BAL)\n肺泡灌洗液 件(如胸部X光\n或支氣管\n(BAL) 或支氣 異常、皮膚潰\n沖 洗 液\n(BW) 或 管沖洗液。 瘍、結節性紅\n病灶組織 2. 病灶組織檢體 斑)及流行病學\n檢體 置入無菌檢體 條件(如發病前\n小瓶。 1-4週內,具有\n2-8oC\n血清 抗體檢測 發病後10 以無菌試管收集 球黴菌症流行\n(B 類感染\n球黴菌症 天以上 2-3 mL 血清。 地 區 之 活 動\n性物質\n史)。\nP650 包裝)\n腦脊髓液 病原體檢 發病後10 以無菌試管收集\n2. 經由本署「實\n測、抗體 天以上 5 mL 腦脊髓液。\n驗室資訊管理\n檢測\n系統」登錄送\n驗。(送驗資料\n管理→送驗單\n新增→非法傳\n送驗單→球黴\n菌症)\n「球黴菌症」送驗地點及檢驗期間\n實驗室生物\n傳染病名\n採檢單位 採檢項目 檢驗方法 檢驗期限 收件單位 安全等級 備註\n稱\n(BSL)\n支氣管肺泡 核酸檢測 3-10工作\n灌洗液\n日\n(BAL)或支\n氣管沖洗液 2(負壓)\n疾病管制署\n全國各醫 (BW)或病\n球黴菌症 南港臨時辦公\n療院所 灶組織檢體\n室\n或腦脊髓液\n血清、腦脊 抗體檢測 1-3工作日\n髓液\n2\n2",
    "pdf_path": "pdfs/球黴菌症.pdf",
    "臨床條件": "具有下列任一個條件:\n(一) 胸部X光異常,包括實質化、空洞性病灶、肺部結節等。\n(二) 肺外病灶(如皮膚潰瘍、骨關節炎、腦膜腦炎等)。\n(三) 免疫低下者或孕婦有發燒、畏寒、咳嗽、呼吸喘、胸痛、\n皮疹(結節性紅斑或多形性紅斑)等任一症狀。",
    "檢驗條件": "",
    "流行病學條件": "具有下列任一個條件:\n(一) 發病前1-4週內或發現無症狀之胸部X光異常前1年內,具\n有球黴菌症流行地區之活動史。如美國西南部、墨西哥、\n中南美洲等沙漠或類沙漠地區。\n(二) 發病前1-4週內或發現無症狀之胸部X光異常前1年內,曾\n於無適當防護情形下,操作球黴菌培養物或針對培養陽性\n檢體執行會產生氣膠之程序,致有吸入孢子風險者。\n1\n「球黴菌症」檢體採檢及運送規定\n傳染病名\n採檢項目 採檢目的 採檢時間 採檢量及規定 送驗方式 注意事項\n稱\n支氣管肺病原體檢出現臨床 1. 以無菌容器收 1. 適用對象:同\n泡灌洗液 測\n症狀 集 5 mL支氣管 時符合臨床條\n(BAL)\n肺泡灌洗液 件(如胸部X光\n或支氣管\n(BAL) 或支氣 異常、皮膚潰\n沖 洗 液\n(BW) 或 管沖洗液。 瘍、結節性紅\n病灶組織 2. 病灶組織檢體 斑)及流行病學\n檢體 置入無菌檢體 條件(如發病前\n小瓶。 1-4週內,具有\n2-8oC\n血清 抗體檢測 發病後10 以無菌試管收集 球黴菌症流行\n(B 類感染\n球黴菌症 天以上 2-3 mL 血清。 地 區 之 活 動\n性物質\n史)。\nP650 包裝)\n腦脊髓液 病原體檢 發病後10 以無菌試管收集\n2. 經由本署「實\n測、抗體 天以上 5 mL 腦脊髓液。\n驗室資訊管理\n檢測\n系統」登錄送\n驗。(送驗資料\n管理→送驗單\n新增→非法傳\n送驗單→球黴\n菌症)\n「球黴菌症」送驗地點及檢驗期間\n實驗室生物\n傳染病名\n採檢單位 採檢項目 檢驗方法 檢驗期限 收件單位 安全等級 備註\n稱\n(BSL)\n支氣管肺泡 核酸檢測 3-10工作\n灌洗液\n日\n(BAL)或支\n氣管沖洗液 2(負壓)\n疾病管制署\n全國各醫 (BW)或病\n球黴菌症 南港臨時辦公\n療院所 灶組織檢體\n室\n或腦脊髓液\n血清、腦脊 抗體檢測 1-3工作日\n髓液\n2\n2",
    "通報定義": "",
    "疾病分類": "",
    "檢體採檢送驗事項": "",
    "english_name": ""
  },
  {
    "name": "疱疹B病毒感染症",
    "url": "https://www.cdc.gov.tw/File/Get/h_cnNJ5WhkxHlEODaMVL9Q",
    "source_category": "第四類",
    "content": "疱疹 B 病毒感染症\n(Herpesvirus B Infection)\n一、 臨床條件\n符合下列部分或全部臨床描述者:\n早期症狀:\n(一) 外傷部位周邊出現水泡或潰瘍。\n(二) 接觸部位有刺激痛或搔癢感。\n(三) 所屬淋巴結腫大。\n中期症狀:\n(四) 發燒。\n(五) 接觸部位感覺異常。\n(六) 接觸部位肌肉無力或麻痺。\n(七) 結膜炎。\n晚期症狀:\n(八) 鼻竇炎。\n(九) 頸部僵直、頭痛超過 24 小時。\n(十) 噁心、嘔吐。\n(十一) 腦幹症狀:複視、語言障礙、暈眩、交叉性麻痺、知覺異\n常、腦神經麻痺。\n(十二) 意識不清。\n(十三) 有腦炎及中樞神經症狀。\n二、 檢驗條件\n具有下列任一個條件:\n(一) 臨床檢體(傷口擦拭液、血液或脊髓液)分離並鑑定出疱疹 B\n病毒(Herpesvirus B)。\n(二) 臨床檢體分子生物學核酸檢測陽性。\n(三) 血清學抗體檢測 IgM 或 IgG 陽性。\n三、 流行病學條件\n發病前 3 週內,具有下列任一個條件:\n(一) 有相關流行地區旅遊史,且曾被猿猴類動物咬、抓傷之暴露\n史。\n(二) 與確定病例或其污染物接觸史(如針扎...)。\n(三) 進行疱疹 B 病毒或檢體實驗室操作。\n四、 通報定義\n具有下列任一個條件:\n(一) 符合臨床條件及流行病學條件。\n(二) 經醫院自行檢驗,符合檢驗條件。\n(三) 醫師或法醫師高度懷疑。\n五、 疾病分類\n(一) 可能病例:\nNA\n(二) 極可能病例:\n雖未經實驗室檢驗證實,但符合臨床條件及流行病學條件。\n(三) 確定病例:\n符合檢驗條件。\n六、 檢體採檢送驗事項\n採檢項目 檢體種類 採檢目的 採檢時間 採檢量及規定 送驗方式 注意事項\n以病毒拭子之棉 1. 切勿於受傷當日採集\n傷口擦拭 病原體檢 傷口未清潔處棒擦拭傷口,插 脊髓液送驗。受傷當\n液 測 理之當日 入病毒保存輸送 日採集之血清僅做為\n管。 建立參照基準值用。\n發病 3 天內第 2. 在發生創傷時,愈早\n一次基準血清 採樣愈佳,傷口病毒\n病原體檢\n(愈接近受傷以無菌試管收集 拭子採檢後,須浸入\n血清 測;抗體\n時愈佳);恢復至少 3 mL血清。 保存液,保持潮濕。\n疱疹B病 檢測\n期(受傷後 3-6 低溫 3. 傷口擦拭液採檢步驟\n毒感染症\n週之間) 請參考第 3.11 節。\n4. 血清檢體見 2.8.3 及\n2.8.4 備註說明,採檢\n以無菌容器收集 步驟見第 3.3 節。\n病原體檢\n腦脊髓液 發病 3 天內 至少1.5 mL脊髓 5. 脊髓液採檢步驟請參\n測\n液。 考第 3.6 節。",
    "pdf_path": "pdfs/疱疹B病毒感染症.pdf",
    "臨床條件": "符合下列部分或全部臨床描述者:\n早期症狀:\n(一) 外傷部位周邊出現水泡或潰瘍。\n(二) 接觸部位有刺激痛或搔癢感。\n(三) 所屬淋巴結腫大。\n中期症狀:\n(四) 發燒。\n(五) 接觸部位感覺異常。\n(六) 接觸部位肌肉無力或麻痺。\n(七) 結膜炎。\n晚期症狀:\n(八) 鼻竇炎。\n(九) 頸部僵直、頭痛超過 24 小時。\n(十) 噁心、嘔吐。\n(十一) 腦幹症狀:複視、語言障礙、暈眩、交叉性麻痺、知覺異\n常、腦神經麻痺。\n(十二) 意識不清。\n(十三) 有腦炎及中樞神經症狀。",
    "檢驗條件": "具有下列任一個條件:\n(一) 臨床檢體(傷口擦拭液、血液或脊髓液)分離並鑑定出疱疹 B\n病毒(Herpesvirus B)。\n(二) 臨床檢體分子生物學核酸檢測陽性。\n(三) 血清學抗體檢測 IgM 或 IgG 陽性。",
    "流行病學條件": "發病前 3 週內,具有下列任一個條件:\n(一) 有相關流行地區旅遊史,且曾被猿猴類動物咬、抓傷之暴露\n史。\n(二) 與確定病例或其污染物接觸史(如針扎...)。\n(三) 進行疱疹 B 病毒或檢體實驗室操作。",
    "通報定義": "具有下列任一個條件:\n(一) 符合臨床條件及流行病學條件。\n(二) 經醫院自行檢驗,符合檢驗條件。\n(三) 醫師或法醫師高度懷疑。",
    "疾病分類": "(一) 可能病例:\nNA\n(二) 極可能病例:\n雖未經實驗室檢驗證實,但符合臨床條件及流行病學條件。\n(三) 確定病例:\n符合檢驗條件。",
    "檢體採檢送驗事項": "採檢項目 檢體種類 採檢目的 採檢時間 採檢量及規定 送驗方式 注意事項\n以病毒拭子之棉 1. 切勿於受傷當日採集\n傷口擦拭 病原體檢 傷口未清潔處棒擦拭傷口,插 脊髓液送驗。受傷當\n液 測 理之當日 入病毒保存輸送 日採集之血清僅做為\n管。 建立參照基準值用。\n發病 3 天內第 2. 在發生創傷時,愈早\n一次基準血清 採樣愈佳,傷口病毒\n病原體檢\n(愈接近受傷以無菌試管收集 拭子採檢後,須浸入\n血清 測;抗體\n時愈佳);恢復至少 3 mL血清。 保存液,保持潮濕。\n疱疹B病 檢測\n期(受傷後 3-6 低溫 3. 傷口擦拭液採檢步驟\n毒感染症\n週之間) 請參考第 3.11 節。\n4. 血清檢體見 2.8.3 及\n2.8.4 備註說明,採檢\n以無菌容器收集 步驟見第 3.3 節。\n病原體檢\n腦脊髓液 發病 3 天內 至少1.5 mL脊髓 5. 脊髓液採檢步驟請參\n測\n液。 考第 3.6 節。",
    "english_name": "Herpesvirus B Infection",
    "suspected_case": "NA",
    "probable_case": "雖未經實驗室檢驗證實,但符合臨床條件及流行病學條件。",
    "confirmed_case": "符合檢驗條件。"
  },
  {
    "name": "瘧疾",
    "url": "https://www.cdc.gov.tw/File/Get/Hr3UYJK2ntgciop4pnqM6Q",
    "source_category": "第二類",
    "content": "瘧疾\n(Malaria)\n一、臨床條件\n發燒、寒顫、出汗、頭痛、背痛、肌肉痛、噁心、嘔吐、下痢、脾腫大、黃疸、\n休克、肝腎衰竭、急性腦病變或昏迷等。\n二、檢驗條件\n具有下列任一個條件:\n(一)顯微鏡血液抹片檢查陽性。\n(二)臨床檢體(血液)分子生物學核酸檢測陽性。\n三、流行病學條件\n具有下列任一個條件:\n(一)曾經到過瘧疾流行地區。\n(二)有瘧蚊分布地區相關旅遊史。\n四、通報定義\n具有下列任一個條件:\n(一)符合臨床條件及流行病學條件。\n(二)經醫院自行檢驗,符合檢驗條件。\n(三)醫師高度懷疑。\n五、疾病分類\n(一)可能病例:\nNA\n(二)極可能病例:\nNA\n(三)確定病例:\n符合檢驗條件。\n六、檢體採檢送驗事項\n採檢項目 檢體種類 採檢目的 採檢時機 採檢規定 運送條件 注意事項\n厚層血片必須以新 1. 消毒患者皮膚\n鮮血液滴於玻片中 後,俟酒精乾燥\n央位置由內向外畫 才可採血。\n(7~8圈)直徑1至1.5 2. 疑似病例應於投\ncm同心圓,再由外 藥前採血,並儘\n往內(7~8圈)後,移 快於1小時內製作\n符合病例 至中央提起,自然 血片,延遲可能\n血片 22-35 oC\n定義或緊 風乾。薄層血片以 會導致瘧原蟲形\n(厚層及薄 (三層包\n急通報瘧 機器自動推片最 態和染色特徵的\n層) 裝)\n疾病例 佳,若無推片機需 變化,製作步驟\n手工推片,則將血 請參考傳染病檢\n液塗抹於玻片一端 體採檢手冊第3.14\n以另一玻片30度角 節。血片檢體\n斜推成單層血球之 不可加熱乾燥及\n抹片,並自然風 不得以甲醇固\n乾。 定。\n3. 帶蟲數少或染色\n法差異可能造成\n瘧疾 病原體檢測 不易清楚鑑別,\n病人投藥前得依\n本署指示,以新\n鮮血液製作至少\n6-12片薄層血片\n(同一barcode),染\n以含抗凝劑\n色2片,其他片不\n(EDTA)採血管採集 2-8 oC\n染色。\n抗凝固全 符合病例 3 mL血液檢體,並 (B類感染\n4. 血片不可噴到酒\n血 定義 採檢後上下混合 性物質包\n精,須以血片\n5~10次,以確保混 裝)\n盒、紙夾保護,\n合均勻。\n或2片血片背面相\n對,放入50 ml離\n心管,並常溫運\n送避免溶血。\n5. 抗凝固全血採檢\n請參考傳染病檢\n體採檢手冊第3.2\n節。",
    "pdf_path": "pdfs/瘧疾.pdf",
    "臨床條件": "發燒、寒顫、出汗、頭痛、背痛、肌肉痛、噁心、嘔吐、下痢、脾腫大、黃疸、\n休克、肝腎衰竭、急性腦病變或昏迷等。",
    "檢驗條件": "具有下列任一個條件:\n(一)顯微鏡血液抹片檢查陽性。\n(二)臨床檢體(血液)分子生物學核酸檢測陽性。",
    "流行病學條件": "具有下列任一個條件:\n(一)曾經到過瘧疾流行地區。\n(二)有瘧蚊分布地區相關旅遊史。",
    "通報定義": "具有下列任一個條件:\n(一)符合臨床條件及流行病學條件。\n(二)經醫院自行檢驗,符合檢驗條件。\n(三)醫師高度懷疑。",
    "疾病分類": "(一)可能病例:\nNA\n(二)極可能病例:\nNA\n(三)確定病例:\n符合檢驗條件。",
    "檢體採檢送驗事項": "採檢項目 檢體種類 採檢目的 採檢時機 採檢規定 運送條件 注意事項\n厚層血片必須以新 1. 消毒患者皮膚\n鮮血液滴於玻片中 後,俟酒精乾燥\n央位置由內向外畫 才可採血。\n(7~8圈)直徑1至1.5 2. 疑似病例應於投\ncm同心圓,再由外 藥前採血,並儘\n往內(7~8圈)後,移 快於1小時內製作\n符合病例 至中央提起,自然 血片,延遲可能\n血片 22-35 oC\n定義或緊 風乾。薄層血片以 會導致瘧原蟲形\n(厚層及薄 (三層包\n急通報瘧 機器自動推片最 態和染色特徵的\n層) 裝)\n疾病例 佳,若無推片機需 變化,製作步驟\n手工推片,則將血 請參考傳染病檢\n液塗抹於玻片一端 體採檢手冊第3.14\n以另一玻片30度角 節。血片檢體\n斜推成單層血球之 不可加熱乾燥及\n抹片,並自然風 不得以甲醇固\n乾。 定。\n3. 帶蟲數少或染色\n法差異可能造成\n瘧疾 病原體檢測 不易清楚鑑別,\n病人投藥前得依\n本署指示,以新\n鮮血液製作至少\n6-12片薄層血片\n(同一barcode),染\n以含抗凝劑\n色2片,其他片不\n(EDTA)採血管採集 2-8 oC\n染色。\n抗凝固全 符合病例 3 mL血液檢體,並 (B類感染\n4. 血片不可噴到酒\n血 定義 採檢後上下混合 性物質包\n精,須以血片\n5~10次,以確保混 裝)\n盒、紙夾保護,\n合均勻。\n或2片血片背面相\n對,放入50 ml離\n心管,並常溫運\n送避免溶血。\n5. 抗凝固全血採檢\n請參考傳染病檢\n體採檢手冊第3.2\n節。",
    "english_name": "Malaria",
    "suspected_case": "NA",
    "probable_case": "NA",
    "confirmed_case": "符合檢驗條件。"
  },
  {
    "name": "登革熱",
    "url": "https://www.cdc.gov.tw/File/Get/V2K1Jcudq7IWXrq_zUGYZQ",
    "source_category": "第二類",
    "content": "登革熱\n(Dengue Fever)\n一、 臨床條件\n突發發燒並伴隨下列任二(含)項以上症狀\n(一) 頭痛/後眼窩痛/肌肉痛/關節痛/骨頭痛\n(二) 出疹\n(三) 白血球減少(leukopenia)\n(四) 噁心/嘔吐\n(五) 血壓帶試驗陽性\n(六) 任一警示徵象\n警示徵象:1.腹部疼痛及壓痛\n2.持續性嘔吐\n3.臨床上體液蓄積(腹水、胸水...)\n4.黏膜出血\n5.嗜睡/躁動不安\n6.肝臟腫大超出肋骨下緣 2 公分\n7.血比容增加伴隨血小板急速下降\n二、 檢驗條件\n符合下列檢驗結果之任一項者,定義為檢驗結果陽性:\n(一) 臨床檢體分離並鑑定出登革病毒。\n(二) 臨床檢體分子生物學核酸檢測陽性。\n(三) 血清學抗原(指登革病毒的非結構蛋白 non-structural protein\n1,簡稱 NS1)檢測陽性。\n(四) 急性期(或初次採檢)血清中,登革病毒特異性 IgM 或 IgG\n抗體為陽性者。\n(五) 成對血清(恢復期及急性期)中,登革病毒特異性 IgM 或 IgG\n抗體(二者任一)有陽轉或≧4 倍上升。\n三、 流行病學條件\n具有下列任一個條件:\n(一) 住家或活動範圍附近有登革熱陽性病例。\n(二) 有登革熱流行地區相關旅遊史。\n四、 通報定義\n符合臨床條件。\n五、 疾病分類\n(一) 可能病例:\n符合臨床條件及流行病學條件。\n(二) 極可能病例:\n符合臨床條件及檢驗結果陽性定義之第四項。\n(三) 確定病例:符合以下二項條件任一者。\n1. 符合檢驗結果陽性定義之第一、二、五項之任一項者。\n2. 符合檢驗結果陽性定義之第三項(限流行區,或由疾病管\n制署或其認可實驗室執行者)。\n六、 檢體採檢送驗事項\n傳染病 採檢項目 採檢目 採檢時間 採檢量及 送驗方式 應保存種類 注意事項\n名稱 的 規定 (應保存時\n間)\n血清檢體見 2.8.3 及 2.8.4\n急性期\n病毒株(30備註說明及血清採檢步驟\n(發病7\n2-8°C(B 日);陽性血請參考第3.3 節。\n日內採\n病 原 體 以無菌試 類感 清(30 日)\n檢)\n登革熱 血清 檢測;抗 管收集 3 染性物質\n體檢測 恢復期 mL 血清。 P650 包\n(發病 裝) 陽 性 血 清\n14-40 日 (30 日)\n之間)",
    "pdf_path": "pdfs/登革熱.pdf",
    "臨床條件": "突發發燒並伴隨下列任二(含)項以上症狀\n(一) 頭痛/後眼窩痛/肌肉痛/關節痛/骨頭痛\n(二) 出疹\n(三) 白血球減少(leukopenia)\n(四) 噁心/嘔吐\n(五) 血壓帶試驗陽性\n(六) 任一警示徵象\n警示徵象:1.腹部疼痛及壓痛\n2.持續性嘔吐\n3.臨床上體液蓄積(腹水、胸水...)\n4.黏膜出血\n5.嗜睡/躁動不安\n6.肝臟腫大超出肋骨下緣 2 公分\n7.血比容增加伴隨血小板急速下降",
    "檢驗條件": "符合下列檢驗結果之任一項者,定義為檢驗結果陽性:\n(一) 臨床檢體分離並鑑定出登革病毒。\n(二) 臨床檢體分子生物學核酸檢測陽性。\n(三) 血清學抗原(指登革病毒的非結構蛋白 non-structural protein\n1,簡稱 NS1)檢測陽性。\n(四) 急性期(或初次採檢)血清中,登革病毒特異性 IgM 或 IgG\n抗體為陽性者。\n(五) 成對血清(恢復期及急性期)中,登革病毒特異性 IgM 或 IgG\n抗體(二者任一)有陽轉或≧4 倍上升。",
    "流行病學條件": "具有下列任一個條件:\n(一) 住家或活動範圍附近有登革熱陽性病例。\n(二) 有登革熱流行地區相關旅遊史。",
    "通報定義": "符合臨床條件。",
    "疾病分類": "(一) 可能病例:\n符合臨床條件及流行病學條件。\n(二) 極可能病例:\n符合臨床條件及檢驗結果陽性定義之第四項。\n(三) 確定病例:符合以下二項條件任一者。\n1. 符合檢驗結果陽性定義之第一、二、五項之任一項者。\n2. 符合檢驗結果陽性定義之第三項(限流行區,或由疾病管\n制署或其認可實驗室執行者)。",
    "檢體採檢送驗事項": "傳染病 採檢項目 採檢目 採檢時間 採檢量及 送驗方式 應保存種類 注意事項\n名稱 的 規定 (應保存時\n間)\n血清檢體見 2.8.3 及 2.8.4\n急性期\n病毒株(30備註說明及血清採檢步驟\n(發病7\n2-8°C(B 日);陽性血請參考第3.3 節。\n日內採\n病 原 體 以無菌試 類感 清(30 日)\n檢)\n登革熱 血清 檢測;抗 管收集 3 染性物質\n體檢測 恢復期 mL 血清。 P650 包\n(發病 裝) 陽 性 血 清\n14-40 日 (30 日)\n之間)",
    "english_name": "Dengue Fever",
    "suspected_case": "符合臨床條件及流行病學條件。",
    "probable_case": "符合臨床條件及檢驗結果陽性定義之第四項。",
    "confirmed_case": "符合以下二項條件任一者。\n1. 符合檢驗結果陽性定義之第一、二、五項之任一項者。\n2. 符合檢驗結果陽性定義之第三項(限流行區,或由疾病管\n制署或其認可實驗室執行者)。"
  },
  {
    "name": "發熱伴血小板減少綜合症",
    "url": "https://www.cdc.gov.tw/File/Get/MQTlaQUGBp94ze2FLYuohw",
    "source_category": "第四類",
    "content": "發熱伴血小板減少綜合症(Severe Fever with\nThrombocytopenia Syndrome, SFTS)\n一、 臨床條件\n(一) 急性發燒≧38°C;\n(二) 血小板減少(<100,000 platelets /mm3),以及下列任一(含)項症\n狀:腸胃道症狀(噁心、嘔吐或腹瀉)、頭痛、肌肉痛、神經學\n症狀、淋巴腺腫大、出血,且無法以其他醫學診斷解釋者。\n二、 檢驗條件\n具有下列任一個條件:\n(一) 臨床檢體分離並鑑定出發熱伴血小板減少綜合症病毒\n( Severe Fever with Thrombocytopenia Syndrome\nVirus)。\n(二) 臨床檢體分子生物學核酸檢測陽性。\n(三) 成對血清(急性期及恢復期)中,發熱伴血小板減少綜合\n症病毒特異性 IgM 或 IgG 抗體(二者任一)有陽轉或≧4\n倍上升。\n(四) 單支血清(不限急性期)中,發熱伴血小板減少綜合症病\n毒特異性 IgM 或 IgG 抗體為陽性者。\n三、 流行病學條件\n(一) 發病前兩週內曾有蜱蟲叮咬史;\n(二) 發病前兩週內曾具國內戶外(畜牧場、農場、山林等)活動史;\n(三) 發病前兩週內有發熱伴血小板減少綜合症流行疫情地區之戶外\n活動史;\n(四) 發病前兩週內曾與在可傳染期之極可能或確定病例有密切接\n觸,包括在無適當防護下提供照護、相處,或有血液、體液之\n直接接觸。\n四、 通報定義\n具有以下任一條件\n(一) 符合所有臨床條件及任一項流行病學條件;\n(二) 僅符合臨床條件第(一)項及流行病學條件第(四)項;\n(三) 符合檢驗條件。\n1\n五、 疾病分類\n(一) 可能病例:\n符合臨床條件及流行病學條件。\n(二) 極可能病例:\n符合檢驗結果陽性定義之第四項。\n(三) 確定病例:\n符合檢驗結果陽性定義之第一、二、三項之任一項。\n六、 檢體採檢送驗事項\n應保存種類\n項目 採檢項目 採檢目的 採檢時間 採檢量及規定 送驗方式 (應保存時 注意事項\n間)\n1.檢體勿加\n入任何添加\n物。\n2.血清檢體\n見 2.8.3 及\n2.8.4備註。\n急性期(發病7\n說明及血清\n日內採檢)\n採檢步驟請\n參 考 第 3.3\n節。\n2-8°C 3.血清為必\n發 熱 伴 病原體檢 以無菌血清管 病 毒 株 (30\n(B 類感染\n採項目,其\n血 小 板 血清 測;抗體檢 收集 3~5 mL血 日);血清(30\n性物質\n綜合症 測 清。 日) 他體液須經\n包裝)\n臨床醫師認\n定有額外檢\n驗需求,且\n恢復期(發 經與本署各\n病 14~40 日之\n區管中心連\n間)\n繫後,認有\n必要者,才\n需採檢。\n2",
    "pdf_path": "pdfs/發熱伴血小板減少綜合症.pdf",
    "臨床條件": "(一) 急性發燒≧38°C;\n(二) 血小板減少(<100,000 platelets /mm3),以及下列任一(含)項症\n狀:腸胃道症狀(噁心、嘔吐或腹瀉)、頭痛、肌肉痛、神經學\n症狀、淋巴腺腫大、出血,且無法以其他醫學診斷解釋者。",
    "檢驗條件": "具有下列任一個條件:\n(一) 臨床檢體分離並鑑定出發熱伴血小板減少綜合症病毒\n( Severe Fever with Thrombocytopenia Syndrome\nVirus)。\n(二) 臨床檢體分子生物學核酸檢測陽性。\n(三) 成對血清(急性期及恢復期)中,發熱伴血小板減少綜合\n症病毒特異性 IgM 或 IgG 抗體(二者任一)有陽轉或≧4\n倍上升。\n(四) 單支血清(不限急性期)中,發熱伴血小板減少綜合症病\n毒特異性 IgM 或 IgG 抗體為陽性者。",
    "流行病學條件": "(一) 發病前兩週內曾有蜱蟲叮咬史;\n(二) 發病前兩週內曾具國內戶外(畜牧場、農場、山林等)活動史;\n(三) 發病前兩週內有發熱伴血小板減少綜合症流行疫情地區之戶外\n活動史;\n(四) 發病前兩週內曾與在可傳染期之極可能或確定病例有密切接\n觸,包括在無適當防護下提供照護、相處,或有血液、體液之\n直接接觸。",
    "通報定義": "具有以下任一條件\n(一) 符合所有臨床條件及任一項流行病學條件;\n(二) 僅符合臨床條件第(一)項及流行病學條件第(四)項;\n(三) 符合檢驗條件。\n1",
    "疾病分類": "(一) 可能病例:\n符合臨床條件及流行病學條件。\n(二) 極可能病例:\n符合檢驗結果陽性定義之第四項。\n(三) 確定病例:\n符合檢驗結果陽性定義之第一、二、三項之任一項。",
    "檢體採檢送驗事項": "應保存種類\n項目 採檢項目 採檢目的 採檢時間 採檢量及規定 送驗方式 (應保存時 注意事項\n間)\n1.檢體勿加\n入任何添加\n物。\n2.血清檢體\n見 2.8.3 及\n2.8.4備註。\n急性期(發病7\n說明及血清\n日內採檢)\n採檢步驟請\n參 考 第 3.3\n節。\n2-8°C 3.血清為必\n發 熱 伴 病原體檢 以無菌血清管 病 毒 株 (30\n(B 類感染\n採項目,其\n血 小 板 血清 測;抗體檢 收集 3~5 mL血 日);血清(30\n性物質\n綜合症 測 清。 日) 他體液須經\n包裝)\n臨床醫師認\n定有額外檢\n驗需求,且\n恢復期(發 經與本署各\n病 14~40 日之\n區管中心連\n間)\n繫後,認有\n必要者,才\n需採檢。\n2",
    "english_name": "Severe Fever with Thrombocytopenia Syndrome, SFTS",
    "suspected_case": "符合臨床條件及流行病學條件。",
    "probable_case": "符合檢驗結果陽性定義之第四項。",
    "confirmed_case": "符合檢驗結果陽性定義之第一、二、三項之任一項。"
  },
  {
    "name": "白喉",
    "url": "https://www.cdc.gov.tw/File/Get/NYppYldyAOVu-9NUXCYMjA",
    "source_category": "第二類",
    "content": "白喉\n(Diphtheria)\n一、 臨床條件\n(一) 呼吸道白喉:\n急性扁桃腺炎、咽喉炎或鼻咽炎,並伴有組織壞死形成灰白色\n膜(偽膜)。\n(二) 皮膚白喉:\n持久不癒的皮膚感染及潰瘍,可能形成膿疱並被偽膜覆蓋。\n二、 檢驗條件\n臨床檢體(咽、喉或鼻黏膜之病灶偽膜或皮膚病灶),分離並鑑定\n出 產 毒 素 之 白 喉 相 關 棒 狀 桿 菌 ( 包 含 Corynebacterium\ndiphtheriae, Corynebacterium ulcerans 及 Corynebacterium\npseudotuberculosis)。\n三、 流行病學條件\n與確定病例具有密切接觸,即照護、同住,或與確定病例有呼吸\n道分泌物等接觸。\n四、 通報定義\n符合臨床條件。\n五、 疾病分類\n(一) 可能病例:\n符合臨床條件。\n(二) 極可能病例:\nNA\n(三) 確定病例:\n具有下列任一個條件:\n1. 符合臨床條件和檢驗條件。\n2. 符合臨床條件,雖未經實驗室檢驗證實,但與經實驗室\n證實之確定病例具有流行病學之關聯。\n1\n六、 檢體採檢送驗事項\n傳染病 應保存種類\n採檢項目 採檢目的 採檢時間 採檢量及規定 送驗方式 注意事項\n名稱 (應保存時間)\n以無菌細菌拭子之\n咽頭、喉 1. 見備註 2.8.6 及\n棉棒直接採集咽2-8oC\n頭及鼻黏病原體檢 圖 2.5,採檢步\n臨床診斷頭、喉頭及鼻黏膜(B類感染\n驟請參考第 3.7\n膜之病灶測;毒素\n白喉 為疑似病等之病灶偽膜或皮性 物 質 菌株(30日) 節說明。\n偽膜或皮鑑 定 ( 分\n例時 膚病灶偽膜,插入P650 包 2. 病 灶 偽 膜 採\n膚病灶偽生鑑定) 集,以由醫師執\nCary-Blair保存輸送裝)\n膜 行為原則。\n培養基。\n2",
    "pdf_path": "pdfs/白喉.pdf",
    "臨床條件": "(一) 呼吸道白喉:\n急性扁桃腺炎、咽喉炎或鼻咽炎,並伴有組織壞死形成灰白色\n膜(偽膜)。\n(二) 皮膚白喉:\n持久不癒的皮膚感染及潰瘍,可能形成膿疱並被偽膜覆蓋。",
    "檢驗條件": "臨床檢體(咽、喉或鼻黏膜之病灶偽膜或皮膚病灶),分離並鑑定\n出 產 毒 素 之 白 喉 相 關 棒 狀 桿 菌 ( 包 含 Corynebacterium\ndiphtheriae, Corynebacterium ulcerans 及 Corynebacterium\npseudotuberculosis)。",
    "流行病學條件": "與確定病例具有密切接觸,即照護、同住,或與確定病例有呼吸\n道分泌物等接觸。",
    "通報定義": "符合臨床條件。",
    "疾病分類": "(一) 可能病例:\n符合臨床條件。\n(二) 極可能病例:\nNA\n(三) 確定病例:\n具有下列任一個條件:\n1. 符合臨床條件和檢驗條件。\n2. 符合臨床條件,雖未經實驗室檢驗證實,但與經實驗室\n證實之確定病例具有流行病學之關聯。\n1",
    "檢體採檢送驗事項": "傳染病 應保存種類\n採檢項目 採檢目的 採檢時間 採檢量及規定 送驗方式 注意事項\n名稱 (應保存時間)\n以無菌細菌拭子之\n咽頭、喉 1. 見備註 2.8.6 及\n棉棒直接採集咽2-8oC\n頭及鼻黏病原體檢 圖 2.5,採檢步\n臨床診斷頭、喉頭及鼻黏膜(B類感染\n驟請參考第 3.7\n膜之病灶測;毒素\n白喉 為疑似病等之病灶偽膜或皮性 物 質 菌株(30日) 節說明。\n偽膜或皮鑑 定 ( 分\n例時 膚病灶偽膜,插入P650 包 2. 病 灶 偽 膜 採\n膚病灶偽生鑑定) 集,以由醫師執\nCary-Blair保存輸送裝)\n膜 行為原則。\n培養基。\n2",
    "english_name": "Diphtheria",
    "suspected_case": "符合臨床條件。",
    "probable_case": "NA",
    "confirmed_case": "具有下列任一個條件:\n1. 符合臨床條件和檢驗條件。\n2. 符合臨床條件,雖未經實驗室檢驗證實,但與經實驗室\n證實之確定病例具有流行病學之關聯。\n1"
  },
  {
    "name": "百日咳",
    "url": "https://www.cdc.gov.tw/File/Get/hXlOZtreRs3dNqSHcgjomg",
    "source_category": "第三類",
    "content": "百日咳\nPertussis\n( )\n一、 臨床條件\n持續咳嗽至少 2 週,且至少具有下列任一個條件:\n(一) 陣發性咳嗽(Paroxysmal cough)\n(二) 吸入性哮聲(Inspiratory whoop)\n(三) 咳嗽後嘔吐(Post-tussive vomiting)\n二、 檢驗條件\n具有下列任一個條件:\n(一) 臨床檢體(鼻咽腔後部分泌物)分離並鑑定出百日咳桿菌\n(Bordetella pertussis)。\n(二) 臨床檢體分子生物學核酸檢測陽性。\n三、 流行病學條件\n曾與經實驗室證實之確定病例有飛沫、近距離或親密之接觸史。\n四、 通報定義\n具有下列任一個條件:\n(一) 符合臨床條件。\n(二) 有咳嗽病史或僅出現輕微症狀,且經醫院自行檢驗,符合檢驗\n條件。\n五、 疾病分類\n(一) 可能病例:\n符合臨床條件。\n(二) 極可能病例:\n符合流行病學條件,且近期有咳嗽史。\n(三) 確定病例:\n具有下列任一個條件:\n1. 符合臨床條件及檢驗條件。\n2. 符合臨床條件及流行病學條件。\n3. 具有急性咳嗽(不須符合臨床條件)及符合檢驗條件第一\n項。\n六、 檢體採檢送驗事項\n採檢項目 檢體種類 採檢目的 採檢時間 採檢量及規定 送驗方式 注意事項\n以百日咳專用鼻咽\n1. 見第 2.8.6 節說明及\n拭子採集鼻咽腔後\n圖 2.3,採檢步驟請參\n部分泌物,插入\n考第 3.8 節及圖 3.9。\n鼻咽腔後病原體檢 未投藥前Regan-Lowe 保存輸\n百日咳 低溫 2. 所需鼻咽拭子及其輸\n部分泌物 測 立即採檢 送培養管。\n送培養基,請事先與\n百日咳專用 PCR 拭 本署昆陽辦公室檢體\n子 單一窗口聯繫。",
    "pdf_path": "pdfs/百日咳.pdf",
    "臨床條件": "持續咳嗽至少 2 週,且至少具有下列任一個條件:\n(一) 陣發性咳嗽(Paroxysmal cough)\n(二) 吸入性哮聲(Inspiratory whoop)\n(三) 咳嗽後嘔吐(Post-tussive vomiting)",
    "檢驗條件": "具有下列任一個條件:\n(一) 臨床檢體(鼻咽腔後部分泌物)分離並鑑定出百日咳桿菌\n(Bordetella pertussis)。\n(二) 臨床檢體分子生物學核酸檢測陽性。",
    "流行病學條件": "曾與經實驗室證實之確定病例有飛沫、近距離或親密之接觸史。",
    "通報定義": "具有下列任一個條件:\n(一) 符合臨床條件。\n(二) 有咳嗽病史或僅出現輕微症狀,且經醫院自行檢驗,符合檢驗\n條件。",
    "疾病分類": "(一) 可能病例:\n符合臨床條件。\n(二) 極可能病例:\n符合流行病學條件,且近期有咳嗽史。\n(三) 確定病例:\n具有下列任一個條件:\n1. 符合臨床條件及檢驗條件。\n2. 符合臨床條件及流行病學條件。\n3. 具有急性咳嗽(不須符合臨床條件)及符合檢驗條件第一\n項。",
    "檢體採檢送驗事項": "採檢項目 檢體種類 採檢目的 採檢時間 採檢量及規定 送驗方式 注意事項\n以百日咳專用鼻咽\n1. 見第 2.8.6 節說明及\n拭子採集鼻咽腔後\n圖 2.3,採檢步驟請參\n部分泌物,插入\n考第 3.8 節及圖 3.9。\n鼻咽腔後病原體檢 未投藥前Regan-Lowe 保存輸\n百日咳 低溫 2. 所需鼻咽拭子及其輸\n部分泌物 測 立即採檢 送培養管。\n送培養基,請事先與\n百日咳專用 PCR 拭 本署昆陽辦公室檢體\n子 單一窗口聯繫。",
    "english_name": "Paroxysmal cough",
    "suspected_case": "符合臨床條件。",
    "probable_case": "符合流行病學條件,且近期有咳嗽史。",
    "confirmed_case": "具有下列任一個條件:\n1. 符合臨床條件及檢驗條件。\n2. 符合臨床條件及流行病學條件。\n3. 具有急性咳嗽(不須符合臨床條件)及符合檢驗條件第一\n項。"
  },
  {
    "name": "破傷風",
    "url": "https://www.cdc.gov.tw/File/Get/9mXtICTXA86NISmVoaYGag",
    "source_category": "第三類",
    "content": "破傷風\nTetanus\n( )\n一、 臨床條件\n具下列任一條件,且排除其他臨床診斷者。\n(一) 痛性之肌肉收縮(最初在咬肌及頸部肌肉,而後為軀幹肌肉)\n(二) 腹部僵硬(abdominal rigidity)\n(三) 肌肉痙攣(spasm)\n(四) 角弓反張(opisthotonus)\n(五) 臉部表情出現「痙笑」(risus sardonicus)\n二、 檢驗條件\nNA\n三、 流行病學條件\n發病前3-12天內有受傷,且未經破傷風抗毒素處理。\n四、 通報定義\n符合臨床條件。\n五、 疾病分類\n(一) 可能病例:\n符合臨床條件。\n(二) 極可能病例:\nNA\n(三) 確定病例:\nNA\n六、 檢體採檢送驗事項\n採檢項目 檢體種類 採檢目的 採檢時機 採檢規定 運送條件 注意事項\n破傷風桿菌自感染部\n位檢出機率極低,通\n常無法從患者血液中\n無(見注\n破傷風 無 無 無 無 檢出抗體反應。故不\n意事項)\n採集疑似患者檢體檢\n驗,以臨床症狀作為\n病例確認判定依據。",
    "pdf_path": "pdfs/破傷風.pdf",
    "臨床條件": "具下列任一條件,且排除其他臨床診斷者。\n(一) 痛性之肌肉收縮(最初在咬肌及頸部肌肉,而後為軀幹肌肉)\n(二) 腹部僵硬(abdominal rigidity)\n(三) 肌肉痙攣(spasm)\n(四) 角弓反張(opisthotonus)\n(五) 臉部表情出現「痙笑」(risus sardonicus)",
    "檢驗條件": "NA",
    "流行病學條件": "發病前3-12天內有受傷,且未經破傷風抗毒素處理。",
    "通報定義": "符合臨床條件。",
    "疾病分類": "(一) 可能病例:\n符合臨床條件。\n(二) 極可能病例:\nNA\n(三) 確定病例:\nNA",
    "檢體採檢送驗事項": "採檢項目 檢體種類 採檢目的 採檢時機 採檢規定 運送條件 注意事項\n破傷風桿菌自感染部\n位檢出機率極低,通\n常無法從患者血液中\n無(見注\n破傷風 無 無 無 無 檢出抗體反應。故不\n意事項)\n採集疑似患者檢體檢\n驗,以臨床症狀作為\n病例確認判定依據。",
    "english_name": "Tetanus",
    "suspected_case": "符合臨床條件。",
    "probable_case": "NA",
    "confirmed_case": "NA"
  },
  {
    "name": "結核病",
    "url": "https://www.cdc.gov.tw/File/Get/u9_mICGcjgec3R7Bu7GqqA",
    "source_category": "第三類",
    "content": "結核病\n( Tuberculosis )\n一、臨床條件\n(一) 接受抗結核藥物治療之結核病人。\n(二) 具有結核病之症狀、徵候或胸部X 光顯示疑似結核病灶且醫師高度懷疑。\n二、檢驗條件\n(一) 臨床檢體(如痰、肋膜液、胃洗液、支氣管沖洗液、組織切片等)結核菌培養陽\n性,鑑定為結核菌群(Mycobacterium tuberculosis complex)(不含 Mycobacterium\nbovis BCG)。\n(二) 臨床檢體(如痰、肋膜液、胃洗液、支氣管沖洗液、組織切片等)\n經Mycobacterium tuberculosis complex核酸偵測為陽性。\n(三) 組織切片顯示典型病理報告。\n(四) 臨床檢體塗片抗酸菌染色檢驗陽性。\n三、流行病學條件:NA\n四、通報定義:\n具有下列任一個條件:\n(一) 符合檢驗條件第一項或第二項,或\n(二) 符合臨床條件第一項,或\n(三) 符合檢驗條件第三項或第四項,且醫師高度懷疑,或\n(四) 符合臨床條件第二項。\n五、疾病分類:\n(一) 可能病例:NA\n(二) 極可能病例:NA\n(三) 確定病例:\n具有下列任一個條件:\n1. 符合檢驗條件第一項,或\n2. 符合臨床條件第一項且胸部X 光進步或臨床症狀改善,或\n3. 符合檢驗條件第二項及第四項。\n六、檢體採檢送驗事項\n請參閱衛生福利部疾病管制署「傳染病檢體採驗手冊」。\n(可至疾病管制署全球資訊網(https://www.cdc.gov.tw/) 首頁 /檢驗項下查詢)\n採檢項目 檢體種類 採檢目的 採檢時間 採檢規定 送驗方式 保存時間 注意事項\n結核病 臨床檢體 病原體傳統 配合臨床或 痰液檢體: 2-8oC 菌株(2 年)\n1. 初次驗\n檢測 公衛需求 詳傳染病檢 (B 類感染\n痰:未用\n臨床檢體 病原體分子 體採檢手冊 性物質\n藥前\n檢測 3.9 痰液檢 P650 包\n體 裝)\n2. 非痰液\n菌株 詳傳染病檢 2-8oC\n檢 體:\n體採檢手冊 (A 類感染\n請依標\n3.15.2菌株 性物質\n準操作\n檢體 P620 包\n程序執\n裝)\n行",
    "pdf_path": "pdfs/結核病.pdf",
    "臨床條件": "(一) 接受抗結核藥物治療之結核病人。\n(二) 具有結核病之症狀、徵候或胸部X 光顯示疑似結核病灶且醫師高度懷疑。",
    "檢驗條件": "(一) 臨床檢體(如痰、肋膜液、胃洗液、支氣管沖洗液、組織切片等)結核菌培養陽\n性,鑑定為結核菌群(Mycobacterium tuberculosis complex)(不含 Mycobacterium\nbovis BCG)。\n(二) 臨床檢體(如痰、肋膜液、胃洗液、支氣管沖洗液、組織切片等)\n經Mycobacterium tuberculosis complex核酸偵測為陽性。\n(三) 組織切片顯示典型病理報告。\n(四) 臨床檢體塗片抗酸菌染色檢驗陽性。\n三、流行病學條件:NA",
    "流行病學條件": "",
    "通報定義": "具有下列任一個條件:\n(一) 符合檢驗條件第一項或第二項,或\n(二) 符合臨床條件第一項,或\n(三) 符合檢驗條件第三項或第四項,且醫師高度懷疑,或\n(四) 符合臨床條件第二項。",
    "疾病分類": "(一) 可能病例:NA\n(二) 極可能病例:NA\n(三) 確定病例:\n具有下列任一個條件:\n1. 符合檢驗條件第一項,或\n2. 符合臨床條件第一項且胸部X 光進步或臨床症狀改善,或\n3. 符合檢驗條件第二項及第四項。",
    "檢體採檢送驗事項": "請參閱衛生福利部疾病管制署「傳染病檢體採驗手冊」。\n(可至疾病管制署全球資訊網(https://www.cdc.gov.tw/) 首頁 /檢驗項下查詢)\n採檢項目 檢體種類 採檢目的 採檢時間 採檢規定 送驗方式 保存時間 注意事項\n結核病 臨床檢體 病原體傳統 配合臨床或 痰液檢體: 2-8oC 菌株(2 年)\n1. 初次驗\n檢測 公衛需求 詳傳染病檢 (B 類感染\n痰:未用\n臨床檢體 病原體分子 體採檢手冊 性物質\n藥前\n檢測 3.9 痰液檢 P650 包\n體 裝)\n2. 非痰液\n菌株 詳傳染病檢 2-8oC\n檢 體:\n體採檢手冊 (A 類感染\n請依標\n3.15.2菌株 性物質\n準操作\n檢體 P620 包\n程序執\n裝)\n行",
    "english_name": "Tuberculosis",
    "suspected_case": "NA",
    "probable_case": "NA",
    "confirmed_case": "具有下列任一個條件:\n1. 符合檢驗條件第一項,或\n2. 符合臨床條件第一項且胸部X 光進步或臨床症狀改善,或\n3. 符合檢驗條件第二項及第四項。"
  },
  {
    "name": "肉毒桿菌中毒",
    "content": "肉毒桿菌中毒\nBotulism\n( )\n一、臨床條件\n疑似肉毒桿菌之毒素引起之腸道或神經學症狀,包含\n(一) 症狀最初可以視覺模糊或複視、吞嚥困難、口乾、眼瞼下垂等表\n現。之後,可能出現弛緩性麻痺之現象,也可能有嘔吐、便秘或\n下痢,嚴重時會發展至呼吸無力衰竭而死亡。\n或\n(二) 發生在不足 1 歲嬰兒,症狀從便秘開始,昏睡、倦怠、食慾不\n振、眼瞼下垂、嚥物困難、失去頭部控制、肌肉張力低下及全身\n性虛弱,有時會發展至呼吸無力衰竭而死亡。\n二、檢驗條件\n(一) 食品、血液或糞便檢測出肉毒桿菌毒素(Botulinum toxin)。\n(二) 糞便分離並鑑定出肉毒桿菌(Clostridium botulinum)。\n(三) 傷口分離並鑑定出肉毒桿菌(Clostridium botulinum)。\n三、流行病學條件\n具有下列任一個條件:\n(一) 曾與確定病例有共同嫌疑食品暴露史。\n(二) 潛伏期內(4 小時 ~8 天,平均 3 天)曾食用市售或家庭自製罐頭\n食品或醃漬食品(如:蔬菜、水果、魚類、肉類、水產品等)、真空\n包裝食品或其他肉毒桿菌中毒嫌疑食品(如:低溫煙燻即時食品)。\n(三) 攝食可能含肉毒桿菌孢子之嫌疑食品,如蜂蜜(偶亦含此孢子)、\n蔬果(表面可能有孢子)或海鮮。\n2019年10月\n(四) 發病前 2 週有傷口受細砂、泥土之污染。\n(五) 發病前 2 週曾使用靜脈藥物者。\n(六) 發病前(6 週內)曾注射肉毒桿菌毒素。\n(七) 因意外(如實驗室操作)或故意(如生物攻擊)之肉毒桿菌毒素暴露\n史者。\n(八) 因腸道手術或腸道菌叢改變者,致肉毒桿菌孢子存在腸道產生毒\n素者。\n四、通報定義\n符合臨床條件。\n五、疾病分類\n(一) 食因型肉毒桿菌中毒:\n1. 極可能病例:符合臨床條件(一)及流行病學條件(一)。\n2. 確定病例:符合臨床條件(一)及檢驗條件之(一)或(二),並排除流\n行病學條件之(四)、(五)、(六)、(七)及(八)。\n(二) 嬰兒型肉毒桿菌中毒:\n1. 極可能病例:NA\n2. 確定病例:符合臨床條件(二)及檢驗條件之(一)或(二) 。\n(三) 創傷型肉毒桿菌中毒:\n1. 極可能病例:\n符合臨床條件(一)及流行病學條件之(四)或(五) ,並排除流行病學\n條件之(一)、(二)及(三)。\n2. 確定病例:\n符合臨床條件(一) 及檢驗條件之(三)或(一)之血液檢體陽性,同時\n符合流行病學條件之(四)或(五),並排除流行病學條件之(一)、(二)\n2019年10月\n及(三)。\n(四) 其他型肉毒桿菌中毒:\n1.極可能病例:\n符合臨床條件(一)及流行病學條件之(六)、(七)或(八),並\n排除流行病學條件之(一)、(二)、(三)、(四)及(五)。\n2.確定病例:\n一歲以上且符合臨床條件(一)及檢驗條件之(二)或(一)血液或糞\n便檢體陽性,並排除流行病學條件之(一)、(二)、(三)、(四)及(五)。\n六、檢體採檢送驗事項\n採驗項目 採檢種類 採檢目的 採檢時間 採檢量及規定 送驗方式 注意事項\n1. 患者如施以任何\n治療措施,應備註\n於檢體送驗單。\n施打抗毒\n毒素與型 以無菌試管收集 20 2. 本菌毒素毒性劇\n血清 素前立即\n別鑑定 mL 血清。 烈,致死率高,採\n採檢 檢時應謹慎操作\n3. 勿使用細菌拭子\n採集糞便檢體,採\n檢步驟請參考第\n3.5 及見 2.8.2 備\n註說明。\n以無菌容器收集至\n糞便\n2-8oC\n4. 血清檢體見 2.8.3\n少 25 g糞便。 (B類感染 及 2.8.4 備註說\n肉毒桿菌\n性物質 明,血清採檢步驟\n中毒\n請參考第 3.3 節。\nP650 包\n5. 見 2.8.2 備註說明\n裝)\n及糞便檢體採檢\n病原體檢 以無菌容器收集 25 請參考第 3.5 節。\n嘔吐物 立即採檢\n測 g以上嘔吐物。 6. 傷口採檢請參考\n第 3.11 節。\n7. 屬於食品中毒案\n件,送檢時須附食\n品中毒調查表影\n以厭氧細菌拭子採 本。\n皮膚傷口 取傷口分泌物或潰\n8. 寄送檢體前,先\n與檢驗單位聯\n爛處之檢體\n繫。\n2019年10月\n2019年10月",
    "臨床條件": "疑似肉毒桿菌之毒素引起之腸道或神經學症狀,包含\n(一) 症狀最初可以視覺模糊或複視、吞嚥困難、口乾、眼瞼下垂等表\n現。之後,可能出現弛緩性麻痺之現象,也可能有嘔吐、便秘或\n下痢,嚴重時會發展至呼吸無力衰竭而死亡。\n或\n(二) 發生在不足 1 歲嬰兒,症狀從便秘開始,昏睡、倦怠、食慾不\n振、眼瞼下垂、嚥物困難、失去頭部控制、肌肉張力低下及全身\n性虛弱,有時會發展至呼吸無力衰竭而死亡。",
    "檢驗條件": "(一) 食品、血液或糞便檢測出肉毒桿菌毒素(Botulinum toxin)。\n(二) 糞便分離並鑑定出肉毒桿菌(Clostridium botulinum)。\n(三) 傷口分離並鑑定出肉毒桿菌(Clostridium botulinum)。",
    "流行病學條件": "具有下列任一個條件:\n(一) 曾與確定病例有共同嫌疑食品暴露史。\n(二) 潛伏期內(4 小時 ~8 天,平均 3 天)曾食用市售或家庭自製罐頭\n食品或醃漬食品(如:蔬菜、水果、魚類、肉類、水產品等)、真空\n包裝食品或其他肉毒桿菌中毒嫌疑食品(如:低溫煙燻即時食品)。\n(三) 攝食可能含肉毒桿菌孢子之嫌疑食品,如蜂蜜(偶亦含此孢子)、\n蔬果(表面可能有孢子)或海鮮。\n2019年10月\n(四) 發病前 2 週有傷口受細砂、泥土之污染。\n(五) 發病前 2 週曾使用靜脈藥物者。\n(六) 發病前(6 週內)曾注射肉毒桿菌毒素。\n(七) 因意外(如實驗室操作)或故意(如生物攻擊)之肉毒桿菌毒素暴露\n史者。\n(八) 因腸道手術或腸道菌叢改變者,致肉毒桿菌孢子存在腸道產生毒\n素者。",
    "通報定義": "符合臨床條件。",
    "疾病分類": "(一) 食因型肉毒桿菌中毒:\n1. 極可能病例:符合臨床條件(一)及流行病學條件(一)。\n2. 確定病例:符合臨床條件(一)及檢驗條件之(一)或(二),並排除流\n行病學條件之(四)、(五)、(六)、(七)及(八)。\n(二) 嬰兒型肉毒桿菌中毒:\n1. 極可能病例:NA\n2. 確定病例:符合臨床條件(二)及檢驗條件之(一)或(二) 。\n(三) 創傷型肉毒桿菌中毒:\n1. 極可能病例:\n符合臨床條件(一)及流行病學條件之(四)或(五) ,並排除流行病學\n條件之(一)、(二)及(三)。\n2. 確定病例:\n符合臨床條件(一) 及檢驗條件之(三)或(一)之血液檢體陽性,同時\n符合流行病學條件之(四)或(五),並排除流行病學條件之(一)、(二)\n2019年10月\n及(三)。\n(四) 其他型肉毒桿菌中毒:\n1.極可能病例:\n符合臨床條件(一)及流行病學條件之(六)、(七)或(八),並\n排除流行病學條件之(一)、(二)、(三)、(四)及(五)。\n2.確定病例:\n一歲以上且符合臨床條件(一)及檢驗條件之(二)或(一)血液或糞\n便檢體陽性,並排除流行病學條件之(一)、(二)、(三)、(四)及(五)。",
    "檢體採檢送驗事項": "採驗項目 採檢種類 採檢目的 採檢時間 採檢量及規定 送驗方式 注意事項\n1. 患者如施以任何\n治療措施,應備註\n於檢體送驗單。\n施打抗毒\n毒素與型 以無菌試管收集 20 2. 本菌毒素毒性劇\n血清 素前立即\n別鑑定 mL 血清。 烈,致死率高,採\n採檢 檢時應謹慎操作\n3. 勿使用細菌拭子\n採集糞便檢體,採\n檢步驟請參考第\n3.5 及見 2.8.2 備\n註說明。\n以無菌容器收集至\n糞便\n2-8oC\n4. 血清檢體見 2.8.3\n少 25 g糞便。 (B類感染 及 2.8.4 備註說\n肉毒桿菌\n性物質 明,血清採檢步驟\n中毒\n請參考第 3.3 節。\nP650 包\n5. 見 2.8.2 備註說明\n裝)\n及糞便檢體採檢\n病原體檢 以無菌容器收集 25 請參考第 3.5 節。\n嘔吐物 立即採檢\n測 g以上嘔吐物。 6. 傷口採檢請參考\n第 3.11 節。\n7. 屬於食品中毒案\n件,送檢時須附食\n品中毒調查表影\n以厭氧細菌拭子採 本。\n皮膚傷口 取傷口分泌物或潰\n8. 寄送檢體前,先\n與檢驗單位聯\n爛處之檢體\n繫。\n2019年10月\n2019年10月",
    "source_category": "第四類",
    "url": "https://www.cdc.gov.tw/File/Get/gAMp_7hIsMnV80poQ-P5xg",
    "english_name": "Botulism",
    "suspected_case": "",
    "probable_case": "符合臨床條件(一)及流行病學條件之(六)、(七)或(八),並\n排除流行病學條件之(一)、(二)、(三)、(四)及(五)。",
    "confirmed_case": "一歲以上且符合臨床條件(一)及檢驗條件之(二)或(一)血液或糞\n便檢體陽性,並排除流行病學條件之(一)、(二)、(三)、(四)及(五)。"
  },
  {
    "name": "腸病毒感染併發重症",
    "url": "https://www.cdc.gov.tw/File/Get/HzGB6fHpfPspHMHu_96DEg",
    "source_category": "第三類",
    "content": "腸病毒感染併發重症\n(Enteroviruses Infection with Severe Complications)\n一、 臨床條件\n具有下列任一個條件:\n(一) 出現典型的手足口病或疱疹性咽峽炎,同時有肌抽躍\n(myoclonic jerks)之症狀或併發腦炎、急性肢體麻痺症候群、\n急性肝炎、心肌炎、急性心肌病變、心肺衰竭等嚴重病例。\n(二) 無手足口病或疱疹性咽峽炎,但出現呼吸道感染症狀,伴有腦\n幹腦炎或急性無力脊髓炎,懷疑為腸病毒感染導致者。\n(三) 出生三個月內嬰兒,出現心肌炎、肝炎、腦炎、血小板下降、\n多發性器官衰竭等敗血症徵候,並排除細菌等其他常見病原感\n染者。\n二、 檢驗條件\n具有下列任一個條件:\n(一) 臨床檢體(咽喉擦拭液或咽喉洗液、糞便或直腸拭子、腦脊髓\n液或水泡液等),分離並鑑定出腸病毒(Enterovirus)。\n(二) 臨床檢體分子生物學核酸檢測陽性。\n(三) 血清學抗體檢測陽性(指血清中腸病毒 71 型特異性 IgM 抗\n體)。\n三、 流行病學條件\n個案發病前兩個月內,家庭或嬰幼兒托育場所之共同居住成員(尤其\n是嬰幼兒)曾感染腸病毒。\n四、 通報定義\n符合臨床條件。\n五、 疾病分類\n由防疫醫師審查判定。\n(一) 排除個案:\n嚴重程度未達臨床條件,或不符合檢驗條件。\n(二) 極可能病例:\n符合臨床條件但無實驗室確認,或高度懷疑為腸病毒感染。\n(三) 確定病例:\n符合臨床條件及檢驗條件。\n六、 檢體採檢送驗事項\n採檢項目 檢體種類 採檢目的 採檢時機 採檢規定 運送條件 注意事項\n1.由醫師研判視需\n以無菌檢體小瓶 要採檢。\n水疱液呈透\n水疱液 收集至少 0.5 mL 2. 水疱液採檢步\n明狀時\n水疱液。 驟請參考第 3.13\n節。\n1. 由醫師研判視需\n要採檢。\n2. 腦脊髓液勿加入\n以無菌試管收集 任何添加物並置\n發病\n腦脊髓液 1.0 mL 以上腦脊 入無菌試管。\n5天內\n髓液。 3. 腦脊髓液採檢步\n驟請參考第 3.6\n病原體檢\n節,由醫師採\n測\n檢。\n以病毒拭子之棉 2-8°C\n咽喉擦拭\n腸病毒感 棒擦拭咽喉,插入\n液\n染併發重 病毒保存輸送管。 (B類感染 1. 見2.8.5備註說明\n症 性物質包 及咽喉採檢步驟\n1. 以病毒拭子之\n發病 棉棒採直腸檢 裝) 請參考第3.7 節。\n7天內 2. 見2.8.2備註說明\n體,插入病毒保\n肛門拭子 及糞便採檢步驟\n存輸送管。\n或糞便 請見第3.5節。\n2. 以糞便專用採\n檢瓶挖取約 3 g\n糞便。\n急性期(發病\n血清檢體見2.8.3及\n7天內)\n以無菌試管收集 2.8.4備註說明及血\n血清 抗體檢測 ;恢復期(發\n至少1.5 mL血清。 清採檢步驟請參考\n病14-21天\n第3.3節。\n內)\n將病毒培養後上\n已分離病毒 清液放入無菌病\n病毒株 檢體保留\n株時 毒 保 存 管 , 0.5\n-1.0mL/管",
    "pdf_path": "pdfs/腸病毒感染併發重症.pdf",
    "臨床條件": "具有下列任一個條件:\n(一) 出現典型的手足口病或疱疹性咽峽炎,同時有肌抽躍\n(myoclonic jerks)之症狀或併發腦炎、急性肢體麻痺症候群、\n急性肝炎、心肌炎、急性心肌病變、心肺衰竭等嚴重病例。\n(二) 無手足口病或疱疹性咽峽炎,但出現呼吸道感染症狀,伴有腦\n幹腦炎或急性無力脊髓炎,懷疑為腸病毒感染導致者。\n(三) 出生三個月內嬰兒,出現心肌炎、肝炎、腦炎、血小板下降、\n多發性器官衰竭等敗血症徵候,並排除細菌等其他常見病原感\n染者。",
    "檢驗條件": "具有下列任一個條件:\n(一) 臨床檢體(咽喉擦拭液或咽喉洗液、糞便或直腸拭子、腦脊髓\n液或水泡液等),分離並鑑定出腸病毒(Enterovirus)。\n(二) 臨床檢體分子生物學核酸檢測陽性。\n(三) 血清學抗體檢測陽性(指血清中腸病毒 71 型特異性 IgM 抗\n體)。",
    "流行病學條件": "個案發病前兩個月內,家庭或嬰幼兒托育場所之共同居住成員(尤其\n是嬰幼兒)曾感染腸病毒。",
    "通報定義": "符合臨床條件。",
    "疾病分類": "由防疫醫師審查判定。\n(一) 排除個案:\n嚴重程度未達臨床條件,或不符合檢驗條件。\n(二) 極可能病例:\n符合臨床條件但無實驗室確認,或高度懷疑為腸病毒感染。\n(三) 確定病例:\n符合臨床條件及檢驗條件。",
    "檢體採檢送驗事項": "採檢項目 檢體種類 採檢目的 採檢時機 採檢規定 運送條件 注意事項\n1.由醫師研判視需\n以無菌檢體小瓶 要採檢。\n水疱液呈透\n水疱液 收集至少 0.5 mL 2. 水疱液採檢步\n明狀時\n水疱液。 驟請參考第 3.13\n節。\n1. 由醫師研判視需\n要採檢。\n2. 腦脊髓液勿加入\n以無菌試管收集 任何添加物並置\n發病\n腦脊髓液 1.0 mL 以上腦脊 入無菌試管。\n5天內\n髓液。 3. 腦脊髓液採檢步\n驟請參考第 3.6\n病原體檢\n節,由醫師採\n測\n檢。\n以病毒拭子之棉 2-8°C\n咽喉擦拭\n腸病毒感 棒擦拭咽喉,插入\n液\n染併發重 病毒保存輸送管。 (B類感染 1. 見2.8.5備註說明\n症 性物質包 及咽喉採檢步驟\n1. 以病毒拭子之\n發病 棉棒採直腸檢 裝) 請參考第3.7 節。\n7天內 2. 見2.8.2備註說明\n體,插入病毒保\n肛門拭子 及糞便採檢步驟\n存輸送管。\n或糞便 請見第3.5節。\n2. 以糞便專用採\n檢瓶挖取約 3 g\n糞便。\n急性期(發病\n血清檢體見2.8.3及\n7天內)\n以無菌試管收集 2.8.4備註說明及血\n血清 抗體檢測 ;恢復期(發\n至少1.5 mL血清。 清採檢步驟請參考\n病14-21天\n第3.3節。\n內)\n將病毒培養後上\n已分離病毒 清液放入無菌病\n病毒株 檢體保留\n株時 毒 保 存 管 , 0.5\n-1.0mL/管",
    "english_name": "Enteroviruses Infection with Severe Complications",
    "suspected_case": "",
    "probable_case": "符合臨床條件但無實驗室確認,或高度懷疑為腸病毒感染。",
    "confirmed_case": "符合臨床條件及檢驗條件。"
  },
  {
    "name": "腸道出血性大腸桿菌感染症",
    "url": "https://www.cdc.gov.tw/File/Get/u9hIZa2RMbReXr5R4moVfw",
    "source_category": "第二類",
    "content": "腸道出血性大腸桿菌感染症\n(Enterohaemorrhagic E. coli Infection)\n一、 臨床條件\n出現腸胃道症狀,嚴重者可導致出血性腹瀉、溶血性尿毒症候群\n(hemolytic uremic syndrome, HUS)或栓塞性血小板減少性紫斑症\n(thrombotic thrombocytopenic purpura, TTP)等。\n二、 檢驗條件\n臨床檢體(糞便或肛門拭子)分離並鑑定出產類志賀毒素(shiga-like\ntoxin)之大腸桿菌(E. coli)。\n三、 流行病學條件\n具有下列任一個條件:\n(一) 曾經與確定病例具有密切接觸。\n(二) 與確定病例暴露共同感染源。\n四、 通報定義\n具有下列任一個條件:\n(一) 符合臨床條件。\n(二) 經醫院自行檢驗,符合檢驗條件。\n五、 疾病分類\n(一) 可能病例:\nNA\n(二) 極可能病例:\n符合臨床條件,雖未經實驗室檢驗證實,但與確定病例具有流\n行病學之關聯。\n(三) 確定病例:\n符合臨床條件和檢驗條件。\n六、 檢體採檢送驗事項\n採檢項目 檢體種類 採檢目的 採檢時機 採檢規定 運送條件 注意事項\n以無菌細菌拭子之棉 1. 見2.8.6備註\n病 原 體 檢\n棒,採集帶血或膿之 說明及圖 2.5,\n測;毒素及\n糞便 立即採檢 黏 液 糞 便 , 置 入低溫 糞便採檢步驟\n抗 血 清 檢\nCary-Blair 保存輸送 請參考第 3.5\n測\n培養基。 節。\n腸道出血 2. 患者如施以任\n性大腸桿 何治療措施,應\n菌感染症 菌 株 鑑 純化之菌株以拭子沾低溫 備註於檢體送\n定;毒素及 滿 一 圈 後 置 入 (B 類感染 驗單。\n菌株 儘速送驗\n抗 血 清 測 Cary-Blair 保存輸送 性物質包3. 屬於食品中毒\n試 培養基。 裝) 案件,送檢時附\n食品中毒調查\n表影本。",
    "pdf_path": "pdfs/腸道出血性大腸桿菌感染症.pdf",
    "臨床條件": "出現腸胃道症狀,嚴重者可導致出血性腹瀉、溶血性尿毒症候群\n(hemolytic uremic syndrome, HUS)或栓塞性血小板減少性紫斑症\n(thrombotic thrombocytopenic purpura, TTP)等。",
    "檢驗條件": "臨床檢體(糞便或肛門拭子)分離並鑑定出產類志賀毒素(shiga-like\ntoxin)之大腸桿菌(E. coli)。",
    "流行病學條件": "具有下列任一個條件:\n(一) 曾經與確定病例具有密切接觸。\n(二) 與確定病例暴露共同感染源。",
    "通報定義": "具有下列任一個條件:\n(一) 符合臨床條件。\n(二) 經醫院自行檢驗,符合檢驗條件。",
    "疾病分類": "(一) 可能病例:\nNA\n(二) 極可能病例:\n符合臨床條件,雖未經實驗室檢驗證實,但與確定病例具有流\n行病學之關聯。\n(三) 確定病例:\n符合臨床條件和檢驗條件。",
    "檢體採檢送驗事項": "採檢項目 檢體種類 採檢目的 採檢時機 採檢規定 運送條件 注意事項\n以無菌細菌拭子之棉 1. 見2.8.6備註\n病 原 體 檢\n棒,採集帶血或膿之 說明及圖 2.5,\n測;毒素及\n糞便 立即採檢 黏 液 糞 便 , 置 入低溫 糞便採檢步驟\n抗 血 清 檢\nCary-Blair 保存輸送 請參考第 3.5\n測\n培養基。 節。\n腸道出血 2. 患者如施以任\n性大腸桿 何治療措施,應\n菌感染症 菌 株 鑑 純化之菌株以拭子沾低溫 備註於檢體送\n定;毒素及 滿 一 圈 後 置 入 (B 類感染 驗單。\n菌株 儘速送驗\n抗 血 清 測 Cary-Blair 保存輸送 性物質包3. 屬於食品中毒\n試 培養基。 裝) 案件,送檢時附\n食品中毒調查\n表影本。",
    "english_name": "Enterohaemorrhagic E. coli Infection",
    "suspected_case": "NA",
    "probable_case": "符合臨床條件,雖未經實驗室檢驗證實,但與確定病例具有流\n行病學之關聯。",
    "confirmed_case": "符合臨床條件和檢驗條件。"
  },
  {
    "name": "茲卡病毒感染症",
    "url": "https://www.cdc.gov.tw/File/Get/2gJGyats5wLBtOgQp8AZ4g",
    "source_category": "第二類",
    "content": "茲卡病毒感染症\n(Zika Virus Infection)\n一、臨床條件\n(一)有紅疹或發燒,且有下列任一(含)項以上症狀:關節痛\n(arthralgia)、關節炎(arthritis)、非化膿性或充血性結膜炎\n(non-purulent/hyperemicconjunctivitis),無法以其他醫學診斷\n解釋者。\n(二)新生兒/胎兒具有下列任一個條件,且生母有茲卡病毒暴露史*:\n1. 小頭畸形**。\n2. 顱內鈣化或先天性神經系統相關異常,且已排除其他病因。\n*暴露史定義:\n懷孕期間,或其性伴侶於該孕婦懷孕前六個月內或懷孕期間,有茲卡病\n毒感染症流行地區相關活動史,或活動範圍內有茲卡病毒感染症確定病\n例。\n**小頭畸形定義:\n(1) 依據年齡、性別及出生時妊娠期之生長曲線,頭圍小於第3個百分\n位(third percentile),且與身長、體重不成比例,經專科醫師評估\n為小頭畸形者。\n(2) 胎兒超音波檢查頭圍小於3個標準差者(SD, standard deviation)。\n二、檢驗條件\n符合下列檢驗結果之任一項者,定義為檢驗結果陽性:\n(一)臨床檢體分離並鑑定出茲卡病毒。\n(二)臨床檢體分子生物學核酸檢測陽性。\n(三)急性期(或初次採檢)血清中,茲卡病毒特異性IgM或IgG抗體\n為陽性,並排除其他黃病毒交叉反應。\n(四)成對血清(恢復期及急性期)中,茲卡病毒特異性IgM或IgG抗\n體(二者任一)有陽轉或≧4倍上升。\n三、流行病學條件\n具有下列任一個條件:\n(一)發病前二週,活動範圍內有茲卡病毒感染症確定病例。\n(二)發病前二週,有茲卡病毒感染症流行地區相關活動史。\n(三)性伴侶於個案發病前6個月內,有茲卡病毒感染症流行地區相關\n活動史,或活動範圍內有茲卡病毒感染症確定病例。\n四、通報定義\n具有下列任一個條件:\n(一)符合臨床條件(一),及流行病學條件。\n(二)符合臨床條件(二)。\n五、疾病分類\n(一)可能病例:\nNA\n(二)極可能病例:\n符合流行病學條件及檢驗結果陽性定義之第三項。\n(三)確定病例:\n符合檢驗結果陽性定義之第一、二、四項之任一項。\n六、檢體採檢送驗事項\n傳染病 採檢量 應保存種類\n採檢項目 採檢目的 採檢時間 送驗方式 注意事項\n名稱 及規定 (應保存時間)\n以無菌 1. 檢體勿加\n2-8°C\n茲卡病 病原體檢 急性期(發 血清管 入任何添\n血清 測;抗體 收集 3~5 (B類感染 病毒株(30日) 加物。\n毒感染 病7日內採\n檢測 mL血 性物質 ;血清(30日) 2. 血清檢體\n症 檢) 清。 見2.8.3 及\n包裝)\n2.8.4 備註\n說明及血\n清採檢步\n驟請參考\n恢復期(發\n第3.3 節。\n病14-40 日 3. 尿液採檢\n之間) 步驟請參\n考第3.4\n節。\n以無菌 4. 血清及尿\n離心管\n病原體檢 發病1~14 病毒株(30日) 液為必採\n尿液 收集 10\n測 日採檢 ;尿液(30日) 項目。\nmL尿\n液。\n以無菌\n須經臨床醫師\n試管收\n認定有額外檢\n集 1 mL\n急性期(發 驗需求,且經\n體液(如羊 病原體檢 臍帶血 病毒株(30日)\n病7日內採 與本署各區管\n水、臍帶血、 測 或 3mL ;體液(30日)\n檢) 中心連繫後,\n唾液、脊髓液) 羊水、唾\n認有必要者,\n液、脊髓\n才需採檢。\n液。\n實施日期:110 年9月6日\n通報「重點監視項目」之「茲卡病毒篩檢」原則\n不符合茲卡病毒感染症通報定義,但有茲卡病毒之檢驗需求者,僅限:\n1. 孕婦於懷孕期間具有茲卡病毒暴露史*。\n2. 新生兒/胎兒具有小頭畸形或疑似感染茲卡病毒症狀,但生母無茲卡\n病毒暴露史*或暴露史不明。\n*暴露史定義:懷孕期間,或其性伴侶於該孕婦懷孕前六個月內或懷孕期間,\n有茲卡病毒感染症流行地區相關活動史,或活動範圍內有茲卡病毒感染症確定\n病例。",
    "pdf_path": "pdfs/茲卡病毒感染症.pdf",
    "臨床條件": "(一)有紅疹或發燒,且有下列任一(含)項以上症狀:關節痛\n(arthralgia)、關節炎(arthritis)、非化膿性或充血性結膜炎\n(non-purulent/hyperemicconjunctivitis),無法以其他醫學診斷\n解釋者。\n(二)新生兒/胎兒具有下列任一個條件,且生母有茲卡病毒暴露史*:\n1. 小頭畸形**。\n2. 顱內鈣化或先天性神經系統相關異常,且已排除其他病因。\n*暴露史定義:\n懷孕期間,或其性伴侶於該孕婦懷孕前六個月內或懷孕期間,有茲卡病\n毒感染症流行地區相關活動史,或活動範圍內有茲卡病毒感染症確定病\n例。\n**小頭畸形定義:\n(1) 依據年齡、性別及出生時妊娠期之生長曲線,頭圍小於第3個百分\n位(third percentile),且與身長、體重不成比例,經專科醫師評估\n為小頭畸形者。\n(2) 胎兒超音波檢查頭圍小於3個標準差者(SD, standard deviation)。",
    "檢驗條件": "符合下列檢驗結果之任一項者,定義為檢驗結果陽性:\n(一)臨床檢體分離並鑑定出茲卡病毒。\n(二)臨床檢體分子生物學核酸檢測陽性。\n(三)急性期(或初次採檢)血清中,茲卡病毒特異性IgM或IgG抗體\n為陽性,並排除其他黃病毒交叉反應。\n(四)成對血清(恢復期及急性期)中,茲卡病毒特異性IgM或IgG抗\n體(二者任一)有陽轉或≧4倍上升。",
    "流行病學條件": "具有下列任一個條件:\n(一)發病前二週,活動範圍內有茲卡病毒感染症確定病例。\n(二)發病前二週,有茲卡病毒感染症流行地區相關活動史。\n(三)性伴侶於個案發病前6個月內,有茲卡病毒感染症流行地區相關\n活動史,或活動範圍內有茲卡病毒感染症確定病例。",
    "通報定義": "具有下列任一個條件:\n(一)符合臨床條件(一),及流行病學條件。\n(二)符合臨床條件(二)。",
    "疾病分類": "(一)可能病例:\nNA\n(二)極可能病例:\n符合流行病學條件及檢驗結果陽性定義之第三項。\n(三)確定病例:\n符合檢驗結果陽性定義之第一、二、四項之任一項。",
    "檢體採檢送驗事項": "傳染病 採檢量 應保存種類\n採檢項目 採檢目的 採檢時間 送驗方式 注意事項\n名稱 及規定 (應保存時間)\n以無菌 1. 檢體勿加\n2-8°C\n茲卡病 病原體檢 急性期(發 血清管 入任何添\n血清 測;抗體 收集 3~5 (B類感染 病毒株(30日) 加物。\n毒感染 病7日內採\n檢測 mL血 性物質 ;血清(30日) 2. 血清檢體\n症 檢) 清。 見2.8.3 及\n包裝)\n2.8.4 備註\n說明及血\n清採檢步\n驟請參考\n恢復期(發\n第3.3 節。\n病14-40 日 3. 尿液採檢\n之間) 步驟請參\n考第3.4\n節。\n以無菌 4. 血清及尿\n離心管\n病原體檢 發病1~14 病毒株(30日) 液為必採\n尿液 收集 10\n測 日採檢 ;尿液(30日) 項目。\nmL尿\n液。\n以無菌\n須經臨床醫師\n試管收\n認定有額外檢\n集 1 mL\n急性期(發 驗需求,且經\n體液(如羊 病原體檢 臍帶血 病毒株(30日)\n病7日內採 與本署各區管\n水、臍帶血、 測 或 3mL ;體液(30日)\n檢) 中心連繫後,\n唾液、脊髓液) 羊水、唾\n認有必要者,\n液、脊髓\n才需採檢。\n液。\n實施日期:110 年9月6日\n通報「重點監視項目」之「茲卡病毒篩檢」原則\n不符合茲卡病毒感染症通報定義,但有茲卡病毒之檢驗需求者,僅限:\n1. 孕婦於懷孕期間具有茲卡病毒暴露史*。\n2. 新生兒/胎兒具有小頭畸形或疑似感染茲卡病毒症狀,但生母無茲卡\n病毒暴露史*或暴露史不明。\n*暴露史定義:懷孕期間,或其性伴侶於該孕婦懷孕前六個月內或懷孕期間,\n有茲卡病毒感染症流行地區相關活動史,或活動範圍內有茲卡病毒感染症確定\n病例。",
    "english_name": "Zika Virus Infection",
    "suspected_case": "NA",
    "probable_case": "符合流行病學條件及檢驗結果陽性定義之第三項。",
    "confirmed_case": "符合檢驗結果陽性定義之第一、二、四項之任一項。"
  },
  {
    "name": "萊姆病",
    "url": "https://www.cdc.gov.tw/File/Get/05kDzMm_N48vAXrlLcc3AQ",
    "source_category": "第四類",
    "content": "萊姆病(Lyme Disease)\n一、 臨床條件\n頭痛、發燒、淋巴腺腫大、肌肉疼痛、喉嚨痛、頸部僵硬、遊走性\n紅斑,病程進展到後期會出現神經根發炎。\n二、 檢驗條件\n具有下列任一個條件:\n(一)臨床檢體(皮膚病灶區之檢體或腦脊髓液、關節囊液等)分\n離並鑑定出伯氏疏螺旋體(Borrelia burgdorferi )。\n(二)血清學抗體檢測陽性。\n三、 流行病學條件\nNA\n四、 通報定義\n符合臨床條件。\n五、 疾病分類\n(一)可能病例:\nNA\n(二)極可能病例:\nNA\n(三)確定病例:\n符合檢驗條件。\n六、 檢體採檢送驗事項\n傳染病 應保存種類\n採檢項目 採檢目的 採檢時間 採檢量及規定 送驗方式 注意事項\n名稱 應保存時間\n1. 血清檢體勿\n以無菌刀片切\n加入任何添\n取病灶區外緣\n加物。\n往內側 0.5 cm\n皮膚傷口 臨床診斷 2. 傷口採檢,請\n處之檢體,以無\n(遊走性 為疑似病 參閱傳染病\n菌生理食鹽水\n紅斑) 例 檢體採檢手\n沾濕之無菌紗\n冊 第 3.11\n布包裹,再置於\n22-35°C 節。\n無菌容器內。\n病原體 (B 類感 菌株 3. 腦脊髓液採\n檢測 染性物質 (30日) 檢步驟請參\n包裝) 閱傳染病檢\n體採檢手冊\n以無菌檢體小\n腦 脊 髓 臨床診斷 第3.6節,由\n瓶收集 0.5 mL\n液、關節 為疑似病 醫師採檢。\n腦脊髓液或關\n萊姆病 囊液 例 4. 關節囊液採\n節囊液。\n檢步驟請參\n閱傳染病檢\n體採檢手冊\n第 3.10 節,\n由 醫 師 採\n檢。\n5. 血清檢體請\n2-8°C\n發病 參閱傳染病\n以無菌試管收 (B 類感 陽性血清\n抗體檢測 8-30 日 檢體採檢手\n血清\n集3mL血清。 染性物質 (30日)\n內 冊 2.8.3 及\n包裝)\n2.8.4 備註說\n明,血清採檢\n步驟請參閱\n第3.3節。",
    "pdf_path": "pdfs/萊姆病.pdf",
    "臨床條件": "頭痛、發燒、淋巴腺腫大、肌肉疼痛、喉嚨痛、頸部僵硬、遊走性\n紅斑,病程進展到後期會出現神經根發炎。",
    "檢驗條件": "具有下列任一個條件:\n(一)臨床檢體(皮膚病灶區之檢體或腦脊髓液、關節囊液等)分\n離並鑑定出伯氏疏螺旋體(Borrelia burgdorferi )。\n(二)血清學抗體檢測陽性。",
    "流行病學條件": "NA",
    "通報定義": "符合臨床條件。",
    "疾病分類": "(一)可能病例:\nNA\n(二)極可能病例:\nNA\n(三)確定病例:\n符合檢驗條件。",
    "檢體採檢送驗事項": "傳染病 應保存種類\n採檢項目 採檢目的 採檢時間 採檢量及規定 送驗方式 注意事項\n名稱 應保存時間\n1. 血清檢體勿\n以無菌刀片切\n加入任何添\n取病灶區外緣\n加物。\n往內側 0.5 cm\n皮膚傷口 臨床診斷 2. 傷口採檢,請\n處之檢體,以無\n(遊走性 為疑似病 參閱傳染病\n菌生理食鹽水\n紅斑) 例 檢體採檢手\n沾濕之無菌紗\n冊 第 3.11\n布包裹,再置於\n22-35°C 節。\n無菌容器內。\n病原體 (B 類感 菌株 3. 腦脊髓液採\n檢測 染性物質 (30日) 檢步驟請參\n包裝) 閱傳染病檢\n體採檢手冊\n以無菌檢體小\n腦 脊 髓 臨床診斷 第3.6節,由\n瓶收集 0.5 mL\n液、關節 為疑似病 醫師採檢。\n腦脊髓液或關\n萊姆病 囊液 例 4. 關節囊液採\n節囊液。\n檢步驟請參\n閱傳染病檢\n體採檢手冊\n第 3.10 節,\n由 醫 師 採\n檢。\n5. 血清檢體請\n2-8°C\n發病 參閱傳染病\n以無菌試管收 (B 類感 陽性血清\n抗體檢測 8-30 日 檢體採檢手\n血清\n集3mL血清。 染性物質 (30日)\n內 冊 2.8.3 及\n包裝)\n2.8.4 備註說\n明,血清採檢\n步驟請參閱\n第3.3節。",
    "english_name": "Lyme Disease",
    "suspected_case": "NA",
    "probable_case": "NA",
    "confirmed_case": "符合檢驗條件。"
  },
  {
    "name": "裂谷熱",
    "url": "https://www.cdc.gov.tw/File/Get/aXzz24nuZ22J-sZoCpWGSw",
    "source_category": "第五類",
    "content": "裂谷熱\n(Rift Valley Fever)\n一、 臨床條件\n具有下列任一個條件:\n(一) 發燒、頭痛、關節痛、肌痛、腦炎、視網膜病變、畏光等\n任一臨床描述。\n(二) 出現可能導致多重器官衰竭之各種不同形式的出血症狀。\n二、 檢驗條件\n具有下列任一個條件:\n(一) 臨床檢體(血液、腦脊髓液或感染組織(如肝、腦等))\n分離並鑑定出裂谷熱病毒(Rift Valley fever virus)。\n(二) 臨床檢體分子生物學核酸檢測陽性。\n(三) 血清學抗體檢測陽性:單一血清檢體 IgM 抗體陽性或急\n性期與恢復期血清 IgG 抗體效價≧4 倍上升。\n三、 流行病學條件\n發病前 6 天內,具有下列任一個條件:\n(一) 具有裂谷熱流行地區之旅遊史或居住史。\n(二) 具有裂谷熱流行地區綿羊、牛、山羊、駱駝等動物接觸\n史或曾接觸感染動物或感染者的血液、組織、器官或體\n液。\n(三) 被蚊子叮咬且住家或活動範圍附近出現確定病例。\n四、 通報定義\n具有下列任一個條件:\n(一) 符合臨床條件及流行病學條件。\n(二) 符合檢驗條件。\n五、 疾病分類\n(一) 極可能病例:\n雖未經實驗室證實,但符合臨床條件及流行病學條件。\n(二) 確定病例: 符合檢驗條件。\n六、 檢體採檢送驗事項\n請參閱「傳染病檢體採檢手冊」(https://gov.tw/pK8)",
    "pdf_path": "pdfs/裂谷熱.pdf",
    "臨床條件": "具有下列任一個條件:\n(一) 發燒、頭痛、關節痛、肌痛、腦炎、視網膜病變、畏光等\n任一臨床描述。\n(二) 出現可能導致多重器官衰竭之各種不同形式的出血症狀。",
    "檢驗條件": "具有下列任一個條件:\n(一) 臨床檢體(血液、腦脊髓液或感染組織(如肝、腦等))\n分離並鑑定出裂谷熱病毒(Rift Valley fever virus)。\n(二) 臨床檢體分子生物學核酸檢測陽性。\n(三) 血清學抗體檢測陽性:單一血清檢體 IgM 抗體陽性或急\n性期與恢復期血清 IgG 抗體效價≧4 倍上升。",
    "流行病學條件": "發病前 6 天內,具有下列任一個條件:\n(一) 具有裂谷熱流行地區之旅遊史或居住史。\n(二) 具有裂谷熱流行地區綿羊、牛、山羊、駱駝等動物接觸\n史或曾接觸感染動物或感染者的血液、組織、器官或體\n液。\n(三) 被蚊子叮咬且住家或活動範圍附近出現確定病例。",
    "通報定義": "具有下列任一個條件:\n(一) 符合臨床條件及流行病學條件。\n(二) 符合檢驗條件。",
    "疾病分類": "(一) 極可能病例:\n雖未經實驗室證實,但符合臨床條件及流行病學條件。\n(二) 確定病例: 符合檢驗條件。",
    "檢體採檢送驗事項": "請參閱「傳染病檢體採檢手冊」(https://gov.tw/pK8)",
    "english_name": "Rift Valley Fever",
    "suspected_case": "",
    "probable_case": "雖未經實驗室證實,但符合臨床條件及流行病學條件。",
    "confirmed_case": "符合檢驗條件。"
  },
  {
    "name": "西尼羅熱",
    "url": "https://www.cdc.gov.tw/File/Get/PN78eTREUieJ5lAMBo5pFQ",
    "source_category": "第二類",
    "content": "西尼羅熱\n(West Nile Fever)\n一、 臨床條件\n發燒≧38°C,且具有下列任一臨床表現:頭痛、關節痛、肌痛、倦怠、\n丘疹般塊狀紅疹、淋巴腺腫大、腸胃道症狀(如嘔吐或腹瀉)、腦膜\n炎、腦炎、急性無力性麻痺症候群。\n二、 檢驗條件\n符合下列檢驗結果之任一項者,定義為檢驗結果陽性:\n(一) 臨床檢體(組織、血清、腦脊髓液或其他體液)分離並鑑定出\n西尼羅病毒,或證實含有特異性抗原者。\n(二) 臨床檢體分子生物學核酸檢測陽性。\n(三) 腦脊髓液中有西尼羅病毒特異性之 IgM 抗體。\n(四) 急性期(或初次採檢)血清中,西尼羅病毒特異性 IgM 或 IgG\n抗體為陽性者。\n(五) 成對血清(恢復期及急性期)中,西尼羅病毒特異性 IgM 或\nIgG 抗體(二者任一)有陽轉或≧4 倍上升。\n三、 流行病學條件\n具有下列任一個條件:\n(一)有西尼羅熱相關流行地區旅遊史。\n(二)與確定病例有器官移植、輸血之接觸;或母子垂直感染。\n四、 通報定義\n具有下列任一個條件:\n(一) 符合臨床條件及流行病學條件。\n(二) 醫師或法醫師高度懷疑與確定病例具有流行病學上相關。\n五、 疾病分類\n(一) 可能病例:\nNA\n(二)極可能病例:\n符合臨床條件及檢驗結果陽性定義之第四項。\n(三)確定病例:\n符合檢驗結果陽性定義之第一、二、三、五項之任一項。\n六、 檢體採檢送驗事項\n採檢項目 檢體種類 採檢目的 採檢時機 採檢規定 運送條件 注意事項\n1. 若 無 法 取 得 急\n性期之血液,\n急性期(發\n請立即採檢,\n病 後 7 日\n以無菌試管收 並採間隔 7 日\n內);\n血清 集 3 mL 血 之恢復期血\n恢復期(發\n清。 清,分 2次送\n病 14-40 天\n驗。\n之間)\n2. 檢 體 勿 加 入\n任何添加物。\n3. 血 清 檢 體 見\n2-8°C\n病原體檢測; 傳染病檢體採\n(B 類 感\n西尼羅熱 抗體檢測 檢手冊 2.8.3 及\n染性物質\n2.8.4 備註說明\n包裝)\n及血清採檢步\n驟請參考第\n以無菌容器收\n3.3 節。\n腦脊髓液 住院期間 集腦脊髓液 2-\n4. 腦 脊髓 液 採 檢\n3 mL。\n步驟,請參考\n傳染病檢體採\n檢手冊第3.6\n節,由醫師採\n檢。",
    "pdf_path": "pdfs/西尼羅熱.pdf",
    "臨床條件": "發燒≧38°C,且具有下列任一臨床表現:頭痛、關節痛、肌痛、倦怠、\n丘疹般塊狀紅疹、淋巴腺腫大、腸胃道症狀(如嘔吐或腹瀉)、腦膜\n炎、腦炎、急性無力性麻痺症候群。",
    "檢驗條件": "符合下列檢驗結果之任一項者,定義為檢驗結果陽性:\n(一) 臨床檢體(組織、血清、腦脊髓液或其他體液)分離並鑑定出\n西尼羅病毒,或證實含有特異性抗原者。\n(二) 臨床檢體分子生物學核酸檢測陽性。\n(三) 腦脊髓液中有西尼羅病毒特異性之 IgM 抗體。\n(四) 急性期(或初次採檢)血清中,西尼羅病毒特異性 IgM 或 IgG\n抗體為陽性者。\n(五) 成對血清(恢復期及急性期)中,西尼羅病毒特異性 IgM 或\nIgG 抗體(二者任一)有陽轉或≧4 倍上升。",
    "流行病學條件": "具有下列任一個條件:\n(一)有西尼羅熱相關流行地區旅遊史。\n(二)與確定病例有器官移植、輸血之接觸;或母子垂直感染。",
    "通報定義": "具有下列任一個條件:\n(一) 符合臨床條件及流行病學條件。\n(二) 醫師或法醫師高度懷疑與確定病例具有流行病學上相關。",
    "疾病分類": "(一) 可能病例:\nNA\n(二)極可能病例:\n符合臨床條件及檢驗結果陽性定義之第四項。\n(三)確定病例:\n符合檢驗結果陽性定義之第一、二、三、五項之任一項。",
    "檢體採檢送驗事項": "採檢項目 檢體種類 採檢目的 採檢時機 採檢規定 運送條件 注意事項\n1. 若 無 法 取 得 急\n性期之血液,\n急性期(發\n請立即採檢,\n病 後 7 日\n以無菌試管收 並採間隔 7 日\n內);\n血清 集 3 mL 血 之恢復期血\n恢復期(發\n清。 清,分 2次送\n病 14-40 天\n驗。\n之間)\n2. 檢 體 勿 加 入\n任何添加物。\n3. 血 清 檢 體 見\n2-8°C\n病原體檢測; 傳染病檢體採\n(B 類 感\n西尼羅熱 抗體檢測 檢手冊 2.8.3 及\n染性物質\n2.8.4 備註說明\n包裝)\n及血清採檢步\n驟請參考第\n以無菌容器收\n3.3 節。\n腦脊髓液 住院期間 集腦脊髓液 2-\n4. 腦 脊髓 液 採 檢\n3 mL。\n步驟,請參考\n傳染病檢體採\n檢手冊第3.6\n節,由醫師採\n檢。",
    "english_name": "West Nile Fever",
    "suspected_case": "NA",
    "probable_case": "符合臨床條件及檢驗結果陽性定義之第四項。",
    "confirmed_case": "符合檢驗結果陽性定義之第一、二、三、五項之任一項。"
  },
  {
    "name": "退伍軍人病",
    "url": "https://www.cdc.gov.tw/File/Get/t5j7Tf8Hl2PBMMA6tgHqoQ",
    "source_category": "第三類",
    "content": "退伍軍人病\n(Legionnaires' disease)\n一、 臨床條件\n肺炎病人,並出現倦怠感、畏寒、肌肉酸痛、頭痛、發燒、頭昏、咳\n嗽、噁心、腹痛、腹瀉及呼吸困難等任一症狀。\n二、 檢驗條件\n具有下列任一個條件:\n(一) 臨床檢體(痰液、呼吸道分泌物或胸膜液)分離並鑑定出退伍\n軍人菌(Legionella spp.)。\n(二) 尿液抗原檢測陽性。\n(三) 血清學抗體檢測陽性:檢測抗體效價,恢復期(4 ~12 週)比\n起發病初期有 4 倍以上增加,且≧128。\n三、 流行病學條件\n具有下列任一個條件:\n(一) 與確定病例暴露共同感染源。\n(二) 具有經檢驗確認為汙染的環境或水源之接觸史(曾暴露於退伍\n軍人菌高風險環境)。\n四、 通報定義\n符合臨床條件。\n五、 疾病分類\n(一) 可能病例:\n符合臨床條件。\n(二) 極可能病例:\n具有下列任一個條件:\n1. 符合臨床條件及血清學檢測之恢復期抗體效價出現上升,\n但未達 4 倍上升。\n2. 符合臨床條件及流行病學條件。\n(三) 確定病例:\n符合臨床條件和檢驗條件。\n六、 檢體採檢送驗事項\n採檢項目 檢體種類 採檢目的 採檢時機 採檢規定 運送條件 注意事項\n痰液、呼 1. 勿以棉花拭\n吸道分泌病原體檢 以無菌容器收集直接喀 子採集痰液、呼\n物、胸膜測 出之痰液。 吸道分泌物、胸\n立即採檢\n液 膜液等檢體。\n以無菌容器收集 10 mL 2. 勿採患者口\n尿液 抗原檢測\n尿液。 低溫 水。\n急 性 期 3. 痰液檢體採\n( 立 即 採 檢請參考第 3.9\n以無菌試管收集至少 3\n血清 抗體檢測 檢);恢復 節。\nmL 血清。\n期 (4-12 4. 胸膜液等體\n週) 液採檢請參考\n1. 水龍頭、蓮蓬頭、飲水 第 3.10 節。\n機等水源:(1)以細菌拭 5. 尿液檢體見\n子之棉棒在欲採樣之 2.8.2 備註說\n水源下潤溼後,伸入水 明,尿液檢體採\n源出水口內部,上下左 檢步驟請參考\n退伍軍人\n右旋轉數次後,插入 第 3.4 節。\n病\n水龍頭、 Cary-Blair 保存輸送培 6. 血清檢體見\n蓮蓬頭、 養基。或者(2)以無菌棉 2.8.3 及 2.8.4\n飲水機、病原體檢配合陽性 棒在欲採樣之水源下 備註說明,血清\n低溫\n冷卻水塔測 案例 潤溼後,伸入水源出水 採檢步驟請參\n等水源環 口內部,上下左右旋轉 考第 3.3 節。\n境檢體 數次後,折斷棉棒置於 7. 環境檢體\n無 菌 容 器 或 採 水 袋 (水龍頭、蓮蓬\n中,再續接 200 mL 環 頭、飲水機等水\n境水於同一容器中 源):細菌拭子\n2. 冷卻水塔水源:以無菌 (1)或一袋水\n容器或採水袋收集約 (2),擇一送\n100 mL 冷卻水塔水。 檢。\n純化之菌株以拭子沾滿 8. 菌株為陽性\n一圈後置入 Cary-Blair 保 個案臨床分離\n已分離菌 低 溫 / 常\n菌株 菌株鑑定 存輸送培養基,或接種於 株及其相關環\n株時 溫\nBCYE 培養基,以封口膜 境分離株。\n密封,並加夾鏈袋運送。",
    "pdf_path": "pdfs/退伍軍人病.pdf",
    "臨床條件": "肺炎病人,並出現倦怠感、畏寒、肌肉酸痛、頭痛、發燒、頭昏、咳\n嗽、噁心、腹痛、腹瀉及呼吸困難等任一症狀。",
    "檢驗條件": "具有下列任一個條件:\n(一) 臨床檢體(痰液、呼吸道分泌物或胸膜液)分離並鑑定出退伍\n軍人菌(Legionella spp.)。\n(二) 尿液抗原檢測陽性。\n(三) 血清學抗體檢測陽性:檢測抗體效價,恢復期(4 ~12 週)比\n起發病初期有 4 倍以上增加,且≧128。",
    "流行病學條件": "具有下列任一個條件:\n(一) 與確定病例暴露共同感染源。\n(二) 具有經檢驗確認為汙染的環境或水源之接觸史(曾暴露於退伍\n軍人菌高風險環境)。",
    "通報定義": "符合臨床條件。",
    "疾病分類": "(一) 可能病例:\n符合臨床條件。\n(二) 極可能病例:\n具有下列任一個條件:\n1. 符合臨床條件及血清學檢測之恢復期抗體效價出現上升,\n但未達 4 倍上升。\n2. 符合臨床條件及流行病學條件。\n(三) 確定病例:\n符合臨床條件和檢驗條件。",
    "檢體採檢送驗事項": "採檢項目 檢體種類 採檢目的 採檢時機 採檢規定 運送條件 注意事項\n痰液、呼 1. 勿以棉花拭\n吸道分泌病原體檢 以無菌容器收集直接喀 子採集痰液、呼\n物、胸膜測 出之痰液。 吸道分泌物、胸\n立即採檢\n液 膜液等檢體。\n以無菌容器收集 10 mL 2. 勿採患者口\n尿液 抗原檢測\n尿液。 低溫 水。\n急 性 期 3. 痰液檢體採\n( 立 即 採 檢請參考第 3.9\n以無菌試管收集至少 3\n血清 抗體檢測 檢);恢復 節。\nmL 血清。\n期 (4-12 4. 胸膜液等體\n週) 液採檢請參考\n1. 水龍頭、蓮蓬頭、飲水 第 3.10 節。\n機等水源:(1)以細菌拭 5. 尿液檢體見\n子之棉棒在欲採樣之 2.8.2 備註說\n水源下潤溼後,伸入水 明,尿液檢體採\n源出水口內部,上下左 檢步驟請參考\n退伍軍人\n右旋轉數次後,插入 第 3.4 節。\n病\n水龍頭、 Cary-Blair 保存輸送培 6. 血清檢體見\n蓮蓬頭、 養基。或者(2)以無菌棉 2.8.3 及 2.8.4\n飲水機、病原體檢配合陽性 棒在欲採樣之水源下 備註說明,血清\n低溫\n冷卻水塔測 案例 潤溼後,伸入水源出水 採檢步驟請參\n等水源環 口內部,上下左右旋轉 考第 3.3 節。\n境檢體 數次後,折斷棉棒置於 7. 環境檢體\n無 菌 容 器 或 採 水 袋 (水龍頭、蓮蓬\n中,再續接 200 mL 環 頭、飲水機等水\n境水於同一容器中 源):細菌拭子\n2. 冷卻水塔水源:以無菌 (1)或一袋水\n容器或採水袋收集約 (2),擇一送\n100 mL 冷卻水塔水。 檢。\n純化之菌株以拭子沾滿 8. 菌株為陽性\n一圈後置入 Cary-Blair 保 個案臨床分離\n已分離菌 低 溫 / 常\n菌株 菌株鑑定 存輸送培養基,或接種於 株及其相關環\n株時 溫\nBCYE 培養基,以封口膜 境分離株。\n密封,並加夾鏈袋運送。",
    "english_name": "Legionnaires' disease",
    "suspected_case": "符合臨床條件。",
    "probable_case": "具有下列任一個條件:\n1. 符合臨床條件及血清學檢測之恢復期抗體效價出現上升,\n但未達 4 倍上升。\n2. 符合臨床條件及流行病學條件。",
    "confirmed_case": "符合臨床條件和檢驗條件。"
  },
  {
    "name": "鉤端螺旋體病",
    "url": "https://www.cdc.gov.tw/File/Get/vRJ84cWMW3Ri4bJMM_k0WA",
    "source_category": "第四類",
    "content": "鉤端螺旋體病\n(Leptospirosis)\n一、 臨床條件\n出現急性發燒、頭痛、肌肉痛(尤其常見小腿肚痛)、腹痛、腹瀉、\n倦怠,或伴有下列任一種臨床表現:\n(一) 結膜充血(conjunctival suffusion)\n(二) 腦膜炎症狀(meningeal irritation)及無菌性腦膜炎(aseptic\nmeningitis)\n(三) 無尿、少尿或蛋白尿(anuria、oliguria or proteinuria)\n(四) 黃疸(jaundice)\n(五) 急性腎功能不全(acute renal insufficiency)\n(六) 出血傾向(腸道或肺部)(gastrointestinal or pulmonary\nhemorrhage)\n二、 檢驗條件\n具有下列任一個條件:\n(一) 臨床檢體(尿液、血液或腦脊髓液)分離並鑑定出鉤端螺旋體\n(Leptospira spp.)。\n(二) 血清學抗體檢測陽性:無論使用何種篩檢試劑檢驗,必須使用\n顯微凝集試驗(Microscopic Agglutination Test, MAT)做確\n認診斷,恢復期血清較急性期血清抗體效價≧4 倍上升。\n三、 流行病學條件\n發病前 1 個月內曾有接觸動物、野外活動,或暴露於被感染動物尿液\n污染之環境(如污水、溼土等)。\n四、 通報定義\n符合臨床條件及流行病學條件。\n五、 疾病分類\n(一) 可能病例:\nNA\n(二) 極可能病例:\nNA\n(三) 確定病例:\n符合臨床條件及檢驗條件。\n六、 檢體採檢送驗事項\n採檢項目 檢體種類 採檢目的 採檢時間 採檢量及規定 送驗方式 注意事項\n以無菌容器收集\n1. 發病 7 日後且未投藥\n10 mL中段尿液。\n發病 10 天 治療之尿液檢體,仍\n病原體檢 並添加0.5 mL之1\n尿液 後,且未投藥 低溫 視為有效檢體。\n測 M 磷酸緩衝液\n前 2. 尿液採檢請參考第\n(phosphate\n3.4 節。\nbuffer)(pH 7.4)。\n以含抗凝劑 1. 未投藥前及發病 10\n高熱期(發病\n抗凝固全 病原體檢 (EDTA)採血管 日內血液檢體較易培\n10 天內且未 常溫\n血 測 採集 5 mL血液檢 養出螺旋體,故發病\n投藥前)\n體,並混合均勻。 10 日內且未投藥治\n療之血液檢體,仍視\n鉤端螺旋\n為有效檢體。\n體病\n2. 血清檢體勿加入任何\n添加物。\n3. 需 2 次採檢確認者,\n急性期(發病 急性感染期與緩解期\n7 天內);恢 以無菌試管收集 3 相隔至少 14 天,以做\n血清 抗體檢測 低溫\n復期(發病 mL血清。 配對血清抗體力價變\n8-14 天之間) 化之判斷\n4. 抗凝固全血採檢步驟\n請參考第 3.2 節。\n5. 血清檢體見 2.8.3 及\n2.8.4 備註說明,血清\n採檢步驟見第3.3節。\n具無菌性腦\n以無菌檢體小瓶收 腦脊髓液採檢步驟請\n病原體檢 膜炎症狀,發\n腦脊髓液 集 0.5 mL腦脊髓 常溫 參考第 3.6 節,由醫師\n測 病 5-10 天之\n液。 採檢。\n間",
    "pdf_path": "pdfs/鉤端螺旋體病.pdf",
    "臨床條件": "出現急性發燒、頭痛、肌肉痛(尤其常見小腿肚痛)、腹痛、腹瀉、\n倦怠,或伴有下列任一種臨床表現:\n(一) 結膜充血(conjunctival suffusion)\n(二) 腦膜炎症狀(meningeal irritation)及無菌性腦膜炎(aseptic\nmeningitis)\n(三) 無尿、少尿或蛋白尿(anuria、oliguria or proteinuria)\n(四) 黃疸(jaundice)\n(五) 急性腎功能不全(acute renal insufficiency)\n(六) 出血傾向(腸道或肺部)(gastrointestinal or pulmonary\nhemorrhage)",
    "檢驗條件": "具有下列任一個條件:\n(一) 臨床檢體(尿液、血液或腦脊髓液)分離並鑑定出鉤端螺旋體\n(Leptospira spp.)。\n(二) 血清學抗體檢測陽性:無論使用何種篩檢試劑檢驗,必須使用\n顯微凝集試驗(Microscopic Agglutination Test, MAT)做確\n認診斷,恢復期血清較急性期血清抗體效價≧4 倍上升。",
    "流行病學條件": "發病前 1 個月內曾有接觸動物、野外活動,或暴露於被感染動物尿液\n污染之環境(如污水、溼土等)。",
    "通報定義": "符合臨床條件及流行病學條件。",
    "疾病分類": "(一) 可能病例:\nNA\n(二) 極可能病例:\nNA\n(三) 確定病例:\n符合臨床條件及檢驗條件。",
    "檢體採檢送驗事項": "採檢項目 檢體種類 採檢目的 採檢時間 採檢量及規定 送驗方式 注意事項\n以無菌容器收集\n1. 發病 7 日後且未投藥\n10 mL中段尿液。\n發病 10 天 治療之尿液檢體,仍\n病原體檢 並添加0.5 mL之1\n尿液 後,且未投藥 低溫 視為有效檢體。\n測 M 磷酸緩衝液\n前 2. 尿液採檢請參考第\n(phosphate\n3.4 節。\nbuffer)(pH 7.4)。\n以含抗凝劑 1. 未投藥前及發病 10\n高熱期(發病\n抗凝固全 病原體檢 (EDTA)採血管 日內血液檢體較易培\n10 天內且未 常溫\n血 測 採集 5 mL血液檢 養出螺旋體,故發病\n投藥前)\n體,並混合均勻。 10 日內且未投藥治\n療之血液檢體,仍視\n鉤端螺旋\n為有效檢體。\n體病\n2. 血清檢體勿加入任何\n添加物。\n3. 需 2 次採檢確認者,\n急性期(發病 急性感染期與緩解期\n7 天內);恢 以無菌試管收集 3 相隔至少 14 天,以做\n血清 抗體檢測 低溫\n復期(發病 mL血清。 配對血清抗體力價變\n8-14 天之間) 化之判斷\n4. 抗凝固全血採檢步驟\n請參考第 3.2 節。\n5. 血清檢體見 2.8.3 及\n2.8.4 備註說明,血清\n採檢步驟見第3.3節。\n具無菌性腦\n以無菌檢體小瓶收 腦脊髓液採檢步驟請\n病原體檢 膜炎症狀,發\n腦脊髓液 集 0.5 mL腦脊髓 常溫 參考第 3.6 節,由醫師\n測 病 5-10 天之\n液。 採檢。\n間",
    "english_name": "Leptospirosis",
    "suspected_case": "NA",
    "probable_case": "NA",
    "confirmed_case": "符合臨床條件及檢驗條件。"
  },
  {
    "name": "阿米巴性痢疾",
    "url": "https://www.cdc.gov.tw/File/Get/KYVtviTLOXDH8843JtO3Mg",
    "source_category": "第二類",
    "content": "阿米巴性痢疾\n(Amebiasis)\n一、 臨床條件\n(一)嚴重程度不等的腹瀉,糞便中帶粘液、血絲,上腹疼痛、\n發燒、噁心、嘔吐。\n(二)經醫師確認發現具有下列任一個臨床診斷:\n1.組織切片或潰瘍刮除物發現痢疾阿米巴活動體。\n2.影像醫學診斷為膿瘍(如肝膿瘍、肺膿瘍、腦膿瘍等)且\n*\n血清學檢查痢疾阿米巴抗體陽性 。\n*\n依試劑之使用說明界定\n二、檢驗條件\n(一)臨床檢體(糞便、組織或膿瘍抽出物等)經分子生物學核酸檢測(PCR)\n確認為痢疾阿米巴。\n(二)糞便鏡檢發現疑似痢疾阿米巴之囊體或活動體。\n三、 流行病學條件\n具有下列任一個條件:\n(一)曾經與確定病例具有密切接觸。\n(二)攝食曾被病人或帶菌者糞便直接或間接污染之食物、飲用水。\n四、 通報定義\n符合任一項臨床條件或任一項檢驗條件。\n五、 疾病分類\n(一) 可能病例:\nNA\n(二) 極可能病例:\nNA\n(三) 確定病例:\n具有下列任一個條件:\n1. 符合檢驗條件第一項。\n2. 符合臨床條件第二項。\n六、 檢體採檢送驗事項\n請參閱「傳染病檢體採檢送驗手冊」。",
    "pdf_path": "pdfs/阿米巴性痢疾.pdf",
    "臨床條件": "(一)嚴重程度不等的腹瀉,糞便中帶粘液、血絲,上腹疼痛、\n發燒、噁心、嘔吐。\n(二)經醫師確認發現具有下列任一個臨床診斷:\n1.組織切片或潰瘍刮除物發現痢疾阿米巴活動體。\n2.影像醫學診斷為膿瘍(如肝膿瘍、肺膿瘍、腦膿瘍等)且\n*\n血清學檢查痢疾阿米巴抗體陽性 。\n*\n依試劑之使用說明界定",
    "檢驗條件": "(一)臨床檢體(糞便、組織或膿瘍抽出物等)經分子生物學核酸檢測(PCR)\n確認為痢疾阿米巴。\n(二)糞便鏡檢發現疑似痢疾阿米巴之囊體或活動體。",
    "流行病學條件": "具有下列任一個條件:\n(一)曾經與確定病例具有密切接觸。\n(二)攝食曾被病人或帶菌者糞便直接或間接污染之食物、飲用水。",
    "通報定義": "符合任一項臨床條件或任一項檢驗條件。",
    "疾病分類": "(一) 可能病例:\nNA\n(二) 極可能病例:\nNA\n(三) 確定病例:\n具有下列任一個條件:\n1. 符合檢驗條件第一項。\n2. 符合臨床條件第二項。",
    "檢體採檢送驗事項": "請參閱「傳染病檢體採檢送驗手冊」。",
    "english_name": "Amebiasis",
    "suspected_case": "NA",
    "probable_case": "NA",
    "confirmed_case": "具有下列任一個條件:\n1. 符合檢驗條件第一項。\n2. 符合臨床條件第二項。"
  },
  {
    "name": "霍亂",
    "url": "https://www.cdc.gov.tw/File/Get/VYBZZlriLUSJO9aH-wmXMw",
    "source_category": "第二類",
    "content": "霍亂\nCholera\n( )\n一、 臨床條件\n急性腸胃炎,快速腹瀉或嘔吐的症狀,其嚴重程度因人而異。\n二、 檢驗條件\n臨床檢體(糞便或嘔吐物)分離並鑑定出產毒性O1型或產毒性O139\n型霍亂弧菌(Vibrio cholerae serogroup O1或O139)。\n三、 流行病學條件\n具有下列任一個條件:\n(一) 曾經與確定病例具有密切接觸(如照護、同住)。\n(二) 與確定病例暴露共同感染源。\n四、 通報定義\n具有下列任一個條件:\n(一) 符合臨床條件。\n(二) 經醫院自行檢驗,符合檢驗條件。\n五、 疾病分類\n(一) 可能病例:\nNA\n(二) 極可能病例:\nNA\n(三) 確定病例:\n符合臨床條件及檢驗條件。\n六、 檢體採檢送驗事項\n採檢項目 檢體種類 採檢目的 採檢時機 採檢規定 運送條件 注意事項\n以無菌細菌拭子之 1. 見 2.8.6 備註\n棉棒,沾取混合均 說 明 及 圖\n糞便 勻之糞便檢體,置 2.5,糞便採檢\n入 Cary-Blair 保存 步驟請參考第\n未投藥前立輸送培養基。 3.5 節。\n病 原 體 檢即採檢 以無菌之細菌拭子 2. 可疑環境檢體\n測;毒素及 棒,沾取混合均勻 低溫 請與本署昆陽\n嘔吐物 抗血清檢測 之嘔吐物,置入 辦公室檢體單\nCary-Blair 保存輸 一窗口聯繫。\n送培養基。\n霍亂\n以無菌塑膠袋收集\n水樣環境\n配合案例 2袋800 mL以上可\n檢體\n疑污染源水檢體。\n以無菌細菌拭子之\n非水樣環 棉棒,沾取檢體,\n病原體檢測 配合案例 低溫\n境檢體 置入 Cary-Blair 保 可疑環境檢體請\n存輸送培養基。 與本署昆陽辦公\n純化之菌株以拭子 室檢體單一窗口\n病 原 體 檢 低溫 (B\n沾滿一圈後置入 聯繫。\n菌株 測;毒素及儘速送驗 類感染性\nCary-Blair 保存輸\n抗血清檢測 物質包裝)\n送培養基。",
    "pdf_path": "pdfs/霍亂.pdf",
    "臨床條件": "急性腸胃炎,快速腹瀉或嘔吐的症狀,其嚴重程度因人而異。",
    "檢驗條件": "臨床檢體(糞便或嘔吐物)分離並鑑定出產毒性O1型或產毒性O139\n型霍亂弧菌(Vibrio cholerae serogroup O1或O139)。",
    "流行病學條件": "具有下列任一個條件:\n(一) 曾經與確定病例具有密切接觸(如照護、同住)。\n(二) 與確定病例暴露共同感染源。",
    "通報定義": "具有下列任一個條件:\n(一) 符合臨床條件。\n(二) 經醫院自行檢驗,符合檢驗條件。",
    "疾病分類": "(一) 可能病例:\nNA\n(二) 極可能病例:\nNA\n(三) 確定病例:\n符合臨床條件及檢驗條件。",
    "檢體採檢送驗事項": "採檢項目 檢體種類 採檢目的 採檢時機 採檢規定 運送條件 注意事項\n以無菌細菌拭子之 1. 見 2.8.6 備註\n棉棒,沾取混合均 說 明 及 圖\n糞便 勻之糞便檢體,置 2.5,糞便採檢\n入 Cary-Blair 保存 步驟請參考第\n未投藥前立輸送培養基。 3.5 節。\n病 原 體 檢即採檢 以無菌之細菌拭子 2. 可疑環境檢體\n測;毒素及 棒,沾取混合均勻 低溫 請與本署昆陽\n嘔吐物 抗血清檢測 之嘔吐物,置入 辦公室檢體單\nCary-Blair 保存輸 一窗口聯繫。\n送培養基。\n霍亂\n以無菌塑膠袋收集\n水樣環境\n配合案例 2袋800 mL以上可\n檢體\n疑污染源水檢體。\n以無菌細菌拭子之\n非水樣環 棉棒,沾取檢體,\n病原體檢測 配合案例 低溫\n境檢體 置入 Cary-Blair 保 可疑環境檢體請\n存輸送培養基。 與本署昆陽辦公\n純化之菌株以拭子 室檢體單一窗口\n病 原 體 檢 低溫 (B\n沾滿一圈後置入 聯繫。\n菌株 測;毒素及儘速送驗 類感染性\nCary-Blair 保存輸\n抗血清檢測 物質包裝)\n送培養基。",
    "english_name": "Cholera",
    "suspected_case": "NA",
    "probable_case": "NA",
    "confirmed_case": "符合臨床條件及檢驗條件。"
  },
  {
    "name": "類鼻疽",
    "url": "https://www.cdc.gov.tw/File/Get/2PhRhYYk6tZYSP6flkZoxg",
    "source_category": "第四類",
    "content": "類鼻疽\n(Melioidosis)\n一、 臨床條件\n臨床表現多樣性,從無症狀或局部皮膚潰瘍,到以嚴重肺炎表現,甚\n至是全身性敗血症、休克等。\n二、 檢驗條件\n臨床檢體(咽喉擦拭液或分泌物、膿汁、血液等)分離並鑑定出類鼻\n疽伯克氏菌(Burkholderia pseudomallei)。\n三、 流行病學條件\n具有下列任一個條件:\n(一) 皮膚傷口接觸到受病原菌污染的土壤或水。\n(二) 呼吸道吸入土壤的塵粒。\n(三) 食入受染污的水或被污染的食物。\n四、 通報定義\n符合臨床條件,且經醫院自行檢驗,符合檢驗條件。\n五、 疾病分類\n(一) 可能病例:\nNA\n(二) 極可能病例:\nNA\n(三) 確定病例:\n符合臨床條件及檢驗條件。\n六、 檢體採檢送驗事項\n採檢項目 檢體種類 採檢目的 採檢時間 採檢量及規定 送驗方式 注意事項\n以細菌拭子之棉棒 見 2.8.6 備註說明\n喉部擦拭\n採集,插入 及咽喉拭子採檢\n液或分泌\nCary-Blair保存輸送 步驟請參考第 3.7\n物 病發初期\n病原體檢 培養基。 節及圖3.7。\n(未投藥 低溫\n測 以細菌拭子之棉棒\n前)\n採 集 膿 汁 , 插 入 膿汁採檢步驟請\n膿汁\nCary-Blair 保存輸送 參考第3.11節。\n培養基。\n以含抗凝劑(肝素\n或 EDTA)採血管\n採集 5-10 mL 血\n類鼻疽\n液,並混合均勻。 全血採檢步驟請\n病發初期\n抗凝固全病原體檢 或以採血管採 5-10 參考第3.1節;抗\n(未投藥 常溫\n血或全血 測 mL靜脈血,立即注 凝固全血採檢步\n前)\n入含50 mL TSB或 驟請參考3.2節。\nBHI 培養基之嗜氧\n血瓶內,充分混\n合。\n純化之菌株以拭子\n低溫(A類\n已分離菌沾 滿 一 圈 後 置 入\n菌株 菌株鑑定 感染性物 儘速送驗\n株時 Cary-Blair 輸送培養\n質包裝)\n基。",
    "pdf_path": "pdfs/類鼻疽.pdf",
    "臨床條件": "臨床表現多樣性,從無症狀或局部皮膚潰瘍,到以嚴重肺炎表現,甚\n至是全身性敗血症、休克等。",
    "檢驗條件": "臨床檢體(咽喉擦拭液或分泌物、膿汁、血液等)分離並鑑定出類鼻\n疽伯克氏菌(Burkholderia pseudomallei)。",
    "流行病學條件": "具有下列任一個條件:\n(一) 皮膚傷口接觸到受病原菌污染的土壤或水。\n(二) 呼吸道吸入土壤的塵粒。\n(三) 食入受染污的水或被污染的食物。",
    "通報定義": "符合臨床條件,且經醫院自行檢驗,符合檢驗條件。",
    "疾病分類": "(一) 可能病例:\nNA\n(二) 極可能病例:\nNA\n(三) 確定病例:\n符合臨床條件及檢驗條件。",
    "檢體採檢送驗事項": "採檢項目 檢體種類 採檢目的 採檢時間 採檢量及規定 送驗方式 注意事項\n以細菌拭子之棉棒 見 2.8.6 備註說明\n喉部擦拭\n採集,插入 及咽喉拭子採檢\n液或分泌\nCary-Blair保存輸送 步驟請參考第 3.7\n物 病發初期\n病原體檢 培養基。 節及圖3.7。\n(未投藥 低溫\n測 以細菌拭子之棉棒\n前)\n採 集 膿 汁 , 插 入 膿汁採檢步驟請\n膿汁\nCary-Blair 保存輸送 參考第3.11節。\n培養基。\n以含抗凝劑(肝素\n或 EDTA)採血管\n採集 5-10 mL 血\n類鼻疽\n液,並混合均勻。 全血採檢步驟請\n病發初期\n抗凝固全病原體檢 或以採血管採 5-10 參考第3.1節;抗\n(未投藥 常溫\n血或全血 測 mL靜脈血,立即注 凝固全血採檢步\n前)\n入含50 mL TSB或 驟請參考3.2節。\nBHI 培養基之嗜氧\n血瓶內,充分混\n合。\n純化之菌株以拭子\n低溫(A類\n已分離菌沾 滿 一 圈 後 置 入\n菌株 菌株鑑定 感染性物 儘速送驗\n株時 Cary-Blair 輸送培養\n質包裝)\n基。",
    "english_name": "Melioidosis",
    "suspected_case": "NA",
    "probable_case": "NA",
    "confirmed_case": "符合臨床條件及檢驗條件。"
  },
  {
    "name": "馬堡病毒出血熱",
    "url": "https://www.cdc.gov.tw/File/Get/SIho8-g92lElxe1EY7JDYg",
    "source_category": "第五類",
    "content": "附件一\n馬堡病毒出血熱\n(Marburg Virus Disease)\n一、臨床條件\n具有下列任一個條件:\n(一)急性發燒(≧38°C)\n(二)頭痛、肌肉痛、噁心、嘔吐、腹瀉、腹痛、吞嚥困難、\n丘疹、紫斑、中樞神經系統症狀等任一臨床描述。\n(三)不明原因出血。\n(四)突發性不明原因死亡。\n二、檢驗條件\n具有下列任一個條件:\n(一) 臨床檢體分離並鑑定出馬堡病毒。\n(二) 臨床檢體分子生物學核酸檢測陽性。\n(三) 血清學抗體檢測陽性。\n(四) 組織切片免疫化學染色(IHC)陽性。\n三、流行病學條件\n發病前 3 週內,具有下列任一個條件:\n(一) 具有馬堡病毒出血熱流行地區之旅遊史或居住史。\n(二) 接觸極可能病例或確定病例之血液或體液或其汙染物。\n(三) 具有馬堡病毒出血熱流行地區動物(例如蝙蝠、豬隻、\n家畜或靈長類等)之接觸史。\n(四) 進行馬堡病毒或檢體之實驗室操作。\n四、通報定義\n具有下列任一個條件:\n(一) 符合臨床條件以及流行病學條件。\n(二) 符合檢驗條件。\n五、 疾病分類\n(一) 極可能病例:\n雖未經實驗室證實,但符合臨床條件,且於發病前 3 週\n內接觸確定病例之血液或體液者。\n(二) 確定病例:\n符合檢驗條件。\n六、檢體採檢送驗事項\n請參閱「傳染病檢體採檢手冊」(https://gov.tw/pK8)",
    "pdf_path": "pdfs/馬堡病毒出血熱.pdf",
    "臨床條件": "具有下列任一個條件:\n(一)急性發燒(≧38°C)\n(二)頭痛、肌肉痛、噁心、嘔吐、腹瀉、腹痛、吞嚥困難、\n丘疹、紫斑、中樞神經系統症狀等任一臨床描述。\n(三)不明原因出血。\n(四)突發性不明原因死亡。",
    "檢驗條件": "具有下列任一個條件:\n(一) 臨床檢體分離並鑑定出馬堡病毒。\n(二) 臨床檢體分子生物學核酸檢測陽性。\n(三) 血清學抗體檢測陽性。\n(四) 組織切片免疫化學染色(IHC)陽性。",
    "流行病學條件": "發病前 3 週內,具有下列任一個條件:\n(一) 具有馬堡病毒出血熱流行地區之旅遊史或居住史。\n(二) 接觸極可能病例或確定病例之血液或體液或其汙染物。\n(三) 具有馬堡病毒出血熱流行地區動物(例如蝙蝠、豬隻、\n家畜或靈長類等)之接觸史。\n(四) 進行馬堡病毒或檢體之實驗室操作。",
    "通報定義": "具有下列任一個條件:\n(一) 符合臨床條件以及流行病學條件。\n(二) 符合檢驗條件。",
    "疾病分類": "(一) 極可能病例:\n雖未經實驗室證實,但符合臨床條件,且於發病前 3 週\n內接觸確定病例之血液或體液者。\n(二) 確定病例:\n符合檢驗條件。",
    "檢體採檢送驗事項": "請參閱「傳染病檢體採檢手冊」(https://gov.tw/pK8)",
    "english_name": "Marburg Virus Disease",
    "suspected_case": "",
    "probable_case": "雖未經實驗室證實,但符合臨床條件,且於發病前 3 週\n內接觸確定病例之血液或體液者。",
    "confirmed_case": "符合檢驗條件。"
  },
  {
    "name": "麻疹",
    "url": "https://www.cdc.gov.tw/File/Get/iHEj_B66b_QH_AdjsCsENQ",
    "source_category": "第二類",
    "content": "麻疹\nMeasles\n( )\n一、 臨床條件\n(一)出疹(斑丘疹)且發燒(耳溫或肛溫)≧38°C。\n(二)有時伴隨咳嗽,或流鼻水或結膜炎(畏光、流淚水或眼睛發紅)。\n二、 檢驗條件\n符合下列四種情形之一者,判定為陽性:\n(一)咽喉拭子、尿液或全血等檢體病毒培養結果陽性。\n(二)RT-PCR試驗結果陽性。\n(三)急性期與恢復期血清IgG抗體由陰性陽轉或效價有4倍以上增加。\n(四)IgM抗體陽性,並排除其他可能的偽陽性因子影響。\n三、流行病學條件\n具有下列任一個條件:\n(一)發病前三週內,曾有麻疹流行地區旅遊史。\n(二)曾與確定病例有空氣或飛沫接觸,或曾直接接觸確定病例之鼻咽分\n泌物。\n四、 通報定義\n出疹且發燒(耳溫或肛溫)高於38°C,並具有下列三項條件之任一者:\n(一)咳嗽、流鼻水或結膜炎(畏光、流淚水或眼睛發紅)三種症狀中\n的一種。\n(二)無麻疹相關疫苗接種史。\n(三)發病前三週內,曾有麻疹流行地區旅遊史。\n五、 疾病分類\n個案之判定除參考檢驗結果外,需送請防疫醫師,合併考量其臨床症\n狀、疫苗接種情形與近期旅遊史後,進行病例最終判定,病例分類如\n下:\n(一) 可能病例:符合通報定義,但血清學、病毒學或其他相關檢驗無\n法證實或並未檢驗,並與實驗室確診個案無流行病學上之關聯。\n(二) 確定病例:\n符合下列條件之一者,並經防疫醫師審查判定確定者:\n1. 經實驗室檢驗確認者。\n2. 符合通報定義,且與實驗室確診個案有流行病學相關者。\n六、檢體採檢送驗事項\n採檢項目 檢體種類 採檢目的 採檢時機 採檢規定 運送條件 注意事項\n以 含 抗 凝 劑\n急性期(發病\n病原體檢 ( 肝 素 或 抗凝固檢體採\n抗凝固全 7日內);恢復\n測;抗體 EDTA)採血管 檢步驟請參考\n血 期(發病14-\n檢測 採集5 mL 血 第3.2節。\n40 日之間)\n液,混合均勻。\n以無菌病毒拭 見2.8.5 備註\n子之棉棒擦拭 2-8oC(B 說明及咽喉採\n麻 咽喉擦拭\n咽喉,插入病 類感染性 檢步驟請參考\n疹 液\n毒 保 存 輸 送 物質包裝) 第3.7 節及圖\n病原體檢 急性期(發病 管。 3.7。\n測 7日內) 尿液收集以晨\n以取無菌容器\n起第1 次為最\n收集10-50 mL\n尿液 佳。尿液採檢\n尿液,緊密封\n步驟請參考第\n口。\n3.4 節。",
    "pdf_path": "pdfs/麻疹.pdf",
    "臨床條件": "(一)出疹(斑丘疹)且發燒(耳溫或肛溫)≧38°C。\n(二)有時伴隨咳嗽,或流鼻水或結膜炎(畏光、流淚水或眼睛發紅)。",
    "檢驗條件": "符合下列四種情形之一者,判定為陽性:\n(一)咽喉拭子、尿液或全血等檢體病毒培養結果陽性。\n(二)RT-PCR試驗結果陽性。\n(三)急性期與恢復期血清IgG抗體由陰性陽轉或效價有4倍以上增加。\n(四)IgM抗體陽性,並排除其他可能的偽陽性因子影響。",
    "流行病學條件": "具有下列任一個條件:\n(一)發病前三週內,曾有麻疹流行地區旅遊史。\n(二)曾與確定病例有空氣或飛沫接觸,或曾直接接觸確定病例之鼻咽分\n泌物。",
    "通報定義": "出疹且發燒(耳溫或肛溫)高於38°C,並具有下列三項條件之任一者:\n(一)咳嗽、流鼻水或結膜炎(畏光、流淚水或眼睛發紅)三種症狀中\n的一種。\n(二)無麻疹相關疫苗接種史。\n(三)發病前三週內,曾有麻疹流行地區旅遊史。",
    "疾病分類": "個案之判定除參考檢驗結果外,需送請防疫醫師,合併考量其臨床症\n狀、疫苗接種情形與近期旅遊史後,進行病例最終判定,病例分類如\n下:\n(一) 可能病例:符合通報定義,但血清學、病毒學或其他相關檢驗無\n法證實或並未檢驗,並與實驗室確診個案無流行病學上之關聯。\n(二) 確定病例:\n符合下列條件之一者,並經防疫醫師審查判定確定者:\n1. 經實驗室檢驗確認者。\n2. 符合通報定義,且與實驗室確診個案有流行病學相關者。",
    "檢體採檢送驗事項": "採檢項目 檢體種類 採檢目的 採檢時機 採檢規定 運送條件 注意事項\n以 含 抗 凝 劑\n急性期(發病\n病原體檢 ( 肝 素 或 抗凝固檢體採\n抗凝固全 7日內);恢復\n測;抗體 EDTA)採血管 檢步驟請參考\n血 期(發病14-\n檢測 採集5 mL 血 第3.2節。\n40 日之間)\n液,混合均勻。\n以無菌病毒拭 見2.8.5 備註\n子之棉棒擦拭 2-8oC(B 說明及咽喉採\n麻 咽喉擦拭\n咽喉,插入病 類感染性 檢步驟請參考\n疹 液\n毒 保 存 輸 送 物質包裝) 第3.7 節及圖\n病原體檢 急性期(發病 管。 3.7。\n測 7日內) 尿液收集以晨\n以取無菌容器\n起第1 次為最\n收集10-50 mL\n尿液 佳。尿液採檢\n尿液,緊密封\n步驟請參考第\n口。\n3.4 節。",
    "english_name": "Measles",
    "suspected_case": "符合通報定義,但血清學、病毒學或其他相關檢驗無\n法證實或並未檢驗,並與實驗室確診個案無流行病學上之關聯。",
    "probable_case": "",
    "confirmed_case": "符合下列條件之一者,並經防疫醫師審查判定確定者:\n1. 經實驗室檢驗確認者。\n2. 符合通報定義,且與實驗室確診個案有流行病學相關者。"
  },
  {
    "name": "黃熱病",
    "url": "https://www.cdc.gov.tw/File/Get/kKAg1J6Hj2F8yh_SEjG_lA",
    "source_category": "第五類",
    "content": "黃熱病\n(Yellow Fever)\n一、 臨床條件\n發燒及肝功能異常,且出現下列任何一項症狀: 猝發性冷顫、\n頭痛、背痛、全身肌肉酸痛、虛脫、噁心、嘔吐。\n二、 檢驗條件\n符合下列檢驗結果之任一項者,定義為檢驗結果陽性:\n(一)臨床檢體(組織、血液或其他體液)分離並鑑定出黃熱病毒。\n(二)臨床檢體分子生物學核酸檢測陽性。\n(三)急性期(或初次採檢)血清中,黃熱病毒特異性 IgM 或 IgG\n抗體為陽性者。\n(四)在最近未接受預防注射及排除其他黃病毒交叉反應的情形下,\n成對血清(恢復期及急性期)中,黃熱病毒特異性 IgM 或\nIgG 抗體(二者任一)有陽轉或≧4 倍上升。\n三、 流行病學條件\n具有黃熱病流行地區之旅遊史。\n四、 通報定義\n具有下列任一個條件:\n(一)符合臨床條件及流行病學條件。\n(二)醫師高度懷疑,且與確定病例具有流行病學上相關。\n五、 疾病分類\n(一) 可能病例:\nNA\n(二) 極可能病例:\n具有下列任一個條件:\n1. 符合臨床條件及檢驗結果陽性定義之第三項。\n2. 符合臨床條件及流行病學條件。\n(三) 確定病例:\n具有下列任一個條件:\n1. 符合檢驗結果陽性定義之第一、二、四項之任一項。\n2. 符合臨床條件,且與經實驗室證實之病例或突發流行疫情具有\n流行病學上相關聯。\n六、 檢體採檢送驗事項\n採檢項目 檢體種類 採檢目的 採檢時間 採檢量及規定 送驗方式 注意事項\n病 原 體 檢 1.若無法取得急性期\n測\n之血液,請立即採\n急性期(發病\n後 7日內); 以無菌試管收 檢,並採間隔 7 日\n黃熱病 血清\n恢復期(發病 集 3 mL 血清。 之恢復期血清,分\n抗體檢測\n14-40 日 之 2-8°C (B 2次送驗。\n間) 類感染性\n2.檢體勿加入任何添\n物質包\n加物。\n裝)\n3.血清檢體見傳染病\n檢體採檢手冊\n2.8.3及 2.8.4 備註\n說明,血清採檢步\n驟請參考傳染病檢\n體採檢手冊第3.3\n節。",
    "pdf_path": "pdfs/黃熱病.pdf",
    "臨床條件": "發燒及肝功能異常,且出現下列任何一項症狀: 猝發性冷顫、\n頭痛、背痛、全身肌肉酸痛、虛脫、噁心、嘔吐。",
    "檢驗條件": "符合下列檢驗結果之任一項者,定義為檢驗結果陽性:\n(一)臨床檢體(組織、血液或其他體液)分離並鑑定出黃熱病毒。\n(二)臨床檢體分子生物學核酸檢測陽性。\n(三)急性期(或初次採檢)血清中,黃熱病毒特異性 IgM 或 IgG\n抗體為陽性者。\n(四)在最近未接受預防注射及排除其他黃病毒交叉反應的情形下,\n成對血清(恢復期及急性期)中,黃熱病毒特異性 IgM 或\nIgG 抗體(二者任一)有陽轉或≧4 倍上升。",
    "流行病學條件": "具有黃熱病流行地區之旅遊史。",
    "通報定義": "具有下列任一個條件:\n(一)符合臨床條件及流行病學條件。\n(二)醫師高度懷疑,且與確定病例具有流行病學上相關。",
    "疾病分類": "(一) 可能病例:\nNA\n(二) 極可能病例:\n具有下列任一個條件:\n1. 符合臨床條件及檢驗結果陽性定義之第三項。\n2. 符合臨床條件及流行病學條件。\n(三) 確定病例:\n具有下列任一個條件:\n1. 符合檢驗結果陽性定義之第一、二、四項之任一項。\n2. 符合臨床條件,且與經實驗室證實之病例或突發流行疫情具有\n流行病學上相關聯。",
    "檢體採檢送驗事項": "採檢項目 檢體種類 採檢目的 採檢時間 採檢量及規定 送驗方式 注意事項\n病 原 體 檢 1.若無法取得急性期\n測\n之血液,請立即採\n急性期(發病\n後 7日內); 以無菌試管收 檢,並採間隔 7 日\n黃熱病 血清\n恢復期(發病 集 3 mL 血清。 之恢復期血清,分\n抗體檢測\n14-40 日 之 2-8°C (B 2次送驗。\n間) 類感染性\n2.檢體勿加入任何添\n物質包\n加物。\n裝)\n3.血清檢體見傳染病\n檢體採檢手冊\n2.8.3及 2.8.4 備註\n說明,血清採檢步\n驟請參考傳染病檢\n體採檢手冊第3.3\n節。",
    "english_name": "Yellow Fever",
    "suspected_case": "NA",
    "probable_case": "具有下列任一個條件:\n1. 符合臨床條件及檢驗結果陽性定義之第三項。\n2. 符合臨床條件及流行病學條件。",
    "confirmed_case": "具有下列任一個條件:\n1. 符合檢驗結果陽性定義之第一、二、四項之任一項。\n2. 符合臨床條件,且與經實驗室證實之病例或突發流行疫情具有\n流行病學上相關聯。"
  },
  {
    "name": "鼠疫",
    "url": "https://www.cdc.gov.tw/File/Get/umCKYMvqz2ATg6azvXbqfA",
    "source_category": "第一類",
    "content": "鼠疫\n(Plague)\n一、 臨床條件\n出現發燒、寒顫、頭痛、不適、虛脫及白血球增多,且伴隨下\n列一種(含)以上之主要臨床型態:\n(一) 局部淋巴腺炎(腺鼠疫)。\n(二) 沒有明顯淋巴腺腫之敗血症(敗血性鼠疫)。\n(三) 肺鼠疫:腺鼠疫或敗血性鼠疫經血行蔓延造成(次發\n性肺鼠疫)或吸入飛沫感染(原發性肺鼠疫)。\n(四) 由暴露於較大感染性飛沫或食入受感染組織(咽鼠\n疫)所造成之咽炎和頸部淋巴腺炎。\n二、 檢驗條件\n具有下列任一個條件:\n(一) 臨床檢體(淋巴液、血液、痰液、咽喉擦拭液等)分\n離並鑑定出鼠疫桿菌(Yersinia pestis)。\n(二) 臨床檢體分子生物學核酸檢測陽性。\n(三) 血清學抗體檢測陽性:恢復期血清較急性期血清抗體\n效價≧4倍上升。\n三、 流行病學條件\n具有下列任一個條件:\n(一)具有鼠疫流行地區之旅遊史,且曾接觸囓齒類動物,或\n遭跳蚤叮咬。\n(二)曾接觸鼠疫確定病例。\n四、 通報定義\n具有下列任一個條件:\n(一) 符合臨床條件及流行病學條件。\n(二) 經醫院自行檢驗,符合檢驗條件。\n(三) 醫師或法醫師高度懷疑。\n五、 疾病分類\n(一) 可能病例: NA\n(二) 極可能病例:符合臨床條件雖未經實驗室證實,但與\n實驗室證實之確定病例 具有流行病學之關聯。\n(三) 確定病例:符合臨床條件及檢驗條件。\n六、 檢體採檢送驗事項\n請參閱「傳染病檢體採檢手冊」(https://gov.tw/pK8)",
    "pdf_path": "pdfs/鼠疫.pdf",
    "臨床條件": "出現發燒、寒顫、頭痛、不適、虛脫及白血球增多,且伴隨下\n列一種(含)以上之主要臨床型態:\n(一) 局部淋巴腺炎(腺鼠疫)。\n(二) 沒有明顯淋巴腺腫之敗血症(敗血性鼠疫)。\n(三) 肺鼠疫:腺鼠疫或敗血性鼠疫經血行蔓延造成(次發\n性肺鼠疫)或吸入飛沫感染(原發性肺鼠疫)。\n(四) 由暴露於較大感染性飛沫或食入受感染組織(咽鼠\n疫)所造成之咽炎和頸部淋巴腺炎。",
    "檢驗條件": "具有下列任一個條件:\n(一) 臨床檢體(淋巴液、血液、痰液、咽喉擦拭液等)分\n離並鑑定出鼠疫桿菌(Yersinia pestis)。\n(二) 臨床檢體分子生物學核酸檢測陽性。\n(三) 血清學抗體檢測陽性:恢復期血清較急性期血清抗體\n效價≧4倍上升。",
    "流行病學條件": "具有下列任一個條件:\n(一)具有鼠疫流行地區之旅遊史,且曾接觸囓齒類動物,或\n遭跳蚤叮咬。\n(二)曾接觸鼠疫確定病例。",
    "通報定義": "具有下列任一個條件:\n(一) 符合臨床條件及流行病學條件。\n(二) 經醫院自行檢驗,符合檢驗條件。\n(三) 醫師或法醫師高度懷疑。",
    "疾病分類": "(一) 可能病例: NA\n(二) 極可能病例:符合臨床條件雖未經實驗室證實,但與\n實驗室證實之確定病例 具有流行病學之關聯。\n(三) 確定病例:符合臨床條件及檢驗條件。",
    "檢體採檢送驗事項": "請參閱「傳染病檢體採檢手冊」(https://gov.tw/pK8)",
    "english_name": "Plague",
    "suspected_case": "NA",
    "probable_case": "符合臨床條件雖未經實驗室證實,但與\n實驗室證實之確定病例 具有流行病學之關聯。",
    "confirmed_case": "符合臨床條件及檢驗條件。"
  }
]